Workbook

Sheet 00-三表与联动
A1: MU · Micron Technology, Inc. —— 三表与联动
A2: 单位：百万美元 | 财年截止约每年 8 月底/9 月初 | 数据源：公司 FY26 Q1/Q2/Q3 财报原文 + FY26 Q4 官方指引 | Q3 止于 2026-05-28
A4: 00 公司速览与估值锚点
A5: 项目 | B5: 数值 | D5: 口径与说明
A6: 现价（2026-08-24 收盘） | B6: 903.09 | D6: 当日区间 $887.61–$942.52。52 周区间 $114.25–$1,255.00。★ 本格可改
A7: 市值 | B7: 1018685 | D7: ＝ 现价 × 基本股数，已突破 1 万亿美元
A8: 基本股数（百万股） | B8: 1128 | D8: FY26 Q3 基本加权股数
A9: 摊薄股数（百万股） | B9: 1150 | D9: 公司 FY26 Q4 指引「约 11.5 亿摊薄股」
A10: 现金及可交易投资 | B10: 30155 | D10: 现金 24,995 + 短期投资 1,027 + 长期可交易投资 4,106 + 受限现金 27
A11: 有息负债 | B11: 5722 | D11: 一年内到期 582 + 长期 5,140。已从 FY25 末的 14,577 降至 5,722
A12: 净现金 | B12: =B10-B11 -> 24433 | D12: ＝ 现金及投资 − 有息负债。MU 为净现金结构
A13: 季度股息（美元/股） | B13: 0.15 | D13: 年化 $0.60。CHIPS 协议对回购有限制，2026-12-09 后放开
A14: 无风险利率 Rf | B14: 0.042 | D14: 10 年期美国国债收益率
A15: 股权风险溢价 ERP | B15: 0.05 | D15: 美国成熟市场长期股权风险溢价
A16: 01 三情形估值对比（数字实时链接自后面三张 DCF 表）
A17: 情形 | B17: 每股内在价值 | C17: 相对现价 | D17: 终值占 EV | E17: FY27 收入 | F17: FY27 毛利率 | G17: FY32 毛利率 | H17: WACC | I17: 永续 g | J17: 一句话论点
A18: 悲观 | B18: ='01-DCF-悲观'!B72 -> 282.16108 | C18: ='01-DCF-悲观'!B74 -> -0.6875604 | D18: ='01-DCF-悲观'!B65 -> 0.46946174 | E18: ='01-DCF-悲观'!F13 -> 176999.93 | F18: ='01-DCF-悲观'!F15 -> 0.73401133 | G18: ='01-DCF-悲观'!G34 -> 0.43 | H18: ='01-DCF-悲观'!$B$211 -> 0.13 | I18: ='01-DCF-悲观'!$B$213 -> 0.025 | J18: DRAM 随 NAND 在 2027 年转向，而自建厂的资本开支是刚性的
A19: 基准 | B19: ='02-DCF-基准'!B72 -> 1081.8568 | C19: ='02-DCF-基准'!B74 -> 0.19795015 | D19: ='02-DCF-基准'!B65 -> 0.64257993 | E19: ='02-DCF-基准'!F13 -> 205000.09 | F19: ='02-DCF-基准'!F15 -> 0.82656096 | G19: ='02-DCF-基准'!G34 -> 0.68 | H19: ='02-DCF-基准'!$B$211 -> 0.11 | I19: ='02-DCF-基准'!$B$213 -> 0.03 | J19: FY27 见顶但不崩塌；MU 的 DRAM 权重使其下行风险小于纯 NAND 标的
A20: 乐观 | B20: ='03-DCF-乐观'!B72 -> 2640.66 | C20: ='03-DCF-乐观'!B74 -> 1.9240275 | D20: ='03-DCF-乐观'!B65 -> 0.72534669 | E20: ='03-DCF-乐观'!F13 -> 243000 | F20: ='03-DCF-乐观'!F15 -> 0.86615226 | G20: ='03-DCF-乐观'!G34 -> 0.74 | H20: ='03-DCF-乐观'!$B$211 -> 0.095 | I20: ='03-DCF-乐观'!$B$213 -> 0.035 | J20: SCA 照付不议合约把存储从周期股变成合约制生意
A21: 当前股价（2026-08-24） | B21: 903.09 | C21: 52 周区间 $114.25 – $1,255.00。过去一年涨约 700%，市值突破 1 万亿美元
A22: 卖方一致目标价 | B22: 1515 | C22: S&P Global 汇总 47 家机构，评级「强烈买入」；最低 $361、最高 $2,200。这个 6 倍的区间跨度本身就说明分歧极大
A23: ★ 读这张表之前必须知道的三件事：① MU 与纯 NAND 标的（如 SNDK）最根本的不同是自建晶圆厂——FY25 资本开支占收入 36.9%，FY26 约 20.9%，绝对额从 $138 亿升到约 $270 亿，管理层已指引 FY27 继续上升。收入下行时资本开支不会同步下行，这是存储自建厂商现金流崩塌的机制；② MU 约 76% 收入来自 DRAM（FY26 Q3 DRAM 收入 $313 亿），而《缺口的算术》的结论是 NAND 先于 DRAM 转过剩——这构成 MU 相对纯 NAND 标的的结构性优势，也是本模型三个情形分歧的核心；③ FY26 Q4 尚未披露（财年止于 2026-09-03），本表该列为公司官方指引，未指引的利息与税项按注明假设填列。
A25: 02 合并利润表（季度 + 年度）
A26: 科目（百万美元） | B26: FY26 Q1 | C26: FY26 Q2 | D26: FY26 Q3 | E26: FY26 Q4E （指引） | F26: FY2026E | G26: FY2025 | H26: Q4E 环比 | I26: FY26E 同比 | J26: 备注
A27: 营业收入 Revenue | B27: 13643 | C27: 23860 | D27: 41456 | E27: 50000 | F27: 128959 | G27: 37382 | H27: =IF(D27=0,"n/a",E27/ABS(D27)-1) -> 0.20609803 | I27: =IF(G27=0,"n/a",F27/ABS(G27)-1) -> 2.4497619
A28: 营业成本 Cost of goods sold | B28: 5997 | C28: 6105 | D28: 6400 | E28: 7000 | F28: 25502 | G28: 22363 | H28: =IF(D28=0,"n/a",E28/ABS(D28)-1) -> 0.09375 | I28: =IF(G28=0,"n/a",F28/ABS(G28)-1) -> 0.14036578
A29: 毛利 Gross margin | B29: 7646 | C29: 17755 | D29: 35056 | E29: 43000 | F29: 103457 | G29: 15019 | H29: =IF(D29=0,"n/a",E29/ABS(D29)-1) -> 0.22660885 | I29: =IF(G29=0,"n/a",F29/ABS(G29)-1) -> 5.888408
A30: 研发费用 R&D | B30: 1171 | C30: 1250 | D30: 1316 | E30: 1408 | F30: 5145 | G30: 3951 | H30: =IF(D30=0,"n/a",E30/ABS(D30)-1) -> 0.069908815 | I30: =IF(G30=0,"n/a",F30/ABS(G30)-1) -> 0.30220197
A31: 销售管理费用 SG&A | B31: 337 | C31: 344 | D31: 407 | E31: 436 | F31: 1524 | G31: 1195 | H31: =IF(D31=0,"n/a",E31/ABS(D31)-1) -> 0.071253071 | I31: =IF(G31=0,"n/a",F31/ABS(G31)-1) -> 0.27531381
A32: 其他营业(收入)费用净额 Other opex | B32: 2 | C32: 26 | D32: 15 | E32: 16 | F32: 59 | G32: -243 | H32: =IF(D32=0,"n/a",E32/ABS(D32)-1) -> 0.066666667 | I32: =IF(G32=0,"n/a",F32/ABS(G32)-1) -> -0.75720165
A33: 营业费用合计 Total opex | B33: 1510 | C33: 1620 | D33: 1738 | E33: 1860 | F33: 6728 | G33: 4903 | H33: =IF(D33=0,"n/a",E33/ABS(D33)-1) -> 0.070195627 | I33: =IF(G33=0,"n/a",F33/ABS(G33)-1) -> 0.37222109
A34: 营业利润 Operating income | B34: 6136 | C34: 16135 | D34: 33318 | E34: 41140 | F34: 96729 | G34: 10116 | H34: =IF(D34=0,"n/a",E34/ABS(D34)-1) -> 0.23476799 | I34: =IF(G34=0,"n/a",F34/ABS(G34)-1) -> 8.561981
A35: 利息收入 Interest income | B35: 139 | C35: 155 | D35: 215 | E35: 300 | F35: 809 | G35: 485 | H35: =IF(D35=0,"n/a",E35/ABS(D35)-1) -> 0.39534884 | I35: =IF(G35=0,"n/a",F35/ABS(G35)-1) -> 0.66804124
A36: 利息支出 Interest expense | B36: -74 | C36: -32 | D36: 0 | E36: 0 | F36: -106 | G36: -476 | H36: =IF(D36=0,"n/a",E36/ABS(D36)-1) -> n/a | I36: =IF(G36=0,"n/a",F36/ABS(G36)-1) -> -1.2226891
A37: 其他非经营损益 Other non-operating | B37: -140 | C37: -98 | D37: -321 | E37: -100 | F37: -659 | G37: -145 | H37: =IF(D37=0,"n/a",E37/ABS(D37)-1) -> -1.3115265 | I37: =IF(G37=0,"n/a",F37/ABS(G37)-1) -> -5.5448276
A38: 税前利润 Income before taxes | B38: 6061 | C38: 16160 | D38: 33212 | E38: 41340 | F38: 96773 | G38: 9980 | H38: =IF(D38=0,"n/a",E38/ABS(D38)-1) -> 0.24473082 | I38: =IF(G38=0,"n/a",F38/ABS(G38)-1) -> 8.6966934
... A41: 净利润 Net income | B41: 5240 | C41: 13785 | D41: 28243 | E41: 35340 | F41: 82608 | G41: 8540 | H41: =IF(D41=0,"n/a",E41/ABS(D41)-1) -> 0.2512835 | I41: =IF(G41=0,"n/a",F41/ABS(G41)-1) -> 8.6730679
A42: 毛利率 Gross margin | B42: =B29/B27 -> 0.56043392 | C42: =C29/C27 -> 0.74413244 | D42: =D29/D27 -> 0.84561945 | E42: =E29/E27 -> 0.86 | F42: =F29/F27 -> 0.80224723 | G42: =G29/G27 -> 0.40177091
A43: 营业利润率 Operating margin | B43: =B34/B27 -> 0.44975445 | C43: =C34/C27 -> 0.67623638 | D43: =D34/D27 -> 0.80369548 | E43: =E34/E27 -> 0.8228 | F43: =F34/F27 -> 0.75007561 | G43: =G34/G27 -> 0.27061152
A44: 净利率 Net margin | B44: =B41/B27 -> 0.38407975 | C44: =C41/C27 -> 0.57774518 | D44: =D41/D27 -> 0.68127653 | E44: =E41/E27 -> 0.7068 | F44: =F41/F27 -> 0.64057569 | G44: =G41/G27 -> 0.2284522
A45: 费用率 Opex % of revenue | B45: =B33/B27 -> 0.11067947 | C45: =C33/C27 -> 0.06789606 | D45: =D33/D27 -> 0.041923968 | E45: =E33/E27 -> 0.0372 | F45: =F33/F27 -> 0.05217162 | G45: =G33/G27 -> 0.13115938
A46: 摊薄每股收益 Diluted EPS ($) | B46: 4.6 | C46: 12.07 | D46: 24.67 | E46: 30.73 | F46: 72.21 | G46: 7.59
A47: 基本每股收益 Basic EPS ($) | B47: 4.66 | C47: 12.25 | D47: 25.03 | E47: 31.2 | F47: 73.32 | G47: 7.67
A48: 摊薄股数 Diluted shares (M) | B48: 1139 | C48: 1142 | D48: 1145 | E48: 1150 | F48: 1144 | G48: 1125
A49: 基本股数 Basic shares (M) | B49: 1124 | C49: 1126 | D49: 1128 | E49: 1133 | F49: 1128 | G49: 1114
A50: ★ 四个季度的毛利率路径是 56.0% → 74.4% → 84.6% → 约86%（指引）。注意营业成本几乎没动（5,997 → 6,105 → 6,400），而收入从 $136 亿涨到 $500 亿——这轮周期的全部利润都来自价格，不是来自量。公司口径：FY26 Q3 DRAM 平均售价环比约 +60%，bit 出货量仅增长低个位数；NAND 售价环比约 +85%。
A51: 口径说明：① FY26 Q1 的各明细行由「九个月累计 − Q2 − Q3」倒算，并与公司 Q1 财报原文逐项交叉验证一致（收入 $13.64B、净利 $5.24B、EPS $4.60、经营现金流 $8.41B、调整后自由现金流 $3.9B 全部吻合）；② FY26 Q4E 列为公司官方指引（收入 $50.0B、毛利率约 86%、GAAP 费用约 $1.86B、GAAP EPS $30.73、约 11.5 亿摊薄股），研发/销售管理费用按 Q3 结构拆分，利息收入假设 $300M、其他非经营 −$100M，所得税为倒算项（使净利润等于指引 EPS × 指引股数，隐含税率 14.5%，与 Q3 实际 15.0% 一致）；③ FY2025 列的营业成本与费用由「九个月实际 + Q4 电话会口径（毛利率 45.7%、费用约 $12 亿、营业利润约 $40 亿）」拼合，存在小数级四舍五入。
A53: 03 业务单元收入与利润率（FY26 Q3）
A54: 业务单元 | B54: Q2 收入 | C54: Q3 收入 | D54: Q3-25 收入 | E54: Q3 环比 | F54: Q3 同比 | G54: Q3 占比 | H54: Q3 毛利率 | I54: Q3 营业利润率 | J54: 说明
A55: 云内存 Cloud Memory (CMBU) | B55: 7749 | C55: 13769 | D55: 3386 | E55: =C55/B55-1 -> 0.77687444 | F55: =C55/D55-1 -> 3.0664501 | G55: =C55/C27 -> 0.5770746 | H55: 0.83 | I55: 0.78 | J55: HBM 与高性能 DRAM。HBM3E/HBM4 已售罄至 2027 年，HBM4 出货爬坡速度是 HBM3E 的两倍
A56: 核心数据中心 Core Data Center (CDBU) | B56: 5687 | C56: 11524 | D56: 1530 | E56: =C56/B56-1 -> 1.0263759 | F56: =C56/D56-1 -> 6.5320261 | G56: =C56/C27 -> 0.48298407 | H56: 0.87 | I56: 0.83 | J56: 服务器 DRAM 与数据中心 SSD。Q3 数据中心 SSD 收入超 $50 亿，环比翻倍以上
A57: 移动与客户端 Mobile & Client (MCBU) | B57: 7711 | C57: 11521 | D57: 3255 | E57: =C57/B57-1 -> 0.49409934 | F57: =C57/D57-1 -> 2.5394777 | G57: =C57/C27 -> 0.48285834 | H57: 0.87 | I57: 0.86 | J57: 手机与 PC。LP5X SOCAMM2 已量产；1-gamma LPDDR5X 已在头部手机厂放量
A58: 汽车与嵌入式 Auto & Embedded (AEBU) | B58: 2708 | C58: 4634 | D58: 1127 | E58: =C58/B58-1 -> 0.711226 | F58: =C58/D58-1 -> 3.1118012 | G58: =C58/C27 -> 0.19421626 | H58: 0.79 | I58: 0.75 | J58: 汽车与嵌入式。1-gamma LPDDR5 已达车规就绪
A59: 合计（应等于营业收入） | B59: =SUM(B55:B58) -> 23855 | C59: =SUM(C55:C58) -> 41448 | D59: =SUM(D55:D58) -> 9298
A60: ★ 两个数据中心相关业务（云内存 + 核心数据中心）Q3 合计收入 $253 亿，占总收入 61%，年化超 $1,000 亿。核心数据中心业务的毛利率 87%、营业利润率 83%——这是整家公司利润的发动机。
A62: 04 合并资产负债表（三个时点，全部为公司披露原值）
A63: 科目（百万美元） | B63: 2025-08-28 (FY25末) | C63: 2026-02-26 (FY26 Q2末) | D63: 2026-05-28 (FY26 Q3末) | E63: Q3 较 FY25末 | F63: 变动率 | G63: 备注
A64: 【资产】
A65: 货币资金 Cash & equivalents | B65: 9642 | C65: 13908 | D65: 24995 | E65: =D65-B65 -> 15353 | F65: =IF(B65=0,"n/a",D65/B65-1) -> 1.5923045
A66: 短期投资 Short-term investments | B66: 665 | C66: 681 | D66: 1027 | E66: =D66-B66 -> 362 | F66: =IF(B66=0,"n/a",D66/B66-1) -> 0.5443609
A67: 应收账款 Receivables | B67: 9265 | C67: 17314 | D67: 31025 | E67: =D67-B67 -> 21760 | F67: =IF(B67=0,"n/a",D67/B67-1) -> 2.3486239
A68: 存货 Inventories | B68: 8355 | C68: 8267 | D68: 8567 | E68: =D68-B68 -> 212 | F68: =IF(B68=0,"n/a",D68/B68-1) -> 0.025374028
A69: 其他流动资产 Other current assets | B69: 914 | C69: 1243 | D69: 1123 | E69: =D69-B69 -> 209 | F69: =IF(B69=0,"n/a",D69/B69-1) -> 0.22866521
A70: 流动资产合计 Total current assets | B70: 28841 | C70: 41413 | D70: 66737 | E70: =D70-B70 -> 37896 | F70: =IF(B70=0,"n/a",D70/B70-1) -> 1.3139628
A71: 长期可交易投资 LT marketable investments | B71: 1629 | C71: 2038 | D71: 4106 | E71: =D71-B71 -> 2477 | F71: =IF(B71=0,"n/a",D71/B71-1) -> 1.5205648
A72: 固定资产净额 Property, plant & equipment | B72: 46590 | C72: 51408 | D72: 56426 | E72: =D72-B72 -> 9836 | F72: =IF(B72=0,"n/a",D72/B72-1) -> 0.21111827
A73: 经营租赁使用权资产 Operating lease ROU | B73: 736 | C73: 684 | D73: 683 | E73: =D73-B73 -> -53 | F73: =IF(B73=0,"n/a",D73/B73-1) -> -0.07201087
A74: 无形资产 Intangible assets | B74: 453 | C74: 468 | D74: 473 | E74: =D74-B74 -> 20 | F74: =IF(B74=0,"n/a",D74/B74-1) -> 0.04415011
A75: 递延所得税资产 Deferred tax assets | B75: 616 | C75: 680 | D75: 700 | E75: =D75-B75 -> 84 | F75: =IF(B75=0,"n/a",D75/B75-1) -> 0.13636364
A76: 商誉 Goodwill | B76: 1150 | C76: 1150 | D76: 1150 | E76: =D76-B76 -> 0 | F76: =IF(B76=0,"n/a",D76/B76-1) -> 0
... A78: 资产总计 Total assets | B78: 82798 | C78: 101509 | D78: 134112 | E78: =D78-B78 -> 51314 | F78: =IF(B78=0,"n/a",D78/B78-1) -> 0.61974927
A79: 【负债】
A80: 应付账款及应计费用 AP & accrued expenses | B80: 9649 | C80: 10997 | D80: 15521 | E80: =D80-B80 -> 5872 | F80: =IF(B80=0,"n/a",D80/B80-1) -> 0.60856047
A81: 一年内到期债务 Current debt | B81: 560 | C81: 585 | D81: 582 | E81: =D81-B81 -> 22 | F81: =IF(B81=0,"n/a",D81/B81-1) -> 0.039285714
A82: 其他流动负债 Other current liabilities | B82: 1245 | C82: 2714 | D82: 3385 | E82: =D82-B82 -> 2140 | F82: =IF(B82=0,"n/a",D82/B82-1) -> 1.7188755
A83: 流动负债合计 Total current liabilities | B83: 11454 | C83: 14296 | D83: 19488 | E83: =D83-B83 -> 8034 | F83: =IF(B83=0,"n/a",D83/B83-1) -> 0.70141435
A84: 长期债务 Long-term debt | B84: 14017 | C84: 9557 | D84: 5140 | E84: =D84-B84 -> -8877 | F84: =IF(B84=0,"n/a",D84/B84-1) -> -0.63330242
A85: 非流动经营租赁负债 Noncurrent lease liab. | B85: 701 | C85: 656 | D85: 654 | E85: =D85-B85 -> -47 | F85: =IF(B85=0,"n/a",D85/B85-1) -> -0.067047076
A86: 非流动递延政府补贴 Unearned govt incentives | B86: 1018 | C86: 1002 | D86: 1020 | E86: =D86-B86 -> 2 | F86: =IF(B86=0,"n/a",D86/B86-1) -> 0.0019646365
A87: 其他非流动负债 Other noncurrent liabilities | B87: 1443 | C87: 3539 | D87: 7086 | E87: =D87-B87 -> 5643 | F87: =IF(B87=0,"n/a",D87/B87-1) -> 3.9106029
A88: 负债合计 Total liabilities | B88: 28633 | C88: 29050 | D88: 33388 | E88: =D88-B88 -> 4755 | F88: =IF(B88=0,"n/a",D88/B88-1) -> 0.16606713
A89: 【股东权益】
A90: 普通股 Common stock | B90: 127 | C90: 127 | D90: 128 | E90: =D90-B90 -> 1 | F90: =IF(B90=0,"n/a",D90/B90-1) -> 0.0078740157
A91: 资本公积 Additional capital | B91: 13339 | C91: 14092 | D91: 14442 | E91: =D91-B91 -> 1103 | F91: =IF(B91=0,"n/a",D91/B91-1) -> 0.082689857
A92: 留存收益 Retained earnings | B92: 48583 | C92: 66824 | D92: 94682 | E92: =D92-B92 -> 46099 | F92: =IF(B92=0,"n/a",D92/B92-1) -> 0.948871
A93: 库存股 Treasury stock | B93: -7852 | C93: -8502 | D93: -8502 | E93: =D93-B93 -> -650 | F93: =IF(B93=0,"n/a",D93/B93-1) -> 0.082781457
A94: 累计其他综合收益 AOCI | B94: -32 | C94: -82 | D94: -26 | E94: =D94-B94 -> 6 | F94: =IF(B94=0,"n/a",D94/B94-1) -> -0.1875
A95: 股东权益合计 Total equity | B95: 54165 | C95: 72459 | D95: 100724 | E95: =D95-B95 -> 46559 | F95: =IF(B95=0,"n/a",D95/B95-1) -> 0.85957722
A96: ★ 应收账款从 $92.65 亿膨胀到 $310.25 亿（+235%），这是本轮周期在资产负债表上最触目的一笔。它同时也是自由现金流的最大拖累项：FY26 前九个月应收账款变动为 −$199.53 亿，几乎抵消了一半的净利润。另一侧，长期债务从 $140.17 亿降到 $51.40 亿，公司已进入净现金状态。
A98: 05 合并现金流量表（九个月累计，公司披露口径）
A99: 科目（百万美元） | B99: 9M FY2026 | C99: 9M FY2025 | D99: 占收入比 | E99: 同比变动 | F99: 备注
A100: 【经营活动】
A101: 净利润 Net income | B101: =SUM(B41:D41) -> 47268 | C101: 5338 | D101: =B101/F27 -> 0.3665351 | E101: =IF(C101=0,"n/a",B101/ABS(C101)-1) -> 7.8550019
A102: 折旧与摊销 Depreciation & amortization | B102: 6862 | C102: 6203 | D102: =B102/F27 -> 0.05321071 | E102: =IF(C102=0,"n/a",B102/ABS(C102)-1) -> 0.10623892
A103: 股份支付 Stock-based compensation | B103: 954 | C103: 722 | D103: =B103/F27 -> 0.0073977 | E103: =IF(C103=0,"n/a",B103/ABS(C103)-1) -> 0.32132964
A104: 应收账款变动 Δ Receivables | B104: -19953 | C104: -123 | D104: =B104/F27 -> -0.15472359 | E104: =IF(C104=0,"n/a",B104/ABS(C104)-1) -> -163.21951
A105: 存货变动 Δ Inventories | B105: -212 | C105: 148 | D105: =B105/F27 -> -0.0016439333 | E105: =IF(C105=0,"n/a",B105/ABS(C105)-1) -> -2.4324324
A106: 应付及应计变动 Δ AP & accrued expenses | B106: 3329 | C106: 38 | D106: =B106/F27 -> 0.025814406 | E106: =IF(C106=0,"n/a",B106/ABS(C106)-1) -> 86.605263
A107: 其他流动负债变动 Δ Other current liabilities | B107: 2139 | C107: -681 | D107: =B107/F27 -> 0.016586667 | E107: =IF(C107=0,"n/a",B107/ABS(C107)-1) -> 2.1409692
A108: 其他非流动负债变动 Δ Other noncurrent liab. | B108: 5203 | C108: 259 | D108: =B108/F27 -> 0.040346157 | E108: =IF(C108=0,"n/a",B108/ABS(C108)-1) -> 19.088803
...

Sheet 01-DCF-悲观
A1: BEAR · MU 现金流折现模型 —— 悲观情形
A2: FY2027 分四个季度 → FY2028–FY2032 按年 → 永续 | 自由现金流口径：FCFF（资本开支扣除 CHIPS 补贴后） | ▼ 全部参数由本表底部的参数控制台滑标驱动
A4: 00 本情形的论点：这套数字建立在什么判断之上
A5: 承接《缺口的算术》：NAND 在 2027 年先转过剩，DRAM 随后跟上。SCA 虽锁定约 20% 的 DRAM 量与三分之一的 NAND 量，但意味着还有约 80% 的 DRAM 敞口在合约价重定价时无保护。本情形假设合约价在 FY27 下半年见顶回落，FY28 出现典型的存储下行周期——而 MU 的固定成本（FY26 资本开支约 $270 亿、折旧摊销约 $94 亿）在下行年不会同步缩减。
A6: 1．FY27 下半年 DRAM 合约价环比转负，Q4 收入回到 $330 亿（约为 FY26 Q4 指引的 66%）
A7: 2．FY28 收入 −35%、毛利率回到 38%——接近 MU FY2025 的 40.2%，即「超级周期之前的正常年份」
A8: 3．★ 资本开支的刚性是 MU 与 SNDK 最大的不同：收入腰斩时资本开支率会被动飙到 23% 以上
A9: 4．WACC 用 13%（周期底部风险溢价上升），永续增长 2.5%
A11: 01 FY2027 季度预测（先用季度把最近的可见度做实，再转年度）
A12: 科目（百万美元） | B12: FY27 Q1 | C12: FY27 Q2 | D12: FY27 Q3 | E12: FY27 Q4 | F12: FY2027 合计 | G12: 变量怎么来的
A13: 营业收入 | B13: =$B$189 -> 52000 | C13: =B13*(1+-0.038462+$B$191) -> 49999.976 | D13: =C13*(1+-0.16+$B$191) -> 41999.98 | E13: =D13*(1+-0.214286+$B$191) -> 32999.972 | F13: =SUM(B13:E13) -> 176999.93 | G13: Q1 ＝ 控制台滑标（官方指引 $10.3–10.8B）；Q2–Q4 ＝ 上一季 ×(1 + 情形环比增速 + 滑标平移)
A14: 环比增速 QoQ | B14: =B13/'00-三表与联动'!E27-1 -> 0.04 | C14: =C13/B13-1 -> -0.038462 | D14: =D13/C13-1 -> -0.16 | E14: =E13/D13-1 -> -0.214286 | F14: =F13/'00-三表与联动'!F27-1 -> 0.3725287 | G14: Q1 的环比基数是 FY26 Q4 的 $8,965M（不是 FY26 全年）；Q2–Q4 为上一季
A15: 毛利率 | B15: =MAX(0.05,MIN(0.92,0.85+$B$193)) -> 0.85 | C15: =MAX(0.05,MIN(0.92,0.8+$B$193)) -> 0.8 | D15: =MAX(0.05,MIN(0.92,0.68+$B$193)) -> 0.68 | E15: =MAX(0.05,MIN(0.92,0.52+$B$193)) -> 0.52 | F15: =F16/F13 -> 0.73401133 | G15: 情形设定的季度毛利率路径 + 控制台「毛利率平移」，上下限锁在 5%–92%
A16: 毛利 | B16: =B13*B15 -> 44200 | C16: =C13*C15 -> 39999.981 | D16: =D13*D15 -> 28559.986 | E16: =E13*E15 -> 17159.986 | F16: =SUM(B16:E16) -> 129919.95 | G16: ＝ 收入 × 毛利率
A17: 营业费用 | B17: =B13*$B$199 -> 2860 | C17: =C13*$B$199 -> 2749.9987 | D17: =D13*$B$199 -> 2309.9989 | E17: =E13*$B$199 -> 1814.9985 | F17: =SUM(B17:E17) -> 9734.996 | G17: ＝ 收入 × 控制台「营业费用率」。公司 FY27 Q1 GAAP 指引为 $574–614M
A18: 营业利润 EBIT | B18: =B16-B17 -> 41340 | C18: =C16-C17 -> 37249.982 | D18: =D16-D17 -> 26249.987 | E18: =E16-E17 -> 15344.987 | F18: =SUM(B18:E18) -> 120184.96 | G18: ＝ 毛利 − 营业费用
A19: 营业利润率 | B19: =B18/B13 -> 0.795 | C19: =C18/C13 -> 0.745 | D19: =D18/D13 -> 0.625 | E19: =E18/E13 -> 0.465 | F19: =F18/F13 -> 0.67901133 | G19: ＝ EBIT ÷ 收入
A20: 所得税 | B20: =MAX(0,B18)*$B$201 -> 7441.2 | C20: =MAX(0,C18)*$B$201 -> 6704.9968 | D20: =MAX(0,D18)*$B$201 -> 4724.9977 | E20: =MAX(0,E18)*$B$201 -> 2762.0977 | F20: =SUM(B20:E20) -> 21633.292 | G20: ＝ EBIT × 控制台「有效税率」（FCFF 口径按 EBIT 计税，不含利息）
A21: 税后经营利润 NOPAT | B21: =B18-B20 -> 33898.8 | C21: =C18-C20 -> 30544.985 | D21: =D18-D20 -> 21524.99 | E21: =E18-E20 -> 12582.889 | F21: =SUM(B21:E21) -> 98551.664 | G21: ＝ EBIT − 所得税
A22: ＋ 折旧摊销 D&A | B22: =B13*$B$207 -> 5460 | C22: =C13*$B$207 -> 5249.9975 | D22: =D13*$B$207 -> 4409.9979 | E22: =E13*$B$207 -> 3464.9971 | F22: =SUM(B22:E22) -> 18584.992 | G22: ＝ 收入 × 控制台「折旧摊销率」。FY26 前九个月 $6,862M，全年约 $94 亿（占收入 7.3%）。★ MU 自建晶圆厂，折旧全部落在自己报表上
A23: − 资本开支（总额） | B23: =-B13*$B$203 -> -11960 | C23: =-C13*$B$203 -> -11499.994 | D23: =-D13*$B$203 -> -9659.9954 | E23: =-E13*$B$203 -> -7589.9936 | F23: =SUM(B23:E23) -> -40709.983 | G23: ＝ 收入 × 控制台「资本开支率」。FY26 约 $270 亿；管理层已指引 FY27 季度资本开支高于 FY26 Q4 的约 $100 亿/季
A24: ＋ CHIPS 政府补贴抵扣 | B24: =-B23*$B$205 -> 1435.2 | C24: =-C23*$B$205 -> 1379.9993 | D24: =-D23*$B$205 -> 1159.1994 | E24: =-E23*$B$205 -> 910.79923 | F24: =SUM(B24:E24) -> 4885.198 | G24: ＝ 资本开支 × 控制台「政府补贴抵扣比例」。FY26 前九个月收到 $2,989M，占同期资本开支 15.2%
A25: 营运资本余额 | B25: =B13*4*$B$209 -> 36400 | C25: =C13*4*$B$209 -> 34999.983 | D25: =D13*4*$B$209 -> 29399.986 | E25: =E13*4*$B$209 -> 23099.981 | F25: =E25 -> 23099.981 | G25: ＝ 控制台「营运资本占年化收入比」× 当季收入 × 4。期初取 FY26 Q4 的年化收入基准
A26: − 营运资本增加 ΔNWC | B26: =-(B25-'00-三表与联动'!E27*4*$B$209) -> -1400 | C26: =-(C25-B25) -> 1400.0168 | D26: =-(D25-C25) -> 5599.9973 | E26: =-(E25-D25) -> 6300.0054 | F26: =SUM(B26:E26) -> 11900.019 | G26: ＝ 本季余额 − 上季余额。余额法，不再用「占收入增量比」
A27: ＝ 自由现金流 FCFF | B27: =B21+B22+B23+B24+B26 -> 27434 | C27: =C21+C22+C23+C24+C26 -> 27075.004 | D27: =D21+D22+D23+D24+D26 -> 23034.189 | E27: =E21+E22+E23+E24+E26 -> 15668.697 | F27: =SUM(B27:E27) -> 93211.891 | G27: ＝ NOPAT + D&A − 资本开支 + 政府补贴 − ΔNWC
A28: 口径说明：这里算的是 FCFF（企业自由现金流），所以税按 EBIT 计、不扣利息——利息的价值已经体现在折现率里。公司目前零负债，FCFF 与 FCFE 的差异只剩利息收入。
A30: 02 FY2028–FY2032 年度预测 + 永续
A31: 科目（百万美元） | B31: FY2027 | C31: FY2028 | D31: FY2029 | E31: FY2030 | F31: FY2031 | G31: FY2032 | H31: 永续期 | I31: 变量怎么来的
A32: 营业收入 | B32: =F13 -> 176999.93 | C32: =B32*(1+-0.35) -> 115049.95 | D32: =C32*(1+-0.08+$B$197) -> 105845.96 | E32: =D32*(1+0.14+$B$197) -> 120664.39 | F32: =E32*(1+0.12+$B$197) -> 135144.12 | G32: =F32*(1+0.08+$B$197) -> 145955.65 | H32: =G32*(1+$B$213) -> 149604.54 | I32: FY27 取季度合计；FY28 ＝ 情形设定增速；FY29–32 ＝ 情形增速 + 控制台「长期增速平移」
A33: 收入增速 YoY | B33: =B32/'00-三表与联动'!F27-1 -> 0.3725287 | C33: =C32/B32-1 -> -0.35 | D33: =D32/C32-1 -> -0.08 | E33: =E32/D32-1 -> 0.14 | F33: =F32/E32-1 -> 0.12 | G33: =G32/F32-1 -> 0.08 | H33: =$B$213 -> 0.025 | I33: 逐年同比。FY26 实际为 +175%
A34: 毛利率 | B34: =F16/F13 -> 0.73401133 | C34: =MAX(0.05,MIN(0.92,0.38+$B$193)) -> 0.38 | D34: =MAX(0.05,MIN(0.92,0.33+$B$193)) -> 0.33 | E34: =MAX(0.05,MIN(0.92,0.4+$B$193)) -> 0.4 | F34: =MAX(0.05,MIN(0.92,0.43+$B$193)) -> 0.43 | G34: =$B$195 -> 0.43 | H34: =G34 -> 0.43 | I34: 情形设定的年度毛利率 + 控制台「毛利率平移」；FY32 直接取控制台「终局毛利率」
A35: 毛利 | B35: =B32*B34 -> 129919.95 | C35: =C32*C34 -> 43718.982 | D35: =D32*D34 -> 34929.166 | E35: =E32*E34 -> 48265.756 | F35: =F32*F34 -> 58111.971 | G35: =G32*G34 -> 62760.928 | H35: =H32*H34 -> 64329.952 | I35: ＝ 收入 × 毛利率
A36: 营业费用 | B36: =B32*$B$199 -> 9734.996 | C36: =C32*$B$199 -> 6327.7474 | D36: =D32*$B$199 -> 5821.5276 | E36: =E32*$B$199 -> 6636.5415 | F36: =F32*$B$199 -> 7432.9265 | G36: =G32*$B$199 -> 8027.5606 | H36: =H32*$B$199 -> 8228.2496 | I36: ＝ 收入 × 控制台「营业费用率」
A37: 营业利润 EBIT | B37: =B35-B36 -> 120184.96 | C37: =C35-C36 -> 37391.235 | D37: =D35-D36 -> 29107.638 | E37: =E35-E36 -> 41629.215 | F37: =F35-F36 -> 50679.044 | G37: =G35-G36 -> 54733.368 | H37: =H35-H36 -> 56101.702 | I37: ＝ 毛利 − 营业费用
A38: 营业利润率 | B38: =B37/B32 -> 0.67901133 | C38: =C37/C32 -> 0.325 | D38: =D37/D32 -> 0.275 | E38: =E37/E32 -> 0.345 | F38: =F37/F32 -> 0.375 | G38: =G37/G32 -> 0.375 | H38: =H37/H32 -> 0.375 | I38: ＝ EBIT ÷ 收入。可与投资者日目标「约 75%」对照
A39: 税后经营利润 NOPAT | B39: =B37*(1-$B$201) -> 98551.664 | C39: =C37*(1-$B$201) -> 30660.813 | D39: =D37*(1-$B$201) -> 23868.263 | E39: =E37*(1-$B$201) -> 34135.956 | F39: =F37*(1-$B$201) -> 41556.816 | G39: =G37*(1-$B$201) -> 44881.362 | H39: =H37*(1-$B$201) -> 46003.396 | I39: ＝ EBIT ×(1 − 有效税率)
A40: ＋ 折旧摊销 D&A | B40: =B32*$B$207 -> 18584.992 | C40: =C32*$B$207 -> 12080.245 | D40: =D32*$B$207 -> 11113.825 | E40: =E32*$B$207 -> 12669.761 | F40: =F32*$B$207 -> 14190.132 | G40: =G32*$B$207 -> 15325.343 | H40: =H32*$B$207 -> 15708.477 | I40: ＝ 收入 × 控制台「折旧摊销率」。★ 折旧跟随资产基数而非收入，收入下行年该比例会被动上升
A41: − 资本开支（总额） | B41: =-B32*$B$203 -> -40709.983 | C41: =-C32*$B$203 -> -26461.489 | D41: =-D32*$B$203 -> -24344.57 | E41: =-E32*$B$203 -> -27752.81 | F41: =-F32*$B$203 -> -31083.147 | G41: =-G32*$B$203 -> -33569.799 | H41: =-H32*$B$203 -> -34409.044 | I41: ＝ 收入 × 控制台「资本开支率」
A42: ＋ CHIPS 政府补贴抵扣 | B42: =-B41*$B$205 -> 4885.198 | C42: =-C41*$B$205 -> 3175.3787 | D42: =-D41*$B$205 -> 2921.3484 | E42: =-E41*$B$205 -> 3330.3372 | F42: =-F41*$B$205 -> 3729.9777 | G42: =-G41*$B$205 -> 4028.3759 | H42: =-H41*$B$205 -> 4129.0853 | I42: ＝ 资本开支 × 控制台「政府补贴抵扣比例」
A43: 营运资本余额 | B43: =B32*$B$209 -> 30974.987 | C43: =C32*$B$209 -> 20133.742 | D43: =D32*$B$209 -> 18523.042 | E43: =E32*$B$209 -> 21116.268 | F43: =F32*$B$209 -> 23650.221 | G43: =G32*$B$209 -> 25542.238 | H43: =H32*$B$209 -> 26180.794 | I43: ＝ 控制台「营运资本占年化收入比」× 当年收入。期初取 FY26 Q4 年化收入 × 同一比例
A44: − 营运资本增加 ΔNWC | B44: =-(B43-'00-三表与联动'!E27*4*$B$209) -> 4025.0126 | C44: =-(C43-B43) -> 10841.246 | D44: =-(D43-C43) -> 1610.6993 | E44: =-(E43-D43) -> -2593.2259 | F44: =-(F43-E43) -> -2533.9522 | G44: =-(G43-F43) -> -1892.0176 | H44: =-(H43-G43) -> -638.55596 | I44: ＝ 本年余额 − 上年余额（余额法）
A45: ＝ 自由现金流 FCFF | B45: =B39+B40+B41+B42+B44 -> 85336.884 | C45: =C39+C40+C41+C42+C44 -> 30296.193 | D45: =D39+D40+D41+D42+D44 -> 15169.566 | E45: =E39+E40+E41+E42+E44 -> 19790.019 | F45: =F39+F40+F41+F42+F44 -> 25859.827 | G45: =G39+G40+G41+G42+G44 -> 28773.264 | H45: =H39+H40+H41+H42+H44 -> 30793.358 | I45: ＝ NOPAT + D&A − 资本开支 + 政府补贴 − ΔNWC。★ 估值采用的是这一行，不是季度块
A46: FCFF 利润率 | B46: =B45/B32 -> 0.48212948 | C46: =C45/C32 -> 0.26333077 | D46: =D45/D32 -> 0.14331739 | E46: =E45/E32 -> 0.16400877 | F46: =F45/F32 -> 0.19135 | G46: =G45/G32 -> 0.19713704 | H46: =H45/H32 -> 0.20583171 | I46: ＝ FCFF ÷ 收入。可与投资者日「调整后自由现金流率约 50%」对照（口径不同，见溯源表）
A47: 折现期（年，期中折现） | B47: =0.5 -> 0.5 | C47: =1.5 -> 1.5 | D47: =2.5 -> 2.5 | E47: =3.5 -> 3.5 | F47: =4.5 -> 4.5 | G47: =5.5 -> 5.5 | H47: — | I47: 期中折现法：第 n 年的折现期为 n − 0.5，假设现金流在年内均匀发生
A48: 折现因子 | B48: =1/(1+$B$211)^B47 -> 0.94072087 | C48: =1/(1+$B$211)^C47 -> 0.83249634 | D48: =1/(1+$B$211)^D47 -> 0.73672243 | E48: =1/(1+$B$211)^E47 -> 0.65196675 | F48: =1/(1+$B$211)^F47 -> 0.57696173 | G48: =1/(1+$B$211)^G47 -> 0.5105856 | H48: — | I48: ＝ 1 ÷ (1 + WACC)^折现期
A49: 折现后 FCFF 现值 | B49: =B45*B48 -> 80278.188 | C49: =C45*C48 -> 25221.47 | D49: =D45*D48 -> 11175.76 | E49: =E45*E48 -> 12902.434 | F49: =F45*F48 -> 14920.13 | G49: =G45*G48 -> 14691.214 | H49: — | I49: ＝ FCFF × 折现因子
A51: 03 折现率 WACC（MU 为净现金结构，WACC ≈ 股权成本）
A52: 参数 | B52: 取值 | D52: 来源与说明
A53: 无风险利率 Rf | B53: ='00-三表与联动'!$B$14 -> 0.042 | D53: 10 年期美国国债收益率，取 4.20%
A54: 股权风险溢价 ERP | B54: ='00-三表与联动'!$B$15 -> 0.05 | D54: 美国成熟市场长期 ERP，取 5.00%
A55: 贝塔 β（隐含） | B55: =(B56-B53)/B54 -> 1.76 | D55: ★ 由控制台 WACC 反解：β = (WACC − Rf) ÷ ERP。MU 有足够长的交易历史，但 52 周振幅 $114.25–$1,255.00 使得任何时点的回归 β 都高度依赖窗口选择，因此本模型的做法是直接设定 WACC、反算隐含 β 供你判断合理性。
A56: 股权成本 Ke = WACC | B56: =$B$211 -> 0.13 | D56: 控制台滑标直接给定
A57: 有息负债 / 总资本 | B57: 0.0056 | D57: ＝ 有息负债 $5,722M ÷（有息负债 + 市值 $1.02 万亿）。MU 已从 FY25 末的 $145.8 亿债务降到 $57.2 亿，加权平均到期日 2034 年 8 月。占总资本不足 1%，对 WACC 的影响可忽略，故直接用 Ke 近似 WACC。
A58: 净现金（现金及投资 − 有息负债） | B58: 24433 | D58: 现金及可交易投资 $30,155M − 有息负债 $5,722M。在下方估值桥中单独加回。
A60: 04 估值：从终值到每股内在价值
A61: 步骤 | B61: 金额（百万美元） | D61: 计算方式与说明
A62: ① 预测期 FCFF 现值合计 | B62: =SUM(B49:G49) -> 159189.2 | D62: FY2027–FY2032 六年折现值加总（期中折现）
A63: ② 终值 TV（永续增长法） | B63: =H45/($B$211-$B$213) -> 293270.07 | D63: ＝ 永续期 FCFF ÷ (WACC − g)。★ 若 WACC ≤ g 公式失效，控制台已把 g 上限设在 6%
A64: ③ 终值现值 PV(TV) | B64: =B63*G48/(1+$B$211)^0.5 -> 140863.05 | D64: 用 FY32 的折现因子再折半年，与期中折现保持一致
A65: ④ 终值占企业价值比重 | B65: =B64/B66 -> 0.46946174 | D65: ★ 这个比例越高，说明估值越依赖你对永续期的猜测，而不是可见的现金流
A66: ⑤ 企业价值 EV | B66: =B62+B64 -> 300052.24 | D66: ＝ ① + ③
A67: ⑥ ＋ 现金及可交易投资 | B67: ='00-三表与联动'!$B$10 -> 30155 | D67: FY26 Q3末 $30,155M（现金 24,995 + 短期投资 1,027 + 长期可交易投资 4,106 + 受限现金 27）
A68: ⑦ ＋ 政府补贴应收/其他非经营资产 | B68: 0 | D68: MU 的现金及可交易投资已包含短期与长期投资，此处不再重复计入，置 0
A69: ⑧ − 有息负债 | B69: =-'00-三表与联动'!$B$11 -> -5722 | D69: FY26 Q3末 $5,722M。已从 FY25 末的 $14,577M 大幅下降，加权平均到期日 2034 年 8 月
A70: ⑨ 股权价值 | B70: =B66+B67+B68+B69 -> 324485.24 | D70: ＝ EV + 净现金
A71: ⑩ 摊薄股数（百万股） | B71: ='00-三表与联动'!$B$9 -> 1150 | D71: 公司 FY27 Q1 指引「约 155」
A72: ⑪ 每股内在价值 | B72: =B70/B71 -> 282.16108 | D72: ＝ 股权价值 ÷ 摊薄股数
A73: ⑫ 当前股价 | B73: ='00-三表与联动'!$B$6 -> 903.09 | D73: 2026-08-26 盘中 $1,500.17
A74: ⑬ 相对现价的上行/下行 | B74: =B72/B73-1 -> -0.6875604 | D74: ★ 正数 = 模型认为被低估；负数 = 被高估
A75: ★ 请先看第 ④ 行「终值占企业价值比重」再看第 ⑬ 行的结论。对一个处在周期顶点的存储公司，如果终值占比超过 70%，那么这个 DCF 实际上不是在给现金流定价，而是在给你对 2032 年之后 NAND 行业格局的猜测定价。
A77: 05 交叉验证：退出倍数法与相对估值
A78: 方法 | B78: 关键输入 | D78: 隐含结果 | F78: 说明
A79: 永续增长法隐含的退出 EV/EBITDA | D79: =B63/(G37+G40) -> 4.1860615 | F79: ＝ 终值 ÷ FY32 EBITDA。若这个倍数远高于半导体行业常见的 8–14x，说明永续增长率给得过于激进
A80: 永续增长法隐含的退出 EV/收入 | D80: =B63/G32 -> 2.0093095 | F80: ＝ 终值 ÷ FY32 收入
A81: 本模型每股价值 ÷ FY27 每股 FCFF | D81: =B72/(F27/'00-三表与联动'!$B$9) -> 3.4811572 | F81: 把内在价值换算成 FY27 自由现金流的倍数，便于与同业横比
A82: 当前股价隐含的 FY27 P/FCFF | D82: ='00-三表与联动'!$B$6/(F27/'00-三表与联动'!$B$9) -> 11.141856 | F82: 市场正在为 FY27 的自由现金流付多少倍
A83: 当前市值 ÷ 本模型股权价值 | D83: ='00-三表与联动'!$B$6*'00-三表与联动'!$B$9/B70 -> 3.2006186 | F83: 大于 1 = 市场比模型乐观
A85: 06 回购与每股收益：EPS × P/E 交叉估值（与 DCF 并排看）
A86: 为什么要做这一块：DCF 给的是「整个企业值多少钱」，它对回购是中性的——按公允价值回购既不创造也不毁灭价值。但管理层已承诺把 100% 的剩余现金用于回购，股数会大幅下降，所以从「持有不卖的股东」角度看，每股口径会变。这一节把回购显式建模：股数逐年递减 → 经营性 EPS 抬升 → 用当年的 P/E 给一个价格 → 折回今天，再与 DCF 的结果并排比较。
A87: ★ 关于 P/E：本节不再用同一个倍数乘所有年份。FY2027、FY2028、FY2032 各有独立滑标，FY29–FY31 在 FY28 与 FY32 之间线性过渡。原因是周期股的 P/E 与盈利反向：盈利高点（FY27）市场给的倍数最低，盈利回落年（FY28）分母掉得比股价快、倍数反而扩张，终局年（FY32）回到正常中枢。用一个固定倍数乘所有年份，会系统性高估高点年份的目标价。
A88: ★ 关于回购均价：＝ 当前股价 × 倍数 ×(1+WACC)^(t−0.5)。让回购价按折现率复利，是「市场对股票定价合理」的中性假设。如果假设股价六年不动，模型会机械地算出巨额增厚——那是假的。有了这个设定，当 FY32 的 P/E 等于「本 DCF 隐含的退出 P/E」时，两种方法应当收敛。
A89: 科目 | B89: FY2027 | C89: FY2028 | D89: FY2029 | E89: FY2030 | F89: FY2031 | G89: FY2032 | H89: 口径与说明
A90: 自由现金流 FCFF | B90: =B45 -> 85336.884 | C90: =C45 -> 30296.193 | D90: =D45 -> 15169.566 | E90: =E45 -> 19790.019 | F90: =F45 -> 25859.827 | G90: =G45 -> 28773.264 | H90: 链接自上方年度预测表
A91: × 回购比例 | B91: =$B$133 -> 1 | C91: =$B$133 -> 1 | D91: =$B$133 -> 1 | E91: =$B$133 -> 1 | F91: =$B$133 -> 1 | G91: =$B$133 -> 1 | H91: 本节内控制台滑标，默认 100%（管理层承诺返还 100% 剩余现金）
A92: ＝ 用于回购的金额 | B92: =MAX(0,B90*B91) -> 85336.884 | C92: =MAX(0,C90*C91) -> 30296.193 | D92: =MAX(0,D90*D91) -> 15169.566 | E92: =MAX(0,E90*E91) -> 19790.019 | F92: =MAX(0,F90*F91) -> 25859.827 | G92: =MAX(0,G90*G91) -> 28773.264 | H92: ＝ MAX(0, FCFF × 回购比例)。FCFF 为负时不回购
A93: 回购均价（美元/股） | B93: ='00-三表与联动'!$B$6*$B$135*(1+$B$211)^0.5 -> 959.99784 | C93: ='00-三表与联动'!$B$6*$B$135*(1+$B$211)^1.5 -> 1084.7976 | D93: ='00-三表与联动'!$B$6*$B$135*(1+$B$211)^2.5 -> 1225.8212 | E93: ='00-三表与联动'!$B$6*$B$135*(1+$B$211)^3.5 -> 1385.178 | F93: ='00-三表与联动'!$B$6*$B$135*(1+$B$211)^4.5 -> 1565.2511 | G93: ='00-三表与联动'!$B$6*$B$135*(1+$B$211)^5.5 -> 1768.7338 | H93: ＝ 当前股价 × 本节滑标倍数 ×(1+WACC)^(t−0.5)
A94: − 回购注销股数（百万股） | B94: =B92/B93 -> 88.892788 | C94: =C92/C93 -> 27.927969 | D94: =D92/D93 -> 12.375023 | E94: =E92/E93 -> 14.286986 | F94: =F92/F93 -> 16.5212 | G94: =G92/G93 -> 16.267719 | H94: ＝ 回购金额 ÷ 回购均价
A95: ＋ 股权激励新增股数（百万股） | B95: =B32*0.0115/B93 -> 2.1203164 | C95: =C32*0.0115/C93 -> 1.219651 | D95: =D32*0.0115/D93 -> 0.99299022 | E95: =E32*0.0115/E93 -> 1.0017777 | F95: =F32*0.0115/F93 -> 0.99291246 | G95: =G32*0.0115/G93 -> 0.94897828 | H95: ＝ 收入 × 1.15% ÷ 回购均价。FY26 股份支付 $232M ÷ 收入 $20,248M ＝ 1.15%
A96: 期初摊薄股数（百万股） | B96: ='00-三表与联动'!$B$9 -> 1150 | C96: =B97 -> 1063.2275 | D96: =C97 -> 1036.5192 | E96: =D97 -> 1025.1372 | F96: =E97 -> 1011.852 | G96: =F97 -> 996.32368 | H96: FY27 期初取公司指引的 155；其后为上年期末
A97: 期末摊薄股数（百万股） | B97: =MAX(20,B96-B94+B95) -> 1063.2275 | C97: =MAX(20,C96-C94+C95) -> 1036.5192 | D97: =MAX(20,D96-D94+D95) -> 1025.1372 | E97: =MAX(20,E96-E94+E95) -> 1011.852 | F97: =MAX(20,F96-F94+F95) -> 996.32368 | G97: =MAX(20,G96-G94+G95) -> 981.00494 | H97: ＝ 期初 − 回购注销 + 股权激励新增，下限锁 20
A98: 净现金余额 | B98: =('00-三表与联动'!$B$10-'00-三表与联动'!$B$11)+B90-B92 -> 24433 | C98: =B98+C90-C92 -> 24433 | D98: =C98+D90-D92 -> 24433 | E98: =D98+E90-E92 -> 24433 | F98: =E98+F90-F92 -> 24433 | G98: =F98+G90-G92 -> 24433 | H98: ＝ 上期净现金 + FCFF − 回购金额。★ 回购比例＜100% 时现金会累积，这部分价值必须计入，否则会低估
A99: 税后经营利润 NOPAT | B99: =B39 -> 98551.664 | C99: =C39 -> 30660.813 | D99: =D39 -> 23868.263 | E99: =E39 -> 34135.956 | F99: =F39 -> 41556.816 | G99: =G39 -> 44881.362 | H99: 链接自上方年度预测表。★ 用 NOPAT 而非净利润，是为了与 DCF 同口径（不含利息）
A100: 经营性每股收益 EPS | B100: =B99/B97 -> 92.691039 | C100: =C99/C97 -> 29.580554 | D100: =D99/D97 -> 23.282995 | E100: =E99/E97 -> 33.736117 | F100: =F99/F97 -> 41.710156 | G100: =G99/G97 -> 45.750393 | H100: ＝ NOPAT ÷ 期末股数。用期末股数而非加权平均，因为要回答的是「那个时点每一股值多少」
A101: 每股净现金 | B101: =B98/B97 -> 22.98003 | C101: =C98/C97 -> 23.572163 | D101: =D98/D97 -> 23.833883 | E101: =E98/E97 -> 24.146813 | F101: =F98/F97 -> 24.523155 | G101: =G98/G97 -> 24.906093 | H101: ＝ 净现金余额 ÷ 期末股数
A102: ★ 采用的 P/E 倍数 | B102: =$B$137 -> 4 | C102: =$B$139 -> 7 | D102: =$B$139+($B$141-$B$139)*1/4 -> 7.5 | E102: =$B$139+($B$141-$B$139)*2/4 -> 8 | F102: =$B$139+($B$141-$B$139)*3/4 -> 8.5 | G102: =$B$141 -> 9 | H102: FY27 / FY28 / FY32 各由本节独立滑标给定；FY29–FY31 在 FY28 与 FY32 之间线性过渡（四等分）
A103: 隐含股价（EPS×当年PE + 每股净现金） | B103: =B100*B102+B101 -> 393.74419 | C103: =C100*C102+C101 -> 230.63604 | D103: =D100*D102+D101 -> 198.45634 | E103: =E100*E102+E101 -> 294.03575 | F103: =F100*F102+F101 -> 379.05948 | G103: =G100*G102+G101 -> 436.65963 | H103: 把现金单独加回，使本方法与 DCF（EV + 净现金）口径一致
A104: 折现因子（期末折现） | B104: =1/(1+$B$211)^1 -> 0.88495575 | C104: =1/(1+$B$211)^2 -> 0.78314668 | D104: =1/(1+$B$211)^3 -> 0.69305016 | E104: =1/(1+$B$211)^4 -> 0.61331873 | F104: =1/(1+$B$211)^5 -> 0.54275994 | G104: =1/(1+$B$211)^6 -> 0.48031853 | H104: ＝ 1 ÷ (1+WACC)^t。股价是时点数用期末折现；上方 DCF 的现金流是期间数用期中折现
A105: 折现后每股价值 | B105: =B103*B104 -> 348.44618 | C105: =C103*C104 -> 180.62185 | D105: =D103*D104 -> 137.5402 | E105: =E103*E104 -> 180.33763 | F105: =F103*F104 -> 205.7383 | G105: =G103*G104 -> 209.73571 | H105: ＝ 隐含股价 × 折现因子
A107: 6.1 三个关键年份的目标价：各用各的 P/E
A108: 年份 | B108: 经营性 EPS | C108: 每股净现金 | D108: 采用 P/E | E108: 隐含目标价 | F108: 折现期（年） | G108: 折现后每股价值 | H108: 折现后 ÷ 现价 − 1 | I108: 这个数字回答什么
...

Sheet 02-DCF-基准
A1: BASE · MU 现金流折现模型 —— 基准情形
A2: FY2027 分四个季度 → FY2028–FY2032 按年 → 永续 | 自由现金流口径：FCFF（资本开支扣除 CHIPS 补贴后） | ▼ 全部参数由本表底部的参数控制台滑标驱动
A4: 00 本情形的论点：这套数字建立在什么判断之上
A5: 以公司 FY26 Q4 指引（收入 $500 亿、毛利率约 86%）为起点。管理层称供需紧张将持续到 2027 日历年之后，但本情形不完全接受「周期已被 SCA 消灭」。★ 关键差异：MU 约 76% 收入来自 DRAM，而《缺口的算术》的结论是NAND 在 2027 年转过剩、DRAM 仍然偏紧——这意味着 MU 的下行风险结构性小于纯 NAND 标的。本情形假设 FY27 见顶、FY28 温和回落一年，之后毛利率稳定在 68%–72% 的新中枢。
A6: 1．FY27 Q1 取 $530 亿（较 FY26 Q4 指引 $500 亿环比 +6%），全年 $2,050 亿
A7: 2．FY28 收入 −20%：一次温和的价格修正，而非崩塌；DRAM 的紧张度好于 NAND
A8: 3．★ SCA 覆盖约 20% DRAM 量 + 三分之一 NAND 量、$1,000 亿最低合约收入，构成价格地板但不是全部
A9: 4．终局毛利率 68%，远高于 FY25 的 40.2%，但低于当前的 86%
A11: 01 FY2027 季度预测（先用季度把最近的可见度做实，再转年度）
A12: 科目（百万美元） | B12: FY27 Q1 | C12: FY27 Q2 | D12: FY27 Q3 | E12: FY27 Q4 | F12: FY2027 合计 | G12: 变量怎么来的
A13: 营业收入 | B13: =$B$189 -> 53000 | C13: =B13*(1+0.037736+$B$191) -> 55000.008 | D13: =C13*(1+-0.054545+$B$191) -> 52000.033 | E13: =D13*(1+-0.134615+$B$191) -> 45000.048 | F13: =SUM(B13:E13) -> 205000.09 | G13: Q1 ＝ 控制台滑标（官方指引 $10.3–10.8B）；Q2–Q4 ＝ 上一季 ×(1 + 情形环比增速 + 滑标平移)
A14: 环比增速 QoQ | B14: =B13/'00-三表与联动'!E27-1 -> 0.06 | C14: =C13/B13-1 -> 0.037736 | D14: =D13/C13-1 -> -0.054545 | E14: =E13/D13-1 -> -0.134615 | F14: =F13/'00-三表与联动'!F27-1 -> 0.58965321 | G14: Q1 的环比基数是 FY26 Q4 的 $8,965M（不是 FY26 全年）；Q2–Q4 为上一季
A15: 毛利率 | B15: =MAX(0.05,MIN(0.92,0.86+$B$193)) -> 0.86 | C15: =MAX(0.05,MIN(0.92,0.855+$B$193)) -> 0.855 | D15: =MAX(0.05,MIN(0.92,0.82+$B$193)) -> 0.82 | E15: =MAX(0.05,MIN(0.92,0.76+$B$193)) -> 0.76 | F15: =F16/F13 -> 0.82656096 | G15: 情形设定的季度毛利率路径 + 控制台「毛利率平移」，上下限锁在 5%–92%
A16: 毛利 | B16: =B13*B15 -> 45580 | C16: =C13*C15 -> 47025.007 | D16: =D13*D15 -> 42640.027 | E16: =E13*E15 -> 34200.037 | F16: =SUM(B16:E16) -> 169445.07 | G16: ＝ 收入 × 毛利率
A17: 营业费用 | B17: =B13*$B$199 -> 2226 | C17: =C13*$B$199 -> 2310.0003 | D17: =D13*$B$199 -> 2184.0014 | E17: =E13*$B$199 -> 1890.002 | F17: =SUM(B17:E17) -> 8610.0037 | G17: ＝ 收入 × 控制台「营业费用率」。公司 FY27 Q1 GAAP 指引为 $574–614M
A18: 营业利润 EBIT | B18: =B16-B17 -> 43354 | C18: =C16-C17 -> 44715.007 | D18: =D16-D17 -> 40456.025 | E18: =E16-E17 -> 32310.035 | F18: =SUM(B18:E18) -> 160835.07 | G18: ＝ 毛利 − 营业费用
A19: 营业利润率 | B19: =B18/B13 -> 0.818 | C19: =C18/C13 -> 0.813 | D19: =D18/D13 -> 0.778 | E19: =E18/E13 -> 0.718 | F19: =F18/F13 -> 0.78456096 | G19: ＝ EBIT ÷ 收入
A20: 所得税 | B20: =MAX(0,B18)*$B$201 -> 7153.41 | C20: =MAX(0,C18)*$B$201 -> 7377.9761 | D20: =MAX(0,D18)*$B$201 -> 6675.2442 | E20: =MAX(0,E18)*$B$201 -> 5331.1557 | F20: =SUM(B20:E20) -> 26537.786 | G20: ＝ EBIT × 控制台「有效税率」（FCFF 口径按 EBIT 计税，不含利息）
A21: 税后经营利润 NOPAT | B21: =B18-B20 -> 36200.59 | C21: =C18-C20 -> 37337.03 | D21: =D18-D20 -> 33780.781 | E21: =E18-E20 -> 26978.879 | F21: =SUM(B21:E21) -> 134297.28 | G21: ＝ EBIT − 所得税
A22: ＋ 折旧摊销 D&A | B22: =B13*$B$207 -> 3975 | C22: =C13*$B$207 -> 4125.0006 | D22: =D13*$B$207 -> 3900.0024 | E22: =E13*$B$207 -> 3375.0036 | F22: =SUM(B22:E22) -> 15375.007 | G22: ＝ 收入 × 控制台「折旧摊销率」。FY26 前九个月 $6,862M，全年约 $94 亿（占收入 7.3%）。★ MU 自建晶圆厂，折旧全部落在自己报表上
A23: − 资本开支（总额） | B23: =-B13*$B$203 -> -9540 | C23: =-C13*$B$203 -> -9900.0014 | D23: =-D13*$B$203 -> -9360.0059 | E23: =-E13*$B$203 -> -8100.0087 | F23: =SUM(B23:E23) -> -36900.016 | G23: ＝ 收入 × 控制台「资本开支率」。FY26 约 $270 亿；管理层已指引 FY27 季度资本开支高于 FY26 Q4 的约 $100 亿/季
A24: ＋ CHIPS 政府补贴抵扣 | B24: =-B23*$B$205 -> 954 | C24: =-C23*$B$205 -> 990.00014 | D24: =-D23*$B$205 -> 936.00059 | E24: =-E23*$B$205 -> 810.00087 | F24: =SUM(B24:E24) -> 3690.0016 | G24: ＝ 资本开支 × 控制台「政府补贴抵扣比例」。FY26 前九个月收到 $2,989M，占同期资本开支 15.2%
A25: 营运资本余额 | B25: =B13*4*$B$209 -> 31800 | C25: =C13*4*$B$209 -> 33000.005 | D25: =D13*4*$B$209 -> 31200.02 | E25: =E13*4*$B$209 -> 27000.029 | F25: =E25 -> 27000.029 | G25: ＝ 控制台「营运资本占年化收入比」× 当季收入 × 4。期初取 FY26 Q4 的年化收入基准
A26: − 营运资本增加 ΔNWC | B26: =-(B25-'00-三表与联动'!E27*4*$B$209) -> -1800 | C26: =-(C25-B25) -> -1200.0048 | D26: =-(D25-C25) -> 1799.9853 | E26: =-(E25-D25) -> 4199.9906 | F26: =SUM(B26:E26) -> 2999.9711 | G26: ＝ 本季余额 − 上季余额。余额法，不再用「占收入增量比」
A27: ＝ 自由现金流 FCFF | B27: =B21+B22+B23+B24+B26 -> 29789.59 | C27: =C21+C22+C23+C24+C26 -> 31352.025 | D27: =D21+D22+D23+D24+D26 -> 31056.764 | E27: =E21+E22+E23+E24+E26 -> 27263.865 | F27: =SUM(B27:E27) -> 119462.24 | G27: ＝ NOPAT + D&A − 资本开支 + 政府补贴 − ΔNWC
A28: 口径说明：这里算的是 FCFF（企业自由现金流），所以税按 EBIT 计、不扣利息——利息的价值已经体现在折现率里。公司目前零负债，FCFF 与 FCFE 的差异只剩利息收入。
A30: 02 FY2028–FY2032 年度预测 + 永续
A31: 科目（百万美元） | B31: FY2027 | C31: FY2028 | D31: FY2029 | E31: FY2030 | F31: FY2031 | G31: FY2032 | H31: 永续期 | I31: 变量怎么来的
A32: 营业收入 | B32: =F13 -> 205000.09 | C32: =B32*(1+-0.2) -> 164000.07 | D32: =C32*(1+0.12+$B$197) -> 183680.08 | E32: =D32*(1+0.14+$B$197) -> 209395.29 | F32: =E32*(1+0.12+$B$197) -> 234522.73 | G32: =F32*(1+0.1+$B$197) -> 257975 | H32: =G32*(1+$B$213) -> 265714.25 | I32: FY27 取季度合计；FY28 ＝ 情形设定增速；FY29–32 ＝ 情形增速 + 控制台「长期增速平移」
A33: 收入增速 YoY | B33: =B32/'00-三表与联动'!F27-1 -> 0.58965321 | C33: =C32/B32-1 -> -0.2 | D33: =D32/C32-1 -> 0.12 | E33: =E32/D32-1 -> 0.14 | F33: =F32/E32-1 -> 0.12 | G33: =G32/F32-1 -> 0.1 | H33: =$B$213 -> 0.03 | I33: 逐年同比。FY26 实际为 +175%
A34: 毛利率 | B34: =F16/F13 -> 0.82656096 | C34: =MAX(0.05,MIN(0.92,0.68+$B$193)) -> 0.68 | D34: =MAX(0.05,MIN(0.92,0.7+$B$193)) -> 0.7 | E34: =MAX(0.05,MIN(0.92,0.72+$B$193)) -> 0.72 | F34: =MAX(0.05,MIN(0.92,0.7+$B$193)) -> 0.7 | G34: =$B$195 -> 0.68 | H34: =G34 -> 0.68 | I34: 情形设定的年度毛利率 + 控制台「毛利率平移」；FY32 直接取控制台「终局毛利率」
A35: 毛利 | B35: =B32*B34 -> 169445.07 | C35: =C32*C34 -> 111520.05 | D35: =D32*D34 -> 128576.06 | E35: =E32*E34 -> 150764.61 | F35: =F32*F34 -> 164165.91 | G35: =G32*G34 -> 175423 | H35: =H32*H34 -> 180685.69 | I35: ＝ 收入 × 毛利率
A36: 营业费用 | B36: =B32*$B$199 -> 8610.0037 | C36: =C32*$B$199 -> 6888.003 | D36: =D32*$B$199 -> 7714.5633 | E36: =E32*$B$199 -> 8794.6022 | F36: =F32*$B$199 -> 9849.9545 | G36: =G32*$B$199 -> 10834.95 | H36: =H32*$B$199 -> 11159.998 | I36: ＝ 收入 × 控制台「营业费用率」
A37: 营业利润 EBIT | B37: =B35-B36 -> 160835.07 | C37: =C35-C36 -> 104632.05 | D37: =D35-D36 -> 120861.49 | E37: =E35-E36 -> 141970.01 | F37: =F35-F36 -> 154315.95 | G37: =G35-G36 -> 164588.05 | H37: =H35-H36 -> 169525.69 | I37: ＝ 毛利 − 营业费用
A38: 营业利润率 | B38: =B37/B32 -> 0.78456096 | C38: =C37/C32 -> 0.638 | D38: =D37/D32 -> 0.658 | E38: =E37/E32 -> 0.678 | F38: =F37/F32 -> 0.658 | G38: =G37/G32 -> 0.638 | H38: =H37/H32 -> 0.638 | I38: ＝ EBIT ÷ 收入。可与投资者日目标「约 75%」对照
A39: 税后经营利润 NOPAT | B39: =B37*(1-$B$201) -> 134297.28 | C39: =C37*(1-$B$201) -> 87367.758 | D39: =D37*(1-$B$201) -> 100919.35 | E39: =E37*(1-$B$201) -> 118544.96 | F39: =F37*(1-$B$201) -> 128853.82 | G39: =G37*(1-$B$201) -> 137431.02 | H39: =H37*(1-$B$201) -> 141553.95 | I39: ＝ EBIT ×(1 − 有效税率)
A40: ＋ 折旧摊销 D&A | B40: =B32*$B$207 -> 15375.007 | C40: =C32*$B$207 -> 12300.005 | D40: =D32*$B$207 -> 13776.006 | E40: =E32*$B$207 -> 15704.647 | F40: =F32*$B$207 -> 17589.204 | G40: =G32*$B$207 -> 19348.125 | H40: =H32*$B$207 -> 19928.569 | I40: ＝ 收入 × 控制台「折旧摊销率」。★ 折旧跟随资产基数而非收入，收入下行年该比例会被动上升
A41: − 资本开支（总额） | B41: =-B32*$B$203 -> -36900.016 | C41: =-C32*$B$203 -> -29520.013 | D41: =-D32*$B$203 -> -33062.414 | E41: =-E32*$B$203 -> -37691.152 | F41: =-F32*$B$203 -> -42214.091 | G41: =-G32*$B$203 -> -46435.5 | H41: =-H32*$B$203 -> -47828.565 | I41: ＝ 收入 × 控制台「资本开支率」
A42: ＋ CHIPS 政府补贴抵扣 | B42: =-B41*$B$205 -> 3690.0016 | C42: =-C41*$B$205 -> 2952.0013 | D42: =-D41*$B$205 -> 3306.2414 | E42: =-E41*$B$205 -> 3769.1152 | F42: =-F41*$B$205 -> 4221.4091 | G42: =-G41*$B$205 -> 4643.55 | H42: =-H41*$B$205 -> 4782.8565 | I42: ＝ 资本开支 × 控制台「政府补贴抵扣比例」
A43: 营运资本余额 | B43: =B32*$B$209 -> 30750.013 | C43: =C32*$B$209 -> 24600.011 | D43: =D32*$B$209 -> 27552.012 | E43: =E32*$B$209 -> 31409.294 | F43: =F32*$B$209 -> 35178.409 | G43: =G32*$B$209 -> 38696.25 | H43: =H32*$B$209 -> 39857.137 | I43: ＝ 控制台「营运资本占年化收入比」× 当年收入。期初取 FY26 Q4 年化收入 × 同一比例
A44: − 营运资本增加 ΔNWC | B44: =-(B43-'00-三表与联动'!E27*4*$B$209) -> -750.01331 | C44: =-(C43-B43) -> 6150.0027 | D44: =-(D43-C43) -> -2952.0013 | E44: =-(E43-D43) -> -3857.2817 | F44: =-(F43-E43) -> -3769.1152 | G44: =-(G43-F43) -> -3517.8409 | H44: =-(H43-G43) -> -1160.8875 | I44: ＝ 本年余额 − 上年余额（余额法）
A45: ＝ 自由现金流 FCFF | B45: =B39+B40+B41+B42+B44 -> 115712.26 | C45: =C39+C40+C41+C42+C44 -> 79249.754 | D45: =D39+D40+D41+D42+D44 -> 81987.178 | E45: =E39+E40+E41+E42+E44 -> 96470.284 | F45: =F39+F40+F41+F42+F44 -> 104681.23 | G45: =G39+G40+G41+G42+G44 -> 111469.36 | H45: =H39+H40+H41+H42+H44 -> 117275.92 | I45: ＝ NOPAT + D&A − 资本开支 + 政府补贴 − ΔNWC。★ 估值采用的是这一行，不是季度块
A46: FCFF 利润率 | B46: =B45/B32 -> 0.5644498 | C46: =C45/C32 -> 0.48323 | D46: =D45/D32 -> 0.44635857 | E46: =E45/E32 -> 0.46070895 | F46: =F45/F32 -> 0.44635857 | G46: =G45/G32 -> 0.43209364 | H46: =H45/H32 -> 0.44136107 | I46: ＝ FCFF ÷ 收入。可与投资者日「调整后自由现金流率约 50%」对照（口径不同，见溯源表）
A47: 折现期（年，期中折现） | B47: =0.5 -> 0.5 | C47: =1.5 -> 1.5 | D47: =2.5 -> 2.5 | E47: =3.5 -> 3.5 | F47: =4.5 -> 4.5 | G47: =5.5 -> 5.5 | H47: — | I47: 期中折现法：第 n 年的折现期为 n − 0.5，假设现金流在年内均匀发生
A48: 折现因子 | B48: =1/(1+$B$211)^B47 -> 0.949158 | C48: =1/(1+$B$211)^C47 -> 0.85509729 | D48: =1/(1+$B$211)^D47 -> 0.77035792 | E48: =1/(1+$B$211)^E47 -> 0.69401615 | F48: =1/(1+$B$211)^F47 -> 0.62523977 | G48: =1/(1+$B$211)^G47 -> 0.56327907 | H48: — | I48: ＝ 1 ÷ (1 + WACC)^折现期
A49: 折现后 FCFF 现值 | B49: =B45*B48 -> 109829.22 | C49: =C45*C48 -> 67766.25 | D49: =D45*D48 -> 63159.472 | E49: =E45*E48 -> 66951.935 | F49: =F45*F48 -> 65450.867 | G49: =G45*G48 -> 62788.355 | H49: — | I49: ＝ FCFF × 折现因子
A51: 03 折现率 WACC（MU 为净现金结构，WACC ≈ 股权成本）
A52: 参数 | B52: 取值 | D52: 来源与说明
A53: 无风险利率 Rf | B53: ='00-三表与联动'!$B$14 -> 0.042 | D53: 10 年期美国国债收益率，取 4.20%
A54: 股权风险溢价 ERP | B54: ='00-三表与联动'!$B$15 -> 0.05 | D54: 美国成熟市场长期 ERP，取 5.00%
A55: 贝塔 β（隐含） | B55: =(B56-B53)/B54 -> 1.36 | D55: ★ 由控制台 WACC 反解：β = (WACC − Rf) ÷ ERP。MU 有足够长的交易历史，但 52 周振幅 $114.25–$1,255.00 使得任何时点的回归 β 都高度依赖窗口选择，因此本模型的做法是直接设定 WACC、反算隐含 β 供你判断合理性。
A56: 股权成本 Ke = WACC | B56: =$B$211 -> 0.11 | D56: 控制台滑标直接给定
A57: 有息负债 / 总资本 | B57: 0.0056 | D57: ＝ 有息负债 $5,722M ÷（有息负债 + 市值 $1.02 万亿）。MU 已从 FY25 末的 $145.8 亿债务降到 $57.2 亿，加权平均到期日 2034 年 8 月。占总资本不足 1%，对 WACC 的影响可忽略，故直接用 Ke 近似 WACC。
A58: 净现金（现金及投资 − 有息负债） | B58: 24433 | D58: 现金及可交易投资 $30,155M − 有息负债 $5,722M。在下方估值桥中单独加回。
A60: 04 估值：从终值到每股内在价值
A61: 步骤 | B61: 金额（百万美元） | D61: 计算方式与说明
A62: ① 预测期 FCFF 现值合计 | B62: =SUM(B49:G49) -> 435946.1 | D62: FY2027–FY2032 六年折现值加总（期中折现）
A63: ② 终值 TV（永续增长法） | B63: =H45/($B$211-$B$213) -> 1465949.1 | D63: ＝ 永续期 FCFF ÷ (WACC − g)。★ 若 WACC ≤ g 公式失效，控制台已把 g 上限设在 6%
A64: ③ 终值现值 PV(TV) | B64: =B63*G48/(1+$B$211)^0.5 -> 783756.23 | D64: 用 FY32 的折现因子再折半年，与期中折现保持一致
A65: ④ 终值占企业价值比重 | B65: =B64/B66 -> 0.64257993 | D65: ★ 这个比例越高，说明估值越依赖你对永续期的猜测，而不是可见的现金流
A66: ⑤ 企业价值 EV | B66: =B62+B64 -> 1219702.3 | D66: ＝ ① + ③
A67: ⑥ ＋ 现金及可交易投资 | B67: ='00-三表与联动'!$B$10 -> 30155 | D67: FY26 Q3末 $30,155M（现金 24,995 + 短期投资 1,027 + 长期可交易投资 4,106 + 受限现金 27）
A68: ⑦ ＋ 政府补贴应收/其他非经营资产 | B68: 0 | D68: MU 的现金及可交易投资已包含短期与长期投资，此处不再重复计入，置 0
A69: ⑧ − 有息负债 | B69: =-'00-三表与联动'!$B$11 -> -5722 | D69: FY26 Q3末 $5,722M。已从 FY25 末的 $14,577M 大幅下降，加权平均到期日 2034 年 8 月
A70: ⑨ 股权价值 | B70: =B66+B67+B68+B69 -> 1244135.3 | D70: ＝ EV + 净现金
A71: ⑩ 摊薄股数（百万股） | B71: ='00-三表与联动'!$B$9 -> 1150 | D71: 公司 FY27 Q1 指引「约 155」
A72: ⑪ 每股内在价值 | B72: =B70/B71 -> 1081.8568 | D72: ＝ 股权价值 ÷ 摊薄股数
A73: ⑫ 当前股价 | B73: ='00-三表与联动'!$B$6 -> 903.09 | D73: 2026-08-26 盘中 $1,500.17
A74: ⑬ 相对现价的上行/下行 | B74: =B72/B73-1 -> 0.19795015 | D74: ★ 正数 = 模型认为被低估；负数 = 被高估
A75: ★ 请先看第 ④ 行「终值占企业价值比重」再看第 ⑬ 行的结论。对一个处在周期顶点的存储公司，如果终值占比超过 70%，那么这个 DCF 实际上不是在给现金流定价，而是在给你对 2032 年之后 NAND 行业格局的猜测定价。
A77: 05 交叉验证：退出倍数法与相对估值
A78: 方法 | B78: 关键输入 | D78: 隐含结果 | F78: 说明
A79: 永续增长法隐含的退出 EV/EBITDA | D79: =B63/(G37+G40) -> 7.969879 | F79: ＝ 终值 ÷ FY32 EBITDA。若这个倍数远高于半导体行业常见的 8–14x，说明永续增长率给得过于激进
A80: 永续增长法隐含的退出 EV/收入 | D80: =B63/G32 -> 5.6825237 | F80: ＝ 终值 ÷ FY32 收入
A81: 本模型每股价值 ÷ FY27 每股 FCFF | D81: =B72/(F27/'00-三表与联动'!$B$9) -> 10.414465 | F81: 把内在价值换算成 FY27 自由现金流的倍数，便于与同业横比
A82: 当前股价隐含的 FY27 P/FCFF | D82: ='00-三表与联动'!$B$6/(F27/'00-三表与联动'!$B$9) -> 8.693571 | F82: 市场正在为 FY27 的自由现金流付多少倍
A83: 当前市值 ÷ 本模型股权价值 | D83: ='00-三表与联动'!$B$6*'00-三表与联动'!$B$9/B70 -> 0.83475927 | F83: 大于 1 = 市场比模型乐观
A85: 06 回购与每股收益：EPS × P/E 交叉估值（与 DCF 并排看）
A86: 为什么要做这一块：DCF 给的是「整个企业值多少钱」，它对回购是中性的——按公允价值回购既不创造也不毁灭价值。但管理层已承诺把 100% 的剩余现金用于回购，股数会大幅下降，所以从「持有不卖的股东」角度看，每股口径会变。这一节把回购显式建模：股数逐年递减 → 经营性 EPS 抬升 → 用当年的 P/E 给一个价格 → 折回今天，再与 DCF 的结果并排比较。
A87: ★ 关于 P/E：本节不再用同一个倍数乘所有年份。FY2027、FY2028、FY2032 各有独立滑标，FY29–FY31 在 FY28 与 FY32 之间线性过渡。原因是周期股的 P/E 与盈利反向：盈利高点（FY27）市场给的倍数最低，盈利回落年（FY28）分母掉得比股价快、倍数反而扩张，终局年（FY32）回到正常中枢。用一个固定倍数乘所有年份，会系统性高估高点年份的目标价。
A88: ★ 关于回购均价：＝ 当前股价 × 倍数 ×(1+WACC)^(t−0.5)。让回购价按折现率复利，是「市场对股票定价合理」的中性假设。如果假设股价六年不动，模型会机械地算出巨额增厚——那是假的。有了这个设定，当 FY32 的 P/E 等于「本 DCF 隐含的退出 P/E」时，两种方法应当收敛。
A89: 科目 | B89: FY2027 | C89: FY2028 | D89: FY2029 | E89: FY2030 | F89: FY2031 | G89: FY2032 | H89: 口径与说明
A90: 自由现金流 FCFF | B90: =B45 -> 115712.26 | C90: =C45 -> 79249.754 | D90: =D45 -> 81987.178 | E90: =E45 -> 96470.284 | F90: =F45 -> 104681.23 | G90: =G45 -> 111469.36 | H90: 链接自上方年度预测表
A91: × 回购比例 | B91: =$B$133 -> 1 | C91: =$B$133 -> 1 | D91: =$B$133 -> 1 | E91: =$B$133 -> 1 | F91: =$B$133 -> 1 | G91: =$B$133 -> 1 | H91: 本节内控制台滑标，默认 100%（管理层承诺返还 100% 剩余现金）
A92: ＝ 用于回购的金额 | B92: =MAX(0,B90*B91) -> 115712.26 | C92: =MAX(0,C90*C91) -> 79249.754 | D92: =MAX(0,D90*D91) -> 81987.178 | E92: =MAX(0,E90*E91) -> 96470.284 | F92: =MAX(0,F90*F91) -> 104681.23 | G92: =MAX(0,G90*G91) -> 111469.36 | H92: ＝ MAX(0, FCFF × 回购比例)。FCFF 为负时不回购
A93: 回购均价（美元/股） | B93: ='00-三表与联动'!$B$6*$B$135*(1+$B$211)^0.5 -> 951.46435 | C93: ='00-三表与联动'!$B$6*$B$135*(1+$B$211)^1.5 -> 1056.1254 | D93: ='00-三表与联动'!$B$6*$B$135*(1+$B$211)^2.5 -> 1172.2992 | E93: ='00-三表与联动'!$B$6*$B$135*(1+$B$211)^3.5 -> 1301.2521 | F93: ='00-三表与联动'!$B$6*$B$135*(1+$B$211)^4.5 -> 1444.3899 | G93: ='00-三表与联动'!$B$6*$B$135*(1+$B$211)^5.5 -> 1603.2728 | H93: ＝ 当前股价 × 本节滑标倍数 ×(1+WACC)^(t−0.5)
A94: − 回购注销股数（百万股） | B94: =B92/B93 -> 121.61492 | C94: =C92/C93 -> 75.038203 | D94: =D92/D93 -> 69.937074 | E94: =E92/E93 -> 74.136503 | F94: =F92/F93 -> 72.474357 | G94: =G92/G93 -> 69.526132 | H94: ＝ 回购金额 ÷ 回购均价
A95: ＋ 股权激励新增股数（百万股） | B95: =B32*0.0115/B93 -> 2.4777607 | C95: =C32*0.0115/C93 -> 1.7857735 | D95: =D32*0.0115/D93 -> 1.8018616 | E95: =E32*0.0115/E93 -> 1.8505605 | F95: =F32*0.0115/F93 -> 1.8672322 | G95: =G32*0.0115/G93 -> 1.8504103 | H95: ＝ 收入 × 1.15% ÷ 回购均价。FY26 股份支付 $232M ÷ 收入 $20,248M ＝ 1.15%
A96: 期初摊薄股数（百万股） | B96: ='00-三表与联动'!$B$9 -> 1150 | C96: =B97 -> 1030.8628 | D96: =C97 -> 957.61041 | E96: =D97 -> 889.4752 | F96: =E97 -> 817.18926 | G96: =F97 -> 746.58213 | H96: FY27 期初取公司指引的 155；其后为上年期末
A97: 期末摊薄股数（百万股） | B97: =MAX(20,B96-B94+B95) -> 1030.8628 | C97: =MAX(20,C96-C94+C95) -> 957.61041 | D97: =MAX(20,D96-D94+D95) -> 889.4752 | E97: =MAX(20,E96-E94+E95) -> 817.18926 | F97: =MAX(20,F96-F94+F95) -> 746.58213 | G97: =MAX(20,G96-G94+G95) -> 678.90641 | H97: ＝ 期初 − 回购注销 + 股权激励新增，下限锁 20
A98: 净现金余额 | B98: =('00-三表与联动'!$B$10-'00-三表与联动'!$B$11)+B90-B92 -> 24433 | C98: =B98+C90-C92 -> 24433 | D98: =C98+D90-D92 -> 24433 | E98: =D98+E90-E92 -> 24433 | F98: =E98+F90-F92 -> 24433 | G98: =F98+G90-G92 -> 24433 | H98: ＝ 上期净现金 + FCFF − 回购金额。★ 回购比例＜100% 时现金会累积，这部分价值必须计入，否则会低估
A99: 税后经营利润 NOPAT | B99: =B39 -> 134297.28 | C99: =C39 -> 87367.758 | D99: =D39 -> 100919.35 | E99: =E39 -> 118544.96 | F99: =F39 -> 128853.82 | G99: =G39 -> 137431.02 | H99: 链接自上方年度预测表。★ 用 NOPAT 而非净利润，是为了与 DCF 同口径（不含利息）
A100: 经营性每股收益 EPS | B100: =B99/B97 -> 130.27658 | C100: =C99/C97 -> 91.235179 | D100: =D99/D97 -> 113.45943 | E100: =E99/E97 -> 145.06426 | F100: =F99/F97 -> 172.59162 | G100: =G99/G97 -> 202.42999 | H100: ＝ NOPAT ÷ 期末股数。用期末股数而非加权平均，因为要回答的是「那个时点每一股值多少」
A101: 每股净现金 | B101: =B98/B97 -> 23.701504 | C101: =C98/C97 -> 25.514551 | D101: =D98/D97 -> 27.469006 | E101: =E98/E97 -> 29.898827 | F101: =F98/F97 -> 32.726473 | G101: =G98/G97 -> 35.98876 | H101: ＝ 净现金余额 ÷ 期末股数
A102: ★ 采用的 P/E 倍数 | B102: =$B$137 -> 6 | C102: =$B$139 -> 9 | D102: =$B$139+($B$141-$B$139)*1/4 -> 9.5 | E102: =$B$139+($B$141-$B$139)*2/4 -> 10 | F102: =$B$139+($B$141-$B$139)*3/4 -> 10.5 | G102: =$B$141 -> 11 | H102: FY27 / FY28 / FY32 各由本节独立滑标给定；FY29–FY31 在 FY28 与 FY32 之间线性过渡（四等分）
A103: 隐含股价（EPS×当年PE + 每股净现金） | B103: =B100*B102+B101 -> 805.36095 | C103: =C100*C102+C101 -> 846.63117 | D103: =D100*D102+D101 -> 1105.3336 | E103: =E100*E102+E101 -> 1480.5414 | F103: =F100*F102+F101 -> 1844.9385 | G103: =G100*G102+G101 -> 2262.7187 | H103: 把现金单独加回，使本方法与 DCF（EV + 净现金）口径一致
A104: 折现因子（期末折现） | B104: =1/(1+$B$211)^1 -> 0.9009009 | C104: =1/(1+$B$211)^2 -> 0.81162243 | D104: =1/(1+$B$211)^3 -> 0.73119138 | E104: =1/(1+$B$211)^4 -> 0.65873097 | F104: =1/(1+$B$211)^5 -> 0.59345133 | G104: =1/(1+$B$211)^6 -> 0.53464084 | H104: ＝ 1 ÷ (1+WACC)^t。股价是时点数用期末折现；上方 DCF 的现金流是期间数用期中折现
A105: 折现后每股价值 | B105: =B103*B104 -> 725.55041 | C105: =C103*C104 -> 687.14485 | D105: =D103*D104 -> 808.21037 | E105: =E103*E104 -> 975.2785 | F105: =F103*F104 -> 1094.8812 | G105: =G103*G104 -> 1209.7418 | H105: ＝ 隐含股价 × 折现因子
A107: 6.1 三个关键年份的目标价：各用各的 P/E
A108: 年份 | B108: 经营性 EPS | C108: 每股净现金 | D108: 采用 P/E | E108: 隐含目标价 | F108: 折现期（年） | G108: 折现后每股价值 | H108: 折现后 ÷ 现价 − 1 | I108: 这个数字回答什么
...

Sheet 03-DCF-乐观
A1: BULL · MU 现金流折现模型 —— 乐观情形
A2: FY2027 分四个季度 → FY2028–FY2032 按年 → 永续 | 自由现金流口径：FCFF（资本开支扣除 CHIPS 补贴后） | ▼ 全部参数由本表底部的参数控制台滑标驱动
A4: 00 本情形的论点：这套数字建立在什么判断之上
A5: 完全采纳管理层口径：DRAM 与 NAND 供需紧张持续到 2027 日历年之后，HBM3E/HBM4 已售罄至 2027 年，16 份 SCA 带来约 $1,000 亿最低合约收入与 $220 亿客户资金承诺，管理层目标是把一半以上收入纳入 SCA。如果这套「照付不议」的合约体系真的把存储从周期股变成合约制生意，那么当前 6–7 倍的前瞻市盈率是严重错配。
A6: 1．FY27 逐季爬坡至 $660 亿/季，全年 $2,430 亿
A7: 2．FY28–FY30 毛利率维持 78%–82%，对应管理层「紧张持续到 CY2027 之后」的判断
A8: 3．★ SCA 把价格地板锁在 FY26 Q2 水平，下行周期的深度被合约结构截断
A9: 4．WACC 降到 9.5%（现金流可预测性提高），永续增长 3.5%
A11: 01 FY2027 季度预测（先用季度把最近的可见度做实，再转年度）
A12: 科目（百万美元） | B12: FY27 Q1 | C12: FY27 Q2 | D12: FY27 Q3 | E12: FY27 Q4 | F12: FY2027 合计 | G12: 变量怎么来的
A13: 营业收入 | B13: =$B$189 -> 55000 | C13: =B13*(1+0.072727+$B$191) -> 58999.985 | D13: =C13*(1+0.067797+$B$191) -> 63000.007 | E13: =D13*(1+0.047619+$B$191) -> 66000.004 | F13: =SUM(B13:E13) -> 243000 | G13: Q1 ＝ 控制台滑标（官方指引 $10.3–10.8B）；Q2–Q4 ＝ 上一季 ×(1 + 情形环比增速 + 滑标平移)
A14: 环比增速 QoQ | B14: =B13/'00-三表与联动'!E27-1 -> 0.1 | C14: =C13/B13-1 -> 0.072727 | D14: =D13/C13-1 -> 0.067797 | E14: =E13/D13-1 -> 0.047619 | F14: =F13/'00-三表与联动'!F27-1 -> 0.88431979 | G14: Q1 的环比基数是 FY26 Q4 的 $8,965M（不是 FY26 全年）；Q2–Q4 为上一季
A15: 毛利率 | B15: =MAX(0.05,MIN(0.92,0.865+$B$193)) -> 0.865 | C15: =MAX(0.05,MIN(0.92,0.87+$B$193)) -> 0.87 | D15: =MAX(0.05,MIN(0.92,0.87+$B$193)) -> 0.87 | E15: =MAX(0.05,MIN(0.92,0.86+$B$193)) -> 0.86 | F15: =F16/F13 -> 0.86615226 | G15: 情形设定的季度毛利率路径 + 控制台「毛利率平移」，上下限锁在 5%–92%
A16: 毛利 | B16: =B13*B15 -> 47575 | C16: =C13*C15 -> 51329.987 | D16: =D13*D15 -> 54810.006 | E16: =E13*E15 -> 56760.004 | F16: =SUM(B16:E16) -> 210475 | G16: ＝ 收入 × 毛利率
A17: 营业费用 | B17: =B13*$B$199 -> 1925 | C17: =C13*$B$199 -> 2064.9995 | D17: =D13*$B$199 -> 2205.0002 | E17: =E13*$B$199 -> 2310.0002 | F17: =SUM(B17:E17) -> 8504.9999 | G17: ＝ 收入 × 控制台「营业费用率」。公司 FY27 Q1 GAAP 指引为 $574–614M
A18: 营业利润 EBIT | B18: =B16-B17 -> 45650 | C18: =C16-C17 -> 49264.987 | D18: =D16-D17 -> 52605.006 | E18: =E16-E17 -> 54450.004 | F18: =SUM(B18:E18) -> 201970 | G18: ＝ 毛利 − 营业费用
A19: 营业利润率 | B19: =B18/B13 -> 0.83 | C19: =C18/C13 -> 0.835 | D19: =D18/D13 -> 0.835 | E19: =E18/E13 -> 0.825 | F19: =F18/F13 -> 0.83115226 | G19: ＝ EBIT ÷ 收入
A20: 所得税 | B20: =MAX(0,B18)*$B$201 -> 7075.75 | C20: =MAX(0,C18)*$B$201 -> 7636.0731 | D20: =MAX(0,D18)*$B$201 -> 8153.7759 | E20: =MAX(0,E18)*$B$201 -> 8439.7506 | F20: =SUM(B20:E20) -> 31305.35 | G20: ＝ EBIT × 控制台「有效税率」（FCFF 口径按 EBIT 计税，不含利息）
A21: 税后经营利润 NOPAT | B21: =B18-B20 -> 38574.25 | C21: =C18-C20 -> 41628.914 | D21: =D18-D20 -> 44451.23 | E21: =E18-E20 -> 46010.253 | F21: =SUM(B21:E21) -> 170664.65 | G21: ＝ EBIT − 所得税
A22: ＋ 折旧摊销 D&A | B22: =B13*$B$207 -> 3575 | C22: =C13*$B$207 -> 3834.999 | D22: =D13*$B$207 -> 4095.0005 | E22: =E13*$B$207 -> 4290.0003 | F22: =SUM(B22:E22) -> 15795 | G22: ＝ 收入 × 控制台「折旧摊销率」。FY26 前九个月 $6,862M，全年约 $94 亿（占收入 7.3%）。★ MU 自建晶圆厂，折旧全部落在自己报表上
A23: − 资本开支（总额） | B23: =-B13*$B$203 -> -8525 | C23: =-C13*$B$203 -> -9144.9977 | D23: =-D13*$B$203 -> -9765.0011 | E23: =-E13*$B$203 -> -10230.001 | F23: =SUM(B23:E23) -> -37664.999 | G23: ＝ 收入 × 控制台「资本开支率」。FY26 约 $270 亿；管理层已指引 FY27 季度资本开支高于 FY26 Q4 的约 $100 亿/季
A24: ＋ CHIPS 政府补贴抵扣 | B24: =-B23*$B$205 -> 767.25 | C24: =-C23*$B$205 -> 823.04979 | D24: =-D23*$B$205 -> 878.8501 | E24: =-E23*$B$205 -> 920.70006 | F24: =SUM(B24:E24) -> 3389.8499 | G24: ＝ 资本开支 × 控制台「政府补贴抵扣比例」。FY26 前九个月收到 $2,989M，占同期资本开支 15.2%
A25: 营运资本余额 | B25: =B13*4*$B$209 -> 29700 | C25: =C13*4*$B$209 -> 31859.992 | D25: =D13*4*$B$209 -> 34020.004 | E25: =E13*4*$B$209 -> 35640.002 | F25: =E25 -> 35640.002 | G25: ＝ 控制台「营运资本占年化收入比」× 当季收入 × 4。期初取 FY26 Q4 的年化收入基准
A26: − 营运资本增加 ΔNWC | B26: =-(B25-'00-三表与联动'!E27*4*$B$209) -> -2700 | C26: =-(C25-B25) -> -2159.9919 | D26: =-(D25-C25) -> -2160.0119 | E26: =-(E25-D25) -> -1619.9986 | F26: =SUM(B26:E26) -> -8640.0023 | G26: ＝ 本季余额 − 上季余额。余额法，不再用「占收入增量比」
A27: ＝ 自由现金流 FCFF | B27: =B21+B22+B23+B24+B26 -> 31691.5 | C27: =C21+C22+C23+C24+C26 -> 34981.974 | D27: =D21+D22+D23+D24+D26 -> 37500.068 | E27: =E21+E22+E23+E24+E26 -> 39370.954 | F27: =SUM(B27:E27) -> 143544.5 | G27: ＝ NOPAT + D&A − 资本开支 + 政府补贴 − ΔNWC
A28: 口径说明：这里算的是 FCFF（企业自由现金流），所以税按 EBIT 计、不扣利息——利息的价值已经体现在折现率里。公司目前零负债，FCFF 与 FCFE 的差异只剩利息收入。
A30: 02 FY2028–FY2032 年度预测 + 永续
A31: 科目（百万美元） | B31: FY2027 | C31: FY2028 | D31: FY2029 | E31: FY2030 | F31: FY2031 | G31: FY2032 | H31: 永续期 | I31: 变量怎么来的
A32: 营业收入 | B32: =F13 -> 243000 | C32: =B32*(1+0.15) -> 279450 | D32: =C32*(1+0.14+$B$197) -> 318573 | E32: =D32*(1+0.12+$B$197) -> 356801.75 | F32: =E32*(1+0.1+$B$197) -> 392481.93 | G32: =F32*(1+0.08+$B$197) -> 423880.48 | H32: =G32*(1+$B$213) -> 438716.3 | I32: FY27 取季度合计；FY28 ＝ 情形设定增速；FY29–32 ＝ 情形增速 + 控制台「长期增速平移」
A33: 收入增速 YoY | B33: =B32/'00-三表与联动'!F27-1 -> 0.88431979 | C33: =C32/B32-1 -> 0.15 | D33: =D32/C32-1 -> 0.14 | E33: =E32/D32-1 -> 0.12 | F33: =F32/E32-1 -> 0.1 | G33: =G32/F32-1 -> 0.08 | H33: =$B$213 -> 0.035 | I33: 逐年同比。FY26 实际为 +175%
A34: 毛利率 | B34: =F16/F13 -> 0.86615226 | C34: =MAX(0.05,MIN(0.92,0.82+$B$193)) -> 0.82 | D34: =MAX(0.05,MIN(0.92,0.8+$B$193)) -> 0.8 | E34: =MAX(0.05,MIN(0.92,0.78+$B$193)) -> 0.78 | F34: =MAX(0.05,MIN(0.92,0.76+$B$193)) -> 0.76 | G34: =$B$195 -> 0.74 | H34: =G34 -> 0.74 | I34: 情形设定的年度毛利率 + 控制台「毛利率平移」；FY32 直接取控制台「终局毛利率」
A35: 毛利 | B35: =B32*B34 -> 210475 | C35: =C32*C34 -> 229149 | D35: =D32*D34 -> 254858.4 | E35: =E32*E34 -> 278305.37 | F35: =F32*F34 -> 298286.27 | G35: =G32*G34 -> 313671.56 | H35: =H32*H34 -> 324650.06 | I35: ＝ 收入 × 毛利率
A36: 营业费用 | B36: =B32*$B$199 -> 8504.9999 | C36: =C32*$B$199 -> 9780.7499 | D36: =D32*$B$199 -> 11150.055 | E36: =E32*$B$199 -> 12488.061 | F36: =F32*$B$199 -> 13736.868 | G36: =G32*$B$199 -> 14835.817 | H36: =H32*$B$199 -> 15355.071 | I36: ＝ 收入 × 控制台「营业费用率」
A37: 营业利润 EBIT | B37: =B35-B36 -> 201970 | C37: =C35-C36 -> 219368.25 | D37: =D35-D36 -> 243708.34 | E37: =E35-E36 -> 265817.31 | F37: =F35-F36 -> 284549.4 | G37: =G35-G36 -> 298835.74 | H37: =H35-H36 -> 309294.99 | I37: ＝ 毛利 − 营业费用
A38: 营业利润率 | B38: =B37/B32 -> 0.83115226 | C38: =C37/C32 -> 0.785 | D38: =D37/D32 -> 0.765 | E38: =E37/E32 -> 0.745 | F38: =F37/F32 -> 0.725 | G38: =G37/G32 -> 0.705 | H38: =H37/H32 -> 0.705 | I38: ＝ EBIT ÷ 收入。可与投资者日目标「约 75%」对照
A39: 税后经营利润 NOPAT | B39: =B37*(1-$B$201) -> 170664.65 | C39: =C37*(1-$B$201) -> 185366.17 | D39: =D37*(1-$B$201) -> 205933.55 | E39: =E37*(1-$B$201) -> 224615.62 | F39: =F37*(1-$B$201) -> 240444.24 | G39: =G37*(1-$B$201) -> 252516.2 | H39: =H37*(1-$B$201) -> 261354.27 | I39: ＝ EBIT ×(1 − 有效税率)
A40: ＋ 折旧摊销 D&A | B40: =B32*$B$207 -> 15795 | C40: =C32*$B$207 -> 18164.25 | D40: =D32*$B$207 -> 20707.245 | E40: =E32*$B$207 -> 23192.114 | F40: =F32*$B$207 -> 25511.325 | G40: =G32*$B$207 -> 27552.231 | H40: =H32*$B$207 -> 28516.56 | I40: ＝ 收入 × 控制台「折旧摊销率」。★ 折旧跟随资产基数而非收入，收入下行年该比例会被动上升
A41: − 资本开支（总额） | B41: =-B32*$B$203 -> -37664.999 | C41: =-C32*$B$203 -> -43314.749 | D41: =-D32*$B$203 -> -49378.814 | E41: =-E32*$B$203 -> -55304.272 | F41: =-F32*$B$203 -> -60834.699 | G41: =-G32*$B$203 -> -65701.475 | H41: =-H32*$B$203 -> -68001.027 | I41: ＝ 收入 × 控制台「资本开支率」
A42: ＋ CHIPS 政府补贴抵扣 | B42: =-B41*$B$205 -> 3389.8499 | C42: =-C41*$B$205 -> 3898.3274 | D42: =-D41*$B$205 -> 4444.0933 | E42: =-E41*$B$205 -> 4977.3845 | F42: =-F41*$B$205 -> 5475.1229 | G42: =-G41*$B$205 -> 5913.1328 | H42: =-H41*$B$205 -> 6120.0924 | I42: ＝ 资本开支 × 控制台「政府补贴抵扣比例」
A43: 营运资本余额 | B43: =B32*$B$209 -> 32805 | C43: =C32*$B$209 -> 37725.749 | D43: =D32*$B$209 -> 43007.354 | E43: =E32*$B$209 -> 48168.237 | F43: =F32*$B$209 -> 52985.061 | G43: =G32*$B$209 -> 57223.865 | H43: =H32*$B$209 -> 59226.701 | I43: ＝ 控制台「营运资本占年化收入比」× 当年收入。期初取 FY26 Q4 年化收入 × 同一比例
A44: − 营运资本增加 ΔNWC | B44: =-(B43-'00-三表与联动'!E27*4*$B$209) -> -5804.9995 | C44: =-(C43-B43) -> -4920.7499 | D44: =-(D43-C43) -> -5281.6049 | E44: =-(E43-D43) -> -5160.8825 | F44: =-(F43-E43) -> -4816.8237 | G44: =-(G43-F43) -> -4238.8048 | H44: =-(H43-G43) -> -2002.8353 | I44: ＝ 本年余额 − 上年余额（余额法）
A45: ＝ 自由现金流 FCFF | B45: =B39+B40+B41+B42+B44 -> 146379.5 | C45: =C39+C40+C41+C42+C44 -> 159193.25 | D45: =D39+D40+D41+D42+D44 -> 176424.47 | E45: =E39+E40+E41+E42+E44 -> 192319.97 | F45: =F39+F40+F41+F42+F44 -> 205779.17 | G45: =G39+G40+G41+G42+G44 -> 216041.29 | H45: =H39+H40+H41+H42+H44 -> 225987.06 | I45: ＝ NOPAT + D&A − 资本开支 + 政府补贴 − ΔNWC。★ 估值采用的是这一行，不是季度块
A46: FCFF 利润率 | B46: =B45/B32 -> 0.60238478 | C46: =C45/C32 -> 0.5696663 | D46: =D45/D32 -> 0.55379605 | E46: =E45/E32 -> 0.53901071 | F46: =F45/F32 -> 0.52430227 | G46: =G45/G32 -> 0.509675 | H46: =H45/H32 -> 0.51510978 | I46: ＝ FCFF ÷ 收入。可与投资者日「调整后自由现金流率约 50%」对照（口径不同，见溯源表）
A47: 折现期（年，期中折现） | B47: =0.5 -> 0.5 | C47: =1.5 -> 1.5 | D47: =2.5 -> 2.5 | E47: =3.5 -> 3.5 | F47: =4.5 -> 4.5 | G47: =5.5 -> 5.5 | H47: — | I47: 期中折现法：第 n 年的折现期为 n − 0.5，假设现金流在年内均匀发生
A48: 折现因子 | B48: =1/(1+$B$211)^B47 -> 0.95563697 | C48: =1/(1+$B$211)^C47 -> 0.87272782 | D48: =1/(1+$B$211)^D47 -> 0.79701171 | E48: =1/(1+$B$211)^E47 -> 0.72786458 | F48: =1/(1+$B$211)^F47 -> 0.66471651 | G48: =1/(1+$B$211)^G47 -> 0.60704704 | H48: — | I48: ＝ 1 ÷ (1 + WACC)^折现期
A49: 折现后 FCFF 现值 | B49: =B45*B48 -> 139885.66 | C49: =C45*C48 -> 138932.38 | D49: =D45*D48 -> 140612.37 | E49: =E45*E48 -> 139982.89 | F49: =F45*F48 -> 136784.81 | G49: =G45*G48 -> 131147.22 | H49: — | I49: ＝ FCFF × 折现因子
A51: 03 折现率 WACC（MU 为净现金结构，WACC ≈ 股权成本）
A52: 参数 | B52: 取值 | D52: 来源与说明
A53: 无风险利率 Rf | B53: ='00-三表与联动'!$B$14 -> 0.042 | D53: 10 年期美国国债收益率，取 4.20%
A54: 股权风险溢价 ERP | B54: ='00-三表与联动'!$B$15 -> 0.05 | D54: 美国成熟市场长期 ERP，取 5.00%
A55: 贝塔 β（隐含） | B55: =(B56-B53)/B54 -> 1.06 | D55: ★ 由控制台 WACC 反解：β = (WACC − Rf) ÷ ERP。MU 有足够长的交易历史，但 52 周振幅 $114.25–$1,255.00 使得任何时点的回归 β 都高度依赖窗口选择，因此本模型的做法是直接设定 WACC、反算隐含 β 供你判断合理性。
A56: 股权成本 Ke = WACC | B56: =$B$211 -> 0.095 | D56: 控制台滑标直接给定
A57: 有息负债 / 总资本 | B57: 0.0056 | D57: ＝ 有息负债 $5,722M ÷（有息负债 + 市值 $1.02 万亿）。MU 已从 FY25 末的 $145.8 亿债务降到 $57.2 亿，加权平均到期日 2034 年 8 月。占总资本不足 1%，对 WACC 的影响可忽略，故直接用 Ke 近似 WACC。
A58: 净现金（现金及投资 − 有息负债） | B58: 24433 | D58: 现金及可交易投资 $30,155M − 有息负债 $5,722M。在下方估值桥中单独加回。
A60: 04 估值：从终值到每股内在价值
A61: 步骤 | B61: 金额（百万美元） | D61: 计算方式与说明
A62: ① 预测期 FCFF 现值合计 | B62: =SUM(B49:G49) -> 827345.33 | D62: FY2027–FY2032 六年折现值加总（期中折现）
A63: ② 终值 TV（永续增长法） | B63: =H45/($B$211-$B$213) -> 3766451 | D63: ＝ 永续期 FCFF ÷ (WACC − g)。★ 若 WACC ≤ g 公式失效，控制台已把 g 上限设在 6%
A64: ③ 终值现值 PV(TV) | B64: =B63*G48/(1+$B$211)^0.5 -> 2184980.7 | D64: 用 FY32 的折现因子再折半年，与期中折现保持一致
A65: ④ 终值占企业价值比重 | B65: =B64/B66 -> 0.72534669 | D65: ★ 这个比例越高，说明估值越依赖你对永续期的猜测，而不是可见的现金流
A66: ⑤ 企业价值 EV | B66: =B62+B64 -> 3012326 | D66: ＝ ① + ③
A67: ⑥ ＋ 现金及可交易投资 | B67: ='00-三表与联动'!$B$10 -> 30155 | D67: FY26 Q3末 $30,155M（现金 24,995 + 短期投资 1,027 + 长期可交易投资 4,106 + 受限现金 27）
A68: ⑦ ＋ 政府补贴应收/其他非经营资产 | B68: 0 | D68: MU 的现金及可交易投资已包含短期与长期投资，此处不再重复计入，置 0
A69: ⑧ − 有息负债 | B69: =-'00-三表与联动'!$B$11 -> -5722 | D69: FY26 Q3末 $5,722M。已从 FY25 末的 $14,577M 大幅下降，加权平均到期日 2034 年 8 月
A70: ⑨ 股权价值 | B70: =B66+B67+B68+B69 -> 3036759 | D70: ＝ EV + 净现金
A71: ⑩ 摊薄股数（百万股） | B71: ='00-三表与联动'!$B$9 -> 1150 | D71: 公司 FY27 Q1 指引「约 155」
A72: ⑪ 每股内在价值 | B72: =B70/B71 -> 2640.66 | D72: ＝ 股权价值 ÷ 摊薄股数
A73: ⑫ 当前股价 | B73: ='00-三表与联动'!$B$6 -> 903.09 | D73: 2026-08-26 盘中 $1,500.17
A74: ⑬ 相对现价的上行/下行 | B74: =B72/B73-1 -> 1.9240275 | D74: ★ 正数 = 模型认为被低估；负数 = 被高估
A75: ★ 请先看第 ④ 行「终值占企业价值比重」再看第 ⑬ 行的结论。对一个处在周期顶点的存储公司，如果终值占比超过 70%，那么这个 DCF 实际上不是在给现金流定价，而是在给你对 2032 年之后 NAND 行业格局的猜测定价。
A77: 05 交叉验证：退出倍数法与相对估值
A78: 方法 | B78: 关键输入 | D78: 隐含结果 | F78: 说明
A79: 永续增长法隐含的退出 EV/EBITDA | D79: =B63/(G37+G40) -> 11.539797 | F79: ＝ 终值 ÷ FY32 EBITDA。若这个倍数远高于半导体行业常见的 8–14x，说明永续增长率给得过于激进
A80: 永续增长法隐含的退出 EV/收入 | D80: =B63/G32 -> 8.8856437 | F80: ＝ 终值 ÷ FY32 收入
A81: 本模型每股价值 ÷ FY27 每股 FCFF | D81: =B72/(F27/'00-三表与联动'!$B$9) -> 21.155524 | F81: 把内在价值换算成 FY27 自由现金流的倍数，便于与同业横比
A82: 当前股价隐含的 FY27 P/FCFF | D82: ='00-三表与联动'!$B$6/(F27/'00-三表与联动'!$B$9) -> 7.2350632 | F82: 市场正在为 FY27 的自由现金流付多少倍
A83: 当前市值 ÷ 本模型股权价值 | D83: ='00-三表与联动'!$B$6*'00-三表与联动'!$B$9/B70 -> 0.34199404 | F83: 大于 1 = 市场比模型乐观
A85: 06 回购与每股收益：EPS × P/E 交叉估值（与 DCF 并排看）
A86: 为什么要做这一块：DCF 给的是「整个企业值多少钱」，它对回购是中性的——按公允价值回购既不创造也不毁灭价值。但管理层已承诺把 100% 的剩余现金用于回购，股数会大幅下降，所以从「持有不卖的股东」角度看，每股口径会变。这一节把回购显式建模：股数逐年递减 → 经营性 EPS 抬升 → 用当年的 P/E 给一个价格 → 折回今天，再与 DCF 的结果并排比较。
A87: ★ 关于 P/E：本节不再用同一个倍数乘所有年份。FY2027、FY2028、FY2032 各有独立滑标，FY29–FY31 在 FY28 与 FY32 之间线性过渡。原因是周期股的 P/E 与盈利反向：盈利高点（FY27）市场给的倍数最低，盈利回落年（FY28）分母掉得比股价快、倍数反而扩张，终局年（FY32）回到正常中枢。用一个固定倍数乘所有年份，会系统性高估高点年份的目标价。
A88: ★ 关于回购均价：＝ 当前股价 × 倍数 ×(1+WACC)^(t−0.5)。让回购价按折现率复利，是「市场对股票定价合理」的中性假设。如果假设股价六年不动，模型会机械地算出巨额增厚——那是假的。有了这个设定，当 FY32 的 P/E 等于「本 DCF 隐含的退出 P/E」时，两种方法应当收敛。
A89: 科目 | B89: FY2027 | C89: FY2028 | D89: FY2029 | E89: FY2030 | F89: FY2031 | G89: FY2032 | H89: 口径与说明
A90: 自由现金流 FCFF | B90: =B45 -> 146379.5 | C90: =C45 -> 159193.25 | D90: =D45 -> 176424.47 | E90: =E45 -> 192319.97 | F90: =F45 -> 205779.17 | G90: =G45 -> 216041.29 | H90: 链接自上方年度预测表
A91: × 回购比例 | B91: =$B$133 -> 1 | C91: =$B$133 -> 1 | D91: =$B$133 -> 1 | E91: =$B$133 -> 1 | F91: =$B$133 -> 1 | G91: =$B$133 -> 1 | H91: 本节内控制台滑标，默认 100%（管理层承诺返还 100% 剩余现金）
A92: ＝ 用于回购的金额 | B92: =MAX(0,B90*B91) -> 146379.5 | C92: =MAX(0,C90*C91) -> 159193.25 | D92: =MAX(0,D90*D91) -> 176424.47 | E92: =MAX(0,E90*E91) -> 192319.97 | F92: =MAX(0,F90*F91) -> 205779.17 | G92: =MAX(0,G90*G91) -> 216041.29 | H92: ＝ MAX(0, FCFF × 回购比例)。FCFF 为负时不回购
A93: 回购均价（美元/股） | B93: ='00-三表与联动'!$B$6*$B$135*(1+$B$211)^0.5 -> 945.01367 | C93: ='00-三表与联动'!$B$6*$B$135*(1+$B$211)^1.5 -> 1034.79 | D93: ='00-三表与联动'!$B$6*$B$135*(1+$B$211)^2.5 -> 1133.095 | E93: ='00-三表与联动'!$B$6*$B$135*(1+$B$211)^3.5 -> 1240.739 | F93: ='00-三表与联动'!$B$6*$B$135*(1+$B$211)^4.5 -> 1358.6093 | G93: ='00-三表与联动'!$B$6*$B$135*(1+$B$211)^5.5 -> 1487.6771 | H93: ＝ 当前股价 × 本节滑标倍数 ×(1+WACC)^(t−0.5)
A94: − 回购注销股数（百万股） | B94: =B92/B93 -> 154.8967 | C94: =C92/C93 -> 153.84112 | D94: =D92/D93 -> 155.70139 | E94: =E92/E93 -> 155.00437 | F94: =F92/F93 -> 151.4631 | G94: =G92/G93 -> 145.22055 | H94: ＝ 回购金额 ÷ 回购均价
A95: ＋ 股权激励新增股数（百万股） | B95: =B32*0.0115/B93 -> 2.9571 | C95: =C32*0.0115/C93 -> 3.1056302 | D95: =D32*0.0115/D93 -> 3.2332588 | E95: =E32*0.0115/E93 -> 3.3070775 | F95: =F32*0.0115/F93 -> 3.3221783 | G95: =G32*0.0115/G93 -> 3.276669 | H95: ＝ 收入 × 1.15% ÷ 回购均价。FY26 股份支付 $232M ÷ 收入 $20,248M ＝ 1.15%
A96: 期初摊薄股数（百万股） | B96: ='00-三表与联动'!$B$9 -> 1150 | C96: =B97 -> 998.0604 | D96: =C97 -> 847.32491 | E96: =D97 -> 694.85679 | F96: =E97 -> 543.1595 | G96: =F97 -> 395.01858 | H96: FY27 期初取公司指引的 155；其后为上年期末
A97: 期末摊薄股数（百万股） | B97: =MAX(20,B96-B94+B95) -> 998.0604 | C97: =MAX(20,C96-C94+C95) -> 847.32491 | D97: =MAX(20,D96-D94+D95) -> 694.85679 | E97: =MAX(20,E96-E94+E95) -> 543.1595 | F97: =MAX(20,F96-F94+F95) -> 395.01858 | G97: =MAX(20,G96-G94+G95) -> 253.0747 | H97: ＝ 期初 − 回购注销 + 股权激励新增，下限锁 20
A98: 净现金余额 | B98: =('00-三表与联动'!$B$10-'00-三表与联动'!$B$11)+B90-B92 -> 24433 | C98: =B98+C90-C92 -> 24433 | D98: =C98+D90-D92 -> 24433 | E98: =D98+E90-E92 -> 24433 | F98: =E98+F90-F92 -> 24433 | G98: =F98+G90-G92 -> 24433 | H98: ＝ 上期净现金 + FCFF − 回购金额。★ 回购比例＜100% 时现金会累积，这部分价值必须计入，否则会低估
A99: 税后经营利润 NOPAT | B99: =B39 -> 170664.65 | C99: =C39 -> 185366.17 | D99: =D39 -> 205933.55 | E99: =E39 -> 224615.62 | F99: =F39 -> 240444.24 | G99: =G39 -> 252516.2 | H99: 链接自上方年度预测表。★ 用 NOPAT 而非净利润，是为了与 DCF 同口径（不含利息）
A100: 经营性每股收益 EPS | B100: =B99/B97 -> 170.99631 | C100: =C99/C97 -> 218.76634 | D100: =D99/D97 -> 296.36833 | E100: =E99/E97 -> 413.5353 | F100: =F99/F97 -> 608.69097 | G100: =G99/G97 -> 997.79315 | H100: ＝ NOPAT ÷ 期末股数。用期末股数而非加权平均，因为要回答的是「那个时点每一股值多少」
A101: 每股净现金 | B101: =B98/B97 -> 24.480482 | C101: =C98/C97 -> 28.835456 | D101: =D98/D97 -> 35.162641 | E101: =E98/E97 -> 44.983104 | F101: =F98/F97 -> 61.852787 | G101: =G98/G97 -> 96.544617 | H101: ＝ 净现金余额 ÷ 期末股数
A102: ★ 采用的 P/E 倍数 | B102: =$B$137 -> 9 | C102: =$B$139 -> 12 | D102: =$B$139+($B$141-$B$139)*1/4 -> 12.75 | E102: =$B$139+($B$141-$B$139)*2/4 -> 13.5 | F102: =$B$139+($B$141-$B$139)*3/4 -> 14.25 | G102: =$B$141 -> 15 | H102: FY27 / FY28 / FY32 各由本节独立滑标给定；FY29–FY31 在 FY28 与 FY32 之间线性过渡（四等分）
A103: 隐含股价（EPS×当年PE + 每股净现金） | B103: =B100*B102+B101 -> 1563.4473 | C103: =C100*C102+C101 -> 2654.0315 | D103: =D100*D102+D101 -> 3813.8589 | E103: =E100*E102+E101 -> 5627.7096 | F103: =F100*F102+F101 -> 8735.6992 | G103: =G100*G102+G101 -> 15063.442 | H103: 把现金单独加回，使本方法与 DCF（EV + 净现金）口径一致
A104: 折现因子（期末折现） | B104: =1/(1+$B$211)^1 -> 0.91324201 | C104: =1/(1+$B$211)^2 -> 0.83401097 | D104: =1/(1+$B$211)^3 -> 0.76165385 | E104: =1/(1+$B$211)^4 -> 0.69557429 | F104: =1/(1+$B$211)^5 -> 0.63522767 | G104: =1/(1+$B$211)^6 -> 0.58011659 | H104: ＝ 1 ÷ (1+WACC)^t。股价是时点数用期末折现；上方 DCF 的现金流是期间数用期中折现
A105: 折现后每股价值 | B105: =B103*B104 -> 1427.8057 | C105: =C103*C104 -> 2213.4914 | D105: =D103*D104 -> 2904.8403 | E105: =E103*E104 -> 3914.4901 | F105: =F103*F104 -> 5549.1578 | G105: =G103*G104 -> 8738.5525 | H105: ＝ 隐含股价 × 折现因子
A107: 6.1 三个关键年份的目标价：各用各的 P/E
A108: 年份 | B108: 经营性 EPS | C108: 每股净现金 | D108: 采用 P/E | E108: 隐含目标价 | F108: 折现期（年） | G108: 折现后每股价值 | H108: 折现后 ÷ 现价 − 1 | I108: 这个数字回答什么
...
