Workbook

Sheet 00-三表与联动
A1: SNDK · Sandisk Corporation —— 三表与联动
A2: 单位：百万美元 | 财年截止约每年 7 月初 | 数据源：公司 FY26 Q2/Q3/Q4 财报原文 | FY26 Q4 止于 2026-07-03
A4: 00 公司速览与估值锚点
A5: 项目 | B5: 数值 | D5: 口径与说明
A6: 现价（2026-08-26） | B6: 1500.17 | D6: Yahoo Finance 盘中价
A7: 市值 | B7: 219653 | D7: ＝ 现价 × 基本股数
A8: 基本股数（百万股） | B8: 146.4 | D8: 回购后；FY26末为 149M，其后继续回购
A9: 摊薄股数（百万股） | B9: 155 | D9: 公司 FY27 Q1 指引「约 155」
A10: 货币资金 | B10: 4762 | D10: FY26 Q4末资产负债表
A11: 可交易权益证券 | B11: 1777 | D11: Q4 新增；当季确认 $804M 公允价值收益
A12: 有息负债 | B12: 0 | D12: ★ FY26 Q3 起已清零，公司为净现金结构
A13: 无风险利率 Rf | B13: 0.042 | D13: 10 年期美国国债收益率
A14: 股权风险溢价 ERP | B14: 0.05 | D14: 美国成熟市场长期股权风险溢价
A15: 01 三情形估值对比（数字实时链接自后面三张 DCF 表）
A16: 情形 | B16: 每股内在价值 | C16: 相对现价 | D16: 终值占 EV | E16: FY27 收入 | F16: FY27 毛利率 | G16: FY32 毛利率 | H16: WACC | I16: 永续 g | J16: 一句话论点
A17: 悲观 | B17: ='01-DCF-悲观'!B72 -> 498.8613 | C17: ='01-DCF-悲观'!B74 -> -0.66746348 | D17: ='01-DCF-悲观'!B65 -> 0.45499456 | E17: ='01-DCF-悲观'!F13 -> 37000 | F17: ='01-DCF-悲观'!F15 -> 0.72798647 | G17: ='01-DCF-悲观'!G34 -> 0.46 | H17: ='01-DCF-悲观'!$B$209 -> 0.14 | I17: ='01-DCF-悲观'!$B$211 -> 0.025 | J17: NAND 2027 年转过剩，价格与毛利率回到历史中枢
A18: 基准 | B18: ='02-DCF-基准'!B72 -> 1630.9395 | C18: ='02-DCF-基准'!B74 -> 0.087169783 | D18: ='02-DCF-基准'!B65 -> 0.61941705 | E18: ='02-DCF-基准'!F13 -> 41849.994 | F18: ='02-DCF-基准'!F15 -> 0.80583035 | G18: ='02-DCF-基准'!G34 -> 0.68 | H18: ='02-DCF-基准'!$B$209 -> 0.12 | I18: ='02-DCF-基准'!$B$211 -> 0.03 | J18: 周期见顶但不崩塌，AI 数据中心把毛利率中枢抬到 68%–72%
A19: 乐观 | B19: ='03-DCF-乐观'!B72 -> 4068.1449 | C19: ='03-DCF-乐观'!B74 -> 1.7117893 | D19: ='03-DCF-乐观'!B65 -> 0.70816859 | E19: ='03-DCF-乐观'!F13 -> 49199.987 | F19: ='03-DCF-乐观'!F15 -> 0.84819309 | G19: ='03-DCF-乐观'!G34 -> 0.76 | H19: ='03-DCF-乐观'!$B$209 -> 0.105 | I19: ='03-DCF-乐观'!$B$211 -> 0.035 | J19: NBM 长约把存储合约化，管理层 FY28–30 框架成立
A20: 当前股价（2026-08-26） | B20: 1500.17 | C20: 52 周区间 $46.75 – $2,354.39；距峰值已回撤约 37%
A21: 卖方一致目标价 | B21: 2126 | C21: S&P Global 汇总 24 家机构，评级「买入」；最低 $1,000、最高 $3,600。区间跨度本身说明分歧极大
A22: ★ 三个情形的每股价值跨度是 $484 → $4,087，相差 8.4 倍。这不是模型不精确，而是这个行业在这个时点上真实的不确定性——卖方目标价从 $1,000 到 $3,600 的分布，说明专业机构之间的分歧同样巨大。把任何单一情形当作「答案」都是误用；正确的用法是问：什么样的证据会让我在三者之间移动。
A24: ★ 读这张表之前必须知道的三件事：① SNDK 于 2025-02-21 从西部数据（WDC）分拆独立，2025-02-21 之前为「视同独立」的划分报表，可比性有限；② 公司晶圆厂在与铠侠合资的 Flash Ventures 里，因此账面资本开支极低（FY26 仅 $177M），真实的产能投入走「向 Flash Ventures 发放票据」这条投资活动科目——做 DCF 时必须把它算作资本开支，否则会系统性高估自由现金流；③ FY26 是存储超级周期的顶点，Q4 毛利率 84.6%，把这个盈利水平外推是本模型最大的风险来源。
A26: 02 合并利润表（季度 + 年度）
A27: 科目（百万美元） | B27: FY26 Q1 | C27: FY26 Q2 | D27: FY26 Q3 | E27: FY26 Q4 | F27: FY2026 | G27: FY2025 | H27: Q4 环比 | I27: Q4 同比 | J27: FY26 同比 | K27: 备注
A28: 营业收入 Revenue, net | B28: 2308 | C28: 3025 | D28: 5950 | E28: 8965 | F28: 20248 | G28: 7355 | H28: =IF(D28=0,"n/a",E28/ABS(D28)-1) -> 0.50672269 | I28: =IF(G28=0,"n/a","n/a") -> n/a | J28: =IF(G28=0,"n/a",F28/ABS(G28)-1) -> 1.7529572
A29: 营业成本 Cost of revenue | B29: 1621 | C29: 1484 | D29: 1288 | E29: 1383 | F29: 5776 | G29: 5143 | H29: =IF(D29=0,"n/a",E29/ABS(D29)-1) -> 0.073757764 | I29: =IF(G29=0,"n/a","n/a") -> n/a | J29: =IF(G29=0,"n/a",F29/ABS(G29)-1) -> 0.12307991
A30: 毛利 Gross profit | B30: 687 | C30: 1541 | D30: 4662 | E30: 7582 | F30: 14472 | G30: 2212 | H30: =IF(D30=0,"n/a",E30/ABS(D30)-1) -> 0.62634063 | I30: =IF(G30=0,"n/a","n/a") -> n/a | J30: =IF(G30=0,"n/a",F30/ABS(G30)-1) -> 5.5424955
A31: 研发费用 R&D | B31: 316 | C31: 327 | D31: 337 | E31: 348 | F31: 1328 | G31: 1132 | H31: =IF(D31=0,"n/a",E31/ABS(D31)-1) -> 0.03264095 | I31: =IF(G31=0,"n/a","n/a") -> n/a | J31: =IF(G31=0,"n/a",F31/ABS(G31)-1) -> 0.17314488
A32: 销售管理费用 SG&A | B32: 179 | C32: 139 | D32: 161 | E32: 197 | F32: 676 | G32: 573 | H32: =IF(D32=0,"n/a",E32/ABS(D32)-1) -> 0.22360248 | I32: =IF(G32=0,"n/a","n/a") -> n/a | J32: =IF(G32=0,"n/a",F32/ABS(G32)-1) -> 0.17975567
A33: 商誉减值 Goodwill impairment | B33: 0 | C33: 0 | D33: 0 | E33: 0 | F33: 0 | G33: 1830 | H33: =IF(D33=0,"n/a",E33/ABS(D33)-1) -> n/a | I33: =IF(G33=0,"n/a","n/a") -> n/a | J33: =IF(G33=0,"n/a",F33/ABS(G33)-1) -> -1
A34: 债务清偿损失 Loss on debt exting. | B34: 0 | C34: 0 | D34: 46 | E34: 0 | F34: 46 | G34: 0 | H34: =IF(D34=0,"n/a",E34/ABS(D34)-1) -> -1 | I34: =IF(G34=0,"n/a","n/a") -> n/a | J34: =IF(G34=0,"n/a",F34/ABS(G34)-1) -> n/a
A35: 分拆费用 Business separation costs | B35: 9 | C35: 9 | D35: 7 | E35: 0 | F35: 25 | G35: 67 | H35: =IF(D35=0,"n/a",E35/ABS(D35)-1) -> -1 | I35: =IF(G35=0,"n/a","n/a") -> n/a | J35: =IF(G35=0,"n/a",F35/ABS(G35)-1) -> -0.62686567
A36: 裁员及其他 Employee term. & other | B36: -3 | C36: 1 | D36: 0 | E36: 0 | F36: -2 | G36: 21 | H36: =IF(D36=0,"n/a",E36/ABS(D36)-1) -> n/a | I36: =IF(G36=0,"n/a","n/a") -> n/a | J36: =IF(G36=0,"n/a",F36/ABS(G36)-1) -> -1.0952381
A37: 业务处置(收益)损失 Divestiture | B37: 10 | C37: 0 | D37: 0 | E37: 0 | F37: 10 | G37: -34 | H37: =IF(D37=0,"n/a",E37/ABS(D37)-1) -> n/a | I37: =IF(G37=0,"n/a","n/a") -> n/a | J37: =IF(G37=0,"n/a",F37/ABS(G37)-1) -> -0.70588235
A38: 营业费用合计 Total opex | B38: 511 | C38: 476 | D38: 551 | E38: 545 | F38: 2083 | G38: 3589 | H38: =IF(D38=0,"n/a",E38/ABS(D38)-1) -> -0.010889292 | I38: =IF(G38=0,"n/a","n/a") -> n/a | J38: =IF(G38=0,"n/a",F38/ABS(G38)-1) -> -0.41961549
A39: 营业利润 Operating income | B39: 176 | C39: 1065 | D39: 4111 | E39: 7037 | F39: 12389 | G39: -1377 | H39: =IF(D39=0,"n/a",E39/ABS(D39)-1) -> 0.71174897 | I39: =IF(G39=0,"n/a","n/a") -> n/a | J39: =IF(G39=0,"n/a",F39/ABS(G39)-1) -> 7.9970951
... A47: 净利润 Net income | B47: 112 | C47: 803 | D47: 3615 | E47: 6903 | F47: 11433 | G47: -1641 | H47: =IF(D47=0,"n/a",E47/ABS(D47)-1) -> 0.90954357 | I47: =IF(G47=0,"n/a","n/a") -> n/a | J47: =IF(G47=0,"n/a",F47/ABS(G47)-1) -> 5.9670932
A48: 毛利率 Gross margin | B48: =B30/B28 -> 0.29766031 | C48: =C30/C28 -> 0.50942149 | D48: =D30/D28 -> 0.78352941 | E48: =E30/E28 -> 0.84573341 | F48: =F30/F28 -> 0.71473726 | G48: =G30/G28 -> 0.30074779
A49: 营业利润率 Operating margin | B49: =B39/B28 -> 0.076256499 | C49: =C39/C28 -> 0.35206612 | D49: =D39/D28 -> 0.69092437 | E49: =E39/E28 -> 0.78494144 | F49: =F39/F28 -> 0.6118629 | G49: =G39/G28 -> -0.18721958
A50: 净利率 Net margin | B50: =B47/B28 -> 0.048526863 | C50: =C47/C28 -> 0.26545455 | D50: =D47/D28 -> 0.60756303 | E50: =E47/E28 -> 0.76999442 | F50: =F47/F28 -> 0.56464836 | G50: =G47/G28 -> -0.22311353
A51: 费用率 Opex % of revenue | B51: =B38/B28 -> 0.22140381 | C51: =C38/C28 -> 0.15735537 | D51: =D38/D28 -> 0.092605042 | E51: =E38/E28 -> 0.060791969 | F51: =F38/F28 -> 0.10287436 | G51: =G38/G28 -> 0.48796737
A52: 摊薄每股收益 Diluted EPS ($) | B52: 0.75 | C52: 5.15 | D52: 23.03 | E52: 43.97 | F52: 73.76 | G52: -11.32
A53: 基本每股收益 Basic EPS ($) | B53: 0.77 | C53: 5.46 | D53: 24.43 | E53: 46.96 | F53: 77.78 | G53: -11.32
A54: 摊薄股数 Diluted shares (M) | B54: 149 | C54: 156 | D54: 157 | E54: 157 | F54: 155 | G54: 145
A55: 基本股数 Basic shares (M) | B55: 145 | C55: 147 | D55: 148 | E55: 147 | F55: 147 | G55: 145
A56: ★ 四个季度的毛利率路径是 29.8% → 50.9% → 78.4% → 84.6%。这不是经营改善，是 NAND 合约价在四个季度里翻了数倍——营业成本几乎没动（1,621 → 1,383），收入却涨了 3.9 倍。做 DCF 时，「毛利率能不能维持」几乎等价于「NAND 价格能不能维持」。
A58: 03 分市场收入
A59: 终端市场 | B59: FY26 Q1 | C59: FY26 Q2 | D59: FY26 Q3 | E59: FY26 Q4 | F59: FY2026 | G59: FY2025 | H59: FY26 同比 | I59: FY26 占比
A60: 数据中心 Datacenter | B60: 269 | C60: 440 | D60: 1467 | E60: 2977 | F60: 5153 | G60: 960 | H60: =F60/G60-1 -> 4.3677083 | I60: =F60/F28 -> 0.25449427
A61: 边缘 Edge | B61: 1387 | C61: 1678 | D61: 3663 | E61: 5432 | F61: 12160 | G61: 4127 | H61: =F61/G61-1 -> 1.9464502 | I61: =F61/F28 -> 0.60055314
A62: 消费 Consumer | B62: 652 | C62: 907 | D62: 820 | E62: 556 | F62: 2935 | G62: 2268 | H62: =F62/G62-1 -> 0.29409171 | I62: =F62/F28 -> 0.14495259
A63: 合计（应等于营业收入） | B63: =SUM(B60:B62) -> 2308 | C63: =SUM(C60:C62) -> 3025 | D63: =SUM(D60:D62) -> 5950 | E63: =SUM(E60:E62) -> 8965 | F63: =SUM(F60:F62) -> 20248 | G63: =SUM(G60:G62) -> 7355
A64: 数据中心收入 FY26 同比 +437%，Q4 单季 $2,977M；而消费业务 Q4 环比 −32%——公司在主动把产能从消费端转向数据中心。这正是《缺口的算术》里说的「需求被重新分配给出得起价的买家」在单个公司报表上的样子。
A66: 04 合并资产负债表（四个时点）
A67: 科目（百万美元） | B67: 2025-06-27 (FY25末) | C67: 2026-01-02 (FY26 Q2末) | D67: 2026-04-03 (FY26 Q3末) | E67: 2026-07-03 (FY26 Q4末) | F67: Q4 较 FY25末 | G67: 变动率 | H67: 备注
A68: 【资产】
A69: 货币资金 Cash & equivalents | B69: 1481 | C69: 1539 | D69: 3735 | E69: 4762 | F69: =E69-B69 -> 3281 | G69: =IF(B69=0,"n/a",E69/B69-1) -> 2.215395
A70: 应收账款净额 Accounts receivable, net | B70: 1068 | C70: 1239 | D70: 2726 | E70: 4708 | F70: =E70-B70 -> 3640 | G70: =IF(B70=0,"n/a",E70/B70-1) -> 3.4082397
A71: 存货 Inventories | B71: 2079 | C71: 1970 | D71: 2238 | E71: 2698 | F71: =E71-B71 -> 619 | G71: =IF(B71=0,"n/a",E71/B71-1) -> 0.2977393
A72: 应收所得税 Income tax receivable | B72: 66 | C72: 45 | D72: 81 | E72: 22 | F72: =E72-B72 -> -44 | G72: =IF(B72=0,"n/a",E72/B72-1) -> -0.66666667
A73: 其他流动资产 Other current assets | B73: 392 | C73: 357 | D73: 388 | E73: 590 | F73: =E73-B73 -> 198 | G73: =IF(B73=0,"n/a",E73/B73-1) -> 0.50510204
A74: 流动资产合计 Total current assets | B74: 5086 | C74: 5150 | D74: 9168 | E74: 12780 | F74: =E74-B74 -> 7694 | G74: =IF(B74=0,"n/a",E74/B74-1) -> 1.5127802
A75: 可交易权益证券 Marketable equity securities | B75: 0 | C75: 0 | D75: 0 | E75: 1777 | F75: =E75-B75 -> 1777 | G75: =IF(B75=0,"n/a",E75/B75-1) -> n/a
A76: 固定资产净额 PP&E, net | B76: 619 | C76: 631 | D76: 649 | E76: 674 | F76: =E76-B76 -> 55 | G76: =IF(B76=0,"n/a",E76/B76-1) -> 0.088852989
A77: Flash Ventures 应收票据及投资 | B77: 654 | C77: 677 | D77: 684 | E77: 678 | F77: =E77-B77 -> 24 | G77: =IF(B77=0,"n/a",E77/B77-1) -> 0.036697248
A78: 商誉 Goodwill | B78: 4999 | C78: 4995 | D78: 4994 | E78: 4994 | F78: =E78-B78 -> -5 | G78: =IF(B78=0,"n/a",E78/B78-1) -> -0.0010002
A79: 非流动应收所得税 Income tax receivable, NC | B79: 80 | C79: 98 | D79: 134 | E79: 169 | F79: =E79-B79 -> 89 | G79: =IF(B79=0,"n/a",E79/B79-1) -> 1.1125
A80: 递延所得税资产 Deferred tax assets | B80: 58 | C80: 62 | D80: 87 | E80: 66 | F80: =E80-B80 -> 8 | G80: =IF(B80=0,"n/a",E80/B80-1) -> 0.13793103
... A82: 资产总计 Total assets | B82: 12985 | C82: 12998 | D82: 17075 | E82: 22507 | F82: =E82-B82 -> 9522 | G82: =IF(B82=0,"n/a",E82/B82-1) -> 0.73330766
A83: 【负债】
A84: 应付账款 Accounts payable | B84: 366 | C84: 436 | D84: 416 | E84: 516 | F84: =E84-B84 -> 150 | G84: =IF(B84=0,"n/a",E84/B84-1) -> 0.40983607
A85: 应付关联方 AP to related parties | B85: 400 | C85: 433 | D85: 435 | E85: 460 | F85: =E85-B85 -> 60 | G85: =IF(B85=0,"n/a",E85/B85-1) -> 0.15
A86: 应计费用 Accrued expenses | B86: 274 | C86: 393 | D86: 383 | E86: 313 | F86: =E86-B86 -> 39 | G86: =IF(B86=0,"n/a",E86/B86-1) -> 0.14233577
A87: 应计薪酬 Accrued compensation | B87: 173 | C87: 273 | D87: 329 | E87: 657 | F87: =E87-B87 -> 484 | G87: =IF(B87=0,"n/a",E87/B87-1) -> 2.7976879
A88: 退款负债 Refund liabilities | B88: 126 | C88: 0 | D88: 0 | E88: 1500 | F88: =E88-B88 -> 1374 | G88: =IF(B88=0,"n/a",E88/B88-1) -> 10.904762
A89: 合同负债 Contract liabilities | B89: 25 | C89: 0 | D89: 323 | E89: 849 | F89: =E89-B89 -> 824 | G89: =IF(B89=0,"n/a",E89/B89-1) -> 32.96
A90: 应交所得税(流动) Income tax payable | B90: 43 | C90: 99 | D90: 31 | E90: 1286 | F90: =E90-B90 -> 1243 | G90: =IF(B90=0,"n/a",E90/B90-1) -> 28.906977
A91: 一年内到期长期债务 Current LTD | B91: 20 | C91: 20 | D91: 0 | E91: 0 | F91: =E91-B91 -> -20 | G91: =IF(B91=0,"n/a",E91/B91-1) -> -1
A92: 流动负债合计 Total current liabilities | B92: 1427 | C92: 1654 | D92: 1917 | E92: 5581 | F92: =E92-B92 -> 4154 | G92: =IF(B92=0,"n/a",E92/B92-1) -> 2.9110021
A93: 递延所得税负债 Deferred tax liabilities | B93: 17 | C93: 22 | D93: 17 | E93: 161 | F93: =E93-B93 -> 144 | G93: =IF(B93=0,"n/a",E93/B93-1) -> 8.4705882
A94: 应交所得税(非流动) Income tax payable, NC | B94: 131 | C94: 0 | D94: 783 | E94: 258 | F94: =E94-B94 -> 127 | G94: =IF(B94=0,"n/a",E94/B94-1) -> 0.96946565
A95: 长期债务 Long-term debt | B95: 1829 | C95: 583 | D95: 0 | E95: 0 | F95: =E95-B95 -> -1829 | G95: =IF(B95=0,"n/a",E95/B95-1) -> -1
... A98: 负债合计 Total liabilities | B98: 3769 | C98: 2785 | D98: 3298 | E98: 6771 | F98: =E98-B98 -> 3002 | G98: =IF(B98=0,"n/a",E98/B98-1) -> 0.79649774
A99: 【股东权益】
A100: 普通股 Common stock | B100: 1 | C100: 1 | D100: 1 | E100: 1 | F100: =E100-B100 -> 0 | G100: =IF(B100=0,"n/a",E100/B100-1) -> 0
A101: 库存股 Treasury stock | B101: 0 | C101: 0 | D101: 0 | E101: -4537 | F101: =E101-B101 -> -4537 | G101: =IF(B101=0,"n/a",E101/B101-1) -> n/a
A102: 资本公积 Additional paid-in capital | B102: 11248 | C102: 11336 | D102: 11289 | E102: 10879 | F102: =E102-B102 -> -369 | G102: =IF(B102=0,"n/a",E102/B102-1) -> -0.032805832
A103: 累计其他综合损失 AOCI | B103: -249 | C103: -255 | D103: -259 | E103: -256 | F103: =E103-B103 -> -7 | G103: =IF(B103=0,"n/a",E103/B103-1) -> 0.02811245
A104: 留存收益(累计亏损) Retained earnings | B104: -1784 | C104: -869 | D104: 2746 | E104: 9649 | F104: =E104-B104 -> 11433 | G104: =IF(B104=0,"n/a",E104/B104-1) -> -6.4086323
A105: 股东权益合计 Total shareholders' equity | B105: 9216 | C105: 10213 | D105: 13777 | E105: 15736 | F105: =E105-B105 -> 6520 | G105: =IF(B105=0,"n/a",E105/B105-1) -> 0.70746528
A106: 口径提示：应计费用 / 退款负债 / 合同负债 三行在不同季度的财报里做过重分类（FY25末的应计费用在 Q2 财报中列示为 425，在 FY26 年报中拆分为应计费用 274 + 退款负债 126 + 合同负债 25）。本表统一采用 FY26 年报（最新）的列示口径，四个时点的资产 = 负债 + 权益均已逐列校验平衡。
A108: 05 合并现金流量表（季度 + 年度）
A109: 科目（百万美元） | B109: FY26 Q1 | C109: FY26 Q2 | D109: FY26 Q3 | E109: FY26 Q4 | F109: FY2026 | G109: 占收入比 | H109: 备注
A110: 【经营活动】
A111: 净利润 Net income | B111: =B47 -> 112 | C111: =C47 -> 803 | D111: =D47 -> 3615 | E111: =E47 -> 6903 | F111: =F47 -> 11433 | G111: =F111/F28 -> 0.56464836
A112: 折旧与摊销 D&A | B112: 36 | C112: 38 | D112: 38 | E112: 37 | F112: 149 | G112: =F112/F28 -> 0.0073587515
A113: 股份支付 Stock-based compensation | B113: 53 | C113: 58 | D113: 54 | E113: 67 | F113: 232 | G113: =F113/F28 -> 0.011457922
A114: 递延所得税 Deferred income taxes | B114: 3 | C114: -13 | D114: -32 | E114: 162 | F114: 120 | G114: =F114/F28 -> 0.0059265113
A115: 权益证券(收益)损失 (Gain) on equity sec. | B115: 0 | C115: 0 | D115: -4 | E115: -804 | F115: -808 | G115: =F115/F28 -> -0.039905176
A116: 汇兑(收益)损失 Unrealized FX | B116: 1 | C116: 19 | D116: 19 | E116: 47 | F116: 86 | G116: =F116/F28 -> 0.0042473331
...

Sheet 01-DCF-悲观
A1: BEAR · SNDK 现金流折现模型 —— 悲观情形
A2: FY2027 分四个季度 → FY2028–FY2032 按年 → 永续 | 自由现金流口径：FCFF（含 Flash Ventures 投入） | ▼ 全部参数由本表底部的参数控制台滑标驱动
A4: 00 本情形的论点：这套数字建立在什么判断之上
A5: 承接《缺口的算术》NAND 侧的结论：层数堆叠与 QLC 让 NAND 供给可以在不建厂的情况下快速放大，2027 年 NAND 先于 DRAM 转向过剩。本情形假设合约价在 FY27 下半年见顶回落，FY28 出现典型的存储下行周期——价格跌幅快于成本，毛利率从 84.6% 一路回到 40% 出头的历史中枢。
A6: 1．FY27 下半年合约价环比转负，Q4 收入回到 $7.1B（≈ FY26 Q4 水平的 79%）
A7: 2．FY28 收入 −34%、毛利率回到 42%——接近 SNDK 分拆前的正常年份
A8: 3．NBM 长约只锁量不锁价，价格下行时无法保护利润率
A9: 4．WACC 用 14%（周期底部风险溢价上升），永续增长 2.5%
A11: 01 FY2027 季度预测（SNDK 分拆才一年半，先用季度把最近的可见度做实）
A12: 科目（百万美元） | B12: FY27 Q1 | C12: FY27 Q2 | D12: FY27 Q3 | E12: FY27 Q4 | F12: FY2027 合计 | G12: 变量怎么来的
A13: 营业收入 | B13: =$B$189 -> 10550 | C13: =B13*(1+-0.009479+$B$191) -> 10449.997 | D13: =C13*(1+-0.148325+$B$191) -> 8900.0008 | E13: =D13*(1+-0.202247+$B$191) -> 7100.0023 | F13: =SUM(B13:E13) -> 37000 | G13: Q1 ＝ 控制台滑标（官方指引 $10.3–10.8B）；Q2–Q4 ＝ 上一季 ×(1 + 情形环比增速 + 滑标平移)
A14: 环比增速 QoQ | B14: =B13/'00-三表与联动'!E28-1 -> 0.17679866 | C14: =C13/B13-1 -> -0.009479 | D14: =D13/C13-1 -> -0.148325 | E14: =E13/D13-1 -> -0.202247 | F14: =F13/'00-三表与联动'!F28-1 -> 0.82734096 | G14: Q1 的环比基数是 FY26 Q4 的 $8,965M（不是 FY26 全年）；Q2–Q4 为上一季
A15: 毛利率 | B15: =MAX(0.05,MIN(0.92,0.83+$B$193)) -> 0.83 | C15: =MAX(0.05,MIN(0.92,0.78+$B$193)) -> 0.78 | D15: =MAX(0.05,MIN(0.92,0.68+$B$193)) -> 0.68 | E15: =MAX(0.05,MIN(0.92,0.56+$B$193)) -> 0.56 | F15: =F16/F13 -> 0.72798647 | G15: 情形设定的季度毛利率路径 + 控制台「毛利率平移」，上下限锁在 5%–92%
A16: 毛利 | B16: =B13*B15 -> 8756.5 | C16: =C13*C15 -> 8150.9973 | D16: =D13*D15 -> 6052.0006 | E16: =E13*E15 -> 3976.0013 | F16: =SUM(B16:E16) -> 26935.499 | G16: ＝ 收入 × 毛利率
A17: 营业费用 | B17: =B13*$B$199 -> 738.5 | C17: =C13*$B$199 -> 731.49976 | D17: =D13*$B$199 -> 623.00006 | E17: =E13*$B$199 -> 497.00016 | F17: =SUM(B17:E17) -> 2590 | G17: ＝ 收入 × 控制台「营业费用率」。公司 FY27 Q1 GAAP 指引为 $574–614M
A18: 营业利润 EBIT | B18: =B16-B17 -> 8018 | C18: =C16-C17 -> 7419.4976 | D18: =D16-D17 -> 5429.0005 | E18: =E16-E17 -> 3479.0012 | F18: =SUM(B18:E18) -> 24345.499 | G18: ＝ 毛利 − 营业费用
A19: 营业利润率 | B19: =B18/B13 -> 0.76 | C19: =C18/C13 -> 0.71 | D19: =D18/D13 -> 0.61 | E19: =E18/E13 -> 0.49 | F19: =F18/F13 -> 0.65798647 | G19: ＝ EBIT ÷ 收入
A20: 所得税 | B20: =MAX(0,B18)*$B$201 -> 1363.06 | C20: =MAX(0,C18)*$B$201 -> 1261.3146 | D20: =MAX(0,D18)*$B$201 -> 922.93008 | E20: =MAX(0,E18)*$B$201 -> 591.4302 | F20: =SUM(B20:E20) -> 4138.7349 | G20: ＝ EBIT × 控制台「有效税率」（FCFF 口径按 EBIT 计税，不含利息）
A21: 税后经营利润 NOPAT | B21: =B18-B20 -> 6654.94 | C21: =C18-C20 -> 6158.183 | D21: =D18-D20 -> 4506.0704 | E21: =E18-E20 -> 2887.571 | F21: =SUM(B21:E21) -> 20206.764 | G21: ＝ EBIT − 所得税
A22: ＋ 折旧摊销 D&A | B22: =B13*0.0074 -> 78.07 | C22: =C13*0.0074 -> 77.329974 | D22: =D13*0.0074 -> 65.860006 | E22: =E13*0.0074 -> 52.540017 | F22: =SUM(B22:E22) -> 273.8 | G22: ＝ 收入 × 0.74%（FY26 实际 D&A $149M ÷ 收入 $20,248M）。数字极低是因为晶圆厂在合资公司里，折旧不落在 SNDK 报表上
A23: − 自有资本开支 | B23: =-B13*$B$203 -> -189.9 | C23: =-C13*$B$203 -> -188.09994 | D23: =-D13*$B$203 -> -160.20001 | E23: =-E13*$B$203 -> -127.80004 | F23: =SUM(B23:E23) -> -665.99999 | G23: ＝ 收入 × 控制台「自有资本开支率」。FY26 实际 0.87%
A24: − Flash Ventures 净投入 | B24: =-B13*$B$205 -> -390.35 | C24: =-C13*$B$205 -> -386.64987 | D24: =-D13*$B$205 -> -329.30003 | E24: =-E13*$B$205 -> -262.70009 | F24: =SUM(B24:E24) -> -1369 | G24: ＝ 收入 × 控制台「FV 净投入率」。FY26 实际 1.36%（发放票据 462 − 回收 187）
A25: 营运资本余额 | B25: =B13*4*$B$207 -> 8440 | C25: =C13*4*$B$207 -> 8359.9972 | D25: =D13*4*$B$207 -> 7120.0006 | E25: =E13*4*$B$207 -> 5680.0019 | F25: =E25 -> 5680.0019 | G25: ＝ 控制台「营运资本占年化收入比」× 当季收入 × 4。期初取 FY26 Q4 的年化收入基准
A26: − 营运资本增加 ΔNWC | B26: =-(B25-'00-三表与联动'!E28*4*$B$207) -> -1268 | C26: =-(C25-B25) -> 80.00276 | D26: =-(D25-C25) -> 1239.9966 | E26: =-(E25-D25) -> 1439.9988 | F26: =SUM(B26:E26) -> 1491.9981 | G26: ＝ 本季余额 − 上季余额。余额法，不再用「占收入增量比」
A27: ＝ 自由现金流 FCFF | B27: =B21+B22+B23+B24+B26 -> 4884.76 | C27: =C21+C22+C23+C24+C26 -> 5740.7659 | D27: =D21+D22+D23+D24+D26 -> 5322.427 | E27: =E21+E22+E23+E24+E26 -> 3989.6096 | F27: =SUM(B27:E27) -> 19937.562 | G27: ＝ NOPAT + D&A − 自有资本开支 − FV 净投入 − ΔNWC
A28: 口径说明：这里算的是 FCFF（企业自由现金流），所以税按 EBIT 计、不扣利息——利息的价值已经体现在折现率里。公司目前零负债，FCFF 与 FCFE 的差异只剩利息收入。
A30: 02 FY2028–FY2032 年度预测 + 永续
A31: 科目（百万美元） | B31: FY2027 | C31: FY2028 | D31: FY2029 | E31: FY2030 | F31: FY2031 | G31: FY2032 | H31: 永续期 | I31: 变量怎么来的
A32: 营业收入 | B32: =F13 -> 37000 | C32: =B32*(1+-0.34) -> 24420 | D32: =C32*(1+-0.1+$B$197) -> 21978 | E32: =D32*(1+0.12+$B$197) -> 24615.36 | F32: =E32*(1+0.1+$B$197) -> 27076.896 | G32: =F32*(1+0.08+$B$197) -> 29243.047 | H32: =G32*(1+$B$211) -> 29974.124 | I32: FY27 取季度合计；FY28 ＝ 情形设定增速；FY29–32 ＝ 情形增速 + 控制台「长期增速平移」
A33: 收入增速 YoY | B33: =B32/'00-三表与联动'!F28-1 -> 0.82734096 | C33: =C32/B32-1 -> -0.34 | D33: =D32/C32-1 -> -0.1 | E33: =E32/D32-1 -> 0.12 | F33: =F32/E32-1 -> 0.1 | G33: =G32/F32-1 -> 0.08 | H33: =$B$211 -> 0.025 | I33: 逐年同比。FY26 实际为 +175%
A34: 毛利率 | B34: =F16/F13 -> 0.72798647 | C34: =MAX(0.05,MIN(0.92,0.42+$B$193)) -> 0.42 | D34: =MAX(0.05,MIN(0.92,0.36+$B$193)) -> 0.36 | E34: =MAX(0.05,MIN(0.92,0.43+$B$193)) -> 0.43 | F34: =MAX(0.05,MIN(0.92,0.46+$B$193)) -> 0.46 | G34: =$B$195 -> 0.46 | H34: =G34 -> 0.46 | I34: 情形设定的年度毛利率 + 控制台「毛利率平移」；FY32 直接取控制台「终局毛利率」
A35: 毛利 | B35: =B32*B34 -> 26935.499 | C35: =C32*C34 -> 10256.4 | D35: =D32*D34 -> 7912.0799 | E35: =E32*E34 -> 10584.605 | F35: =F32*F34 -> 12455.372 | G35: =G32*G34 -> 13451.802 | H35: =H32*H34 -> 13788.097 | I35: ＝ 收入 × 毛利率
A36: 营业费用 | B36: =B32*$B$199 -> 2590 | C36: =C32*$B$199 -> 1709.4 | D36: =D32*$B$199 -> 1538.46 | E36: =E32*$B$199 -> 1723.0752 | F36: =F32*$B$199 -> 1895.3827 | G36: =G32*$B$199 -> 2047.0133 | H36: =H32*$B$199 -> 2098.1887 | I36: ＝ 收入 × 控制台「营业费用率」
A37: 营业利润 EBIT | B37: =B35-B36 -> 24345.499 | C37: =C35-C36 -> 8546.9999 | D37: =D35-D36 -> 6373.6199 | E37: =E35-E36 -> 8861.5295 | F37: =F35-F36 -> 10559.989 | G37: =G35-G36 -> 11404.789 | H37: =H35-H36 -> 11689.908 | I37: ＝ 毛利 − 营业费用
A38: 营业利润率 | B38: =B37/B32 -> 0.65798647 | C38: =C37/C32 -> 0.35 | D38: =D37/D32 -> 0.29 | E38: =E37/E32 -> 0.36 | F38: =F37/F32 -> 0.39 | G38: =G37/G32 -> 0.39 | H38: =H37/H32 -> 0.39 | I38: ＝ EBIT ÷ 收入。可与投资者日目标「约 75%」对照
A39: 税后经营利润 NOPAT | B39: =B37*(1-$B$201) -> 20206.764 | C39: =C37*(1-$B$201) -> 7094.0099 | D39: =D37*(1-$B$201) -> 5290.1046 | E39: =E37*(1-$B$201) -> 7355.0695 | F39: =F37*(1-$B$201) -> 8764.7912 | G39: =G37*(1-$B$201) -> 9465.9745 | H39: =H37*(1-$B$201) -> 9702.6238 | I39: ＝ EBIT ×(1 − 有效税率)
A40: ＋ 折旧摊销 D&A | B40: =B32*0.0074 -> 273.8 | C40: =C32*0.0074 -> 180.708 | D40: =D32*0.0074 -> 162.6372 | E40: =E32*0.0074 -> 182.15366 | F40: =F32*0.0074 -> 200.36903 | G40: =G32*0.0074 -> 216.39855 | H40: =H32*0.0074 -> 221.80851 | I40: ＝ 收入 × 0.74%
A41: − 自有资本开支 | B41: =-B32*$B$203 -> -665.99999 | C41: =-C32*$B$203 -> -439.56 | D41: =-D32*$B$203 -> -395.604 | E41: =-E32*$B$203 -> -443.07648 | F41: =-F32*$B$203 -> -487.38412 | G41: =-G32*$B$203 -> -526.37485 | H41: =-H32*$B$203 -> -539.53423 | I41: ＝ 收入 × 控制台「自有资本开支率」
A42: − Flash Ventures 净投入 | B42: =-B32*$B$205 -> -1369 | C42: =-C32*$B$205 -> -903.53999 | D42: =-D32*$B$205 -> -813.18599 | E42: =-E32*$B$205 -> -910.76831 | F42: =-F32*$B$205 -> -1001.8451 | G42: =-G32*$B$205 -> -1081.9928 | H42: =-H32*$B$205 -> -1109.0426 | I42: ＝ 收入 × 控制台「FV 净投入率」
A43: 营运资本余额 | B43: =B32*$B$207 -> 7399.9999 | C43: =C32*$B$207 -> 4884 | D43: =D32*$B$207 -> 4395.6 | E43: =E32*$B$207 -> 4923.072 | F43: =F32*$B$207 -> 5415.3792 | G43: =G32*$B$207 -> 5848.6095 | H43: =H32*$B$207 -> 5994.8247 | I43: ＝ 控制台「营运资本占年化收入比」× 当年收入。期初取 FY26 Q4 年化收入 × 同一比例
A44: − 营运资本增加 ΔNWC | B44: =-(B43-'00-三表与联动'!E28*4*$B$207) -> -227.99994 | C44: =-(C43-B43) -> 2516 | D44: =-(D43-C43) -> 488.4 | E44: =-(E43-D43) -> -527.472 | F44: =-(F43-E43) -> -492.3072 | G44: =-(G43-F43) -> -433.23033 | H44: =-(H43-G43) -> -146.21524 | I44: ＝ 本年余额 − 上年余额（余额法）
A45: ＝ 自由现金流 FCFF | B45: =B39+B40+B41+B42+B44 -> 18217.564 | C45: =C39+C40+C41+C42+C44 -> 8447.6179 | D45: =D39+D40+D41+D42+D44 -> 4732.3518 | E45: =E39+E40+E41+E42+E44 -> 5655.9064 | F45: =F39+F40+F41+F42+F44 -> 6983.6237 | G45: =G39+G40+G41+G42+G44 -> 7640.7751 | H45: =H39+H40+H41+H42+H44 -> 8129.6403 | I45: ＝ NOPAT + D&A − 自有资本开支 − FV 净投入 − ΔNWC。★ 估值采用的是这一行，不是季度块
A46: FCFF 利润率 | B46: =B45/B32 -> 0.49236661 | C46: =C45/C32 -> 0.3459303 | D46: =D45/D32 -> 0.21532222 | E46: =E45/E32 -> 0.22977143 | F46: =F45/F32 -> 0.25791818 | G46: =G45/G32 -> 0.26128519 | H46: =H45/H32 -> 0.27122195 | I46: ＝ FCFF ÷ 收入。可与投资者日「调整后自由现金流率约 50%」对照（口径不同，见溯源表）
A47: 折现期（年，期中折现） | B47: =0.5 -> 0.5 | C47: =1.5 -> 1.5 | D47: =2.5 -> 2.5 | E47: =3.5 -> 3.5 | F47: =4.5 -> 4.5 | G47: =5.5 -> 5.5 | H47: — | I47: 期中折现法：第 n 年的折现期为 n − 0.5，假设现金流在年内均匀发生
A48: 折现因子 | B48: =1/(1+$B$209)^B47 -> 0.93658581 | C48: =1/(1+$B$209)^C47 -> 0.8215665 | D48: =1/(1+$B$209)^D47 -> 0.72067237 | E48: =1/(1+$B$209)^E47 -> 0.63216875 | F48: =1/(1+$B$209)^F47 -> 0.55453399 | G48: =1/(1+$B$209)^G47 -> 0.48643332 | H48: — | I48: ＝ 1 ÷ (1 + WACC)^折现期
A49: 折现后 FCFF 现值 | B49: =B45*B48 -> 17062.312 | C49: =C45*C48 -> 6940.2799 | D49: =D45*D48 -> 3410.4752 | E49: =E45*E48 -> 3575.4872 | F49: =F45*F48 -> 3872.6567 | G49: =G45*G48 -> 3716.7276 | H49: — | I49: ＝ FCFF × 折现因子
A51: 03 折现率 WACC（公司零负债，WACC = 股权成本）
A52: 参数 | B52: 取值 | D52: 来源与说明
A53: 无风险利率 Rf | B53: ='00-三表与联动'!$B$13 -> 0.042 | D53: 10 年期美国国债收益率，取 4.20%
A54: 股权风险溢价 ERP | B54: ='00-三表与联动'!$B$14 -> 0.05 | D54: 美国成熟市场长期 ERP，取 5.00%
A55: 贝塔 β（隐含） | B55: =(B56-B53)/B54 -> 1.96 | D55: ★ 由控制台 WACC 反解：β = (WACC − Rf) ÷ ERP。SNDK 2025-02 才上市，交易历史不足两年，回归贝塔极不稳定（Yahoo/CNBC 均不提供 β），因此本模型的做法是直接设定 WACC、反算隐含 β 供你判断合理性。
A56: 股权成本 Ke = WACC | B56: =$B$209 -> 0.14 | D56: 控制台滑标直接给定
A57: 有息负债 / 总资本 | B57: 0 | D57: FY26 Q3 起公司已还清全部长期债务，D/(D+E) = 0
A58: 债务成本 Kd（税后） | B58: 0 | D58: 无负债，不适用
A60: 04 估值：从终值到每股内在价值
A61: 步骤 | B61: 金额（百万美元） | D61: 计算方式与说明
A62: ① 预测期 FCFF 现值合计 | B62: =SUM(B49:G49) -> 38577.939 | D62: FY2027–FY2032 六年折现值加总（期中折现）
A63: ② 终值 TV（永续增长法） | B63: =H45/($B$209-$B$211) -> 70692.524 | D63: ＝ 永续期 FCFF ÷ (WACC − g)。★ 若 WACC ≤ g 公式失效，控制台已把 g 上限设在 6%
A64: ③ 终值现值 PV(TV) | B64: =B63*G48/(1+$B$209)^0.5 -> 32206.563 | D64: 用 FY32 的折现因子再折半年，与期中折现保持一致
A65: ④ 终值占企业价值比重 | B65: =B64/B66 -> 0.45499456 | D65: ★ 这个比例越高，说明估值越依赖你对永续期的猜测，而不是可见的现金流
A66: ⑤ 企业价值 EV | B66: =B62+B64 -> 70784.502 | D66: ＝ ① + ③
A67: ⑥ ＋ 货币资金 | B67: ='00-三表与联动'!$B$10 -> 4762 | D67: FY26 Q4末 $4,762M
A68: ⑦ ＋ 可交易权益证券 | B68: ='00-三表与联动'!$B$11 -> 1777 | D68: FY26 Q4末 $1,777M，按非经营性资产处理
A69: ⑧ − 有息负债 | B69: =-'00-三表与联动'!$B$12 -> 0 | D69: 公司已零负债
A70: ⑨ 股权价值 | B70: =B66+B67+B68+B69 -> 77323.502 | D70: ＝ EV + 净现金
A71: ⑩ 摊薄股数（百万股） | B71: ='00-三表与联动'!$B$9 -> 155 | D71: 公司 FY27 Q1 指引「约 155」
A72: ⑪ 每股内在价值 | B72: =B70/B71 -> 498.8613 | D72: ＝ 股权价值 ÷ 摊薄股数
A73: ⑫ 当前股价 | B73: ='00-三表与联动'!$B$6 -> 1500.17 | D73: 2026-08-26 盘中 $1,500.17
A74: ⑬ 相对现价的上行/下行 | B74: =B72/B73-1 -> -0.66746348 | D74: ★ 正数 = 模型认为被低估；负数 = 被高估
A75: ★ 请先看第 ④ 行「终值占企业价值比重」再看第 ⑬ 行的结论。对一个处在周期顶点的存储公司，如果终值占比超过 70%，那么这个 DCF 实际上不是在给现金流定价，而是在给你对 2032 年之后 NAND 行业格局的猜测定价。
A77: 05 交叉验证：退出倍数法与相对估值
A78: 方法 | B78: 关键输入 | D78: 隐含结果 | F78: 说明
A79: 永续增长法隐含的退出 EV/EBITDA | D79: =B63/(G37+G40) -> 6.0830726 | F79: ＝ 终值 ÷ FY32 EBITDA。若这个倍数远高于半导体行业常见的 8–14x，说明永续增长率给得过于激进
A80: 永续增长法隐含的退出 EV/收入 | D80: =B63/G32 -> 2.417413 | F80: ＝ 终值 ÷ FY32 收入
A81: 本模型每股价值 ÷ FY27 每股 FCFF | D81: =B72/(F27/'00-三表与联动'!$B$9) -> 3.8782826 | F81: 把内在价值换算成 FY27 自由现金流的倍数，便于与同业横比
A82: 当前股价隐含的 FY27 P/FCFF | D82: ='00-三表与联动'!$B$6/(F27/'00-三表与联动'!$B$9) -> 11.662727 | F82: 市场正在为 FY27 的自由现金流付多少倍
A83: 当前市值 ÷ 本模型股权价值 | D83: ='00-三表与联动'!$B$6*'00-三表与联动'!$B$9/B70 -> 3.0071885 | F83: 大于 1 = 市场比模型乐观
A85: 06 回购与每股收益：EPS × P/E 交叉估值（与 DCF 并排看）
A86: 为什么要做这一块：DCF 给的是「整个企业值多少钱」，它对回购是中性的——按公允价值回购既不创造也不毁灭价值。但管理层已承诺把 100% 的剩余现金用于回购，股数会大幅下降，所以从「持有不卖的股东」角度看，每股口径会变。这一节把回购显式建模：股数逐年递减 → 经营性 EPS 抬升 → 用当年的 P/E 给一个价格 → 折回今天，再与 DCF 的结果并排比较。
A87: ★ 关于 P/E：本节不再用同一个倍数乘所有年份。FY2027、FY2028、FY2032 各有独立滑标，FY29–FY31 在 FY28 与 FY32 之间线性过渡。原因是周期股的 P/E 与盈利反向：盈利高点（FY27）市场给的倍数最低，盈利回落年（FY28）分母掉得比股价快、倍数反而扩张，终局年（FY32）回到正常中枢。用一个固定倍数乘所有年份，会系统性高估高点年份的目标价。
A88: ★ 关于回购均价：＝ 当前股价 × 倍数 ×(1+WACC)^(t−0.5)。让回购价按折现率复利，是「市场对股票定价合理」的中性假设。如果假设股价六年不动，模型会机械地算出巨额增厚——那是假的。有了这个设定，当 FY32 的 P/E 等于「本 DCF 隐含的退出 P/E」时，两种方法应当收敛。
A89: 科目 | B89: FY2027 | C89: FY2028 | D89: FY2029 | E89: FY2030 | F89: FY2031 | G89: FY2032 | H89: 口径与说明
A90: 自由现金流 FCFF | B90: =B45 -> 18217.564 | C90: =C45 -> 8447.6179 | D90: =D45 -> 4732.3518 | E90: =E45 -> 5655.9064 | F90: =F45 -> 6983.6237 | G90: =G45 -> 7640.7751 | H90: 链接自上方年度预测表
A91: × 回购比例 | B91: =$B$133 -> 1 | C91: =$B$133 -> 1 | D91: =$B$133 -> 1 | E91: =$B$133 -> 1 | F91: =$B$133 -> 1 | G91: =$B$133 -> 1 | H91: 本节内控制台滑标，默认 100%（管理层承诺返还 100% 剩余现金）
A92: ＝ 用于回购的金额 | B92: =MAX(0,B90*B91) -> 18217.564 | C92: =MAX(0,C90*C91) -> 8447.6179 | D92: =MAX(0,D90*D91) -> 4732.3518 | E92: =MAX(0,E90*E91) -> 5655.9064 | F92: =MAX(0,F90*F91) -> 6983.6237 | G92: =MAX(0,G90*G91) -> 7640.7751 | H92: ＝ MAX(0, FCFF × 回购比例)。FCFF 为负时不回购
A93: 回购均价（美元/股） | B93: ='00-三表与联动'!$B$6*$B$135*(1+$B$209)^0.5 -> 1601.7432 | C93: ='00-三表与联动'!$B$6*$B$135*(1+$B$209)^1.5 -> 1825.9873 | D93: ='00-三表与联动'!$B$6*$B$135*(1+$B$209)^2.5 -> 2081.6255 | E93: ='00-三表与联动'!$B$6*$B$135*(1+$B$209)^3.5 -> 2373.0531 | F93: ='00-三表与联动'!$B$6*$B$135*(1+$B$209)^4.5 -> 2705.2805 | G93: ='00-三表与联动'!$B$6*$B$135*(1+$B$209)^5.5 -> 3084.0198 | H93: ＝ 当前股价 × 本节滑标倍数 ×(1+WACC)^(t−0.5)
A94: − 回购注销股数（百万股） | B94: =B92/B93 -> 11.373586 | C94: =C92/C93 -> 4.626329 | D94: =D92/D93 -> 2.2733925 | E94: =E92/E93 -> 2.383388 | F94: =F92/F93 -> 2.5814786 | G94: =G92/G93 -> 2.4775376 | H94: ＝ 回购金额 ÷ 回购均价
A95: ＋ 股权激励新增股数（百万股） | B95: =B32*0.0115/B93 -> 0.26564807 | C95: =C32*0.0115/C93 -> 0.15379625 | D95: =D32*0.0115/D93 -> 0.12141809 | E95: =E32*0.0115/E93 -> 0.11928795 | F95: =F32*0.0115/F93 -> 0.11510241 | G95: =G32*0.0115/G93 -> 0.10904439 | H95: ＝ 收入 × 1.15% ÷ 回购均价。FY26 股份支付 $232M ÷ 收入 $20,248M ＝ 1.15%
A96: 期初摊薄股数（百万股） | B96: ='00-三表与联动'!$B$9 -> 155 | C96: =B97 -> 143.89206 | D96: =C97 -> 139.41953 | E96: =D97 -> 137.26756 | F96: =E97 -> 135.00346 | G96: =F97 -> 132.53708 | H96: FY27 期初取公司指引的 155；其后为上年期末
A97: 期末摊薄股数（百万股） | B97: =MAX(20,B96-B94+B95) -> 143.89206 | C97: =MAX(20,C96-C94+C95) -> 139.41953 | D97: =MAX(20,D96-D94+D95) -> 137.26756 | E97: =MAX(20,E96-E94+E95) -> 135.00346 | F97: =MAX(20,F96-F94+F95) -> 132.53708 | G97: =MAX(20,G96-G94+G95) -> 130.16859 | H97: ＝ 期初 − 回购注销 + 股权激励新增，下限锁 20
A98: 净现金余额 | B98: =('00-三表与联动'!$B$10+'00-三表与联动'!$B$11-'00-三表与联动'!$B$12)+B90-B92 -> 6539 | C98: =B98+C90-C92 -> 6539 | D98: =C98+D90-D92 -> 6539 | E98: =D98+E90-E92 -> 6539 | F98: =E98+F90-F92 -> 6539 | G98: =F98+G90-G92 -> 6539 | H98: ＝ 上期净现金 + FCFF − 回购金额。★ 回购比例＜100% 时现金会累积，这部分价值必须计入，否则会低估
A99: 税后经营利润 NOPAT | B99: =B39 -> 20206.764 | C99: =C39 -> 7094.0099 | D99: =D39 -> 5290.1046 | E99: =E39 -> 7355.0695 | F99: =F39 -> 8764.7912 | G99: =G39 -> 9465.9745 | H99: 链接自上方年度预测表。★ 用 NOPAT 而非净利润，是为了与 DCF 同口径（不含利息）
A100: 经营性每股收益 EPS | B100: =B99/B97 -> 140.43001 | C100: =C99/C97 -> 50.882469 | D100: =D99/D97 -> 38.538638 | E100: =E99/E97 -> 54.480602 | F100: =F99/F97 -> 66.130861 | G100: =G99/G97 -> 72.720883 | H100: ＝ NOPAT ÷ 期末股数。用期末股数而非加权平均，因为要回答的是「那个时点每一股值多少」
A101: 每股净现金 | B101: =B98/B97 -> 45.443785 | C101: =C98/C97 -> 46.901607 | D101: =D98/D97 -> 47.636894 | E101: =E98/E97 -> 48.435797 | F101: =F98/F97 -> 49.337137 | G101: =G98/G97 -> 50.234855 | H101: ＝ 净现金余额 ÷ 期末股数
A102: ★ 采用的 P/E 倍数 | B102: =$B$137 -> 5 | C102: =$B$139 -> 8 | D102: =$B$139+($B$141-$B$139)*1/4 -> 8.25 | E102: =$B$139+($B$141-$B$139)*2/4 -> 8.5 | F102: =$B$139+($B$141-$B$139)*3/4 -> 8.75 | G102: =$B$141 -> 9 | H102: FY27 / FY28 / FY32 各由本节独立滑标给定；FY29–FY31 在 FY28 与 FY32 之间线性过渡（四等分）
A103: 隐含股价（EPS×当年PE + 每股净现金） | B103: =B100*B102+B101 -> 747.59386 | C103: =C100*C102+C101 -> 453.96136 | D103: =D100*D102+D101 -> 365.58065 | E103: =E100*E102+E101 -> 511.52092 | F103: =F100*F102+F101 -> 627.98217 | G103: =G100*G102+G101 -> 704.7228 | H103: 把现金单独加回，使本方法与 DCF（EV + 净现金）口径一致
A104: 折现因子（期末折现） | B104: =1/(1+$B$209)^1 -> 0.87719298 | C104: =1/(1+$B$209)^2 -> 0.76946753 | D104: =1/(1+$B$209)^3 -> 0.67497152 | E104: =1/(1+$B$209)^4 -> 0.59208028 | F104: =1/(1+$B$209)^5 -> 0.51936866 | G104: =1/(1+$B$209)^6 -> 0.45558655 | H104: ＝ 1 ÷ (1+WACC)^t。股价是时点数用期末折现；上方 DCF 的现金流是期间数用期中折现
A105: 折现后每股价值 | B105: =B103*B104 -> 655.78408 | C105: =C103*C104 -> 349.30853 | D105: =D103*D104 -> 246.75653 | E105: =E103*E104 -> 302.86145 | F105: =F103*F104 -> 326.15426 | G105: =G103*G104 -> 321.06223 | H105: ＝ 隐含股价 × 折现因子
A107: 6.1 三个关键年份的目标价：各用各的 P/E
A108: 年份 | B108: 经营性 EPS | C108: 每股净现金 | D108: 采用 P/E | E108: 隐含目标价 | F108: 折现期（年） | G108: 折现后每股价值 | H108: 折现后 ÷ 现价 − 1 | I108: 这个数字回答什么
...

Sheet 02-DCF-基准
A1: BASE · SNDK 现金流折现模型 —— 基准情形
A2: FY2027 分四个季度 → FY2028–FY2032 按年 → 永续 | 自由现金流口径：FCFF（含 Flash Ventures 投入） | ▼ 全部参数由本表底部的参数控制台滑标驱动
A4: 00 本情形的论点：这套数字建立在什么判断之上
A5: 采用公司 FY27 Q1 指引中值作为起点，但不接受管理层「FY28–30 毛利率维持 80%」的长期框架。本情形假设周期在 FY27 见顶、FY28 温和回落一年，之后由 AI 数据中心需求托住，毛利率稳定在 66%–72% 这个「比历史高、但低于当前峰值」的新中枢。
A6: 1．FY27 Q1 用官方指引中值 $10.55B（区间 $10.30–10.80B）
A7: 2．FY28 收入 −18%：一次温和的库存与价格修正，而非崩塌
A8: 3．FY29–FY32 收入回到中双位数增长，与管理层的 bit 增长口径一致
A9: 4．终局毛利率 68%，显著高于分拆前的 30%，但低于管理层的 80%
A11: 01 FY2027 季度预测（SNDK 分拆才一年半，先用季度把最近的可见度做实）
A12: 科目（百万美元） | B12: FY27 Q1 | C12: FY27 Q2 | D12: FY27 Q3 | E12: FY27 Q4 | F12: FY2027 合计 | G12: 变量怎么来的
A13: 营业收入 | B13: =$B$189 -> 10550 | C13: =B13*(1+0.061611+$B$191) -> 11199.996 | D13: =C13*(1+-0.053571+$B$191) -> 10600.001 | E13: =D13*(1+-0.103774+$B$191) -> 9499.9966 | F13: =SUM(B13:E13) -> 41849.994 | G13: Q1 ＝ 控制台滑标（官方指引 $10.3–10.8B）；Q2–Q4 ＝ 上一季 ×(1 + 情形环比增速 + 滑标平移)
A14: 环比增速 QoQ | B14: =B13/'00-三表与联动'!E28-1 -> 0.17679866 | C14: =C13/B13-1 -> 0.061611 | D14: =D13/C13-1 -> -0.053571 | E14: =E13/D13-1 -> -0.103774 | F14: =F13/'00-三表与联动'!F28-1 -> 1.0668705 | G14: Q1 的环比基数是 FY26 Q4 的 $8,965M（不是 FY26 全年）；Q2–Q4 为上一季
A15: 毛利率 | B15: =MAX(0.05,MIN(0.92,0.84+$B$193)) -> 0.84 | C15: =MAX(0.05,MIN(0.92,0.835+$B$193)) -> 0.835 | D15: =MAX(0.05,MIN(0.92,0.8+$B$193)) -> 0.8 | E15: =MAX(0.05,MIN(0.92,0.74+$B$193)) -> 0.74 | F15: =F16/F13 -> 0.80583035 | G15: 情形设定的季度毛利率路径 + 控制台「毛利率平移」，上下限锁在 5%–92%
A16: 毛利 | B16: =B13*B15 -> 8862 | C16: =C13*C15 -> 9351.9967 | D16: =D13*D15 -> 8480.0008 | E16: =E13*E15 -> 7029.9974 | F16: =SUM(B16:E16) -> 33723.995 | G16: ＝ 收入 × 毛利率
A17: 营业费用 | B17: =B13*$B$199 -> 611.9 | C17: =C13*$B$199 -> 649.59977 | D17: =D13*$B$199 -> 614.80006 | E17: =E13*$B$199 -> 550.9998 | F17: =SUM(B17:E17) -> 2427.2996 | G17: ＝ 收入 × 控制台「营业费用率」。公司 FY27 Q1 GAAP 指引为 $574–614M
A18: 营业利润 EBIT | B18: =B16-B17 -> 8250.1 | C18: =C16-C17 -> 8702.3969 | D18: =D16-D17 -> 7865.2008 | E18: =E16-E17 -> 6478.9976 | F18: =SUM(B18:E18) -> 31296.695 | G18: ＝ 毛利 − 营业费用
A19: 营业利润率 | B19: =B18/B13 -> 0.782 | C19: =C18/C13 -> 0.777 | D19: =D18/D13 -> 0.742 | E19: =E18/E13 -> 0.682 | F19: =F18/F13 -> 0.74783035 | G19: ＝ EBIT ÷ 收入
A20: 所得税 | B20: =MAX(0,B18)*$B$201 -> 1320.016 | C20: =MAX(0,C18)*$B$201 -> 1392.3835 | D20: =MAX(0,D18)*$B$201 -> 1258.4321 | E20: =MAX(0,E18)*$B$201 -> 1036.6396 | F20: =SUM(B20:E20) -> 5007.4713 | G20: ＝ EBIT × 控制台「有效税率」（FCFF 口径按 EBIT 计税，不含利息）
A21: 税后经营利润 NOPAT | B21: =B18-B20 -> 6930.084 | C21: =C18-C20 -> 7310.0134 | D21: =D18-D20 -> 6606.7687 | E21: =E18-E20 -> 5442.358 | F21: =SUM(B21:E21) -> 26289.224 | G21: ＝ EBIT − 所得税
A22: ＋ 折旧摊销 D&A | B22: =B13*0.0074 -> 78.07 | C22: =C13*0.0074 -> 82.879971 | D22: =D13*0.0074 -> 78.440008 | E22: =E13*0.0074 -> 70.299974 | F22: =SUM(B22:E22) -> 309.68995 | G22: ＝ 收入 × 0.74%（FY26 实际 D&A $149M ÷ 收入 $20,248M）。数字极低是因为晶圆厂在合资公司里，折旧不落在 SNDK 报表上
A23: − 自有资本开支 | B23: =-B13*$B$203 -> -189.9 | C23: =-C13*$B$203 -> -201.59993 | D23: =-D13*$B$203 -> -190.80002 | E23: =-E13*$B$203 -> -170.99994 | F23: =SUM(B23:E23) -> -753.29989 | G23: ＝ 收入 × 控制台「自有资本开支率」。FY26 实际 0.87%
A24: − Flash Ventures 净投入 | B24: =-B13*$B$205 -> -337.6 | C24: =-C13*$B$205 -> -358.39987 | D24: =-D13*$B$205 -> -339.20003 | E24: =-E13*$B$205 -> -303.99989 | F24: =SUM(B24:E24) -> -1339.1998 | G24: ＝ 收入 × 控制台「FV 净投入率」。FY26 实际 1.36%（发放票据 462 − 回收 187）
A25: 营运资本余额 | B25: =B13*4*$B$207 -> 7596 | C25: =C13*4*$B$207 -> 8063.9972 | D25: =D13*4*$B$207 -> 7632.0008 | E25: =E13*4*$B$207 -> 6839.9975 | F25: =E25 -> 6839.9975 | G25: ＝ 控制台「营运资本占年化收入比」× 当季收入 × 4。期初取 FY26 Q4 的年化收入基准
A26: − 营运资本增加 ΔNWC | B26: =-(B25-'00-三表与联动'!E28*4*$B$207) -> -1141.2 | C26: =-(C25-B25) -> -467.99716 | D26: =-(D25-C25) -> 431.99639 | E26: =-(E25-D25) -> 792.00325 | F26: =SUM(B26:E26) -> -385.19752 | G26: ＝ 本季余额 − 上季余额。余额法，不再用「占收入增量比」
A27: ＝ 自由现金流 FCFF | B27: =B21+B22+B23+B24+B26 -> 5339.454 | C27: =C21+C22+C23+C24+C26 -> 6364.8964 | D27: =D21+D22+D23+D24+D26 -> 6587.205 | E27: =E21+E22+E23+E24+E26 -> 5829.6614 | F27: =SUM(B27:E27) -> 24121.217 | G27: ＝ NOPAT + D&A − 自有资本开支 − FV 净投入 − ΔNWC
A28: 口径说明：这里算的是 FCFF（企业自由现金流），所以税按 EBIT 计、不扣利息——利息的价值已经体现在折现率里。公司目前零负债，FCFF 与 FCFE 的差异只剩利息收入。
A30: 02 FY2028–FY2032 年度预测 + 永续
A31: 科目（百万美元） | B31: FY2027 | C31: FY2028 | D31: FY2029 | E31: FY2030 | F31: FY2031 | G31: FY2032 | H31: 永续期 | I31: 变量怎么来的
A32: 营业收入 | B32: =F13 -> 41849.994 | C32: =B32*(1+-0.18) -> 34316.995 | D32: =C32*(1+0.14+$B$197) -> 39121.374 | E32: =D32*(1+0.15+$B$197) -> 44989.58 | F32: =E32*(1+0.12+$B$197) -> 50388.33 | G32: =F32*(1+0.1+$B$197) -> 55427.163 | H32: =G32*(1+$B$211) -> 57089.978 | I32: FY27 取季度合计；FY28 ＝ 情形设定增速；FY29–32 ＝ 情形增速 + 控制台「长期增速平移」
A33: 收入增速 YoY | B33: =B32/'00-三表与联动'!F28-1 -> 1.0668705 | C33: =C32/B32-1 -> -0.18 | D33: =D32/C32-1 -> 0.14 | E33: =E32/D32-1 -> 0.15 | F33: =F32/E32-1 -> 0.12 | G33: =G32/F32-1 -> 0.1 | H33: =$B$211 -> 0.03 | I33: 逐年同比。FY26 实际为 +175%
A34: 毛利率 | B34: =F16/F13 -> 0.80583035 | C34: =MAX(0.05,MIN(0.92,0.66+$B$193)) -> 0.66 | D34: =MAX(0.05,MIN(0.92,0.7+$B$193)) -> 0.7 | E34: =MAX(0.05,MIN(0.92,0.72+$B$193)) -> 0.72 | F34: =MAX(0.05,MIN(0.92,0.7+$B$193)) -> 0.7 | G34: =$B$195 -> 0.68 | H34: =G34 -> 0.68 | I34: 情形设定的年度毛利率 + 控制台「毛利率平移」；FY32 直接取控制台「终局毛利率」
A35: 毛利 | B35: =B32*B34 -> 33723.995 | C35: =C32*C34 -> 22649.217 | D35: =D32*D34 -> 27384.962 | E35: =E32*E34 -> 32392.498 | F35: =F32*F34 -> 35271.831 | G35: =G32*G34 -> 37690.471 | H35: =H32*H34 -> 38821.185 | I35: ＝ 收入 × 毛利率
A36: 营业费用 | B36: =B32*$B$199 -> 2427.2996 | C36: =C32*$B$199 -> 1990.3857 | D36: =D32*$B$199 -> 2269.0397 | E36: =E32*$B$199 -> 2609.3957 | F36: =F32*$B$199 -> 2922.5231 | G36: =G32*$B$199 -> 3214.7754 | H36: =H32*$B$199 -> 3311.2187 | I36: ＝ 收入 × 控制台「营业费用率」
A37: 营业利润 EBIT | B37: =B35-B36 -> 31296.695 | C37: =C35-C36 -> 20658.831 | D37: =D35-D36 -> 25115.922 | E37: =E35-E36 -> 29783.102 | F37: =F35-F36 -> 32349.308 | G37: =G35-G36 -> 34475.695 | H37: =H35-H36 -> 35509.966 | I37: ＝ 毛利 − 营业费用
A38: 营业利润率 | B38: =B37/B32 -> 0.74783035 | C38: =C37/C32 -> 0.602 | D38: =D37/D32 -> 0.642 | E38: =E37/E32 -> 0.662 | F38: =F37/F32 -> 0.642 | G38: =G37/G32 -> 0.622 | H38: =H37/H32 -> 0.622 | I38: ＝ EBIT ÷ 收入。可与投资者日目标「约 75%」对照
A39: 税后经营利润 NOPAT | B39: =B37*(1-$B$201) -> 26289.224 | C39: =C37*(1-$B$201) -> 17353.418 | D39: =D37*(1-$B$201) -> 21097.375 | E39: =E37*(1-$B$201) -> 25017.806 | F39: =F37*(1-$B$201) -> 27173.419 | G39: =G37*(1-$B$201) -> 28959.584 | H39: =H37*(1-$B$201) -> 29828.372 | I39: ＝ EBIT ×(1 − 有效税率)
A40: ＋ 折旧摊销 D&A | B40: =B32*0.0074 -> 309.68995 | C40: =C32*0.0074 -> 253.94576 | D40: =D32*0.0074 -> 289.49817 | E40: =E32*0.0074 -> 332.92289 | F40: =F32*0.0074 -> 372.87364 | G40: =G32*0.0074 -> 410.161 | H40: =H32*0.0074 -> 422.46583 | I40: ＝ 收入 × 0.74%
A41: − 自有资本开支 | B41: =-B32*$B$203 -> -753.29989 | C41: =-C32*$B$203 -> -617.70591 | D41: =-D32*$B$203 -> -704.18473 | E41: =-E32*$B$203 -> -809.81244 | F41: =-F32*$B$203 -> -906.98994 | G41: =-G32*$B$203 -> -997.68893 | H41: =-H32*$B$203 -> -1027.6196 | I41: ＝ 收入 × 控制台「自有资本开支率」
A42: − Flash Ventures 净投入 | B42: =-B32*$B$205 -> -1339.1998 | C42: =-C32*$B$205 -> -1098.1438 | D42: =-D32*$B$205 -> -1251.884 | E42: =-E32*$B$205 -> -1439.6666 | F42: =-F32*$B$205 -> -1612.4266 | G42: =-G32*$B$205 -> -1773.6692 | H42: =-H32*$B$205 -> -1826.8793 | I42: ＝ 收入 × 控制台「FV 净投入率」
A43: 营运资本余额 | B43: =B32*$B$207 -> 7532.9989 | C43: =C32*$B$207 -> 6177.0591 | D43: =D32*$B$207 -> 7041.8473 | E43: =E32*$B$207 -> 8098.1244 | F43: =F32*$B$207 -> 9069.8994 | G43: =G32*$B$207 -> 9976.8893 | H43: =H32*$B$207 -> 10276.196 | I43: ＝ 控制台「营运资本占年化收入比」× 当年收入。期初取 FY26 Q4 年化收入 × 同一比例
A44: − 营运资本增加 ΔNWC | B44: =-(B43-'00-三表与联动'!E28*4*$B$207) -> -1078.1989 | C44: =-(C43-B43) -> 1355.9398 | D44: =-(D43-C43) -> -864.78827 | E44: =-(E43-D43) -> -1056.2771 | F44: =-(F43-E43) -> -971.77493 | G44: =-(G43-F43) -> -906.98994 | H44: =-(H43-G43) -> -299.30668 | I44: ＝ 本年余额 − 上年余额（余额法）
A45: ＝ 自由现金流 FCFF | B45: =B39+B40+B41+B42+B44 -> 23428.216 | C45: =C39+C40+C41+C42+C44 -> 17247.454 | D45: =D39+D40+D41+D42+D44 -> 18566.016 | E45: =E39+E40+E41+E42+E44 -> 22044.973 | F45: =F39+F40+F41+F42+F44 -> 24055.101 | G45: =G39+G40+G41+G42+G44 -> 25691.397 | H45: =H39+H40+H41+H42+H44 -> 27097.032 | I45: ＝ NOPAT + D&A − 自有资本开支 − FV 净投入 − ΔNWC。★ 估值采用的是这一行，不是季度块
A46: FCFF 利润率 | B46: =B45/B32 -> 0.55981408 | C46: =C45/C32 -> 0.5025922 | D46: =D45/D32 -> 0.47457474 | E46: =E45/E32 -> 0.49000174 | F46: =F45/F32 -> 0.47739429 | G46: =G45/G32 -> 0.46351636 | H46: =H45/H32 -> 0.47463728 | I46: ＝ FCFF ÷ 收入。可与投资者日「调整后自由现金流率约 50%」对照（口径不同，见溯源表）
A47: 折现期（年，期中折现） | B47: =0.5 -> 0.5 | C47: =1.5 -> 1.5 | D47: =2.5 -> 2.5 | E47: =3.5 -> 3.5 | F47: =4.5 -> 4.5 | G47: =5.5 -> 5.5 | H47: — | I47: 期中折现法：第 n 年的折现期为 n − 0.5，假设现金流在年内均匀发生
A48: 折现因子 | B48: =1/(1+$B$209)^B47 -> 0.94491118 | C48: =1/(1+$B$209)^C47 -> 0.8436707 | D48: =1/(1+$B$209)^D47 -> 0.75327741 | E48: =1/(1+$B$209)^E47 -> 0.67256912 | F48: =1/(1+$B$209)^F47 -> 0.60050814 | G48: =1/(1+$B$209)^G47 -> 0.53616798 | H48: — | I48: ＝ 1 ÷ (1 + WACC)^折现期
A49: 折现后 FCFF 现值 | B49: =B45*B48 -> 22137.583 | C49: =C45*C48 -> 14551.171 | D49: =D45*D48 -> 13985.36 | E49: =E45*E48 -> 14826.768 | F49: =F45*F48 -> 14445.284 | G49: =G45*G48 -> 13774.904 | H49: — | I49: ＝ FCFF × 折现因子
A51: 03 折现率 WACC（公司零负债，WACC = 股权成本）
A52: 参数 | B52: 取值 | D52: 来源与说明
A53: 无风险利率 Rf | B53: ='00-三表与联动'!$B$13 -> 0.042 | D53: 10 年期美国国债收益率，取 4.20%
A54: 股权风险溢价 ERP | B54: ='00-三表与联动'!$B$14 -> 0.05 | D54: 美国成熟市场长期 ERP，取 5.00%
A55: 贝塔 β（隐含） | B55: =(B56-B53)/B54 -> 1.56 | D55: ★ 由控制台 WACC 反解：β = (WACC − Rf) ÷ ERP。SNDK 2025-02 才上市，交易历史不足两年，回归贝塔极不稳定（Yahoo/CNBC 均不提供 β），因此本模型的做法是直接设定 WACC、反算隐含 β 供你判断合理性。
A56: 股权成本 Ke = WACC | B56: =$B$209 -> 0.12 | D56: 控制台滑标直接给定
A57: 有息负债 / 总资本 | B57: 0 | D57: FY26 Q3 起公司已还清全部长期债务，D/(D+E) = 0
A58: 债务成本 Kd（税后） | B58: 0 | D58: 无负债，不适用
A60: 04 估值：从终值到每股内在价值
A61: 步骤 | B61: 金额（百万美元） | D61: 计算方式与说明
A62: ① 预测期 FCFF 现值合计 | B62: =SUM(B49:G49) -> 93721.07 | D62: FY2027–FY2032 六年折现值加总（期中折现）
A63: ② 终值 TV（永续增长法） | B63: =H45/($B$209-$B$211) -> 301078.13 | D63: ＝ 永续期 FCFF ÷ (WACC − g)。★ 若 WACC ≤ g 公式失效，控制台已把 g 上限设在 6%
A64: ③ 终值现值 PV(TV) | B64: =B63*G48/(1+$B$209)^0.5 -> 152535.55 | D64: 用 FY32 的折现因子再折半年，与期中折现保持一致
A65: ④ 终值占企业价值比重 | B65: =B64/B66 -> 0.61941705 | D65: ★ 这个比例越高，说明估值越依赖你对永续期的猜测，而不是可见的现金流
A66: ⑤ 企业价值 EV | B66: =B62+B64 -> 246256.62 | D66: ＝ ① + ③
A67: ⑥ ＋ 货币资金 | B67: ='00-三表与联动'!$B$10 -> 4762 | D67: FY26 Q4末 $4,762M
A68: ⑦ ＋ 可交易权益证券 | B68: ='00-三表与联动'!$B$11 -> 1777 | D68: FY26 Q4末 $1,777M，按非经营性资产处理
A69: ⑧ − 有息负债 | B69: =-'00-三表与联动'!$B$12 -> 0 | D69: 公司已零负债
A70: ⑨ 股权价值 | B70: =B66+B67+B68+B69 -> 252795.62 | D70: ＝ EV + 净现金
A71: ⑩ 摊薄股数（百万股） | B71: ='00-三表与联动'!$B$9 -> 155 | D71: 公司 FY27 Q1 指引「约 155」
A72: ⑪ 每股内在价值 | B72: =B70/B71 -> 1630.9395 | D72: ＝ 股权价值 ÷ 摊薄股数
A73: ⑫ 当前股价 | B73: ='00-三表与联动'!$B$6 -> 1500.17 | D73: 2026-08-26 盘中 $1,500.17
A74: ⑬ 相对现价的上行/下行 | B74: =B72/B73-1 -> 0.087169783 | D74: ★ 正数 = 模型认为被低估；负数 = 被高估
A75: ★ 请先看第 ④ 行「终值占企业价值比重」再看第 ⑬ 行的结论。对一个处在周期顶点的存储公司，如果终值占比超过 70%，那么这个 DCF 实际上不是在给现金流定价，而是在给你对 2032 年之后 NAND 行业格局的猜测定价。
A77: 05 交叉验证：退出倍数法与相对估值
A78: 方法 | B78: 关键输入 | D78: 隐含结果 | F78: 说明
A79: 永续增长法隐含的退出 EV/EBITDA | D79: =B63/(G37+G40) -> 8.6303781 | F79: ＝ 终值 ÷ FY32 EBITDA。若这个倍数远高于半导体行业常见的 8–14x，说明永续增长率给得过于激进
A80: 永续增长法隐含的退出 EV/收入 | D80: =B63/G32 -> 5.43196 | F80: ＝ 终值 ÷ FY32 收入
A81: 本模型每股价值 ÷ FY27 每股 FCFF | D81: =B72/(F27/'00-三表与联动'!$B$9) -> 10.480218 | F81: 把内在价值换算成 FY27 自由现金流的倍数，便于与同业横比
A82: 当前股价隐含的 FY27 P/FCFF | D82: ='00-三表与联动'!$B$6/(F27/'00-三表与联动'!$B$9) -> 9.6399096 | F82: 市场正在为 FY27 的自由现金流付多少倍
A83: 当前市值 ÷ 本模型股权价值 | D83: ='00-三表与联动'!$B$6*'00-三表与联动'!$B$9/B70 -> 0.91981953 | F83: 大于 1 = 市场比模型乐观
A85: 06 回购与每股收益：EPS × P/E 交叉估值（与 DCF 并排看）
A86: 为什么要做这一块：DCF 给的是「整个企业值多少钱」，它对回购是中性的——按公允价值回购既不创造也不毁灭价值。但管理层已承诺把 100% 的剩余现金用于回购，股数会大幅下降，所以从「持有不卖的股东」角度看，每股口径会变。这一节把回购显式建模：股数逐年递减 → 经营性 EPS 抬升 → 用当年的 P/E 给一个价格 → 折回今天，再与 DCF 的结果并排比较。
A87: ★ 关于 P/E：本节不再用同一个倍数乘所有年份。FY2027、FY2028、FY2032 各有独立滑标，FY29–FY31 在 FY28 与 FY32 之间线性过渡。原因是周期股的 P/E 与盈利反向：盈利高点（FY27）市场给的倍数最低，盈利回落年（FY28）分母掉得比股价快、倍数反而扩张，终局年（FY32）回到正常中枢。用一个固定倍数乘所有年份，会系统性高估高点年份的目标价。
A88: ★ 关于回购均价：＝ 当前股价 × 倍数 ×(1+WACC)^(t−0.5)。让回购价按折现率复利，是「市场对股票定价合理」的中性假设。如果假设股价六年不动，模型会机械地算出巨额增厚——那是假的。有了这个设定，当 FY32 的 P/E 等于「本 DCF 隐含的退出 P/E」时，两种方法应当收敛。
A89: 科目 | B89: FY2027 | C89: FY2028 | D89: FY2029 | E89: FY2030 | F89: FY2031 | G89: FY2032 | H89: 口径与说明
A90: 自由现金流 FCFF | B90: =B45 -> 23428.216 | C90: =C45 -> 17247.454 | D90: =D45 -> 18566.016 | E90: =E45 -> 22044.973 | F90: =F45 -> 24055.101 | G90: =G45 -> 25691.397 | H90: 链接自上方年度预测表
A91: × 回购比例 | B91: =$B$133 -> 1 | C91: =$B$133 -> 1 | D91: =$B$133 -> 1 | E91: =$B$133 -> 1 | F91: =$B$133 -> 1 | G91: =$B$133 -> 1 | H91: 本节内控制台滑标，默认 100%（管理层承诺返还 100% 剩余现金）
A92: ＝ 用于回购的金额 | B92: =MAX(0,B90*B91) -> 23428.216 | C92: =MAX(0,C90*C91) -> 17247.454 | D92: =MAX(0,D90*D91) -> 18566.016 | E92: =MAX(0,E90*E91) -> 22044.973 | F92: =MAX(0,F90*F91) -> 24055.101 | G92: =MAX(0,G90*G91) -> 25691.397 | H92: ＝ MAX(0, FCFF × 回购比例)。FCFF 为负时不回购
A93: 回购均价（美元/股） | B93: ='00-三表与联动'!$B$6*$B$135*(1+$B$209)^0.5 -> 1587.6307 | C93: ='00-三表与联动'!$B$6*$B$135*(1+$B$209)^1.5 -> 1778.1464 | D93: ='00-三表与联动'!$B$6*$B$135*(1+$B$209)^2.5 -> 1991.5239 | E93: ='00-三表与联动'!$B$6*$B$135*(1+$B$209)^3.5 -> 2230.5068 | F93: ='00-三表与联动'!$B$6*$B$135*(1+$B$209)^4.5 -> 2498.1676 | G93: ='00-三表与联动'!$B$6*$B$135*(1+$B$209)^5.5 -> 2797.9478 | H93: ＝ 当前股价 × 本节滑标倍数 ×(1+WACC)^(t−0.5)
A94: − 回购注销股数（百万股） | B94: =B92/B93 -> 14.756716 | C94: =C92/C93 -> 9.6996816 | D94: =D92/D93 -> 9.322517 | E94: =E92/E93 -> 9.8833917 | F94: =F92/F93 -> 9.6290979 | G94: =G92/G93 -> 9.182229 | H94: ＝ 回购金额 ÷ 回购均价
A95: ＋ 股权激励新增股数（百万股） | B95: =B32*0.0115/B93 -> 0.30314035 | C95: =C32*0.0115/C93 -> 0.22194204 | D95: =D32*0.0115/D93 -> 0.22590529 | E95: =E32*0.0115/E93 -> 0.23195633 | F95: =F32*0.0115/F93 -> 0.23195633 | G95: =G32*0.0115/G93 -> 0.22781425 | H95: ＝ 收入 × 1.15% ÷ 回购均价。FY26 股份支付 $232M ÷ 收入 $20,248M ＝ 1.15%
A96: 期初摊薄股数（百万股） | B96: ='00-三表与联动'!$B$9 -> 155 | C96: =B97 -> 140.54642 | D96: =C97 -> 131.06868 | E96: =D97 -> 121.97207 | F96: =E97 -> 112.32064 | G96: =F97 -> 102.9235 | H96: FY27 期初取公司指引的 155；其后为上年期末
A97: 期末摊薄股数（百万股） | B97: =MAX(20,B96-B94+B95) -> 140.54642 | C97: =MAX(20,C96-C94+C95) -> 131.06868 | D97: =MAX(20,D96-D94+D95) -> 121.97207 | E97: =MAX(20,E96-E94+E95) -> 112.32064 | F97: =MAX(20,F96-F94+F95) -> 102.9235 | G97: =MAX(20,G96-G94+G95) -> 93.969081 | H97: ＝ 期初 − 回购注销 + 股权激励新增，下限锁 20
A98: 净现金余额 | B98: =('00-三表与联动'!$B$10+'00-三表与联动'!$B$11-'00-三表与联动'!$B$12)+B90-B92 -> 6539 | C98: =B98+C90-C92 -> 6539 | D98: =C98+D90-D92 -> 6539 | E98: =D98+E90-E92 -> 6539 | F98: =E98+F90-F92 -> 6539 | G98: =F98+G90-G92 -> 6539 | H98: ＝ 上期净现金 + FCFF − 回购金额。★ 回购比例＜100% 时现金会累积，这部分价值必须计入，否则会低估
A99: 税后经营利润 NOPAT | B99: =B39 -> 26289.224 | C99: =C39 -> 17353.418 | D99: =D39 -> 21097.375 | E99: =E39 -> 25017.806 | F99: =F39 -> 27173.419 | G99: =G39 -> 28959.584 | H99: 链接自上方年度预测表。★ 用 NOPAT 而非净利润，是为了与 DCF 同口径（不含利息）
A100: 经营性每股收益 EPS | B100: =B99/B97 -> 187.05011 | C100: =C99/C97 -> 132.39942 | D100: =D99/D97 -> 172.96889 | E100: =E99/E97 -> 222.73561 | F100: =F99/F97 -> 264.0157 | G100: =G99/G97 -> 308.18205 | H100: ＝ NOPAT ÷ 期末股数。用期末股数而非加权平均，因为要回答的是「那个时点每一股值多少」
A101: 每股净现金 | B101: =B98/B97 -> 46.525552 | C101: =C98/C97 -> 49.889873 | D101: =D98/D97 -> 53.610633 | E101: =E98/E97 -> 58.217262 | F101: =F98/F97 -> 63.532626 | G101: =G98/G97 -> 69.586718 | H101: ＝ 净现金余额 ÷ 期末股数
A102: ★ 采用的 P/E 倍数 | B102: =$B$137 -> 8 | C102: =$B$139 -> 11 | D102: =$B$139+($B$141-$B$139)*1/4 -> 11.5 | E102: =$B$139+($B$141-$B$139)*2/4 -> 12 | F102: =$B$139+($B$141-$B$139)*3/4 -> 12.5 | G102: =$B$141 -> 13 | H102: FY27 / FY28 / FY32 各由本节独立滑标给定；FY29–FY31 在 FY28 与 FY32 之间线性过渡（四等分）
A103: 隐含股价（EPS×当年PE + 每股净现金） | B103: =B100*B102+B101 -> 1542.9264 | C103: =C100*C102+C101 -> 1506.2835 | D103: =D100*D102+D101 -> 2042.7529 | E103: =E100*E102+E101 -> 2731.0446 | F103: =F100*F102+F101 -> 3363.7288 | G103: =G100*G102+G101 -> 4075.9534 | H103: 把现金单独加回，使本方法与 DCF（EV + 净现金）口径一致
A104: 折现因子（期末折现） | B104: =1/(1+$B$209)^1 -> 0.89285714 | C104: =1/(1+$B$209)^2 -> 0.79719388 | D104: =1/(1+$B$209)^3 -> 0.71178025 | E104: =1/(1+$B$209)^4 -> 0.63551808 | F104: =1/(1+$B$209)^5 -> 0.56742686 | G104: =1/(1+$B$209)^6 -> 0.50663112 | H104: ＝ 1 ÷ (1+WACC)^t。股价是时点数用期末折现；上方 DCF 的现金流是期间数用期中折现
A105: 折现后每股价值 | B105: =B103*B104 -> 1377.6129 | C105: =C103*C104 -> 1200.8 | D105: =D103*D104 -> 1453.9912 | E105: =E103*E104 -> 1735.6282 | F105: =F103*F104 -> 1908.6701 | G105: =G103*G104 -> 2065.0048 | H105: ＝ 隐含股价 × 折现因子
A107: 6.1 三个关键年份的目标价：各用各的 P/E
A108: 年份 | B108: 经营性 EPS | C108: 每股净现金 | D108: 采用 P/E | E108: 隐含目标价 | F108: 折现期（年） | G108: 折现后每股价值 | H108: 折现后 ÷ 现价 − 1 | I108: 这个数字回答什么
...

Sheet 03-DCF-乐观
A1: BULL · SNDK 现金流折现模型 —— 乐观情形
A2: FY2027 分四个季度 → FY2028–FY2032 按年 → 永续 | 自由现金流口径：FCFF（含 Flash Ventures 投入） | ▼ 全部参数由本表底部的参数控制台滑标驱动
A4: 00 本情形的论点：这套数字建立在什么判断之上
A5: 直接采用公司 2026 投资者日给出的 FY2028–FY2030 长期框架：收入中高双位数增长、非 GAAP 毛利率约 80%、营业利润率约 75%、费用率约 5%、调整后自由现金流率约 50%。背后的逻辑是 NBM 长约锁定了 FY28 三分之二的 bit，把存储从周期股变成了合约制生意。
A6: 1．FY27 Q1 取指引上沿附近 $10.70B，其后随数据中心放量继续爬坡
A7: 2．FY28–FY30 完全对齐投资者日框架：收入 +16%~18%、毛利率 80%
A8: 3．NBM 长约把周期性削平——这是本情形与另外两个情形最根本的分歧点
A9: 4．WACC 降到 10.5%（现金流可预测性提高），永续增长 3.5%
A11: 01 FY2027 季度预测（SNDK 分拆才一年半，先用季度把最近的可见度做实）
A12: 科目（百万美元） | B12: FY27 Q1 | C12: FY27 Q2 | D12: FY27 Q3 | E12: FY27 Q4 | F12: FY2027 合计 | G12: 变量怎么来的
A13: 营业收入 | B13: =$B$189 -> 10700 | C13: =B13*(1+0.121495+$B$191) -> 11999.996 | D13: =C13*(1+0.083333+$B$191) -> 12999.992 | E13: =D13*(1+0.038462+$B$191) -> 13499.998 | F13: =SUM(B13:E13) -> 49199.987 | G13: Q1 ＝ 控制台滑标（官方指引 $10.3–10.8B）；Q2–Q4 ＝ 上一季 ×(1 + 情形环比增速 + 滑标平移)
A14: 环比增速 QoQ | B14: =B13/'00-三表与联动'!E28-1 -> 0.1935304 | C14: =C13/B13-1 -> 0.121495 | D14: =D13/C13-1 -> 0.083333 | E14: =E13/D13-1 -> 0.038462 | F14: =F13/'00-三表与联动'!F28-1 -> 1.429869 | G14: Q1 的环比基数是 FY26 Q4 的 $8,965M（不是 FY26 全年）；Q2–Q4 为上一季
A15: 毛利率 | B15: =MAX(0.05,MIN(0.92,0.848+$B$193)) -> 0.848 | C15: =MAX(0.05,MIN(0.92,0.85+$B$193)) -> 0.85 | D15: =MAX(0.05,MIN(0.92,0.85+$B$193)) -> 0.85 | E15: =MAX(0.05,MIN(0.92,0.845+$B$193)) -> 0.845 | F15: =F16/F13 -> 0.84819309 | G15: 情形设定的季度毛利率路径 + 控制台「毛利率平移」，上下限锁在 5%–92%
A16: 毛利 | B16: =B13*B15 -> 9073.6 | C16: =C13*C15 -> 10199.997 | D16: =D13*D15 -> 11049.993 | E16: =E13*E15 -> 11407.498 | F16: =SUM(B16:E16) -> 41731.089 | G16: ＝ 收入 × 毛利率
A17: 营业费用 | B17: =B13*$B$199 -> 535 | C17: =C13*$B$199 -> 599.99982 | D17: =D13*$B$199 -> 649.99961 | E17: =E13*$B$199 -> 674.9999 | F17: =SUM(B17:E17) -> 2459.9993 | G17: ＝ 收入 × 控制台「营业费用率」。公司 FY27 Q1 GAAP 指引为 $574–614M
A18: 营业利润 EBIT | B18: =B16-B17 -> 8538.6 | C18: =C16-C17 -> 9599.9972 | D18: =D16-D17 -> 10399.994 | E18: =E16-E17 -> 10732.498 | F18: =SUM(B18:E18) -> 39271.089 | G18: ＝ 毛利 − 营业费用
A19: 营业利润率 | B19: =B18/B13 -> 0.798 | C19: =C18/C13 -> 0.8 | D19: =D18/D13 -> 0.8 | E19: =E18/E13 -> 0.795 | F19: =F18/F13 -> 0.79819309 | G19: ＝ EBIT ÷ 收入
A20: 所得税 | B20: =MAX(0,B18)*$B$201 -> 1280.79 | C20: =MAX(0,C18)*$B$201 -> 1439.9996 | D20: =MAX(0,D18)*$B$201 -> 1559.9991 | E20: =MAX(0,E18)*$B$201 -> 1609.8748 | F20: =SUM(B20:E20) -> 5890.6634 | G20: ＝ EBIT × 控制台「有效税率」（FCFF 口径按 EBIT 计税，不含利息）
A21: 税后经营利润 NOPAT | B21: =B18-B20 -> 7257.81 | C21: =C18-C20 -> 8159.9976 | D21: =D18-D20 -> 8839.9947 | E21: =E18-E20 -> 9122.6236 | F21: =SUM(B21:E21) -> 33380.426 | G21: ＝ EBIT − 所得税
A22: ＋ 折旧摊销 D&A | B22: =B13*0.0074 -> 79.18 | C22: =C13*0.0074 -> 88.799974 | D22: =D13*0.0074 -> 96.199942 | E22: =E13*0.0074 -> 99.899985 | F22: =SUM(B22:E22) -> 364.0799 | G22: ＝ 收入 × 0.74%（FY26 实际 D&A $149M ÷ 收入 $20,248M）。数字极低是因为晶圆厂在合资公司里，折旧不落在 SNDK 报表上
A23: − 自有资本开支 | B23: =-B13*$B$203 -> -181.9 | C23: =-C13*$B$203 -> -203.99994 | D23: =-D13*$B$203 -> -220.99987 | E23: =-E13*$B$203 -> -229.49996 | F23: =SUM(B23:E23) -> -836.39977 | G23: ＝ 收入 × 控制台「自有资本开支率」。FY26 实际 0.87%
A24: − Flash Ventures 净投入 | B24: =-B13*$B$205 -> -299.6 | C24: =-C13*$B$205 -> -335.9999 | D24: =-D13*$B$205 -> -363.99978 | E24: =-E13*$B$205 -> -377.99994 | F24: =SUM(B24:E24) -> -1377.5996 | G24: ＝ 收入 × 控制台「FV 净投入率」。FY26 实际 1.36%（发放票据 462 − 回收 187）
A25: 营运资本余额 | B25: =B13*4*$B$207 -> 6848 | C25: =C13*4*$B$207 -> 7679.9978 | D25: =D13*4*$B$207 -> 8319.995 | E25: =E13*4*$B$207 -> 8639.9987 | F25: =E25 -> 8639.9987 | G25: ＝ 控制台「营运资本占年化收入比」× 当季收入 × 4。期初取 FY26 Q4 的年化收入基准
A26: − 营运资本增加 ΔNWC | B26: =-(B25-'00-三表与联动'!E28*4*$B$207) -> -1110.4 | C26: =-(C25-B25) -> -831.99776 | D26: =-(D25-C25) -> -639.99725 | E26: =-(E25-D25) -> -320.00365 | F26: =SUM(B26:E26) -> -2902.3987 | G26: ＝ 本季余额 − 上季余额。余额法，不再用「占收入增量比」
A27: ＝ 自由现金流 FCFF | B27: =B21+B22+B23+B24+B26 -> 5745.09 | C27: =C21+C22+C23+C24+C26 -> 6876.8 | D27: =D21+D22+D23+D24+D26 -> 7711.1977 | E27: =E21+E22+E23+E24+E26 -> 8295.02 | F27: =SUM(B27:E27) -> 28628.108 | G27: ＝ NOPAT + D&A − 自有资本开支 − FV 净投入 − ΔNWC
A28: 口径说明：这里算的是 FCFF（企业自由现金流），所以税按 EBIT 计、不扣利息——利息的价值已经体现在折现率里。公司目前零负债，FCFF 与 FCFE 的差异只剩利息收入。
A30: 02 FY2028–FY2032 年度预测 + 永续
A31: 科目（百万美元） | B31: FY2027 | C31: FY2028 | D31: FY2029 | E31: FY2030 | F31: FY2031 | G31: FY2032 | H31: 永续期 | I31: 变量怎么来的
A32: 营业收入 | B32: =F13 -> 49199.987 | C32: =B32*(1+0.18) -> 58055.984 | D32: =C32*(1+0.17+$B$197) -> 67925.502 | E32: =D32*(1+0.16+$B$197) -> 78793.582 | F32: =E32*(1+0.12+$B$197) -> 88248.812 | G32: =F32*(1+0.1+$B$197) -> 97073.693 | H32: =G32*(1+$B$211) -> 100471.27 | I32: FY27 取季度合计；FY28 ＝ 情形设定增速；FY29–32 ＝ 情形增速 + 控制台「长期增速平移」
A33: 收入增速 YoY | B33: =B32/'00-三表与联动'!F28-1 -> 1.429869 | C33: =C32/B32-1 -> 0.18 | D33: =D32/C32-1 -> 0.17 | E33: =E32/D32-1 -> 0.16 | F33: =F32/E32-1 -> 0.12 | G33: =G32/F32-1 -> 0.1 | H33: =$B$211 -> 0.035 | I33: 逐年同比。FY26 实际为 +175%
A34: 毛利率 | B34: =F16/F13 -> 0.84819309 | C34: =MAX(0.05,MIN(0.92,0.8+$B$193)) -> 0.8 | D34: =MAX(0.05,MIN(0.92,0.8+$B$193)) -> 0.8 | E34: =MAX(0.05,MIN(0.92,0.8+$B$193)) -> 0.8 | F34: =MAX(0.05,MIN(0.92,0.78+$B$193)) -> 0.78 | G34: =$B$195 -> 0.76 | H34: =G34 -> 0.76 | I34: 情形设定的年度毛利率 + 控制台「毛利率平移」；FY32 直接取控制台「终局毛利率」
A35: 毛利 | B35: =B32*B34 -> 41731.089 | C35: =C32*C34 -> 46444.787 | D35: =D32*D34 -> 54340.401 | E35: =E32*E34 -> 63034.865 | F35: =F32*F34 -> 68834.073 | G35: =G32*G34 -> 73776.006 | H35: =H32*H34 -> 76358.167 | I35: ＝ 收入 × 毛利率
A36: 营业费用 | B36: =B32*$B$199 -> 2459.9993 | C36: =C32*$B$199 -> 2902.7992 | D36: =D32*$B$199 -> 3396.2751 | E36: =E32*$B$199 -> 3939.6791 | F36: =F32*$B$199 -> 4412.4406 | G36: =G32*$B$199 -> 4853.6846 | H36: =H32*$B$199 -> 5023.5636 | I36: ＝ 收入 × 控制台「营业费用率」
A37: 营业利润 EBIT | B37: =B35-B36 -> 39271.089 | C37: =C35-C36 -> 43541.988 | D37: =D35-D36 -> 50944.126 | E37: =E35-E36 -> 59095.186 | F37: =F35-F36 -> 64421.632 | G37: =G35-G36 -> 68922.322 | H37: =H35-H36 -> 71334.603 | I37: ＝ 毛利 − 营业费用
A38: 营业利润率 | B38: =B37/B32 -> 0.79819309 | C38: =C37/C32 -> 0.75 | D38: =D37/D32 -> 0.75 | E38: =E37/E32 -> 0.75 | F38: =F37/F32 -> 0.73 | G38: =G37/G32 -> 0.71 | H38: =H37/H32 -> 0.71 | I38: ＝ EBIT ÷ 收入。可与投资者日目标「约 75%」对照
A39: 税后经营利润 NOPAT | B39: =B37*(1-$B$201) -> 33380.426 | C39: =C37*(1-$B$201) -> 37010.69 | D39: =D37*(1-$B$201) -> 43302.507 | E39: =E37*(1-$B$201) -> 50230.908 | F39: =F37*(1-$B$201) -> 54758.388 | G39: =G37*(1-$B$201) -> 58583.974 | H39: =H37*(1-$B$201) -> 60634.413 | I39: ＝ EBIT ×(1 − 有效税率)
A40: ＋ 折旧摊销 D&A | B40: =B32*0.0074 -> 364.0799 | C40: =C32*0.0074 -> 429.61428 | D40: =D32*0.0074 -> 502.64871 | E40: =E32*0.0074 -> 583.07251 | F40: =F32*0.0074 -> 653.04121 | G40: =G32*0.0074 -> 718.34533 | H40: =H32*0.0074 -> 743.48741 | I40: ＝ 收入 × 0.74%
A41: − 自有资本开支 | B41: =-B32*$B$203 -> -836.39977 | C41: =-C32*$B$203 -> -986.95173 | D41: =-D32*$B$203 -> -1154.7335 | E41: =-E32*$B$203 -> -1339.4909 | F41: =-F32*$B$203 -> -1500.2298 | G41: =-G32*$B$203 -> -1650.2528 | H41: =-H32*$B$203 -> -1708.0116 | I41: ＝ 收入 × 控制台「自有资本开支率」
A42: − Flash Ventures 净投入 | B42: =-B32*$B$205 -> -1377.5996 | C42: =-C32*$B$205 -> -1625.5676 | D42: =-D32*$B$205 -> -1901.914 | E42: =-E32*$B$205 -> -2206.2203 | F42: =-F32*$B$205 -> -2470.9667 | G42: =-G32*$B$205 -> -2718.0634 | H42: =-H32*$B$205 -> -2813.1956 | I42: ＝ 收入 × 控制台「FV 净投入率」
A43: 营运资本余额 | B43: =B32*$B$207 -> 7871.9979 | C43: =C32*$B$207 -> 9288.9575 | D43: =D32*$B$207 -> 10868.08 | E43: =E32*$B$207 -> 12606.973 | F43: =F32*$B$207 -> 14119.81 | G43: =G32*$B$207 -> 15531.791 | H43: =H32*$B$207 -> 16075.404 | I43: ＝ 控制台「营运资本占年化收入比」× 当年收入。期初取 FY26 Q4 年化收入 × 同一比例
A44: − 营运资本增加 ΔNWC | B44: =-(B43-'00-三表与联动'!E28*4*$B$207) -> -2134.3979 | C44: =-(C43-B43) -> -1416.9596 | D44: =-(D43-C43) -> -1579.1228 | E44: =-(E43-D43) -> -1738.8928 | F44: =-(F43-E43) -> -1512.8368 | G44: =-(G43-F43) -> -1411.981 | H44: =-(H43-G43) -> -543.61268 | I44: ＝ 本年余额 − 上年余额（余额法）
A45: ＝ 自由现金流 FCFF | B45: =B39+B40+B41+B42+B44 -> 29396.109 | C45: =C39+C40+C41+C42+C44 -> 33410.825 | D45: =D39+D40+D41+D42+D44 -> 39169.386 | E45: =E39+E40+E41+E42+E44 -> 45529.377 | F45: =F39+F40+F41+F42+F44 -> 49927.395 | G45: =G39+G40+G41+G42+G44 -> 53522.022 | H45: =H39+H40+H41+H42+H44 -> 56313.08 | I45: ＝ NOPAT + D&A − 自有资本开支 − FV 净投入 − ΔNWC。★ 估值采用的是这一行，不是季度块
A46: FCFF 利润率 | B46: =B45/B32 -> 0.59748204 | C46: =C45/C32 -> 0.57549322 | D46: =D45/D32 -> 0.57665214 | E46: =E45/E32 -> 0.57783103 | F46: =F45/F32 -> 0.56575714 | G46: =G45/G32 -> 0.55135455 | H46: =H45/H32 -> 0.56048937 | I46: ＝ FCFF ÷ 收入。可与投资者日「调整后自由现金流率约 50%」对照（口径不同，见溯源表）
A47: 折现期（年，期中折现） | B47: =0.5 -> 0.5 | C47: =1.5 -> 1.5 | D47: =2.5 -> 2.5 | E47: =3.5 -> 3.5 | F47: =4.5 -> 4.5 | G47: =5.5 -> 5.5 | H47: — | I47: 期中折现法：第 n 年的折现期为 n − 0.5，假设现金流在年内均匀发生
A48: 折现因子 | B48: =1/(1+$B$209)^B47 -> 0.95130299 | C48: =1/(1+$B$209)^C47 -> 0.86090768 | D48: =1/(1+$B$209)^D47 -> 0.77910197 | E48: =1/(1+$B$209)^E47 -> 0.70506966 | F48: =1/(1+$B$209)^F47 -> 0.63807209 | G48: =1/(1+$B$209)^G47 -> 0.57744081 | H48: — | I48: ＝ 1 ÷ (1 + WACC)^折现期
A49: 折现后 FCFF 现值 | B49: =B45*B48 -> 27964.606 | C49: =C45*C48 -> 28763.636 | D49: =D45*D48 -> 30516.946 | E49: =E45*E48 -> 32101.382 | F49: =F45*F48 -> 31857.278 | G49: =G45*G48 -> 30905.799 | H49: — | I49: ＝ FCFF × 折现因子
A51: 03 折现率 WACC（公司零负债，WACC = 股权成本）
A52: 参数 | B52: 取值 | D52: 来源与说明
A53: 无风险利率 Rf | B53: ='00-三表与联动'!$B$13 -> 0.042 | D53: 10 年期美国国债收益率，取 4.20%
A54: 股权风险溢价 ERP | B54: ='00-三表与联动'!$B$14 -> 0.05 | D54: 美国成熟市场长期 ERP，取 5.00%
A55: 贝塔 β（隐含） | B55: =(B56-B53)/B54 -> 1.26 | D55: ★ 由控制台 WACC 反解：β = (WACC − Rf) ÷ ERP。SNDK 2025-02 才上市，交易历史不足两年，回归贝塔极不稳定（Yahoo/CNBC 均不提供 β），因此本模型的做法是直接设定 WACC、反算隐含 β 供你判断合理性。
A56: 股权成本 Ke = WACC | B56: =$B$209 -> 0.105 | D56: 控制台滑标直接给定
A57: 有息负债 / 总资本 | B57: 0 | D57: FY26 Q3 起公司已还清全部长期债务，D/(D+E) = 0
A58: 债务成本 Kd（税后） | B58: 0 | D58: 无负债，不适用
A60: 04 估值：从终值到每股内在价值
A61: 步骤 | B61: 金额（百万美元） | D61: 计算方式与说明
A62: ① 预测期 FCFF 现值合计 | B62: =SUM(B49:G49) -> 182109.65 | D62: FY2027–FY2032 六年折现值加总（期中折现）
A63: ② 终值 TV（永续增长法） | B63: =H45/($B$209-$B$211) -> 804472.57 | D63: ＝ 永续期 FCFF ÷ (WACC − g)。★ 若 WACC ≤ g 公式失效，控制台已把 g 上限设在 6%
A64: ③ 终值现值 PV(TV) | B64: =B63*G48/(1+$B$209)^0.5 -> 441913.81 | D64: 用 FY32 的折现因子再折半年，与期中折现保持一致
A65: ④ 终值占企业价值比重 | B65: =B64/B66 -> 0.70816859 | D65: ★ 这个比例越高，说明估值越依赖你对永续期的猜测，而不是可见的现金流
A66: ⑤ 企业价值 EV | B66: =B62+B64 -> 624023.46 | D66: ＝ ① + ③
A67: ⑥ ＋ 货币资金 | B67: ='00-三表与联动'!$B$10 -> 4762 | D67: FY26 Q4末 $4,762M
A68: ⑦ ＋ 可交易权益证券 | B68: ='00-三表与联动'!$B$11 -> 1777 | D68: FY26 Q4末 $1,777M，按非经营性资产处理
A69: ⑧ − 有息负债 | B69: =-'00-三表与联动'!$B$12 -> 0 | D69: 公司已零负债
A70: ⑨ 股权价值 | B70: =B66+B67+B68+B69 -> 630562.46 | D70: ＝ EV + 净现金
A71: ⑩ 摊薄股数（百万股） | B71: ='00-三表与联动'!$B$9 -> 155 | D71: 公司 FY27 Q1 指引「约 155」
A72: ⑪ 每股内在价值 | B72: =B70/B71 -> 4068.1449 | D72: ＝ 股权价值 ÷ 摊薄股数
A73: ⑫ 当前股价 | B73: ='00-三表与联动'!$B$6 -> 1500.17 | D73: 2026-08-26 盘中 $1,500.17
A74: ⑬ 相对现价的上行/下行 | B74: =B72/B73-1 -> 1.7117893 | D74: ★ 正数 = 模型认为被低估；负数 = 被高估
A75: ★ 请先看第 ④ 行「终值占企业价值比重」再看第 ⑬ 行的结论。对一个处在周期顶点的存储公司，如果终值占比超过 70%，那么这个 DCF 实际上不是在给现金流定价，而是在给你对 2032 年之后 NAND 行业格局的猜测定价。
A77: 05 交叉验证：退出倍数法与相对估值
A78: 方法 | B78: 关键输入 | D78: 隐含结果 | F78: 说明
A79: 永续增长法隐含的退出 EV/EBITDA | D79: =B63/(G37+G40) -> 11.551764 | F79: ＝ 终值 ÷ FY32 EBITDA。若这个倍数远高于半导体行业常见的 8–14x，说明永续增长率给得过于激进
A80: 永续增长法隐含的退出 EV/收入 | D80: =B63/G32 -> 8.2872357 | F80: ＝ 终值 ÷ FY32 收入
A81: 本模型每股价值 ÷ FY27 每股 FCFF | D81: =B72/(F27/'00-三表与联动'!$B$9) -> 22.025991 | F81: 把内在价值换算成 FY27 自由现金流的倍数，便于与同业横比
A82: 当前股价隐含的 FY27 P/FCFF | D82: ='00-三表与联动'!$B$6/(F27/'00-三表与联动'!$B$9) -> 8.1223094 | F82: 市场正在为 FY27 的自由现金流付多少倍
A83: 当前市值 ÷ 本模型股权价值 | D83: ='00-三表与联动'!$B$6*'00-三表与联动'!$B$9/B70 -> 0.36876022 | F83: 大于 1 = 市场比模型乐观
A85: 06 回购与每股收益：EPS × P/E 交叉估值（与 DCF 并排看）
A86: 为什么要做这一块：DCF 给的是「整个企业值多少钱」，它对回购是中性的——按公允价值回购既不创造也不毁灭价值。但管理层已承诺把 100% 的剩余现金用于回购，股数会大幅下降，所以从「持有不卖的股东」角度看，每股口径会变。这一节把回购显式建模：股数逐年递减 → 经营性 EPS 抬升 → 用当年的 P/E 给一个价格 → 折回今天，再与 DCF 的结果并排比较。
A87: ★ 关于 P/E：本节不再用同一个倍数乘所有年份。FY2027、FY2028、FY2032 各有独立滑标，FY29–FY31 在 FY28 与 FY32 之间线性过渡。原因是周期股的 P/E 与盈利反向：盈利高点（FY27）市场给的倍数最低，盈利回落年（FY28）分母掉得比股价快、倍数反而扩张，终局年（FY32）回到正常中枢。用一个固定倍数乘所有年份，会系统性高估高点年份的目标价。
A88: ★ 关于回购均价：＝ 当前股价 × 倍数 ×(1+WACC)^(t−0.5)。让回购价按折现率复利，是「市场对股票定价合理」的中性假设。如果假设股价六年不动，模型会机械地算出巨额增厚——那是假的。有了这个设定，当 FY32 的 P/E 等于「本 DCF 隐含的退出 P/E」时，两种方法应当收敛。
A89: 科目 | B89: FY2027 | C89: FY2028 | D89: FY2029 | E89: FY2030 | F89: FY2031 | G89: FY2032 | H89: 口径与说明
A90: 自由现金流 FCFF | B90: =B45 -> 29396.109 | C90: =C45 -> 33410.825 | D90: =D45 -> 39169.386 | E90: =E45 -> 45529.377 | F90: =F45 -> 49927.395 | G90: =G45 -> 53522.022 | H90: 链接自上方年度预测表
A91: × 回购比例 | B91: =$B$133 -> 1 | C91: =$B$133 -> 1 | D91: =$B$133 -> 1 | E91: =$B$133 -> 1 | F91: =$B$133 -> 1 | G91: =$B$133 -> 1 | H91: 本节内控制台滑标，默认 100%（管理层承诺返还 100% 剩余现金）
A92: ＝ 用于回购的金额 | B92: =MAX(0,B90*B91) -> 29396.109 | C92: =MAX(0,C90*C91) -> 33410.825 | D92: =MAX(0,D90*D91) -> 39169.386 | E92: =MAX(0,E90*E91) -> 45529.377 | F92: =MAX(0,F90*F91) -> 49927.395 | G92: =MAX(0,G90*G91) -> 53522.022 | H92: ＝ MAX(0, FCFF × 回购比例)。FCFF 为负时不回购
A93: 回购均价（美元/股） | B93: ='00-三表与联动'!$B$6*$B$135*(1+$B$209)^0.5 -> 1576.9634 | C93: ='00-三表与联动'!$B$6*$B$135*(1+$B$209)^1.5 -> 1742.5446 | D93: ='00-三表与联动'!$B$6*$B$135*(1+$B$209)^2.5 -> 1925.5117 | E93: ='00-三表与联动'!$B$6*$B$135*(1+$B$209)^3.5 -> 2127.6905 | F93: ='00-三表与联动'!$B$6*$B$135*(1+$B$209)^4.5 -> 2351.098 | G93: ='00-三表与联动'!$B$6*$B$135*(1+$B$209)^5.5 -> 2597.9633 | H93: ＝ 当前股价 × 本节滑标倍数 ×(1+WACC)^(t−0.5)
A94: − 回购注销股数（百万股） | B94: =B92/B93 -> 18.640958 | C94: =C92/C93 -> 19.173584 | D94: =D92/D93 -> 20.342325 | E94: =E92/E93 -> 21.398496 | F94: =F92/F93 -> 21.235778 | G94: =G92/G93 -> 20.601531 | H94: ＝ 回购金额 ÷ 回购均价
A95: ＋ 股权激励新增股数（百万股） | B95: =B32*0.0115/B93 -> 0.35879073 | C95: =C32*0.0115/C93 -> 0.38314304 | D95: =D32*0.0115/D93 -> 0.40568086 | E95: =E32*0.0115/E93 -> 0.42587312 | F95: =F32*0.0115/F93 -> 0.43165421 | G95: =G32*0.0115/G93 -> 0.42970102 | H95: ＝ 收入 × 1.15% ÷ 回购均价。FY26 股份支付 $232M ÷ 收入 $20,248M ＝ 1.15%
A96: 期初摊薄股数（百万股） | B96: ='00-三表与联动'!$B$9 -> 155 | C96: =B97 -> 136.71783 | D96: =C97 -> 117.92739 | E96: =D97 -> 97.990747 | F96: =E97 -> 77.018124 | G96: =F97 -> 56.214 | H96: FY27 期初取公司指引的 155；其后为上年期末
A97: 期末摊薄股数（百万股） | B97: =MAX(20,B96-B94+B95) -> 136.71783 | C97: =MAX(20,C96-C94+C95) -> 117.92739 | D97: =MAX(20,D96-D94+D95) -> 97.990747 | E97: =MAX(20,E96-E94+E95) -> 77.018124 | F97: =MAX(20,F96-F94+F95) -> 56.214 | G97: =MAX(20,G96-G94+G95) -> 36.042169 | H97: ＝ 期初 − 回购注销 + 股权激励新增，下限锁 20
A98: 净现金余额 | B98: =('00-三表与联动'!$B$10+'00-三表与联动'!$B$11-'00-三表与联动'!$B$12)+B90-B92 -> 6539 | C98: =B98+C90-C92 -> 6539 | D98: =C98+D90-D92 -> 6539 | E98: =D98+E90-E92 -> 6539 | F98: =E98+F90-F92 -> 6539 | G98: =F98+G90-G92 -> 6539 | H98: ＝ 上期净现金 + FCFF − 回购金额。★ 回购比例＜100% 时现金会累积，这部分价值必须计入，否则会低估
A99: 税后经营利润 NOPAT | B99: =B39 -> 33380.426 | C99: =C39 -> 37010.69 | D99: =D39 -> 43302.507 | E99: =E39 -> 50230.908 | F99: =F39 -> 54758.388 | G99: =G39 -> 58583.974 | H99: 链接自上方年度预测表。★ 用 NOPAT 而非净利润，是为了与 DCF 同口径（不含利息）
A100: 经营性每股收益 EPS | B100: =B99/B97 -> 244.15561 | C100: =C99/C97 -> 313.84303 | D100: =D99/D97 -> 441.90404 | E100: =E99/E97 -> 652.19595 | F100: =F99/F97 -> 974.10588 | G100: =G99/G97 -> 1625.4286 | H100: ＝ NOPAT ÷ 期末股数。用期末股数而非加权平均，因为要回答的是「那个时点每一股值多少」
A101: 每股净现金 | B101: =B98/B97 -> 47.828435 | C101: =C98/C97 -> 55.449374 | D101: =D98/D97 -> 66.73079 | E101: =E98/E97 -> 84.902094 | F101: =F98/F97 -> 116.32334 | G101: =G98/G97 -> 181.42637 | H101: ＝ 净现金余额 ÷ 期末股数
A102: ★ 采用的 P/E 倍数 | B102: =$B$137 -> 12 | C102: =$B$139 -> 15 | D102: =$B$139+($B$141-$B$139)*1/4 -> 15.75 | E102: =$B$139+($B$141-$B$139)*2/4 -> 16.5 | F102: =$B$139+($B$141-$B$139)*3/4 -> 17.25 | G102: =$B$141 -> 18 | H102: FY27 / FY28 / FY32 各由本节独立滑标给定；FY29–FY31 在 FY28 与 FY32 之间线性过渡（四等分）
A103: 隐含股价（EPS×当年PE + 每股净现金） | B103: =B100*B102+B101 -> 2977.6958 | C103: =C100*C102+C101 -> 4763.0948 | D103: =D100*D102+D101 -> 7026.7194 | E103: =E100*E102+E101 -> 10846.135 | F103: =F100*F102+F101 -> 16919.65 | G103: =G100*G102+G101 -> 29439.141 | H103: 把现金单独加回，使本方法与 DCF（EV + 净现金）口径一致
A104: 折现因子（期末折现） | B104: =1/(1+$B$209)^1 -> 0.90497738 | C104: =1/(1+$B$209)^2 -> 0.81898405 | D104: =1/(1+$B$209)^3 -> 0.74116204 | E104: =1/(1+$B$209)^4 -> 0.67073487 | F104: =1/(1+$B$209)^5 -> 0.60699989 | G104: =1/(1+$B$209)^6 -> 0.54932116 | H104: ＝ 1 ÷ (1+WACC)^t。股价是时点数用期末折现；上方 DCF 的现金流是期间数用期中折现
A105: 折现后每股价值 | B105: =B103*B104 -> 2694.7473 | C105: =C103*C104 -> 3900.8987 | D105: =D103*D104 -> 5207.9377 | E105: =E103*E104 -> 7274.8812 | F105: =F103*F104 -> 10270.225 | G105: =G103*G104 -> 16171.543 | H105: ＝ 隐含股价 × 折现因子
A107: 6.1 三个关键年份的目标价：各用各的 P/E
A108: 年份 | B108: 经营性 EPS | C108: 每股净现金 | D108: 采用 P/E | E108: 隐含目标价 | F108: 折现期（年） | G108: 折现后每股价值 | H108: 折现后 ÷ 现价 − 1 | I108: 这个数字回答什么
...
