Workbook

Sheet 00-Overview
A1: The Arithmetic of the Gap · Memory Supply–Demand Model
A2: v4.0 Inventory-Exhaustion Edition | DRAM / NAND / HBM | flow basis (growth gap) + stock basis (horizontal adequacy) | data cut-off 2026-09-08 | everything new in v4.0 is marked in amber
A4: How to use this workbook — read this first
A5: This workbook is the computable version of The Arithmetic of the Gap. Every number is a live formula. Sheets 01 and 02 each carry a PARAMETER CONSOLE at the bottom: drag a slider and the whole sheet and every chart recalculates. Sheet 06 carries a second console holding the three v4.0 corrections. This is a framework whose parameters you can replace and recompute — not a forecast.
A6: Blue text | B6: Editable input cell (slider link cells can also be typed into directly)
A7: Black text | B7: Formula output — do not overwrite
A8: Green text | B8: Cross-sheet reference
A9: Yellow fill | B9: Key assumption / current console value — the model is most sensitive to these
A10: Pink fill | B10: Model defect or basis risk found in the audit
A11: Amber fill | B11: Added or revised in v4.0 (2026-09-08) — new relative to the v3.0 workbook
A13: 01 The two bit-supply formulas: everything starts here
A14: DRAM | B14: Effective bits = wafer starts × net good die per wafer × bits per die × yield × (1 − HBM wafer penalty)
B15: Growth form (used by this model): bit growth = (1 + wafer capacity growth) × (1 + node bit uplift) × (1 − HBM crowd-out) − 1
A16: NAND | B16: Effective bits = wafer starts × die per wafer × layer count × bits per cell × yield
B17: Growth form (used by this model): bit growth = (1 + wafer capacity growth) × (1 + layer uplift) × (1 + QLC mix uplift) − 1
A18: ★ The whole difference sits in this line: NAND has two levers that need no new fab (layer stacking 232 → 400+ = +72%, TLC → QLC = +33%, 2.29× in theory when compounded); DRAM has none. That is the source of every conclusion below — the same demand meeting two different supply elasticities must produce two price paths.
A20: 02 Four layers of 'gap': which one this model computes
A21: In the market the words 'memory gap' point to at least four different things whose values differ by up to 20×. Mixing them up is the root of most misreadings.
A22: Layer | B22: Basis | C22: Definition | F22: 2026 value | H22: How this model uses it
A23: ① | B23: LATENT | C23: What customers want but cannot buy (quota method). Micron: able to supply only 50%–2/3 of key-customer demand; buyers receive 60–70% of what they request. Known distortion: customers know they will be cut, so they systematically over-request. | F23: −30% ~ −40% | H23: Upper-bound reference, not used
A24: ② | B24: STOCK | C24: Cumulative horizontal gap under an unconstrained-demand assumption. The v2.0 basis. Narrower than ① (over-requests removed), wider than ③ (demand destruction not removed). | F24: −15.6% | H24: ★ Primary basis of this model
A25: ③ | B25: CLEARED | C25: The residual gap actually transacted after prices have risen and part of demand has been priced out. TrendForce's published 'sufficiency ratio' is this one. | F25: −1% ~ −2% | H25: External benchmark
A26: ④ | B26: FLOW | C26: The annual rate of change of the gap — the first derivative of ②. The v1.0 basis. It tells you whether the gap is widening or narrowing, not how big it is. | F26: −9.3% | H26: ★ Secondary basis of this model
A27: Chain of logic: ① latent −(30~40)% → [strip customer over-requests] → ② stock −(15~16)% → [strip the consumer-electronics demand priced out: handsets −15~20%, notebooks −14.8%] → ③ cleared −(1~2)%. ④ is not on this chain — it is the first derivative of ②.
A29: 03 Inventory: the only physical anchor of the stock basis ▲ rewritten in v4.0
A30: Point in time | B30: Inventory weeks | C30: Note | G30: Implication
A31: Early 2023 | B31: 31 | C31: Peak of the glut — the legacy of 2020–22 double-ordering and the pandemic demand reversal.
A32: End 2025 Q3 | B32: 3.3 | C32: Matched the 2018 super-cycle low; SK hynix and Micron roughly 2 weeks each. | G32: Three-year drawdown of 27.7 weeks = 53% of one full year of demand
A33: Nov 2025 (SK hynix DRAM) | B33: 2 | C33: Korean press. Added in v4.0 — fills the gap between the 3.3-week and the sub-10-day readings.
A34: July 2026 | B34: 4 | C34: Had recovered slightly off the bottom (3–5 week range, midpoint taken).
A35: 2026 Q3 | B35: 1.43 | C35: ★ < 10 days. KB Securities, 2026-09-07, head of research Kim Dong-won. This is the single reading that changes the v4.0 conclusion. | G35: 2026 shipments contained roughly 4.9% of bits released from inventory — a source that is now exhausted
A36: Industry 'healthy' | B36: 5.35 | C36: 30–45 days = 4.3–6.4 weeks (supply-chain benchmark cited by KB). Added in v4.0.
A37: 'Normal' used by the model | B37: 8 | C37: Industry long-run mean. ★ The single most fragile parameter in this model. | G37: It drives both the start-point calibration and the restock demand
A38: ★★ v4.0: for three years the market ran short without running out because it was eating inventory — from 31 weeks down to under 1.5. The buffer is now gone, and the last leg of that drawdown (≈2.57 weeks between July 2026 and Q3 2026) means about 4.9% of 2026 shipments were released from stock rather than produced. From 2027 shipments can only come from production. That single accounting fact, not any new demand datapoint, is what moves the model.
A40: 04 Headline results (every figure links live to sheets 01 / 02 / 06)
A41: Product | B41: Basis | C41: 2025 start | D41: 2026 | E41: 2027 | F41: 2028 | G41: Trough year | H41: Filled within three years?
A42: DRAM | B42: ④ Flow: supply − demand growth | C42: — | D42: ='01-DRAM-Model'!D53 -> -0.096010969 | E42: ='01-DRAM-Model'!E53 -> -0.046477544 | F42: ='01-DRAM-Model'!F53 -> 0.091620263 | G42: 2026 | H42: Gap stops widening when the growth gap turns positive
A43: DRAM | B43: ② Stock: horizontal adequacy | C43: ='01-DRAM-Model'!D64 -> -0.07 | D43: ='01-DRAM-Model'!E64 -> -0.13951261 | E43: ='01-DRAM-Model'!F64 -> -0.16813457 | F43: ='01-DRAM-Model'!G64 -> -0.094430551 | G43: 2027 | H43: Weighted only breaks even / base case does not fill
A44: NAND | B44: ④ Flow: supply − demand growth | C44: — | D44: ='02-NAND-Model'!D34 -> -0.061545 | E44: ='02-NAND-Model'!E34 -> 0.06749035 | F44: ='02-NAND-Model'!F34 -> 0.1274845 | G44: 2026 | H44: Growth gap turns positive in 2027
A45: NAND | B45: ② Stock: horizontal adequacy | C45: ='02-NAND-Model'!D43 -> -0.025 | D45: ='02-NAND-Model'!E43 -> -0.073569218 | E45: ='02-NAND-Model'!F43 -> -0.020312745 | F45: ='02-NAND-Model'!G43 -> 0.093843631 | G45: 2027 | H45: Fills in 2027 and turns to surplus
A47: 05 v4.0 headline: the 2027 DRAM picture before and after the three corrections
A48: Metric | B48: v3.0 (2026-08-27) | C48: v4.0 headline (inventory only) | D48: v4.0 all three corrections | E48: Change vs v3.0 | F48: What moved it
A49: 2027 probability-weighted growth gap | B49: ='01-DRAM-Model'!E53 -> -0.046477544 | C49: ='06-Inventory-Burn-v4'!$E$23 -> -0.095900621 | D49: ='06-Inventory-Burn-v4'!$G$23 -> -0.061628025 | E49: =('06-Inventory-Burn-v4'!$G$23-'01-DRAM-Model'!E53)*100 -> -1.5150481 | F49: Inventory exhaustion removes ≈5pp from 2027 shipment growth; 8-high HBM4 gives back ≈+1pp; the second de-spec caps demand by ≈2.5pp
A50: Probability 2027 is still short | B50: ='06-Inventory-Burn-v4'!$D$25 -> 0.56 | C50: ='06-Inventory-Burn-v4'!$E$25 -> 0.83 | D50: ='06-Inventory-Burn-v4'!$G$25 -> 0.56 | E50: =('06-Inventory-Burn-v4'!$G$25-'06-Inventory-Burn-v4'!$D$25)*100 -> 0 | F50: Under the inventory-only correction three of five scenarios are short (78%); once all three corrections are applied S3 sits on the boundary again
A51: S3 'relief' scenario, 2027 growth gap | B51: ='01-DRAM-Model'!E50 -> 0.023154458 | C51: ='06-Inventory-Burn-v4'!$E$20 -> -0.026268619 | D51: ='06-Inventory-Burn-v4'!$G$20 -> 0.0078435731 | E51: =('06-Inventory-Burn-v4'!$G$20-'01-DRAM-Model'!E50)*100 -> -1.5310884 | F51: ★ The scenario that flips: from 'turns to surplus' to 'still short' on the inventory correction alone
A52: ⚠ Internal inconsistency inside v4.0 itself, carried here on purpose: section 4.2 of the report quotes −2.3% → −7.3% (correction #2 only), while section 4.1 nets all three corrections to roughly −1.7pp. Both cannot be the headline. This workbook computes each correction separately so you can see the two answers side by side — the honest statement is that the inventory correction alone gives −7.3% and 78%, and the fully corrected figure is materially shallower. See sheet 06 block [C].
A54: 06 The most important conclusion: DRAM and NAND part company in 2027
A55: Year | B55: DRAM flow | C55: NAND flow | D55: Flow divergence | E55: DRAM stock | F55: NAND stock | G55: Stock divergence | H55: Median divergence | I55: Robustness
A56: 2026 | B56: ='01-DRAM-Model'!D53 -> -0.096010969 | C56: ='02-NAND-Model'!D34 -> -0.061545 | D56: =(C56-B56)*100 -> 3.4465969 | E56: ='01-DRAM-Model'!E64 -> -0.13951261 | F56: ='02-NAND-Model'!E43 -> -0.073569218 | G56: =(F56-E56)*100 -> 6.5943396 | H56: =('02-NAND-Model'!E44-'01-DRAM-Model'!E65)*100 -> 6.7752861 | I56: Both short in the same direction, DRAM tighter
A57: 2027 | B57: ='01-DRAM-Model'!E53 -> -0.046477544 | C57: ='02-NAND-Model'!E34 -> 0.06749035 | D57: =(C57-B57)*100 -> 11.396789 | E57: ='01-DRAM-Model'!F64 -> -0.16813457 | F57: ='02-NAND-Model'!F43 -> -0.020312745 | G57: =(F57-E57)*100 -> 14.782183 | H57: =('02-NAND-Model'!F44-'01-DRAM-Model'!F65)*100 -> 17.3981 | I57: ★ The decisive year for the divergence
A58: 2028 | B58: ='01-DRAM-Model'!F53 -> 0.091620263 | C58: ='02-NAND-Model'!F34 -> 0.1274845 | D58: =(C58-B58)*100 -> 3.5864237 | E58: ='01-DRAM-Model'!G64 -> -0.094430551 | F58: ='02-NAND-Model'!G43 -> 0.093843631 | G58: =(F58-E58)*100 -> 18.827418 | H58: =('02-NAND-Model'!G44-'01-DRAM-Model'!G65)*100 -> 25.16147 | I58: Divergence widens further
A59: ★ Robustness check (added in this workbook; neither report did it): v2.0 warned only on the DRAM side that the mean is dragged up by extreme scenarios and the median should be read instead. Swap both sides to the probability median and the divergence does not disappear — it widens. So 'DRAM and NAND should be priced separately' is robust to the probability weights; it does not rest on the two low-probability tail scenarios.
A78: 07 Model audit: my review findings on the two reports (added by this workbook)
A79: Arithmetic: the 15 DRAM scenario-years, 12 NAND scenario-years, the HBM penalty formula, the single-variable sensitivity table and every stock recursion have been recomputed cell by cell; all differences are within rounding. The implementation is correct. What follows is at the level of logic and basis.
A80: Grade | B80: Issue | E80: Why it is a problem | H80: Effect on the conclusion
A81: A | B81: The 'model validation' in section 04 contradicts itself | E81: v2.0 section 01 explicitly defines ② stock ≠ ③ cleared, the difference being exactly demand destruction, so the two are not comparable. Section 04 nevertheless uses TrendForce's −4~−5% (③ basis) to 'validate' the model's −4.1% (② basis) and calls it a close match. The same basis logic is used to explain a 14pp discrepancy on DRAM and to claim agreement on NAND. | H81: 'The model has been validated' should be withdrawn. One free parameter (NAND start −2.0%, no derivation) fitted to one target value is not a validation. → That start value is flagged as an editable input with a note in block [A] of sheet 02.
A82: A | B82: Dimensional mismatch in the start-point calibration | E82: The recursion (1+gap_t−1)×(1+supply)÷(1+demand)−1 is mathematically identical to 'this year's supply ÷ this year's demand − 1' — a flow ratio. But the start point is calibrated with an inventory stock (4.7 weeks ÷ 52). Stock and flow ratio are different dimensions. It only looks like accumulation because the ratio of two exponential curves falls monotonically when supply growth stays below demand growth. | H82: The output is still readable but must be relabelled: it is 'the share of unconstrained demand this year's supply can meet', not 'how much has been owed cumulatively'. → Block [H] of sheet 01 computes the true additive accumulation alongside it.
A83: A | B83: Restock 7.7% and start point −9.0% are double-counted | E83: Start −9.0% = (8 − 3.3)/52, whose physical meaning is precisely 'to get back to normal you must refill 4.7 weeks'. Section 05 then adds (8 − 4)/52 = 7.7% again as incremental demand. Both point at the same inventory hole; the overlap is about 85%. | H83: The claim that 'S2's 2028 worsens from −19.4% to −24.2%' should be withdrawn. → Block [I] of sheet 01 sets the three conventions side by side; the double count is exactly 4.78pp.
A84: A | B84: HBM wafer-share basis mismatch (quantifiable) | E84: TrendForce's 18%/22%/30% is explicitly 'HBM wafers of the top three suppliers as a share of their own total DRAM wafers'. The model applied it to a global four-supplier basis that includes CXMT. CXMT makes no HBM and holds 17.1% of global wafers by end-2026. The global-basis figures should be 15.4%/18.2%/24.6%. | H84: The HBM drag is overstated: 2026 −3.0pp should be −2.1pp, 2027 −6.3pp should be −4.8pp. → Columns O–T of the main grid compute the corrected result in parallel; block [G] gives the weighted comparison. This is not a tweak, it changes the qualitative 2028 conclusion.
A85: B | B85: The implicit assumption that unmet demand accumulates does not hold | E85: The stock basis implies that the bits you failed to buy queue up to be repaid. But consumer-electronics demand priced out does not queue — once handsets and notebooks are de-specced those bits are gone for good. The only thing that genuinely queues is inventory refill, and that is exactly what the start point already double-counts. | H85: 'The base case still owes −19.4% in 2028' should be read as 'in 2028 supply still meets only 80.6% of unconstrained demand', not as 'the market is still 19.4% short of goods'.
A86: B | B86: The NAND supply formula omits the yield term and treats layers × QLC as fully independent | E86: The DRAM formula at least states that yield is folded into the node term; the NAND formula does not mention it at all. And 400-layer QLC yields materially worse than 400-layer TLC — when layers and QLC advance together, yield is an unambiguously negative term. The model multiplies (1+layers)(1+QLC), implying independence and constant yield. | H86: NAND supply growth is systematically overstated — and that is exactly the core driver of the divergence conclusion. The loosest assumption is the one the conclusion leans on hardest.
A87: B | B87: The node uplift is applied indiscriminately to CXMT's added wafers | E87: In 2026 CXMT adds 85 thousand wafers per month, 45% of the four-supplier total of 190. But CXMT makes mature-node commodity DRAM, not 1c. The model applies +13% node bit uplift uniformly to every wafer. In addition, line conversion itself consumes wafer capacity (downtime plus added process steps), so (1+wafer) and (1+node) should not be multiplied as fully independent. | H87: Opposite in direction to the item above: it overstates DRAM supply by roughly 1–3pp per year. The two errors partly offset, but both should be modelled explicitly rather than left to cancel.
A88: C | B88: The NAND scenarios' wafer growth contradicts the report's own capacity table | E88: v1.0 section 03 states that the three Korean and US NAND makers hold capacity 'stable at 670–700k wafers per month through 2026–27', yet scenario N4 assigns +16% wafer growth in 2028 and N3 assigns +12%. If capacity really is stable, wafer growth should be close to 0–4%. | H88: N3/N4 2028 supply growth is too high and the NAND surplus is exaggerated. Those two scenarios carry 38% probability combined.
A89: C | B89: Section 8.2 contradicts itself numerically | E89: Within one section it first says that SK hynix, with the highest HBM share (50–62%), is most affected, then says 2Q26 share has become 'Samsung 26%→39%, SK hynix 39%→26%'. If SK hynix has already fallen to 26%, the premise of the first sentence fails. | H89: It does not affect the model but it does affect the competitive inference in 8.2; one of the two must go. Separately, a 13pp single-quarter share swap is anomalous and the source deserves independent checking.
A90: C | B90: 2026 is treated as a pure forecast year | E90: With data through 2026-09-08, 1Q26/2Q26 contract prices and shipments are already fact and most of the full-year supply growth is locked. The model still treats 2026 as one of three forecast years. | H90: It should be split into 'realised + remainder forecast'. Sheets 01 and 02 mark 2026 as a half-actual year pending that split.
A91: C | B91: Demand growth is the largest single driver yet was never derived | E91: The sensitivity table shows demand growth has 1:1 elasticity (among the highest of the four variables); DRAM's 28% for 2026 and 26% for 2027 determine every conclusion, yet both reports say only that the figure is 'inferred from public information'. | H91: This was the biggest hole. Sheet 03 now decomposes it bottom-up across AI servers, conventional servers, handsets, PCs and other, and cross-checks it against two independent external anchors.
A92: Grades: A = affects the direction of the conclusion, should be formally corrected in the next version; B = affects the magnitude; C = internal consistency or wording. All of the above are logic and basis issues — no arithmetic error was found in either report. Five further findings were added in v3.0 (sheet 05) and three more in v4.0 (sheet 06).
A94: 08 Sources, basis and important disclosures
A95: Supply and capacity: SemiAnalysis, 'China's CXMT Is Set to Challenge DRAM Incumbents' (2026-06-24) — four-supplier end-2026 capacity and three-year additions | 'Memory Mania' (2026-02-06) — Samsung 1c carries ~70% more bits per wafer than 1a; DRAM density roughly 2× per decade
A96: HBM and gap benchmarks: TrendForce, 'Tight DRAM Supply Gives Suppliers Greater Pricing Power in HBM' (2026-06-02) — HBM wafer share 18/22/30% and HBM revenue per wafer overtaken by DDR5 64GB RDIMM | 'Diverging Memory Market Outlook in 2027' (2026-07-30) — DRAM sufficiency −1~−2%, NAND −4~−5% | 'Memory Prices Soar; DRAM and NAND to Account for 68% of Major CSP CapEx in 2027' (2026-08-25)
A97: Inventory: UncoverAlpha (3.3 weeks end-2025Q3, 31 weeks early 2023) | Luminix, 'DRAM Cycle Mid-2026 Update' (3–5 weeks in July 2026) | ★ KB Securities research note, 2026-09-07, head of research Kim Dong-won — supplier inventory below 10 days in 2026 Q3, plus four quantifications reproduced on sheet 04 | quota: Micron FY26 Q2 call, Korean press 60–70%
A98: v4.0 primary sources: DigiTimes (2026-08-26/27, NVIDIA's request for a higher 8-high HBM4 mix on the Vera Rubin platform; 2026-09-07, inventory below 10 days) | Seoul Economic Daily, TechTimes, technetbooks (all 2026-09-07) | BiggO Finance (≈2026-09-02, Samsung 8-high HBM4E for NVHBM / Rubin Ultra) | TrendForce (2026-01, 16-high requirement; 2026 Q2 DRAM revenue $154.73bn) | Hankyung (2026-03)
A99: Other: NVIDIA FY2027 Q2 8-K, CFO commentary and Form 10-Q (through 2026-07-26) | Sandisk FY2026 Q4 presentation (NBM pricing with floor and ceiling) | Ben Bajarin, 'Memory's $200B Inflection' (2026-06-23) — wafer starts +6~8% | IDC (2026 DRAM bits +16%, NAND +17%) | Isaiah Research | Gartner memflation | StorageSwiss, XenoSpectrum, MemoryXRef
A100: ★ Built by the author, no external basis: every scenario assumption (wafer growth, node uplift, layers, QLC, demand growth) and every scenario probability (DRAM 15/38/25/15/7%, NAND 22/40/26/12%) is a subjective assignment. Only the HBM wafer share, 2026 wafer growth, the TrendForce gap basis and — new in v4.0 — the 3× HBM wafer penalty, now independently confirmed by KB Securities, have third-party support.
A101: ★ Known simplifications: HBM and conventional DRAM are not modelled separately (CXMT affects only the latter); price transmission sits entirely outside the model and has been structurally changed by long-term-agreement ceilings; supply has no reaction function; the yield term is folded into the node term for DRAM and missing for NAND; Nanya, Winbond, YMTC, Kioxia, Sandisk and Western Digital are absent from the capacity table, which understates total supply; advanced packaging (CoWoS) is outside the model boundary and v4.0 argues part of the bottleneck has moved there.
A102: This workbook is for research and study only. It is not investment advice and not an offer to buy or sell any security. Memory is a high-volatility sector and a change in any single assumption can move the conclusion materially. Treat it as a tool whose parameters you can replace and recompute, not as a forecast.
A103: If you work at a regulated institution, confirm the applicable personal-account reporting and pre-clearance requirements before trading.

Sheet 01-DRAM-Model
A1: 01 · DRAM supply–demand model
A2: Five scenarios × three years | flow basis (growth gap) + stock basis (horizontal adequacy) | ▼ every parameter is driven by the [K] PARAMETER CONSOLE at the bottom of this sheet | amber rows are v4.0 additions
A4: [A] Global assumptions (values come from console [K] below — drag a slider to change them)
A5: Parameter | B5: Current value | C5: Unit | D5: Note
A6: HBM wafer penalty · 2025–2026 (×) | B6: =$B$143 -> 2.8 | C6: × | D6: TrendForce and Micron both use 3:1. ★ v4.0: KB Securities independently states that HBM4 consumes three times the wafer capacity of conventional DRAM — the first third-party confirmation of what had been a self-built assumption.
A7: 8-high HBM4 penalty relief from 2027 (×) | B7: ='06-Inventory-Burn-v4'!$B$10 -> -0.2 | C7: × | D7: ▲ NEW in v4.0. NVIDIA has asked Samsung and SK hynix for a higher 8-high mix on Vera Rubin, and for HBM4E to drop from 12/16-high to 8-high for Rubin Ultra. Net of base-die dilution (−3.7%) and stacking-yield gain (+4~13%), the effective wafer penalty falls by roughly 0.2×. Full arithmetic on sheet 07.
A8: HBM wafer penalty · 2027–2028 (×) | B8: =$B$6+$B$7 -> 2.6 | C8: × | D8: ▲ NEW in v4.0. Used by the v4.0 blocks only — the main grid below deliberately stays on the 3.0× v3.0 basis so that the v3.0 results remain reproducible. 8-high ships from 2027, so 2026 keeps the 12-high penalty.
A9: HBM basis correction switch | B9: =$B$145 -> 1 | C9: 0/1 | D9: ★ Audit finding (A, item 4): TrendForce's 18/22/30% is a top-three-supplier basis; the model applied it to a global basis that includes CXMT. Set to 1 to enable the CXMT dilution correction.
A10: 'Normal' inventory (weeks) | B10: 8 | C10: weeks | D10: Industry long-run mean. ★ The single most fragile parameter — it sets both the start-point calibration and the restock demand.
A11: Healthy finished-goods inventory (weeks) | B11: 5.35 | C11: weeks | D11: ▲ NEW in v4.0. 30–45 days = 4.3–6.4 weeks, the supply-chain benchmark quoted by KB Securities; 5.35 is the midpoint. Shown for reference — on this basis the start gap would be −7.5% rather than −12.6%.
A12: Latest supplier inventory (weeks) | B12: 1.43 | C12: weeks | D12: ▲ REVISED in v4.0: was 3.3 weeks (UncoverAlpha, end-2025Q3). KB Securities puts Samsung and SK hynix below 10 days in 2026 Q3 = 1.43 weeks.
A13: Inventory-implied start point (reference) | B13: =-($B$10-$B$12)/52 -> -0.12634615 | C13: % | D13: Formula: −(normal − actual) ÷ 52. With the v4.0 reading this is −12.6% against the 8-week normal, or −7.5% against the 4.3–6.4 week industry benchmark in row 11. Reference only — the model uses the row below.
A14: 2025 start gap (value used) | B14: =$B$144 -> -0.07 | C14: % | D14: Driven by the console slider. ★ Audit finding (A, item 2): this is a stock (inventory weeks) being fed into a recursion that is a flow ratio — a dimensional mismatch. See sheet 00 section 07 and block [H] below.
A17: [B] Main model: five scenarios × three years (blue on the left = raw inputs; pink on the right = HBM basis-corrected comparison)
A18: Scenario | B18: Year | C18: Wafer capacity growth | D18: Node bit uplift | E18: HBM wafer share (top-3 basis) | F18: CXMT wafer share | G18: HBM share (adopted basis) | H18: HBM-equivalent bit capacity | I18: HBM marginal drag | J18: Supply bit growth | K18: Demand growth (unconstrained) | L18: ④ Growth gap (flow basis) | M18: ② Horizontal adequacy (stock basis) | O18: Corrected HBM share | P18: Corrected equiv. bit capacity | Q18: Corrected HBM drag | R18: Corrected supply bit growth | S18: Corrected growth gap (flow) | T18: Corrected horizontal gap (stock)
A19: S1 Extreme tightness | B19: 2025 (start) | C19: — | D19: — | E19: 0.18 | F19: 0.142 | G19: =IF($B$9=1,E19*(1-F19),E19) -> 0.15444 | H19: =(1-G19)+G19/$B$6 -> 0.90071714 | I19: — | J19: — | K19: — | L19: — | M19: =$B$14 -> -0.07 | O19: =E19*(1-F19) -> 0.15444 | P19: =(1-O19)+O19/$B$6 -> 0.90071714 | Q19: — | R19: — | S19: — | T19: =$B$14 -> -0.07
B20: 2026A | C20: 0.07 | D20: 0.13 | E20: 0.22 | F20: 0.171 | G20: =IF($B$9=1,MAX(0,MIN(0.95,E20+$B$148))*(1-F20),MAX(0,MIN(0.95,E20+$B$148))) -> 0.18238 | H20: =(1-G20)+G20/$B$6 -> 0.88275571 | I20: =H20/H19-1 -> -0.019941253 | J20: =(1+C20+$B$146)*(1+D20+$B$147)*(1+I20)-1 -> 0.18498903 | K20: 0.3 | L20: =J20-(K20+$B$149) -> -0.12501097 | M20: =(1+M19)*(1+J20)/(1+K20+$B$149)-1 -> -0.15874825 | O20: =MAX(0,MIN(0.95,E20+$B$148))*(1-F20) -> 0.18238 | P20: =(1-O20)+O20/$B$6 -> 0.88275571 | Q20: =P20/P19-1 -> -0.019941253 | R20: =(1+C20+$B$146)*(1+D20+$B$147)*(1+Q20)-1 -> 0.18498903 | S20: =R20-(K20+$B$149) -> -0.12501097 | T20: =(1+T19)*(1+R20)/(1+K20+$B$149)-1 -> -0.15874825
B21: 2027 | C21: 0.09 | D21: 0.12 | E21: 0.34 | F21: 0.181 | G21: =IF($B$9=1,MAX(0,MIN(0.95,E21+$B$148))*(1-F21),MAX(0,MIN(0.95,E21+$B$148))) -> 0.27846 | H21: =(1-G21)+G21/$B$6 -> 0.82099 | I21: =H21/H20-1 -> -0.069969204 | J21: =(1+C21+$B$146)*(1+D21+$B$147)*(1+I21)-1 -> 0.1353816 | K21: 0.32 | L21: =J21-(K21+$B$149) -> -0.1946184 | M21: =(1+M20)*(1+J21)/(1+K21+$B$149)-1 -> -0.2818483 | O21: =MAX(0,MIN(0.95,E21+$B$148))*(1-F21) -> 0.27846 | P21: =(1-O21)+O21/$B$6 -> 0.82099 | Q21: =P21/P20-1 -> -0.069969204 | R21: =(1+C21+$B$146)*(1+D21+$B$147)*(1+Q21)-1 -> 0.1353816 | S21: =R21-(K21+$B$149) -> -0.1946184 | T21: =(1+T20)*(1+R21)/(1+K21+$B$149)-1 -> -0.2818483
B22: 2028 | C22: 0.12 | D22: 0.1 | E22: 0.4 | F22: 0.185 | G22: =IF($B$9=1,MAX(0,MIN(0.95,E22+$B$148))*(1-F22),MAX(0,MIN(0.95,E22+$B$148))) -> 0.326 | H22: =(1-G22)+G22/$B$6 -> 0.79042857 | I22: =H22/H21-1 -> -0.037225092 | J22: =(1+C22+$B$146)*(1+D22+$B$147)*(1+I22)-1 -> 0.18613869 | K22: 0.28 | L22: =J22-(K22+$B$149) -> -0.10386131 | M22: =(1+M21)*(1+J22)/(1+K22+$B$149)-1 -> -0.33966859 | O22: =MAX(0,MIN(0.95,E22+$B$148))*(1-F22) -> 0.326 | P22: =(1-O22)+O22/$B$6 -> 0.79042857 | Q22: =P22/P21-1 -> -0.037225092 | R22: =(1+C22+$B$146)*(1+D22+$B$147)*(1+Q22)-1 -> 0.18613869 | S22: =R22-(K22+$B$149) -> -0.10386131 | T22: =(1+T21)*(1+R22)/(1+K22+$B$149)-1 -> -0.33966859
A23: S1 Extreme tightness (probability set in console [K]): AI capex keeps being revised up; HBM wafer share pushes to 40%; Rubin Ultra delivers 384GB per GPU; the consumer end is already on the floor and stops deteriorating. Never turns positive in three years.
A24: S2 Base case | B24: 2025 (start) | C24: — | D24: — | E24: 0.18 | F24: 0.142 | G24: =IF($B$9=1,E24*(1-F24),E24) -> 0.15444 | H24: =(1-G24)+G24/$B$6 -> 0.90071714 | I24: — | J24: — | K24: — | L24: — | M24: =$B$14 -> -0.07 | O24: =E24*(1-F24) -> 0.15444 | P24: =(1-O24)+O24/$B$6 -> 0.90071714 | Q24: — | R24: — | S24: — | T24: =$B$14 -> -0.07
B25: 2026A | C25: 0.07 | D25: 0.13 | E25: 0.22 | F25: 0.171 | G25: =IF($B$9=1,MAX(0,MIN(0.95,E25+$B$148))*(1-F25),MAX(0,MIN(0.95,E25+$B$148))) -> 0.18238 | H25: =(1-G25)+G25/$B$6 -> 0.88275571 | I25: =H25/H24-1 -> -0.019941253 | J25: =(1+C25+$B$146)*(1+D25+$B$147)*(1+I25)-1 -> 0.18498903 | K25: 0.28 | L25: =J25-(K25+$B$149) -> -0.10501097 | M25: =(1+M24)*(1+J25)/(1+K25+$B$149)-1 -> -0.14570558 | O25: =MAX(0,MIN(0.95,E25+$B$148))*(1-F25) -> 0.18238 | P25: =(1-O25)+O25/$B$6 -> 0.88275571 | Q25: =P25/P24-1 -> -0.019941253 | R25: =(1+C25+$B$146)*(1+D25+$B$147)*(1+Q25)-1 -> 0.18498903 | S25: =R25-(K25+$B$149) -> -0.10501097 | T25: =(1+T24)*(1+R25)/(1+K25+$B$149)-1 -> -0.14570558
B26: 2027 | C26: 0.1 | D26: 0.12 | E26: 0.3 | F26: 0.181 | G26: =IF($B$9=1,MAX(0,MIN(0.95,E26+$B$148))*(1-F26),MAX(0,MIN(0.95,E26+$B$148))) -> 0.2457 | H26: =(1-G26)+G26/$B$6 -> 0.84205 | I26: =H26/H25-1 -> -0.046112094 | J26: =(1+C26+$B$146)*(1+D26+$B$147)*(1+I26)-1 -> 0.1751899 | K26: 0.26 | L26: =J26-(K26+$B$149) -> -0.0948101 | M26: =(1+M25)*(1+J26)/(1+K26+$B$149)-1 -> -0.20948175 | O26: =MAX(0,MIN(0.95,E26+$B$148))*(1-F26) -> 0.2457 | P26: =(1-O26)+O26/$B$6 -> 0.84205 | Q26: =P26/P25-1 -> -0.046112094 | R26: =(1+C26+$B$146)*(1+D26+$B$147)*(1+Q26)-1 -> 0.1751899 | S26: =R26-(K26+$B$149) -> -0.0948101 | T26: =(1+T25)*(1+R26)/(1+K26+$B$149)-1 -> -0.20948175
B27: 2028 | C27: 0.16 | D27: 0.11 | E27: 0.32 | F27: 0.185 | G27: =IF($B$9=1,MAX(0,MIN(0.95,E27+$B$148))*(1-F27),MAX(0,MIN(0.95,E27+$B$148))) -> 0.2608 | H27: =(1-G27)+G27/$B$6 -> 0.83234286 | I27: =H27/H26-1 -> -0.011527989 | J27: =(1+C27+$B$146)*(1+D27+$B$147)*(1+I27)-1 -> 0.27275656 | K27: 0.24 | L27: =J27-(K27+$B$149) -> 0.022756562 | M27: =(1+M26)*(1+J27)/(1+K27+$B$149)-1 -> -0.19509017 | O27: =MAX(0,MIN(0.95,E27+$B$148))*(1-F27) -> 0.2608 | P27: =(1-O27)+O27/$B$6 -> 0.83234286 | Q27: =P27/P26-1 -> -0.011527989 | R27: =(1+C27+$B$146)*(1+D27+$B$147)*(1+Q27)-1 -> 0.27275656 | S27: =R27-(K27+$B$149) -> 0.022756562 | T27: =(1+T26)*(1+R27)/(1+K27+$B$149)-1 -> -0.19509017
A28: S2 Base case (probability set in console [K]): aligned to TrendForce — 2026 sufficiency −1~−2%, the 2027 gap widens further, new capacity starts landing in 2028. The flow basis turns positive in 2028.
A29: S3 Relief | B29: 2025 (start) | C29: — | D29: — | E29: 0.18 | F29: 0.142 | G29: =IF($B$9=1,E29*(1-F29),E29) -> 0.15444 | H29: =(1-G29)+G29/$B$6 -> 0.90071714 | I29: — | J29: — | K29: — | L29: — | M29: =$B$14 -> -0.07 | O29: =E29*(1-F29) -> 0.15444 | P29: =(1-O29)+O29/$B$6 -> 0.90071714 | Q29: — | R29: — | S29: — | T29: =$B$14 -> -0.07
B30: 2026A | C30: 0.07 | D30: 0.13 | E30: 0.22 | F30: 0.171 | G30: =IF($B$9=1,MAX(0,MIN(0.95,E30+$B$148))*(1-F30),MAX(0,MIN(0.95,E30+$B$148))) -> 0.18238 | H30: =(1-G30)+G30/$B$6 -> 0.88275571 | I30: =H30/H29-1 -> -0.019941253 | J30: =(1+C30+$B$146)*(1+D30+$B$147)*(1+I30)-1 -> 0.18498903 | K30: 0.26 | L30: =J30-(K30+$B$149) -> -0.085010969 | M30: =(1+M29)*(1+J30)/(1+K30+$B$149)-1 -> -0.13225213 | O30: =MAX(0,MIN(0.95,E30+$B$148))*(1-F30) -> 0.18238 | P30: =(1-O30)+O30/$B$6 -> 0.88275571 | Q30: =P30/P29-1 -> -0.019941253 | R30: =(1+C30+$B$146)*(1+D30+$B$147)*(1+Q30)-1 -> 0.18498903 | S30: =R30-(K30+$B$149) -> -0.085010969 | T30: =(1+T29)*(1+R30)/(1+K30+$B$149)-1 -> -0.13225213
B31: 2027 | C31: 0.12 | D31: 0.14 | E31: 0.28 | F31: 0.181 | G31: =IF($B$9=1,MAX(0,MIN(0.95,E31+$B$148))*(1-F31),MAX(0,MIN(0.95,E31+$B$148))) -> 0.22932 | H31: =(1-G31)+G31/$B$6 -> 0.85258 | I31: =H31/H30-1 -> -0.034183539 | J31: =(1+C31+$B$146)*(1+D31+$B$147)*(1+I31)-1 -> 0.23315446 | K31: 0.2 | L31: =J31-(K31+$B$149) -> 0.023154458 | M31: =(1+M30)*(1+J31)/(1+K31+$B$149)-1 -> -0.11564698 | O31: =MAX(0,MIN(0.95,E31+$B$148))*(1-F31) -> 0.22932 | P31: =(1-O31)+O31/$B$6 -> 0.85258 | Q31: =P31/P30-1 -> -0.034183539 | R31: =(1+C31+$B$146)*(1+D31+$B$147)*(1+Q31)-1 -> 0.23315446 | S31: =R31-(K31+$B$149) -> 0.023154458 | T31: =(1+T30)*(1+R31)/(1+K31+$B$149)-1 -> -0.11564698
B32: 2028 | C32: 0.2 | D32: 0.13 | E32: 0.26 | F32: 0.185 | G32: =IF($B$9=1,MAX(0,MIN(0.95,E32+$B$148))*(1-F32),MAX(0,MIN(0.95,E32+$B$148))) -> 0.2119 | H32: =(1-G32)+G32/$B$6 -> 0.86377857 | I32: =H32/H31-1 -> 0.013134922 | J32: =(1+C32+$B$146)*(1+D32+$B$147)*(1+I32)-1 -> 0.37381095 | K32: 0.18 | L32: =J32-(K32+$B$149) -> 0.18381095 | M32: =(1+M31)*(1+J32)/(1+K32+$B$149)-1 -> 0.020952832 | O32: =MAX(0,MIN(0.95,E32+$B$148))*(1-F32) -> 0.2119 | P32: =(1-O32)+O32/$B$6 -> 0.86377857 | Q32: =P32/P31-1 -> 0.013134922 | R32: =(1+C32+$B$146)*(1+D32+$B$147)*(1+Q32)-1 -> 0.37381095 | S32: =R32-(K32+$B$149) -> 0.18381095 | T32: =(1+T31)*(1+R32)/(1+K32+$B$149)-1 -> 0.020952832
A33: S3 Relief (probability set in console [K]): the core assumption is that HBM economics reverse — revenue per wafer has already been overtaken by DDR5 64GB RDIMM, wafers flow back to conventional DRAM and the HBM share falls. Combined with new fabs ramping on schedule in 2H27. ⚠ v3.0 flagged this assumption as weakened by the 2026-08-25 forecast of +70~140% HBM contract prices; v4.0 flags it again — this is the scenario the inventory correction flips.
A34: S4 Surplus | B34: 2025 (start) | C34: — | D34: — | E34: 0.18 | F34: 0.142 | G34: =IF($B$9=1,E34*(1-F34),E34) -> 0.15444 | H34: =(1-G34)+G34/$B$6 -> 0.90071714 | I34: — | J34: — | K34: — | L34: — | M34: =$B$14 -> -0.07 | O34: =E34*(1-F34) -> 0.15444 | P34: =(1-O34)+O34/$B$6 -> 0.90071714 | Q34: — | R34: — | S34: — | T34: =$B$14 -> -0.07
B35: 2026A | C35: 0.07 | D35: 0.13 | E35: 0.22 | F35: 0.171 | G35: =IF($B$9=1,MAX(0,MIN(0.95,E35+$B$148))*(1-F35),MAX(0,MIN(0.95,E35+$B$148))) -> 0.18238 | H35: =(1-G35)+G35/$B$6 -> 0.88275571 | I35: =H35/H34-1 -> -0.019941253 | J35: =(1+C35+$B$146)*(1+D35+$B$147)*(1+I35)-1 -> 0.18498903 | K35: 0.24 | L35: =J35-(K35+$B$149) -> -0.065010969 | M35: =(1+M34)*(1+J35)/(1+K35+$B$149)-1 -> -0.11836816 | O35: =MAX(0,MIN(0.95,E35+$B$148))*(1-F35) -> 0.18238 | P35: =(1-O35)+O35/$B$6 -> 0.88275571 | Q35: =P35/P34-1 -> -0.019941253 | R35: =(1+C35+$B$146)*(1+D35+$B$147)*(1+Q35)-1 -> 0.18498903 | S35: =R35-(K35+$B$149) -> -0.065010969 | T35: =(1+T34)*(1+R35)/(1+K35+$B$149)-1 -> -0.11836816
B36: 2027 | C36: 0.13 | D36: 0.15 | E36: 0.24 | F36: 0.181 | G36: =IF($B$9=1,MAX(0,MIN(0.95,E36+$B$148))*(1-F36),MAX(0,MIN(0.95,E36+$B$148))) -> 0.19656 | H36: =(1-G36)+G36/$B$6 -> 0.87364 | I36: =H36/H35-1 -> -0.010326429 | J36: =(1+C36+$B$146)*(1+D36+$B$147)*(1+I36)-1 -> 0.28608081 | K36: 0.18 | L36: =J36-(K36+$B$149) -> 0.096080805 | M36: =(1+M35)*(1+J36)/(1+K36+$B$149)-1 -> -0.047185054 | O36: =MAX(0,MIN(0.95,E36+$B$148))*(1-F36) -> 0.19656 | P36: =(1-O36)+O36/$B$6 -> 0.87364 | Q36: =P36/P35-1 -> -0.010326429 | R36: =(1+C36+$B$146)*(1+D36+$B$147)*(1+Q36)-1 -> 0.28608081 | S36: =R36-(K36+$B$149) -> 0.096080805 | T36: =(1+T35)*(1+R36)/(1+K36+$B$149)-1 -> -0.047185054
B37: 2028 | C37: 0.24 | D37: 0.15 | E37: 0.2 | F37: 0.185 | G37: =IF($B$9=1,MAX(0,MIN(0.95,E37+$B$148))*(1-F37),MAX(0,MIN(0.95,E37+$B$148))) -> 0.163 | H37: =(1-G37)+G37/$B$6 -> 0.89521429 | I37: =H37/H36-1 -> 0.024694709 | J37: =(1+C37+$B$146)*(1+D37+$B$147)*(1+I37)-1 -> 0.46121466 | K37: 0.16 | L37: =J37-(K37+$B$149) -> 0.29121466 | M37: =(1+M36)*(1+J37)/(1+K37+$B$149)-1 -> 0.18997193 | O37: =MAX(0,MIN(0.95,E37+$B$148))*(1-F37) -> 0.163 | P37: =(1-O37)+O37/$B$6 -> 0.89521429 | Q37: =P37/P36-1 -> 0.024694709 | R37: =(1+C37+$B$146)*(1+D37+$B$147)*(1+Q37)-1 -> 0.46121466 | S37: =R37-(K37+$B$149) -> 0.29121466 | T37: =(1+T36)*(1+R37)/(1+K37+$B$149)-1 -> 0.18997193
A38: S4 Surplus (probability set in console [K]): AI capex peaks in 2027; hyperscalers repeat the 2019 sudden stop; CXMT runs full; HBM gives way to DDR5.
A39: S5 Collapse | B39: 2025 (start) | C39: — | D39: — | E39: 0.18 | F39: 0.142 | G39: =IF($B$9=1,E39*(1-F39),E39) -> 0.15444 | H39: =(1-G39)+G39/$B$6 -> 0.90071714 | I39: — | J39: — | K39: — | L39: — | M39: =$B$14 -> -0.07 | O39: =E39*(1-F39) -> 0.15444 | P39: =(1-O39)+O39/$B$6 -> 0.90071714 | Q39: — | R39: — | S39: — | T39: =$B$14 -> -0.07
B40: 2026A | C40: 0.07 | D40: 0.13 | E40: 0.22 | F40: 0.171 | G40: =IF($B$9=1,MAX(0,MIN(0.95,E40+$B$148))*(1-F40),MAX(0,MIN(0.95,E40+$B$148))) -> 0.18238 | H40: =(1-G40)+G40/$B$6 -> 0.88275571 | I40: =H40/H39-1 -> -0.019941253 | J40: =(1+C40+$B$146)*(1+D40+$B$147)*(1+I40)-1 -> 0.18498903 | K40: 0.18 | L40: =J40-(K40+$B$149) -> -0.0050109692 | M40: =(1+M39)*(1+J40)/(1+K40+$B$149)-1 -> -0.073916136 | O40: =MAX(0,MIN(0.95,E40+$B$148))*(1-F40) -> 0.18238 | P40: =(1-O40)+O40/$B$6 -> 0.88275571 | Q40: =P40/P39-1 -> -0.019941253 | R40: =(1+C40+$B$146)*(1+D40+$B$147)*(1+Q40)-1 -> 0.18498903 | S40: =R40-(K40+$B$149) -> -0.0050109692 | T40: =(1+T39)*(1+R40)/(1+K40+$B$149)-1 -> -0.073916136
B41: 2027 | C41: 0.14 | D41: 0.16 | E41: 0.2 | F41: 0.181 | G41: =IF($B$9=1,MAX(0,MIN(0.95,E41+$B$148))*(1-F41),MAX(0,MIN(0.95,E41+$B$148))) -> 0.1638 | H41: =(1-G41)+G41/$B$6 -> 0.8947 | I41: =H41/H40-1 -> 0.013530681 | J41: =(1+C41+$B$146)*(1+D41+$B$147)*(1+I41)-1 -> 0.34029297 | K41: 0.12 | L41: =J41-(K41+$B$149) -> 0.21029297 | M41: =(1+M40)*(1+J41)/(1+K41+$B$149)-1 -> 0.098428049 | O41: =MAX(0,MIN(0.95,E41+$B$148))*(1-F41) -> 0.1638 | P41: =(1-O41)+O41/$B$6 -> 0.8947 | Q41: =P41/P40-1 -> 0.013530681 | R41: =(1+C41+$B$146)*(1+D41+$B$147)*(1+Q41)-1 -> 0.34029297 | S41: =R41-(K41+$B$149) -> 0.21029297 | T41: =(1+T40)*(1+R41)/(1+K41+$B$149)-1 -> 0.098428049
B42: 2028 | C42: 0.26 | D42: 0.16 | E42: 0.15 | F42: 0.185 | G42: =IF($B$9=1,MAX(0,MIN(0.95,E42+$B$148))*(1-F42),MAX(0,MIN(0.95,E42+$B$148))) -> 0.12225 | H42: =(1-G42)+G42/$B$6 -> 0.92141071 | I42: =H42/H41-1 -> 0.029854381 | J42: =(1+C42+$B$146)*(1+D42+$B$147)*(1+I42)-1 -> 0.50523516 | K42: -0.08 | L42: =J42-(K42+$B$149) -> 0.57523516 | M42: =(1+M41)*(1+J42)/(1+K42+$B$149)-1 -> 0.77784142 | O42: =MAX(0,MIN(0.95,E42+$B$148))*(1-F42) -> 0.12225 | P42: =(1-O42)+O42/$B$6 -> 0.92141071 | Q42: =P42/P41-1 -> 0.029854381 | R42: =(1+C42+$B$146)*(1+D42+$B$147)*(1+Q42)-1 -> 0.50523516 | S42: =R42-(K42+$B$149) -> 0.57523516 | T42: =(1+T41)*(1+R42)/(1+K42+$B$149)-1 -> 0.77784142
A43: S5 Collapse (probability set in console [K]): a technical breakthrough sharply cuts memory per unit of compute (KV-cache compression, more aggressive quantisation), or the external financing chain behind AI capex breaks; inventory repeats the 31 weeks of 2023.
A44: The 'A' in 2026A marks a half-actual year: with data through 2026-09-08 more than two thirds of the year is behind us and 1Q/2Q contract prices and shipments are fact — audit finding C, item 3, says a formal version should split it into realised plus remaining forecast. | Columns O–T are unaffected by the switch and always show the HBM basis-corrected result for side-by-side reading. | The grid stays on the v3.0 3.0× penalty on purpose; the v4.0 8-high relief is applied in block [M] and on sheet 06.
A46: [C] Summary 1 · ④ flow basis: supply−demand growth gap (supply bit growth − demand bit growth)
A47: Scenario | B47: Probability | C47: Cumulative prob. | D47: 2026 | E47: 2027 | F47: 2028 | G47: Year the gap turns positive
A48: S1 Extreme tightness | B48: =$B$151 -> 0.16 | C48: =B48 -> 0.16 | D48: =L20 -> -0.12501097 | E48: =L21 -> -0.1946184 | F48: =L22 -> -0.10386131 | G48: =IF(D48>0,"2026",IF(E48>0,"2027",IF(F48>0,"2028","not within 3 yrs"))) -> not within 3 yrs
A49: S2 Base case | B49: =$B$152 -> 0.4 | C49: =C48+B49 -> 0.56 | D49: =L25 -> -0.10501097 | E49: =L26 -> -0.0948101 | F49: =L27 -> 0.022756562 | G49: =IF(D49>0,"2026",IF(E49>0,"2027",IF(F49>0,"2028","not within 3 yrs"))) -> 2028
A50: S3 Relief | B50: =$B$153 -> 0.27 | C50: =C49+B50 -> 0.83 | D50: =L30 -> -0.085010969 | E50: =L31 -> 0.023154458 | F50: =L32 -> 0.18381095 | G50: =IF(D50>0,"2026",IF(E50>0,"2027",IF(F50>0,"2028","not within 3 yrs"))) -> 2027
A51: S4 Surplus | B51: =$B$154 -> 0.17 | C51: =C50+B51 -> 1 | D51: =L35 -> -0.065010969 | E51: =L36 -> 0.096080805 | F51: =L37 -> 0.29121466 | G51: =IF(D51>0,"2026",IF(E51>0,"2027",IF(F51>0,"2028","not within 3 yrs"))) -> 2027
A52: S5 Collapse | B52: =$B$155 -> 0 | C52: =C51+B52 -> 1 | D52: =L40 -> -0.0050109692 | E52: =L41 -> 0.21029297 | F52: =L42 -> 0.57523516 | G52: =IF(D52>0,"2026",IF(E52>0,"2027",IF(F52>0,"2028","not within 3 yrs"))) -> 2027
A53: Probability weighted (mean) | B53: =SUM(B48:B52) -> 1 | C53: must = 100% | D53: =SUMPRODUCT($B$48:$B$52,D48:D52) -> -0.096010969 | E53: =SUMPRODUCT($B$48:$B$52,E48:E52) -> -0.046477544 | F53: =SUMPRODUCT($B$48:$B$52,F48:F52) -> 0.091620263 | G53: =IF(D53>0,"2026",IF(E53>0,"2027",IF(F53>0,"2028","not within 3 yrs"))) -> 2028
A54: Probability median | B54: =SUM(B48:B52) -> 1 | C54: must = 100% | D54: =INDEX(D48:D52,IFERROR(MATCH(0.5,$C$48:$C$52,1)+1,1)) -> -0.10501097 | E54: =INDEX(E48:E52,IFERROR(MATCH(0.5,$C$48:$C$52,1)+1,1)) -> -0.0948101 | F54: =INDEX(F48:F52,IFERROR(MATCH(0.5,$C$48:$C$52,1)+1,1)) -> 0.022756562 | G54: =IF(D54>0,"2026",IF(E54>0,"2027",IF(F54>0,"2028","not within 3 yrs"))) -> 2028
A55: ★ How to read it: negative = supply shortage = upward pressure on price. This is the v1.0 basis; it measures how much the gap widens or narrows each year (the first derivative of the gap), not how big the gap is. A positive number in 2028 only means the gap has stopped widening and has started to be filled — it does not mean surplus. The median row sorts the scenarios from tight to loose and takes the one where cumulative probability passes 50%.
A57: [D] Summary 2 · ② stock basis: horizontal adequacy (this year's supply ÷ this year's unconstrained demand − 1)
A58: Scenario | B58: Probability | C58: Cumulative prob. | D58: 2025 start | E58: 2026 | F58: 2027 | G58: 2028 | H58: Filled within three years?
A59: S1 Extreme tightness | B59: =B48 -> 0.16 | C59: =B59 -> 0.16 | D59: =M19 -> -0.07 | E59: =M20 -> -0.15874825 | F59: =M21 -> -0.2818483 | G59: =M22 -> -0.33966859 | H59: =IF(F59>0,"filled in 2027",IF(G59>0,"filled in 2028","not filled in 3 yrs")) -> not filled in 3 yrs
A60: S2 Base case | B60: =B49 -> 0.4 | C60: =C59+B60 -> 0.56 | D60: =M24 -> -0.07 | E60: =M25 -> -0.14570558 | F60: =M26 -> -0.20948175 | G60: =M27 -> -0.19509017 | H60: =IF(F60>0,"filled in 2027",IF(G60>0,"filled in 2028","not filled in 3 yrs")) -> not filled in 3 yrs
A61: S3 Relief | B61: =B50 -> 0.27 | C61: =C60+B61 -> 0.83 | D61: =M29 -> -0.07 | E61: =M30 -> -0.13225213 | F61: =M31 -> -0.11564698 | G61: =M32 -> 0.020952832 | H61: =IF(F61>0,"filled in 2027",IF(G61>0,"filled in 2028","not filled in 3 yrs")) -> filled in 2028
A62: S4 Surplus | B62: =B51 -> 0.17 | C62: =C61+B62 -> 1 | D62: =M34 -> -0.07 | E62: =M35 -> -0.11836816 | F62: =M36 -> -0.047185054 | G62: =M37 -> 0.18997193 | H62: =IF(F62>0,"filled in 2027",IF(G62>0,"filled in 2028","not filled in 3 yrs")) -> filled in 2028
A63: S5 Collapse | B63: =B52 -> 0 | C63: =C62+B63 -> 1 | D63: =M39 -> -0.07 | E63: =M40 -> -0.073916136 | F63: =M41 -> 0.098428049 | G63: =M42 -> 0.77784142 | H63: =IF(F63>0,"filled in 2027",IF(G63>0,"filled in 2028","not filled in 3 yrs")) -> filled in 2027
A64: Probability weighted (mean) | D64: =SUMPRODUCT($B$59:$B$63,D59:D63) -> -0.07 | E64: =SUMPRODUCT($B$59:$B$63,E59:E63) -> -0.13951261 | F64: =SUMPRODUCT($B$59:$B$63,F59:F63) -> -0.16813457 | G64: =SUMPRODUCT($B$59:$B$63,G59:G63) -> -0.094430551 | H64: =IF(F64>0,"filled in 2027",IF(G64>0,"filled in 2028","not filled in 3 yrs")) -> not filled in 3 yrs
A65: Probability median | D65: =INDEX(D59:D63,IFERROR(MATCH(0.5,$C$59:$C$63,1)+1,1)) -> -0.07 | E65: =INDEX(E59:E63,IFERROR(MATCH(0.5,$C$59:$C$63,1)+1,1)) -> -0.14570558 | F65: =INDEX(F59:F63,IFERROR(MATCH(0.5,$C$59:$C$63,1)+1,1)) -> -0.20948175 | G65: =INDEX(G59:G63,IFERROR(MATCH(0.5,$C$59:$C$63,1)+1,1)) -> -0.19509017 | H65: =IF(F65>0,"filled in 2027",IF(G65>0,"filled in 2028","not filled in 3 yrs")) -> not filled in 3 yrs
A66: ★★ The distribution is heavily right-skewed and the mean is misleading. Rank the five scenarios from deepest to shallowest gap; cumulative probability crosses 50% inside S2 — so the median is 'the most likely case', while the weighted mean is pulled up hard by S5 (7% probability by default). Read the median row when deciding, not the weighted row.
A67: ★ Audit note: the recursion in this block is mathematically identical to 'this year's supply ÷ this year's demand − 1' — a flow ratio, not a stock accumulation. It deteriorates year after year because the ratio of two exponential curves falls monotonically whenever supply growth stays below demand growth. The correct reading is 'this year's supply meets only X% of unconstrained demand', not 'X% has been owed cumulatively'. See block [H].
A69: [E] S2 base case: three-factor decomposition of supply bit growth (exact multiplicative split; the three terms sum to supply growth)
A70: Year | B70: Wafer capacity contribution | C70: Node migration contribution | D70: HBM drag | E70: Total = supply bit growth | F70: Cross-check: external forecasts
A71: 2026 | B71: =C25+$B$146 -> 0.07 | C71: =(1+C25+$B$146)*(D25+$B$147) -> 0.1391 | D71: =(1+C25+$B$146)*(1+D25+$B$147)*I25 -> -0.024110969 | E71: =B71+C71+D71 -> 0.18498903 | F71: IDC +16% / Micron 'low-to-mid 20s' — the model sits between the two
A72: 2027 | B72: =C26+$B$146 -> 0.1 | C72: =(1+C26+$B$146)*(D26+$B$147) -> 0.132 | D72: =(1+C26+$B$146)*(1+D26+$B$147)*I26 -> -0.0568101 | E72: =B72+C72+D72 -> 0.1751899 | F72: TrendForce: new capacity only ramps in 2H27, real contribution arrives in 2028
A73: 2028 | B73: =C27+$B$146 -> 0.16 | C73: =(1+C27+$B$146)*(D27+$B$147) -> 0.1276 | D73: =(1+C27+$B$146)*(1+D27+$B$147)*I27 -> -0.014843438 | E73: =B73+C73+D73 -> 0.27275656 | F73: 46% of the three-year capacity addition lands in this single year
A74: How to read it: the three terms are an exact multiplicative split (wafer contribution = C; node contribution = (1+C)×D; HBM contribution = (1+C)×(1+D)×I) and always sum to supply growth. The node contribution therefore comes out slightly higher than the node uplift you typed in, because it acts on an already-enlarged wafer base. That is compounding, not an error.
A76: [F] Single-variable sensitivity for 2027 (on the S2 base case, flow-basis growth gap)
A77: Variable | B77: Current value | C77: −4pp | D77: −2pp | E77: Base | F77: +2pp | G77: +4pp | H77: Effect per 1pp | I77: Move needed to turn positive on its own | J77: Feasibility
A78: Wafer capacity growth | B78: =C26+$B$146 -> 0.1 | C78: =(1+C26+$B$146+(-0.04))*(1+D26+$B$147)*(1+I26)-1-(K26+$B$149) -> -0.13754428 | D78: =(1+C26+$B$146+(-0.02))*(1+D26+$B$147)*(1+I26)-1-(K26+$B$149) -> -0.11617719 | E78: =(1+C26+$B$146+(0))*(1+D26+$B$147)*(1+I26)-1-(K26+$B$149) -> -0.0948101 | F78: =(1+C26+$B$146+(0.02))*(1+D26+$B$147)*(1+I26)-1-(K26+$B$149) -> -0.07344301 | G78: =(1+C26+$B$146+(0.04))*(1+D26+$B$147)*(1+I26)-1-(K26+$B$149) -> -0.052075921 | H78: =(G78-C78)/8*100 -> 1.0683545 | I78: =IF(H78=0,"n/a",-E78/H78*100) -> 8.8744048 | J78: +10.0pp → 20%: physically impossible, the fabs cannot be built. Samsung P5 mass-produces in 2H28, Micron ID1 has first wafers mid-2027, the New York fab only broke ground in Jan 2026.
A79: Node bit uplift | B79: =D26+$B$147 -> 0.12 | C79: =(1+C26+$B$146)*(1+D26+$B$147+(-0.04))*(1+I26)-1-(K26+$B$149) -> -0.13678117 | D79: =(1+C26+$B$146)*(1+D26+$B$147+(-0.02))*(1+I26)-1-(K26+$B$149) -> -0.11579563 | E79: =(1+C26+$B$146)*(1+D26+$B$147+(0))*(1+I26)-1-(K26+$B$149) -> -0.0948101 | F79: =(1+C26+$B$146)*(1+D26+$B$147+(0.02))*(1+I26)-1-(K26+$B$149) -> -0.073824566 | G79: =(1+C26+$B$146)*(1+D26+$B$147+(0.04))*(1+I26)-1-(K26+$B$149) -> -0.052839032 | H79: =(G79-C79)/8*100 -> 1.0492767 | I79: =IF(H79=0,"n/a",-E79/H79*100) -> 9.0357577 | J79: +10.2pp: equally impossible. DRAM density has risen only about 2× in a decade — this is a physics wall.
A80: HBM wafer share | B80: =G26 -> 0.2457 | C80: =(1+C26+$B$146)*(1+D26+$B$147)*(((1-(G26+(-0.04)))+(G26+(-0.04))/$B$6)/H25)-1-(K26+$B$149) -> -0.058922481 | D80: =(1+C26+$B$146)*(1+D26+$B$147)*(((1-(G26+(-0.02)))+(G26+(-0.02))/$B$6)/H25)-1-(K26+$B$149) -> -0.07686629 | E80: =(1+C26+$B$146)*(1+D26+$B$147)*(((1-(G26+(0)))+(G26+(0))/$B$6)/H25)-1-(K26+$B$149) -> -0.0948101 | F80: =(1+C26+$B$146)*(1+D26+$B$147)*(((1-(G26+(0.02)))+(G26+(0.02))/$B$6)/H25)-1-(K26+$B$149) -> -0.11275391 | G80: =(1+C26+$B$146)*(1+D26+$B$147)*(((1-(G26+(0.04)))+(G26+(0.04))/$B$6)/H25)-1-(K26+$B$149) -> -0.13069772 | H80: =(G80-C80)/8*100 -> -0.89719045 | I80: =IF(H80=0,"n/a",-E80/H80*100) -> -10.567444 | J80: Needs to fall to roughly 19%: possible in direction but far too large in size. Even if the HBM economics reversal holds, a fall back to 26% is already an aggressive assumption. ★ v4.0 makes this less likely, not more: 8-high lowers the wafer penalty but NVIDIA's stated reason is availability, not economics.
A81: Demand growth | B81: =K26+$B$149 -> 0.27 | C81: =J26-(K26+$B$149+(-0.04)) -> -0.0548101 | D81: =J26-(K26+$B$149+(-0.02)) -> -0.0748101 | E81: =J26-(K26+$B$149+(0)) -> -0.0948101 | F81: =J26-(K26+$B$149+(0.02)) -> -0.1148101 | G81: =J26-(K26+$B$149+(0.04)) -> -0.1348101 | H81: =(G81-C81)/8*100 -> -1 | I81: =IF(H81=0,"n/a",-E81/H81*100) -> -9.48101 | J81: ★ Needs to fall to roughly 15.5%: this is the only realistic path. Which is why hyperscaler capex guidance carries more information than any fab expansion announcement.
A82: ★ The key result of this table: the four variables have almost identical unit elasticity (about 1pp for 1pp), but their feasible ranges are completely different. All three supply-side routes are physically blocked — whether 2027 moves from shortage to surplus depends almost entirely on the demand side.
A84: [G] Audit correction 1 · HBM wafer-share basis mismatch (A, item 4): the five scenarios after correction
A85: This block is unaffected by the switch and always shows the corrected result, for direct comparison with blocks [C] and [D] above. Correction logic: TrendForce's 18/22/30% is a top-three-supplier basis, so the global basis = top-three share × (1 − CXMT wafer share). The figures are taken from columns O–T of the main grid.
A86: Scenario | B86: Probability | C86: Cumulative prob. | D86: Corrected gap 2026 | E86: Corrected gap 2027 | F86: Corrected gap 2028 | G86: Corrected horiz. gap 2026 | H86: Corrected horiz. gap 2027 | I86: Corrected horiz. gap 2028
A87: S1 Extreme tightness | B87: =B48 -> 0.16 | C87: =B87 -> 0.16 | D87: =S20 -> -0.12501097 | E87: =S21 -> -0.1946184 | F87: =S22 -> -0.10386131 | G87: =T20 -> -0.15874825 | H87: =T21 -> -0.2818483 | I87: =T22 -> -0.33966859
A88: S2 Base case | B88: =B49 -> 0.4 | C88: =C87+B88 -> 0.56 | D88: =S25 -> -0.10501097 | E88: =S26 -> -0.0948101 | F88: =S27 -> 0.022756562 | G88: =T25 -> -0.14570558 | H88: =T26 -> -0.20948175 | I88: =T27 -> -0.19509017
A89: S3 Relief | B89: =B50 -> 0.27 | C89: =C88+B89 -> 0.83 | D89: =S30 -> -0.085010969 | E89: =S31 -> 0.023154458 | F89: =S32 -> 0.18381095 | G89: =T30 -> -0.13225213 | H89: =T31 -> -0.11564698 | I89: =T32 -> 0.020952832
A90: S4 Surplus | B90: =B51 -> 0.17 | C90: =C89+B90 -> 1 | D90: =S35 -> -0.065010969 | E90: =S36 -> 0.096080805 | F90: =S37 -> 0.29121466 | G90: =T35 -> -0.11836816 | H90: =T36 -> -0.047185054 | I90: =T37 -> 0.18997193
A91: S5 Collapse | B91: =B52 -> 0 | C91: =C90+B91 -> 1 | D91: =S40 -> -0.0050109692 | E91: =S41 -> 0.21029297 | F91: =S42 -> 0.57523516 | G91: =T40 -> -0.073916136 | H91: =T41 -> 0.098428049 | I91: =T42 -> 0.77784142
A92: Corrected · probability weighted | D92: =SUMPRODUCT($B$87:$B$91,D87:D91) -> -0.096010969 | E92: =SUMPRODUCT($B$87:$B$91,E87:E91) -> -0.046477544 | F92: =SUMPRODUCT($B$87:$B$91,F87:F91) -> 0.091620263 | G92: =SUMPRODUCT($B$87:$B$91,G87:G91) -> -0.13951261 | H92: =SUMPRODUCT($B$87:$B$91,H87:H91) -> -0.16813457 | I92: =SUMPRODUCT($B$87:$B$91,I87:I91) -> -0.094430551
A93: Report basis · probability weighted | D93: =D53 -> -0.096010969 | E93: =E53 -> -0.046477544 | F93: =F53 -> 0.091620263 | G93: =E64 -> -0.13951261 | H93: =F64 -> -0.16813457 | I93: =G64 -> -0.094430551
A94: Difference from the correction | D94: =(D92-D93)*100 -> 0 | E94: =(E92-E93)*100 -> 0 | F94: =(F92-F93)*100 -> 0 | G94: =(G92-G93)*100 -> 0 | H94: =(H92-H93)*100 -> 0 | I94: =(I92-I93)*100 -> 0
A95: ★ Conclusion: after correction DRAM supply is revised up by roughly 1.0pp (2026) and 1.5pp (2027), and on the stock basis the effect compounds year by year — the 2028 probability-weighted figure flips from 'just breaking even' to a small surplus. This is not a tweak; it changes the qualitative 2028 conclusion. A formal version should default the console switch to 1 and state the basis in the text.
A97: [H] Audit correction 2 · flow ratio vs true stock accumulation (A, item 2): how far apart the two conventions are
A98: The v2.0 recursion (1+gap_t−1)×(1+supply)÷(1+demand)−1 is mathematically identical to 'this year's supply ÷ this year's demand − 1' — a flow ratio. A genuine stock accumulation would be additive: arrears_t = arrears_t−1 ÷ (1 + demand growth_t) + this year's unmet volume. The table below computes both side by side.
A99: Scenario | B99: Probability | C99: Cumulative prob. | D99: Unmet this year 2026 | E99: Unmet this year 2027 | F99: Unmet this year 2028 | G99: Cumulative arrears 2026 | H99: Cumulative arrears 2027 | I99: Cumulative arrears 2028
A100: S1 Extreme tightness | B100: =B48 -> 0.16 | C100: =B100 -> 0.16 | D100: =(1+M20)/(1+$B$14)-1 -> -0.095428221 | E100: =(1+M21)/(1+$B$14)-1 -> -0.22779387 | F100: =(1+M22)/(1+$B$14)-1 -> -0.28996623 | G100: =$B$14/(1+K20+$B$149)+D100 -> -0.14886334 | H100: =G100/(1+K21+$B$149)+E100 -> -0.33972119 | I100: =H100/(1+K22+$B$149)+F100 -> -0.55331599
A101: S2 Base case | B101: =B49 -> 0.4 | C101: =C100+B101 -> 0.56 | D101: =(1+M25)/(1+$B$14)-1 -> -0.081403852 | E101: =(1+M26)/(1+$B$14)-1 -> -0.14998038 | F101: =(1+M27)/(1+$B$14)-1 -> -0.13450556 | G101: =$B$14/(1+K25+$B$149)+D101 -> -0.13566742 | H101: =G101/(1+K26+$B$149)+E101 -> -0.25680512 | I101: =H101/(1+K27+$B$149)+F101 -> -0.33994966
A102: S3 Relief | B102: =B50 -> 0.27 | C102: =C101+B102 -> 0.83 | D102: =(1+M30)/(1+$B$14)-1 -> -0.066937771 | E102: =(1+M31)/(1+$B$14)-1 -> -0.049082771 | F102: =(1+M32)/(1+$B$14)-1 -> 0.097798744 | G102: =$B$14/(1+K30+$B$149)+D102 -> -0.12205588 | H102: =G102/(1+K31+$B$149)+E102 -> -0.1499554 | I102: =H102/(1+K32+$B$149)+F102 -> -0.028214198
A103: S4 Surplus | B103: =B51 -> 0.17 | C103: =C102+B103 -> 1 | D103: =(1+M35)/(1+$B$14)-1 -> -0.052008775 | E103: =(1+M36)/(1+$B$14)-1 -> 0.0245322 | F103: =(1+M37)/(1+$B$14)-1 -> 0.27953971 | G103: =$B$14/(1+K35+$B$149)+D103 -> -0.10800878 | H103: =G103/(1+K36+$B$149)+E103 -> -0.066231477 | I103: =H103/(1+K37+$B$149)+F103 -> 0.22293161
A104: S5 Collapse | B104: =B52 -> 0 | C104: =C103+B104 -> 1 | D104: =(1+M40)/(1+$B$14)-1 -> -0.0042108985 | E104: =(1+M41)/(1+$B$14)-1 -> 0.18110543 | F104: =(1+M42)/(1+$B$14)-1 -> 0.91165744 | G104: =$B$14/(1+K40+$B$149)+D104 -> -0.063034428 | H104: =G104/(1+K41+$B$149)+E104 -> 0.12532275 | I104: =H104/(1+K42+$B$149)+F104 -> 1.0464131
A105: Additive accumulation · weighted | G105: =SUMPRODUCT($B$100:$B$104,G100:G104) -> -0.12940168 | H105: =SUMPRODUCT($B$100:$B$104,H100:H104) -> -0.20882475 | I105: =SUMPRODUCT($B$100:$B$104,I100:I104) -> -0.19422988
A106: Multiplicative recursion · weighted (in use) | G106: =E64 -> -0.13951261 | H106: =F64 -> -0.16813457 | I106: =G64 -> -0.094430551
A107: Gap between the two conventions | G107: =(G105-G106)*100 -> 1.0110933 | H107: =(H105-H106)*100 -> -4.0690175 | I107: =(I105-I106)*100 -> -9.979933
A108: ★ How to read this table: additive accumulation gives much deeper numbers than the multiplicative recursion because it assumes the bits you failed to buy queue up to be repaid. But consumer electronics demand priced out does not queue — once handsets and notebooks are de-specced those bits are gone permanently. So additive accumulation is an upper bound, the multiplicative recursion (= this year's flow ratio) is a lower bound, and the true 'stock arrears' sits between them and closer to the lower bound. The key point is to stop calling the multiplicative result 'cumulative arrears' — it is not.
A110: [I] Audit correction 3 · restock demand double-counted against the start point (A, item 3): three conventions compared (S2 base case)
...

Sheet 02-NAND-Model
A1: 02 · NAND supply–demand model
A2: Four scenarios × three years | the key difference from DRAM: layer stacking and QLC are two bit levers that need no new wafer fab | ▼ every parameter is driven by the [G] PARAMETER CONSOLE at the bottom | amber rows are v4.0 additions
A4: [A] Main model: four scenarios × three years
A5: Scenario | B5: Year | C5: Wafer capacity growth | D5: Layer stacking bit uplift | E5: QLC mix bit uplift | F5: Demand growth (unconstrained) | G5: Supply bit growth | H5: ④ Growth gap (flow basis) | I5: ② Horizontal adequacy (stock basis) | J5: Cross-check: same-year DRAM supply growth | K5: Supply elasticity multiple
A6: N1 Stays tight | B6: 2025 (start) | C6: — | D6: — | E6: — | F6: — | G6: — | H6: — | I6: =$B$76 -> -0.025 | J6: — | K6: —
B7: 2026A | C7: 0 | D7: 0.15 | E7: 0.03 | F7: 0.22 | G7: =(1+C7+$B$78)*(1+D7+$B$79)*(1+E7+$B$80)*(1+$B$77)-1 -> 0.172655 | H7: =G7-(F7+$B$81) -> -0.067345 | I7: =(1+I6)*(1+G7)/(1+F7+$B$81)-1 -> -0.077952722 | J7: ='01-DRAM-Model'!J25 -> 0.18498903 | K7: =IF(J7<=0,"n/a",G7/J7) -> 0.93332561
B8: 2027 | C8: 0.02 | D8: 0.16 | E8: 0.04 | F8: 0.24 | G8: =(1+C8+$B$78)*(1+D8+$B$79)*(1+E8+$B$80)*(1+$B$77)-1 -> 0.218464 | H8: =G8-(F8+$B$81) -> -0.041536 | I8: =(1+I7)*(1+G8)/(1+F8+$B$81)-1 -> -0.10834808 | J8: ='01-DRAM-Model'!J26 -> 0.1751899 | K8: =IF(J8<=0,"n/a",G8/J8) -> 1.2470125
B9: 2028 | C9: 0.05 | D9: 0.15 | E9: 0.04 | F9: 0.24 | G9: =(1+C9+$B$78)*(1+D9+$B$79)*(1+E9+$B$80)*(1+$B$77)-1 -> 0.24384 | H9: =G9-(F9+$B$81) -> -0.01616 | I9: =(1+I8)*(1+G9)/(1+F9+$B$81)-1 -> -0.11978387 | J9: ='01-DRAM-Model'!J27 -> 0.27275656 | K9: =IF(J9<=0,"n/a",G9/J9) -> 0.89398399
A10: N1 Stays tight (probability set in console [G]): enterprise SSD demand keeps beating expectations, AI data staging and model checkpointing demand explodes; layer progression runs behind plan.
A11: N2 Base case | B11: 2025 (start) | C11: — | D11: — | E11: — | F11: — | G11: — | H11: — | I11: =$B$76 -> -0.025 | J11: — | K11: —
B12: 2026A | C12: 0 | D12: 0.15 | E12: 0.03 | F12: 0.22 | G12: =(1+C12+$B$78)*(1+D12+$B$79)*(1+E12+$B$80)*(1+$B$77)-1 -> 0.172655 | H12: =G12-(F12+$B$81) -> -0.067345 | I12: =(1+I11)*(1+G12)/(1+F12+$B$81)-1 -> -0.077952722 | J12: ='01-DRAM-Model'!J25 -> 0.18498903 | K12: =IF(J12<=0,"n/a",G12/J12) -> 0.93332561
B13: 2027 | C13: 0.04 | D13: 0.18 | E13: 0.05 | F13: 0.2 | G13: =(1+C13+$B$78)*(1+D13+$B$79)*(1+E13+$B$80)*(1+$B$77)-1 -> 0.27617 | H13: =G13-(F13+$B$81) -> 0.05617 | I13: =(1+I12)*(1+G13)/(1+F13+$B$81)-1 -> -0.035500758 | J13: ='01-DRAM-Model'!J26 -> 0.1751899 | K13: =IF(J13<=0,"n/a",G13/J13) -> 1.5764037
B14: 2028 | C14: 0.08 | D14: 0.17 | E14: 0.05 | F14: 0.18 | G14: =(1+C14+$B$78)*(1+D14+$B$79)*(1+E14+$B$80)*(1+$B$77)-1 -> 0.314495 | H14: =G14-(F14+$B$81) -> 0.114495 | I14: =(1+I13)*(1+G14)/(1+F14+$B$81)-1 -> 0.056524526 | J14: ='01-DRAM-Model'!J27 -> 0.27275656 | K14: =IF(J14<=0,"n/a",G14/J14) -> 1.1530245
A15: N2 Base case (probability set in console [G]): aligned to TrendForce — 2026 gap −4~−5%, turns positive in 2H27 and starts pressing prices down. SK hynix 321-layer at ~50% of its Korean capacity, Samsung 400+ layer in production, Kioxia BiCS9. ⚠ v4.0: KB Securities contradicts this outright — see block [F].
A16: N3 Turns to surplus | B16: 2025 (start) | C16: — | D16: — | E16: — | F16: — | G16: — | H16: — | I16: =$B$76 -> -0.025 | J16: — | K16: —
B17: 2026A | C17: 0 | D17: 0.15 | E17: 0.03 | F17: 0.2 | G17: =(1+C17+$B$78)*(1+D17+$B$79)*(1+E17+$B$80)*(1+$B$77)-1 -> 0.172655 | H17: =G17-(F17+$B$81) -> -0.047345 | I17: =(1+I16)*(1+G17)/(1+F17+$B$81)-1 -> -0.062837193 | J17: ='01-DRAM-Model'!J25 -> 0.18498903 | K17: =IF(J17<=0,"n/a",G17/J17) -> 0.93332561
B18: 2027 | C18: 0.06 | D18: 0.21 | E18: 0.07 | F18: 0.16 | G18: =(1+C18+$B$78)*(1+D18+$B$79)*(1+E18+$B$80)*(1+$B$77)-1 -> 0.359435 | H18: =G18-(F18+$B$81) -> 0.179435 | I18: =(1+I17)*(1+G18)/(1+F18+$B$81)-1 -> 0.07967112 | J18: ='01-DRAM-Model'!J26 -> 0.1751899 | K18: =IF(J18<=0,"n/a",G18/J18) -> 2.0516879
B19: 2028 | C19: 0.12 | D19: 0.2 | E19: 0.06 | F19: 0.12 | G19: =(1+C19+$B$78)*(1+D19+$B$79)*(1+E19+$B$80)*(1+$B$77)-1 -> 0.41192 | H19: =G19-(F19+$B$81) -> 0.27192 | I19: =(1+I18)*(1+G19)/(1+F19+$B$81)-1 -> 0.33720109 | J19: ='01-DRAM-Model'!J27 -> 0.27275656 | K19: =IF(J19<=0,"n/a",G19/J19) -> 1.5102111
A20: N3 Turns to surplus (probability set in console [G]): Kioxia/Sandisk's +41% capex converts into capacity; YMTC's third Wuhan fab ramps; the PC replacement cycle ends while mobile demand stays weak; enterprise SSD competition intensifies and caps prices.
A21: N4 Large surplus | B21: 2025 (start) | C21: — | D21: — | E21: — | F21: — | G21: — | H21: — | I21: =$B$76 -> -0.025 | J21: — | K21: —
B22: 2026A | C22: 0 | D22: 0.15 | E22: 0.03 | F22: 0.18 | G22: =(1+C22+$B$78)*(1+D22+$B$79)*(1+E22+$B$80)*(1+$B$77)-1 -> 0.172655 | H22: =G22-(F22+$B$81) -> -0.027345 | I22: =(1+I21)*(1+G22)/(1+F22+$B$81)-1 -> -0.047217813 | J22: ='01-DRAM-Model'!J25 -> 0.18498903 | K22: =IF(J22<=0,"n/a",G22/J22) -> 0.93332561
B23: 2027 | C23: 0.08 | D23: 0.24 | E23: 0.08 | F23: 0.12 | G23: =(1+C23+$B$78)*(1+D23+$B$79)*(1+E23+$B$80)*(1+$B$77)-1 -> 0.432944 | H23: =G23-(F23+$B$81) -> 0.292944 | I23: =(1+I22)*(1+G23)/(1+F23+$B$81)-1 -> 0.19761712 | J23: ='01-DRAM-Model'!J26 -> 0.1751899 | K23: =IF(J23<=0,"n/a",G23/J23) -> 2.471284
B24: 2028 | C24: 0.16 | D24: 0.22 | E24: 0.07 | F24: 0.08 | G24: =(1+C24+$B$78)*(1+D24+$B$79)*(1+E24+$B$80)*(1+$B$77)-1 -> 0.50121 | H24: =G24-(F24+$B$81) -> 0.40121 | I24: =(1+I23)*(1+G24)/(1+F24+$B$81)-1 -> 0.63443164 | J24: ='01-DRAM-Model'!J27 -> 0.27275656 | K24: =IF(J24<=0,"n/a",G24/J24) -> 1.8375727
A25: N4 Large surplus (probability set in console [G]): layers and QLC both advance faster than expected while consumer electronics demand stays priced out. This is the risk specific to NAND — supply can keep growing quickly while demand weakens, because adding output needs no new fab.
A26: ★ The two right-hand columns are new in this workbook: NAND supply growth ÷ same-year DRAM supply growth. They turn the qualitative sentence 'the supply elasticities differ by an order of magnitude' into a number you can track. Note that wafer growth is 0% in 2026 across all four scenarios — NAND's bit growth that year comes entirely from layers and QLC, with not one new wafer.
A28: [B] Summary 1 · ④ flow basis: supply−demand growth gap
A29: Scenario | B29: Probability | C29: Cumulative prob. | D29: 2026 | E29: 2027 | F29: 2028 | G29: Year the gap turns positive
A30: N1 Stays tight | B30: =$B$83 -> 0.25 | C30: =B30 -> 0.25 | D30: =H7 -> -0.067345 | E30: =H8 -> -0.041536 | F30: =H9 -> -0.01616 | G30: =IF(D30>0,"2026",IF(E30>0,"2027",IF(F30>0,"2028","not within 3 yrs"))) -> not within 3 yrs
A31: N2 Base case | B31: =$B$84 -> 0.46 | C31: =C30+B31 -> 0.71 | D31: =H12 -> -0.067345 | E31: =H13 -> 0.05617 | F31: =H14 -> 0.114495 | G31: =IF(D31>0,"2026",IF(E31>0,"2027",IF(F31>0,"2028","not within 3 yrs"))) -> 2027
A32: N3 Turns to surplus | B32: =$B$85 -> 0.29 | C32: =C31+B32 -> 1 | D32: =H17 -> -0.047345 | E32: =H18 -> 0.179435 | F32: =H19 -> 0.27192 | G32: =IF(D32>0,"2026",IF(E32>0,"2027",IF(F32>0,"2028","not within 3 yrs"))) -> 2027
A33: N4 Large surplus | B33: =$B$86 -> 0 | C33: =C32+B33 -> 1 | D33: =H22 -> -0.027345 | E33: =H23 -> 0.292944 | F33: =H24 -> 0.40121 | G33: =IF(D33>0,"2026",IF(E33>0,"2027",IF(F33>0,"2028","not within 3 yrs"))) -> 2027
A34: Probability weighted (mean) | B34: =SUM(B30:B33) -> 1 | C34: must = 100% | D34: =SUMPRODUCT($B$30:$B$33,D30:D33) -> -0.061545 | E34: =SUMPRODUCT($B$30:$B$33,E30:E33) -> 0.06749035 | F34: =SUMPRODUCT($B$30:$B$33,F30:F33) -> 0.1274845 | G34: =IF(D34>0,"2026",IF(E34>0,"2027",IF(F34>0,"2028","not within 3 yrs"))) -> 2027
A35: Probability median | B35: =SUM(B30:B33) -> 1 | C35: must = 100% | D35: =INDEX(D30:D33,IFERROR(MATCH(0.5,$C$30:$C$33,1)+1,1)) -> -0.067345 | E35: =INDEX(E30:E33,IFERROR(MATCH(0.5,$C$30:$C$33,1)+1,1)) -> 0.05617 | F35: =INDEX(F30:F33,IFERROR(MATCH(0.5,$C$30:$C$33,1)+1,1)) -> 0.114495 | G35: =IF(D35>0,"2026",IF(E35>0,"2027",IF(F35>0,"2028","not within 3 yrs"))) -> 2027
A37: [C] Summary 2 · ② stock basis: horizontal adequacy
A38: Scenario | B38: Probability | C38: Cumulative prob. | D38: 2025 start | E38: 2026 | F38: 2027 | G38: 2028 | H38: When the gap is filled
A39: N1 Stays tight | B39: =B30 -> 0.25 | C39: =B39 -> 0.25 | D39: =I6 -> -0.025 | E39: =I7 -> -0.077952722 | F39: =I8 -> -0.10834808 | G39: =I9 -> -0.11978387 | H39: =IF(F39>0,"filled in 2027",IF(G39>0,"filled in 2028","not filled in 3 yrs")) -> not filled in 3 yrs
A40: N2 Base case | B40: =B31 -> 0.46 | C40: =C39+B40 -> 0.71 | D40: =I11 -> -0.025 | E40: =I12 -> -0.077952722 | F40: =I13 -> -0.035500758 | G40: =I14 -> 0.056524526 | H40: =IF(F40>0,"filled in 2027",IF(G40>0,"filled in 2028","not filled in 3 yrs")) -> filled in 2028
A41: N3 Turns to surplus | B41: =B32 -> 0.29 | C41: =C40+B41 -> 1 | D41: =I16 -> -0.025 | E41: =I17 -> -0.062837193 | F41: =I18 -> 0.07967112 | G41: =I19 -> 0.33720109 | H41: =IF(F41>0,"filled in 2027",IF(G41>0,"filled in 2028","not filled in 3 yrs")) -> filled in 2027
A42: N4 Large surplus | B42: =B33 -> 0 | C42: =C41+B42 -> 1 | D42: =I21 -> -0.025 | E42: =I22 -> -0.047217813 | F42: =I23 -> 0.19761712 | G42: =I24 -> 0.63443164 | H42: =IF(F42>0,"filled in 2027",IF(G42>0,"filled in 2028","not filled in 3 yrs")) -> filled in 2027
A43: Probability weighted (mean) | D43: =SUMPRODUCT($B$39:$B$42,D39:D42) -> -0.025 | E43: =SUMPRODUCT($B$39:$B$42,E39:E42) -> -0.073569218 | F43: =SUMPRODUCT($B$39:$B$42,F39:F42) -> -0.020312745 | G43: =SUMPRODUCT($B$39:$B$42,G39:G42) -> 0.093843631 | H43: =IF(F43>0,"filled in 2027",IF(G43>0,"filled in 2028","not filled in 3 yrs")) -> filled in 2028
A44: Probability median | D44: =INDEX(D39:D42,IFERROR(MATCH(0.5,$C$39:$C$42,1)+1,1)) -> -0.025 | E44: =INDEX(E39:E42,IFERROR(MATCH(0.5,$C$39:$C$42,1)+1,1)) -> -0.077952722 | F44: =INDEX(F39:F42,IFERROR(MATCH(0.5,$C$39:$C$42,1)+1,1)) -> -0.035500758 | G44: =INDEX(G39:G42,IFERROR(MATCH(0.5,$C$39:$C$42,1)+1,1)) -> 0.056524526 | H44: =IF(F44>0,"filled in 2027",IF(G44>0,"filled in 2028","not filled in 3 yrs")) -> filled in 2028
A45: ★★ Symmetric treatment added by this workbook: v2.0 warned only on the DRAM side that the mean is dragged up by extreme scenarios and the median should be read instead. The NAND skew is worse (N4's 2028 at +105% carries only 12% probability yet pulls the weighted mean from +20.9% to +35.0%). Use the median row.
A47: [D] DRAM × NAND divergence: the most important conclusion in this model
A48: Year | B48: DRAM growth gap | C48: NAND growth gap | D48: Flow-basis divergence | E48: DRAM horizontal gap | F48: NAND horizontal gap | G48: Stock-basis divergence | H48: DRAM median | I48: NAND median | J48: Median-basis divergence | K48: Robustness
A49: 2026 | B49: ='01-DRAM-Model'!D53 -> -0.096010969 | C49: =D34 -> -0.061545 | D49: =(C49-B49)*100 -> 3.4465969 | E49: ='01-DRAM-Model'!E64 -> -0.13951261 | F49: =E43 -> -0.073569218 | G49: =(F49-E49)*100 -> 6.5943396 | H49: ='01-DRAM-Model'!E65 -> -0.14570558 | I49: =E44 -> -0.077952722 | J49: =(I49-H49)*100 -> 6.7752861 | K49: Both short in the same direction, DRAM tighter
A50: 2027 | B50: ='01-DRAM-Model'!E53 -> -0.046477544 | C50: =E34 -> 0.06749035 | D50: =(C50-B50)*100 -> 11.396789 | E50: ='01-DRAM-Model'!F64 -> -0.16813457 | F50: =F43 -> -0.020312745 | G50: =(F50-E50)*100 -> 14.782183 | H50: ='01-DRAM-Model'!F65 -> -0.20948175 | I50: =F44 -> -0.035500758 | J50: =(I50-H50)*100 -> 17.3981 | K50: ★ The decisive year for the divergence
A51: 2028 | B51: ='01-DRAM-Model'!F53 -> 0.091620263 | C51: =F34 -> 0.1274845 | D51: =(C51-B51)*100 -> 3.5864237 | E51: ='01-DRAM-Model'!G64 -> -0.094430551 | F51: =G43 -> 0.093843631 | G51: =(F51-E51)*100 -> 18.827418 | H51: ='01-DRAM-Model'!G65 -> -0.19509017 | I51: =G44 -> 0.056524526 | J51: =(I51-H51)*100 -> 25.16147 | K51: The divergence widens further
A52: Why they diverge: the cause is not on the demand side — the demand drivers overlap heavily (an AI server needs DRAM, HBM and enterprise SSD at the same time). The cause is the structure of the supply formula. NAND can multiply bits 2.29× through layers (232 → 400+ = +72%) and QLC (+33%) without laying a single brick; DRAM density has risen only 2× in a decade, wafer capacity takes 2–3 years to build, and HBM subtracts another 3–6 points every year.
A53: ★ Robustness: on the flow, stock and median bases alike the 2027 divergence exceeds 25pp (it is widest on the median basis). So 'pure NAND exposure (Sandisk, Kioxia, Western Digital) and DRAM exposure (Samsung, SK hynix, Micron) should be priced separately in 2027' does not depend on the few low-probability tail scenarios — but it does depend on the NAND supply elasticity assumption, which is the loosest link in the model (see the yield term in the console). ⚠ v4.0 adds a second challenge to this conclusion from the demand side: see block [F].
A55: [E] N2 base case: three-factor decomposition of supply bit growth
A56: Year | B56: Wafer capacity contribution | C56: Layer stacking contribution | D56: QLC contribution | E56: Total = supply bit growth | F56: Same-year DRAM supply growth | G56: Supply elasticity multiple
A57: 2026 | B57: =C12+$B$78 -> -0.01 | C57: =(1+C12+$B$78)*(D12+$B$79) -> 0.1485 | D57: =(1+C12+$B$78)*(1+D12+$B$79)*(E12+$B$80) -> 0.034155 | E57: =B57+C57+D57 -> 0.172655 | F57: ='01-DRAM-Model'!J25 -> 0.18498903 | G57: =IF(F57<=0,"n/a",E57/F57) -> 0.93332561
A58: 2027 | B58: =C13+$B$78 -> 0.03 | C58: =(1+C13+$B$78)*(D13+$B$79) -> 0.1854 | D58: =(1+C13+$B$78)*(1+D13+$B$79)*(E13+$B$80) -> 0.06077 | E58: =B58+C58+D58 -> 0.27617 | F58: ='01-DRAM-Model'!J26 -> 0.1751899 | G58: =IF(F58<=0,"n/a",E58/F58) -> 1.5764037
A59: 2028 | B59: =C14+$B$78 -> 0.07 | C59: =(1+C14+$B$78)*(D14+$B$79) -> 0.1819 | D59: =(1+C14+$B$78)*(1+D14+$B$79)*(E14+$B$80) -> 0.062595 | E59: =B59+C59+D59 -> 0.314495 | F59: ='01-DRAM-Model'!J27 -> 0.27275656 | G59: =IF(F59<=0,"n/a",E59/F59) -> 1.1530245
A60: Note: the total differs very slightly from the supply growth in the main grid — the decomposition excludes the yield term while the grid includes it. Pull the console yield term back to 0 and the two match exactly.
A62: [F] v4.0 · NAND: KB Securities contradicts the base case head on
A63: KB Securities (2026-09-07) states that NAND, like DRAM, runs a 2027 supply gap above 10% — still short. My N2 base case says +10.9% (turns to surplus). That is an opposite-direction contradiction, not a difference of degree, and the disagreement is on the demand side, not the supply side: KB's logic is that AI server investment pulls server DDR5 and enterprise SSD together. Evidence on KB's side sits in my own earlier reports — Sandisk (QLC adoption accelerating in AI workloads, read-heavy profiles suit QLC), Western Digital (AI data compounds; the warm tier of high-capacity QLC SSD is the fastest-growing and least-discussed layer) and Astera Labs (Leo CXL memory tiering and pooling ships in 2027). ⚠ Honest label: the correction below moves toward KB's judgement; it is not the result of me finding new demand-side data. An independent read on eSSD bit demand is the highest-priority item on the v4.0 tracking list.
A64: Scenario | B64: Probability | C64: 2027 supply v3.0 | D64: 2027 supply v4.0 | E64: 2027 demand v3.0 | F64: 2027 demand v4.0 | G64: 2027 gap v3.0 | H64: 2027 gap v4.0 | I64: Change (pp) | J64: Verdict
A65: N1 Stays tight | B65: =B30 -> 0.25 | C65: =G8 -> 0.218464 | D65: =G8+'06-Inventory-Burn-v4'!$B$14 -> 0.188464 | E65: =F8+$B$81 -> 0.26 | F65: =F8+$B$81+'06-Inventory-Burn-v4'!$B$13 -> 0.3 | G65: =C65-E65 -> -0.041536 | H65: =D65-F65 -> -0.111536 | I65: =(H65-G65)*100 -> -7 | J65: =IF(H65<0,"still short after correction",IF(H65<0.05,"close to balance","still in surplus")) -> still short after correction
A66: N2 Base case | B66: =B31 -> 0.46 | C66: =G13 -> 0.27617 | D66: =G13+'06-Inventory-Burn-v4'!$B$14 -> 0.24617 | E66: =F13+$B$81 -> 0.22 | F66: =F13+$B$81+'06-Inventory-Burn-v4'!$B$13 -> 0.26 | G66: =C66-E66 -> 0.05617 | H66: =D66-F66 -> -0.01383 | I66: =(H66-G66)*100 -> -7 | J66: =IF(H66<0,"still short after correction",IF(H66<0.05,"close to balance","still in surplus")) -> still short after correction
A67: N3 Turns to surplus | B67: =B32 -> 0.29 | C67: =G18 -> 0.359435 | D67: =G18+'06-Inventory-Burn-v4'!$B$14 -> 0.329435 | E67: =F18+$B$81 -> 0.18 | F67: =F18+$B$81+'06-Inventory-Burn-v4'!$B$13 -> 0.22 | G67: =C67-E67 -> 0.179435 | H67: =D67-F67 -> 0.109435 | I67: =(H67-G67)*100 -> -7 | J67: =IF(H67<0,"still short after correction",IF(H67<0.05,"close to balance","still in surplus")) -> still in surplus
A68: N4 Large surplus | B68: =B33 -> 0 | C68: =G23 -> 0.432944 | D68: =G23+'06-Inventory-Burn-v4'!$B$14 -> 0.402944 | E68: =F23+$B$81 -> 0.14 | F68: =F23+$B$81+'06-Inventory-Burn-v4'!$B$13 -> 0.18 | G68: =C68-E68 -> 0.292944 | H68: =D68-F68 -> 0.222944 | I68: =(H68-G68)*100 -> -7 | J68: =IF(H68<0,"still short after correction",IF(H68<0.05,"close to balance","still in surplus")) -> still in surplus
A69: Probability weighted (mean) | C69: =SUMPRODUCT($B$65:$B$68,C65:C68) -> 0.28589035 | D69: =SUMPRODUCT($B$65:$B$68,D65:D68) -> 0.25589035 | G69: =SUMPRODUCT($B$65:$B$68,G65:G68) -> 0.06749035 | H69: =SUMPRODUCT($B$65:$B$68,H65:H68) -> -0.00250965 | I69: =(H69-G69)*100 -> -7
A70: KB Securities, 2026-09-07 | B70: '2027 NAND and DRAM bit demand growth will exceed supply growth by more than 10 percentage points; the 2027 supply gap will exceed 10%.' On my N2 base case the v3.0 answer was +10.9% surplus and the v4.0 answer is close to balance — still short of KB's view, and the residual difference is entirely the eSSD demand assumption.
A71: ★ How the correction is implemented: rather than overwriting the grid inputs, the two v4.0 levers on sheet 06 are applied on top — 2027 NAND demand +4.0pp (enterprise SSD) and 2027 NAND supply −3.0pp (NAND inventory at 4–5 weeks is tight but far less so than DRAM's 1.43). Set both sliders to zero and this block reverts exactly to v3.0. That is deliberate: the correction has to stay reversible, because it is an alignment to someone else's judgement rather than a new measurement.
A73: [G] PARAMETER CONSOLE · drag a slider and every table above and every chart below recalculates
A74: How to use: put the mouse on the grey scroll bar in the middle and drag left or right, or click the arrows at either end to nudge one step at a time. The yellow cell on the left is the converted current value; the blue cell on the right is the slider's raw integer — you can type into it directly. If your build of Excel does not render the sliders, just edit the blue cells.
A75: Parameter | B75: Current value | C75: ◀ drag to adjust ▶ | H75: Slider link cell | I75: Adjustable range | J75: Note
A76: 2025 start horizontal gap | B76: =-H76/1000 -> -0.025 | H76: 25 | I76: 0 ~ −15.0% | J76: ★ Audit finding (A, item 1): v2.0 called this value 'independently estimated' but never derived it. Using it to 'validate' TrendForce's −4~−5% is one free parameter fitted to one target value, which is not a validation.
A77: NAND yield term | B77: =(H77-100)/1000 -> 0 | H77: 100 | I77: −10.0 ~ +5.0pp | J77: ★ Audit finding (B): the NAND formula has no yield term at all. 400-layer QLC yields materially worse than 400-layer TLC — pull negative to impose the penalty.
A78: Wafer capacity growth · global shift | B78: =(H78-50)/1000 -> -0.01 | H78: 40 | I78: −5.0 ~ +10.0pp | J78: ★ Audit finding (C): v1.0 says capacity is 'stable at 670–700k wafers per month' yet N3/N4 assign +12%/+16% for 2028. Pull negative to correct that internal contradiction.
A79: Layer stacking uplift · global shift | B79: =(H79-80)/1000 -> 0 | H79: 80 | I79: −8.0 ~ +8.0pp | J79: NAND's most important bit lever (232 → 400+ = +72%), and it needs no new wafer fab. Hybrid bonding tool lead times and 400-layer yield decide whether it lands.
A80: QLC uplift · global shift | B80: =(H80-50)/1000 -> 0 | H80: 50 | I80: −5.0 ~ +5.0pp | J80: The second lever DRAM does not have (TLC 3 bit → QLC 4 bit = +33%). Note it is not fully independent of layers — pushed together, yield is a negative term.
A81: Demand growth · global shift | B81: =(H81-100)/1000 -> 0.02 | H81: 120 | I81: −10.0 ~ +15.0pp | J81: Enterprise SSD demand against consumer demand destruction. The reports give a 2027 demand range of 5%–24%, extremely wide — the most fragile link on the NAND side. ▲ v4.0: KB Securities argues the base case is too low; the dedicated eSSD lever sits on sheet 06.
A82: Scenario probabilities (1% per step) · the four must sum to 100%
A83: N1 Stays tight · probability | B83: =H83/100 -> 0.25 | H83: 25 | I83: 0 – 100% | J83: Enterprise SSD demand keeps beating expectations; AI data staging and checkpointing explode; layer progression runs behind plan.
A84: N2 Base case · probability | B84: =H84/100 -> 0.46 | H84: 46 | I84: 0 – 100% | J84: Aligned to TrendForce: 2026 gap −4~−5%, turns positive in 2H27 and starts pressing prices down. ⚠ v4.0: contradicted head on by KB Securities.
A85: N3 Turns to surplus · probability | B85: =H85/100 -> 0.29 | H85: 29 | I85: 0 – 100% | J85: Kioxia/Sandisk's +41% capex converts into capacity; YMTC's third Wuhan fab ramps; the PC cycle ends while mobile stays weak.
A86: N4 Large surplus · probability | B86: =H86/100 -> 0 | H86: 0 | I86: 0 – 100% | J86: Layers and QLC both advance faster than expected while consumer demand stays priced out — the risk specific to NAND.
A87: Cumulative probability total | B87: =SUM(B83:B86) -> 1 | C87: =IF(ABS(B87-1)<0.0001,"✔ Cumulative probability = 100%; the weighted and median rows are valid.","⚠ Currently "&TEXT(B87,"0%")&" — "&TEXT(1-B87,"0%")&" still to allocate. Keep adjusting the four rows above until this reads 100%.") -> ✔ Cumulative probability = 100%; the weighted and median rows are valid.
A89: [H] Live readout · probability-weighted results (updates as you drag)
A90: Basis | B90: 2026 | C90: 2027 | D90: 2028 | E90: Median scenario 2027 | F90: Median scenario 2028
A91: ④ Flow: supply−demand growth gap | B91: =D34 -> -0.061545 | C91: =E34 -> 0.06749035 | D91: =F34 -> 0.1274845 | E91: =E35 -> 0.05617 | F91: =F35 -> 0.114495
A92: ② Stock: horizontal adequacy | B92: =E43 -> -0.073569218 | C92: =F43 -> -0.020312745 | D92: =G43 -> 0.093843631 | E92: =F44 -> -0.035500758 | F92: =G44 -> 0.056524526
A93: ④ Flow · v4.0 corrected (2027 only) | B93: — | C93: =H69 -> -0.00250965 | D93: — | E93: — | F93: —
A216: Chart notes | Charts 1 and 2: the black heavy line is the probability weighting, but read the median row in the summary tables first — the NAND skew is worse than DRAM's. | Chart 3: grey (wafers) is almost invisible; blue (layers) and green (QLC) carry the entire growth. That is 'you can multiply bits without building a fab', drawn. | Chart 4: the two lines cross and separate in 2027 — the single most important chart in the model. Pull the demand shift on the DRAM console negative to watch the divergence narrow.

Sheet 03-Demand-BottomUp
A1: 03 · Bottom-up decomposition of DRAM demand growth
A2: Closes audit finding C, item 5: demand growth is the model's largest driver (1:1 elasticity) yet the reports never derived it | the two bases are benchmarked against two different external datasets
A4: [A] Segment weights and growth assumptions (blue cells are editable; the weights must sum to 100%)
A5: Segment | B5: Share of DRAM bit demand | C5: 2027 unconstrained bit growth | D5: 2027 cleared bit growth | E5: Unconstrained contribution | F5: Cleared contribution | G5: Basis for the weight and the growth rate
A6: HBM | B6: 0.09 | C6: 0.6 | D6: 0.6 | E6: =B6*C6 -> 0.054 | F6: =B6*D6 -> 0.054 | G6: Weight backed out from the model's 22% HBM wafer share and the 3× penalty: (0.22/3) ÷ ((1−0.22) + 0.22/3) = 8.6%. Growth: Rubin carries 288GB of HBM4 per card; AWS adds 2 million GPUs across 2027–28; industry expects HBM shipped bits +50~60% per year.
A7: RDIMM / server | B7: 0.42 | C7: 0.3 | D7: 0.3 | E7: =B7*C7 -> 0.126 | F7: =B7*D7 -> 0.126 | G7: TrendForce 2026-08-25: 2027 server DRAM + HBM combined bit supply +27%; 2026-07-09: RDIMM bit supply only +15~20%, 'materially behind server CPU shipment growth'. Demand side taken at 30% because supply is the binding constraint.
A8: Handset LPDDR | B8: 0.27 | C8: 0.12 | D8: -0.05 | E8: =B8*C8 -> 0.0324 | F8: =B8*D8 -> -0.0135 | G8: Unconstrained = natural per-handset capacity growth of about 12% a year. Cleared = TrendForce's 2026 handset build −15~20%, falling again in 2027 but more gently.
A9: PC client | B9: 0.13 | C9: 0.12 | D9: -0.05 | E9: =B9*C9 -> 0.0156 | F9: =B9*D9 -> -0.0065 | G9: Cleared basis: TrendForce cut its 2026 global notebook shipment forecast to −14.8% in July 2026 (the −10% the reports quoted was too optimistic).
A10: Graphics / consumer / auto / industrial | B10: 0.09 | C10: 0.08 | D10: 0 | E10: =B10*C10 -> 0.0072 | F10: =B10*D10 -> 0 | G10: Residual. GDDR7 and automotive are growing; consumer and industrial are being priced out; combined they are close to flat.
A11: Weighted total | B11: =SUM(B6:B10) -> 1 | C11: — | D11: — | E11: =SUM(E6:E10) -> 0.2352 | F11: =SUM(F6:F10) -> 0.16 | G11: =IF(ABS(B11-1)<0.0001,"✔ Weights sum to 100%; the comparison below is valid.","⚠ Currently "&TEXT(B11,"0.0%")&" — put the weights back to 100%.") -> ✔ Weights sum to 100%; the comparison below is valid.
A13: [B] Three-way comparison: against the model assumption and against external data
A14: Item | B14: 2027 value | C14: Implied gap | D14: External benchmark | H14: Verdict
A15: Model S2 2027 supply bit growth | B15: ='01-DRAM-Model'!J26 -> 0.1751899 | C15: — | D15: TrendForce: server DRAM + HBM combined +27% (a server-only basis runs above the all-in basis; direction consistent) | H15: ✔ consistent
A16: Model S2 2027 demand growth (in use) | B16: ='01-DRAM-Model'!K26+'01-DRAM-Model'!$B$149 -> 0.27 | C16: =B15-B16 -> -0.0948101 | D16: No derivation — the hole audit finding C, item 5 pointed at | H16: △ no basis
A17: This decomposition · unconstrained basis | B17: =E11 -> 0.2352 | C17: =B15-B17 -> -0.0600101 | D17: Built here; the weights are cross-checked against TrendForce's 'HBM + RDIMM = 51% of DRAM bit supply' | H17: ★ about 2.5pp below the value in use
A18: This decomposition · cleared basis | B18: =F11 -> 0.16 | C18: =B15-B18 -> 0.0151899 | D18: TrendForce, 'Diverging Memory Market Outlook in 2027': DRAM sufficiency −1%~−2%. This row is a flow × cleared basis, so the two are directly comparable. | H18: ★★ agrees on a like-for-like basis
A20: ★★ This is the most important addition of v3.0. v2.0 once used NAND's −4.1% to 'validate' TrendForce's −4~−5%, but audit finding A, item 1 showed that to be a pseudo-validation — one free parameter (NAND start −2.0%, no derivation) fitted to one target. This table instead decomposes five segments independently first, then matches the two bases against two different external datasets: the unconstrained basis gives roughly −8.0% (the 26% in use gives −10.5%) and the cleared basis gives roughly −0.5% against TrendForce's published −1~−2%. Nothing was fitted.
A22: [C] v3.0 finding (grade A): the start point and the recursion use different denominators
A23: Start −9.0% = (normal 8 weeks − actual 3.3 weeks) ÷ 52 — the v3.0 calibration; on the v4.0 reading of 1.43 weeks the same formula gives −12.6%, which is what the console now uses. Inventory weeks are converted using ACTUAL (cleared) consumption, so the denominator is cleared demand. But the recursion (1+gap_t−1)×(1+supply)÷(1+demand) uses UNCONSTRAINED demand. Two different denominators inside one continued product. Consequence: the gap is systematically computed too deep. The table below quantifies the mismatch.
A24: Item | B24: Value | C24: Note
A25: Unconstrained demand (this sheet) | B25: =B17 -> 0.2352 | C25: The denominator the recursion uses
A26: Cleared demand (this sheet) | B26: =B18 -> 0.16 | C26: The denominator the start-point calibration implies
A27: Single-year basis difference | B27: =(B25-B26)*100 -> 7.52 | C27: percentage points per year
A28: Three-year cumulative mismatch | B28: =(((1+B25)^3/(1+B26)^3)-1)*100 -> 20.736305 | C28: ★ This is the main reason the model's stock gap (−19.4%) runs deeper than any external dataset.
A30: Two ways to fix it, mutually exclusive: ① keep the start point at −9.0% but switch the recursion denominator to cleared demand; or ② keep the unconstrained denominator but recalibrate the start point to an inventory gap measured on the unconstrained basis — which would be shallower than −9.0%, since cleared demand is smaller than unconstrained demand. This workbook does not choose for you; it sets both paths side by side in block [B] of sheet 05.
A32: [D] v4.0 addition: two demand-side items this decomposition cannot yet close
A33: Item | B33: What KB Securities says | E33: What this model says | G33: Why they cannot be compared directly
A34: Memory as a share of AI capex | B34: Memory rises from 14% of global AI infrastructure investment in 2025 to 57% in 2027 — a fourfold expansion in two years. Global AI infrastructure investment reaches $1.3tn in 2027, +60% year on year. | E34: DRAM + NAND rise from 47% of major-CSP capex in 2026 to 68% in 2027 (TrendForce 2026-08-25), used on sheet 04 to back out bit demand. | G34: ★ The denominators differ (CSP capex versus global AI infrastructure investment) so the two percentages are not comparable; the direction is the same. Tracking item 8 on sheet 08 is to put them on one basis.
A35: Enterprise SSD (eSSD) bit demand | B35: AI server investment pulls server DDR5 and enterprise SSD together, so the 2027 NAND gap also exceeds 10%. | E35: This sheet models DRAM only; the NAND demand assumption sits on sheet 02 and the v3.0 base case used 18% for 2027. | G35: ★ No independent read on eSSD bit demand has been obtained. This is the single source of the disagreement with KB on NAND and is the highest-priority information gap on the v4.0 tracking list.
A36: Second de-spec event (NVIDIA 8-high) | B36: Not addressed by KB. DigiTimes gives NVIDIA's reason as thermal limits, packaging yield and memory availability under tight supply. | E36: Tracking item 14 in v3.0 said a second de-spec would materially overturn the unconstrained-demand basis. It has now happened. | G36: ★ The motive is two-sided. Supply-driven de-spec (cannot get the parts) does not constitute a real fall in demand — it defers or displaces it. Technical de-spec (heat, power, packaging yield) does. v4.0's treatment: keep the basis, add a physical ceiling — 600kW per rack is that ceiling.
A37: ★ Honest limitation: nothing in this block changes a number in the decomposition above. It is recorded because v4.0's NAND correction is an alignment to someone else's judgement rather than a new measurement, and because the second de-spec puts a physical ceiling on the unconstrained-demand basis that the model still does not enforce anywhere.

Sheet 04-NVDA-Calibration
A1: 04 · External confirmation: NVIDIA FY2027 Q2, TrendForce 8/25 and KB Securities 9/7
A2: The v3.0 data cut-off was 2026-08-24; the v4.0 cut-off is 2026-09-08. Every item below is tagged with which model assumption it strengthens or weakens, and which cell it touches
A4: [A] Six items confirmed by NVIDIA FY27 Q2 (through 2026-07-26)
A5: Confirmed item | B5: Figure / wording | E5: Direction | G5: Which cell it touches | I5: Assessment
A6: Supply and capacity commitments | B6: $119.0bn → $279.0bn; the 10-Q says explicitly 'primarily memory and manufacturing capacity'; by year: FY27 remaining $92.0bn / FY28 $87.0bn / FY29 $88.0bn, collapsing to $6.0bn in FY30 | E6: ★ Strengthens the demand side (2026–28) △ but draws a 2029 boundary | G6: Sheet 01 column K (demand growth) 2026–2028 | I6: The hardest external support the demand assumption has: one company has locked three years of memory volume under binding contracts. But the 93% collapse in FY30 is information too — NVIDIA itself will not commit beyond 2029.
A7: CFO Kress on the earnings call | B7: 'Today's memory scarcity is in large part driven by the AI build-out itself' | E7: ★ Strengthens the demand attribution | G7: Section 03 of sheet 00, the inventory anchor narrative | I7: The largest buyer publicly accepts that the scarcity is of its own making. That rules out the alternative explanation that scarcity is deliberate supplier restraint.
A8: Q3 FY27 gross margin guidance | B8: 74.0%, down 100bp sequentially, principally on memory cost; Grace Blackwell and Vera Rubin systems priced up 15%+ from early 2027 | E8: ★ Confirms the price transmission chain | G8: Whole model (the price mechanism sits outside it) | I8: Memory inflation is now large enough to cost NVIDIA 100bp of gross margin, and NVIDIA's response was to pass it on rather than de-spec. So the 'physical gap → price' transmission was not being blocked by buyer resistance in 2026–27.
A9: Top five cloud vendors' capex | B9: 2026 above $800bn → 2027 $1.3tn (+63%) | E9: ★ Strengthens the demand side | G9: Sheet 01 K26 (S2 2027 demand) | I9: ★ Note the basis difference against TrendForce, which puts 2027 CSP capex at +50%. The two differ by 13pp and NVIDIA is the seller.
A10: AWS incremental orders | B10: An additional 2 million GPUs deployed across 2027–2028 (Blackwell Ultra / Rubin / Rubin Ultra) | E10: ★ Strengthens HBM demand | G10: Sheet 03 HBM row (weight 9%, growth 60%) | I10: Rubin carries 288GB of HBM4 per card, so 2 million units is roughly 576PB of incremental HBM4 spread over two years — direct support for the HBM growth assumption on sheet 03.
A11: SOCAMM de-spec (2026-06) | B11: Vera CPU-side SOCAMM 192GB → 96GB; SOCAMM DRAM per rack 55TB → 28TB; rack BOM $7.60m → $6.80m | E11: ✗ Weakens the 'unconstrained demand' assumption | G11: The basis premise behind sheet 03 and sheet 01 column K | I11: ★★ The most important counter-evidence against the model: demand is not price-inelastic. Past a certain price the largest buyer redesigns the demand away. HBM is unaffected (architecturally rigid); conventional DRAM and LPDDR are exposed. ▲ v4.0: the 8-high HBM4 request is the SECOND such event — see sheet 06.
A13: [B] TrendForce 2026-08-25: the structure of CSP capex (published after the v3.0 cut-off)
A14: Metric | C14: 2026 | D14: 2027 | E14: Meaning
A15: CSP total capex growth | C15: 0.98 | D15: 0.5 | E15: NVIDIA's basis puts 2027 at +63%; the two differ by 13pp
A16: DRAM + NAND as a share of CSP capex | C16: 0.47 | D16: 0.68 | E16: ★ Memory is eating two thirds of cloud capex
A17: Server DRAM cumulative contract price increase | C17: 2.7 | D17: — | E17: About +270% across 2026 (2H25 alone was +64%)
A18: Enterprise SSD cumulative contract price increase | C18: 2.35 | D18: — | E18: About +235% across 2026 (2H25 alone was +35%)
A19: HBM contract price increase | C19: — | D19: 1.05 | E19: +70~140% in 2027, midpoint taken. ⚠ Opposite in direction to the v1.0 'HBM economics reversal' assumption
A20: HBM + RDIMM as a share of DRAM bit supply | C20: 0.51 | D20: — | E20: ★ Used to check the segment weights on sheet 03
A21: Server DRAM + HBM bit supply growth | C21: — | D21: 0.27 | E21: 2027; RDIMM alone only +15~20% (TrendForce 7/9)
A23: [C] Backing out memory bit demand from the CSP basis — an independent check on the model's 2027 demand
A24: Step | C24: Expression | G24: Result | H24: Note
A25: ① CSP memory spend growth 2027 (in money) | C25: (1 + CSP capex growth_27) × memory share_27 ÷ memory share_26 − 1 | G25: =(1+D15)*D16/C16-1 -> 1.1702128 | H25: CSP memory purchasing growth measured in money
A26: ② 2027 blended ASP increase (editable) | C26: Assumption: server DRAM rising quarter on quarter but decelerating, plus HBM +70~140%, blended at 50% | G26: 0.5 | H26: ★ The most sensitive input on this sheet. Enter 40% and bit growth rises to about 55%; enter 60% and it falls to about 36%.
A27: ③ CSP memory bit demand growth | C27: Expression: (1 + ①) ÷ (1 + ②) − 1 | G27: =(1+G25)/(1+G26)-1 -> 0.44680851 | H27: The CSP leg only; excludes handsets, PCs and consumer
A28: ④ Converted to the whole market | C28: CSP weight × ③ + non-CSP weight × non-CSP growth | G28: =('03-Demand-BottomUp'!B6+'03-Demand-BottomUp'!B7)*G27+(1-'03-Demand-BottomUp'!B6-'03-Demand-BottomUp'!B7)*'03-Demand-BottomUp'!C8 -> 0.28667234 | H28: CSP weight = the HBM and RDIMM rows on sheet 03; non-CSP growth borrows the handset unconstrained rate as a proxy
A29: ⑤ Cross-check: the value the model uses | C29: Sheet 01 K26 plus the console demand shift | G29: ='01-DRAM-Model'!K26+'01-DRAM-Model'!$B$149 -> 0.27 | H29: Two independent routes (the bottom-up build on sheet 03 and this CSP back-out) both land in the 20%–29% band, and the 26% in use sits between them.
A31: ★ How to read it: the value of this section is not a 'more accurate number' but that it turns the one key parameter the model never derived into two mutually corroborating routes, each testable against external data. One route runs slightly low (23.5%), the other slightly high (28.7%), and the 26% in use sits between them — the strongest positive validation the model has had, and it came in the place I expected it to fail.
A33: [D] v4.0 addition: KB Securities research note, 2026-09-07 (head of research Kim Dong-won)
A34: 'As of the third quarter, memory inventory at Samsung Electronics and SK hynix has fallen below 10 days. That goes beyond a simple demand recovery — there is a high probability that the absolute supply available is insufficient. Next year's saleable memory volume running out could become reality.' Carried by DigiTimes, Seoul Economic Daily, TechTimes and technetbooks, all dated 2026-09-07.
A35: # | B35: KB's quantification | F35: Impact on this model | I35: How this workbook handles it
A36: ① | B36: 2027 DRAM and NAND bit demand growth will exceed supply growth by more than 10 percentage points | F36: Directly comparable with the flow basis. My S2 base case gives −10.5% on the production basis and −15.5% after the inventory correction; KB's 'more than 10 points' sits between them. | I36: Sheet 06 block [B] sets both against KB's figure.
A37: ② | B37: The 2027 supply gap will exceed 10% for both DRAM and NAND | F37: On DRAM this corroborates the model. On NAND it contradicts it head on — my N2 base case had 2027 turning to surplus at +10.9%. | I37: Sheet 02 block [F] applies the NAND correction with both levers reversible.
A38: ③ | B38: Producing HBM4 consumes three times the wafer capacity of conventional DRAM | F38: ★★★ The most important external validation the model has received. Every v3.0 conclusion rests on the 3× wafer penalty, and until now that was a self-built assumption with no third-party support. | I38: Sheet 01 row 6 (the console penalty slider) now carries a third-party source rather than an author assumption.
A39: ④ | B39: The shortage is not confined to HBM — AI server investment pulls server DDR5 and enterprise SSD at the same time | F39: Consistent with the RDIMM weight on sheet 03; on the NAND side it is the mechanism behind the disagreement in item ②. | I39: Recorded as the top information gap on the sheet 08 tracking list.
A41: Other data published in the same note | C41: Value | E41: Note
A42: Healthy DRAM finished-goods inventory | C42: 30–45 days = 4.3–6.4 weeks | E42: Supply-chain benchmark. The model's 'normal' of 8 weeks is more conservative still.
A43: Combined share of the two suppliers | C43: About 64% of global DRAM revenue | E43: Samsung plus SK hynix. So a sub-10-day reading at these two is close to an industry reading.
A44: Global DRAM revenue, 2026 Q2 | C44: $154.73bn (TrendForce, April–June) | E44: Used for scale, not in the model.
A45: Global AI infrastructure investment | C45: $1.3tn in 2027, +60% year on year | E45: Same order as NVIDIA's top-five cloud capex figure of $1.3tn.
A46: Memory as a share of that budget | C46: 14% in 2025 → 57% in 2027 | E46: ⚠ A different denominator from the model's 'DRAM+NAND = 47% → 68% of CSP capex'. Not comparable directly; same direction.
A47: Share prices | C47: Down 38% from the peak; the analyst calls the group deeply undervalued | E47: Recorded for completeness. Valuation is outside this model's boundary.
A48: ★ Why item ③ matters more than it looks: a model whose every conclusion rests on one self-built parameter is fragile in a specific way — you cannot tell whether you are measuring the world or your own assumption. An independent sell-side house arriving at exactly the same 3:1 figure does not make the model right, but it does move that parameter out of the 'author assumption' column and into the 'market consensus' column. That is the single largest reduction in model risk in v4.0.

Sheet 05-Audit-v3
A1: 05 · v3.0 audit supplement: five new findings and two robustness tests
A2: Section 07 of sheet 00 lists the original ten (A×4, B×3, C×3); this sheet adds the five found in v3.0, two of them grade A. Sheet 06 block [F] adds the five found in v4.0. Nothing has been removed
A4: [A] The five findings new in v3.0
A5: Grade | B5: Issue | D5: Why it is a problem | G5: Effect on the conclusion | J5: How this workbook handles it
A6: A | B6: Start point and recursion use different denominators | D6: The start point (−9.0% on the v3.0 inventory reading, −12.6% on the v4.0 reading) has cleared demand in its denominator, because inventory weeks are converted using actual consumption; the recursion's denominator is unconstrained demand. Two different denominators inside one continued product. | G6: The gap is systematically computed too deep. On the sheet 03 decomposition the two bases differ by about 7.5pp in a single year and about 20.7pp cumulatively over three — which is the main reason the model's −19.4% runs deeper than any external dataset. | J6: → Quantified in block [C] of sheet 03; block [B] below sets the two correction paths side by side.
A7: A | B7: The supply side has no reaction function (supply is exogenous) | D7: Supply growth is entirely exogenous, decoupled from price and from demand. Scenario S5 produces 'supply = 194% of demand' in 2028 — arithmetically correct, economically absurd. In the real world DRAM makers cut output when prices collapse, as they did in 2019 and 2023. | G7: ★ The right tail of the extreme scenarios is badly exaggerated, and it is precisely that tail which drags the 2028 probability weighting from the median's −19.4% up to −0.1%. | J7: → Block [C] below adds an adjustable output-cut trigger and shows the weighted result after truncation.
A8: B | B8: DRAM and NAND scenarios are not paired | D8: The two sheets assign probabilities independently, allowing 'DRAM collapse (demand −8%)' and 'NAND robust (demand +14%)' to coexist in the same year. But the demand drivers overlap heavily, so that is not self-consistent at the scenario level. | G8: The divergence conclusion might be an artefact of two independent sets of assumptions rather than a real structural difference. | J8: → Block [D] below runs a forced pairing test: after pairing the divergence does not vanish, it widens. Robust ✔
A9: B | B9: 'Unconstrained demand' implies demand has no price elasticity | D9: NVIDIA's SOCAMM de-spec (June 2026, SOCAMM DRAM per rack 55TB → 28TB, −49%) proves that past a certain price the largest buyer redesigns the demand away. HBM is unaffected; conventional DRAM and LPDDR are exposed. | G9: The 'unconstrained demand' basis has a physical ceiling and the model imposes no constraint on it at all. ▲ v4.0: the second de-spec has now happened (NVIDIA's 8-high HBM4 request) and its stated reason includes availability under tight supply. | J9: → Recorded as item 6 in block [A] of sheet 04; sheet 03 sets HBM and conventional DRAM growth separately, which mitigates it in part. ▲ v4.0 adds a de-spec demand ceiling slider on sheet 06.
A10: C | B10: The notebook demand-destruction figure has been revised down externally | D10: The model quotes 'notebooks −10%', but TrendForce cut its 2026 global notebook shipment forecast to −14.8% in July 2026. | G10: The cleared gap is smaller than the model implies, because demand destruction is worse. | J10: → The cleared growth rate on the PC row of sheet 03 is set to −5% on the new data (a bit basis, including per-unit capacity de-spec).
A12: [B] Correcting grade-A finding 1: three basis paths side by side (S2 base case)
A13: Convention | D13: 2026 | E13: 2027 | F13: 2028 | G13: What this convention is doing
A14: In use: start point (cleared basis) × recursion (unconstrained basis) | D14: ='01-DRAM-Model'!M25 -> -0.14570558 | E14: ='01-DRAM-Model'!M26 -> -0.20948175 | F14: ='01-DRAM-Model'!M27 -> -0.19509017 | G14: Stock basis. The start point converts inventory weeks using cleared demand while the recursion denominator is unconstrained demand — two denominators, one continued product. This is the deepest reading.
A15: Correction ①: stock + cleared denominator (bases aligned) | D15: =(1+'01-DRAM-Model'!$B$14)*(1+'01-DRAM-Model'!J25)/(1+'03-Demand-BottomUp'!$F$11)-1 -> -0.049965691 | E15: =(1+D15)*(1+'01-DRAM-Model'!J26)/(1+'03-Demand-BottomUp'!$F$11)-1 -> -0.037525237 | F15: =(1+E15)*(1+'01-DRAM-Model'!J27)/(1+'03-Demand-BottomUp'!$F$11)-1 -> 0.056031095 | G15: Reads as 'at the end of this year, how far is inventory still from normal'. ★ Not directly comparable with TrendForce's flow sufficiency ratio.
A16: Correction ②: stock + unconstrained denominator, start point zeroed | D16: =(1+'01-DRAM-Model'!J25)/(1+'03-Demand-BottomUp'!$E$11)-1 -> -0.040650072 | E16: =(1+D16)*(1+'01-DRAM-Model'!J26)/(1+'03-Demand-BottomUp'!$E$11)-1 -> -0.087258463 | F16: =(1+E16)*(1+'01-DRAM-Model'!J27)/(1+'03-Demand-BottomUp'!$E$11)-1 -> -0.059506331 | G16: Reads as 'if prices never moved, how deep is the cumulative physical gap'.
A17: Correction ③: flow + cleared (★ the only one directly comparable with institutional data) | D17: ='01-DRAM-Model'!J25-'03-Demand-BottomUp'!$F$11 -> 0.024989031 | E17: ='01-DRAM-Model'!J26-'03-Demand-BottomUp'!$F$11 -> 0.0151899 | F17: ='01-DRAM-Model'!J27-'03-Demand-BottomUp'!$F$11 -> 0.11275656 | G17: Basis: this year's supply growth minus cleared demand growth. 2027 gives roughly −0.5% against TrendForce's published DRAM sufficiency of −1~−2% — the first time the model passes a like-for-like external test on DRAM.
A18: How much the convention in use overstates it (in use − correction ②) | D18: =(D14-D16)*100 -> -10.505551 | E18: =(E14-E16)*100 -> -12.222329 | F18: =(F14-F16)*100 -> -13.558384 | G18: percentage points. A negative value means the convention in use computes a deeper gap.
A20: [C] Correcting grade-A finding 2: adding a supply-side output-cut reaction function
A21: Output-cut trigger threshold (editable) | D21: 0.35 | E21: When a scenario's horizontal adequacy exceeds this value (surplus above 35%), suppliers are treated as having started cutting output and the gap is truncated at this level. Enter 999% to switch the feature off.
A22: Scenario | C22: Probability | D22: 2028 raw | E22: 2028 truncated | F22: Note
A23: S1 Extreme tightness | C23: ='01-DRAM-Model'!B48 -> 0.16 | D23: ='01-DRAM-Model'!M22 -> -0.33966859 | E23: =MIN(D23,$D$21) -> -0.33966859
A24: S2 Base case | C24: ='01-DRAM-Model'!B49 -> 0.4 | D24: ='01-DRAM-Model'!M27 -> -0.19509017 | E24: =MIN(D24,$D$21) -> -0.19509017
A25: S3 Relief | C25: ='01-DRAM-Model'!B50 -> 0.27 | D25: ='01-DRAM-Model'!M32 -> 0.020952832 | E25: =MIN(D25,$D$21) -> 0.020952832
A26: S4 Surplus | C26: ='01-DRAM-Model'!B51 -> 0.17 | D26: ='01-DRAM-Model'!M37 -> 0.18997193 | E26: =MIN(D26,$D$21) -> 0.18997193
A27: S5 Collapse | C27: ='01-DRAM-Model'!B52 -> 0 | D27: ='01-DRAM-Model'!M42 -> 0.77784142 | E27: =MIN(D27,$D$21) -> 0.35
A28: Probability weighted (mean) | C28: =SUM(C23:C27) -> 1 | D28: =SUMPRODUCT(C23:C27,D23:D27) -> -0.094430551 | E28: =SUMPRODUCT(C23:C27,E23:E27) -> -0.094430551 | F28: ★ After truncation the mean drops materially and the distance to the median narrows — confirming the raw mean was being pulled up by the right tail.
A29: Probability median (comparison) | C29: — | D29: ='01-DRAM-Model'!G65 -> -0.19509017 | E29: ='01-DRAM-Model'!G65 -> -0.19509017 | F29: The median is unaffected by tail truncation, which is exactly why it is the more robust statistic.
A30: Mean − median gap | C30: — | D30: =(D28-D29)*100 -> 10.065962 | E30: =(E28-E29)*100 -> 10.065962 | F30: Percentage points. How much that gap shrinks after truncation is a measure of how badly the right tail was contaminating the conclusion.
A32: [D] Testing grade-B finding 3: forcing the DRAM and NAND scenarios into pairs
A33: Pair DRAM's S1–S5 with NAND's N1–N4 as though each pair were one macro world (S1↔N1, S2↔N2, S3↔N3, S4↔N4, S5↔N4) and use the DRAM probabilities as the common weight. If the divergence disappears once paired, it was an artefact of two independent assumption sets; if it survives, it is a real structural difference.
A34: Pairing | C34: Common probability | D34: DRAM 2028 horizontal gap | E34: NAND 2028 horizontal gap | F34: Divergence (pp)
A35: S1 ↔ N1 | C35: ='01-DRAM-Model'!B48 -> 0.16 | D35: ='01-DRAM-Model'!M22 -> -0.33966859 | E35: ='02-NAND-Model'!I9 -> -0.11978387 | F35: =(E35-D35)*100 -> 21.988472
A36: S2 ↔ N2 | C36: ='01-DRAM-Model'!B49 -> 0.4 | D36: ='01-DRAM-Model'!M27 -> -0.19509017 | E36: ='02-NAND-Model'!I14 -> 0.056524526 | F36: =(E36-D36)*100 -> 25.16147
A37: S3 ↔ N3 | C37: ='01-DRAM-Model'!B50 -> 0.27 | D37: ='01-DRAM-Model'!M32 -> 0.020952832 | E37: ='02-NAND-Model'!I19 -> 0.33720109 | F37: =(E37-D37)*100 -> 31.624826
A38: S4 ↔ N4 | C38: ='01-DRAM-Model'!B51 -> 0.17 | D38: ='01-DRAM-Model'!M37 -> 0.18997193 | E38: ='02-NAND-Model'!I24 -> 0.63443164 | F38: =(E38-D38)*100 -> 44.44597
A39: S5 ↔ N4 | C39: ='01-DRAM-Model'!B52 -> 0 | D39: ='01-DRAM-Model'!M42 -> 0.77784142 | E39: ='02-NAND-Model'!I24 -> 0.63443164 | F39: =(E39-D39)*100 -> -14.340979
A40: Probability weighted after pairing | C40: =SUM(C35:C39) -> 1 | D40: =SUMPRODUCT(C35:C39,D35:D39) -> -0.094430551 | E40: =SUMPRODUCT(C35:C39,E35:E39) -> 0.20234206 | F40: =(E40-D40)*100 -> 29.677262
A41: Original independent weighting (comparison) | C41: — | D41: ='01-DRAM-Model'!G64 -> -0.094430551 | E41: ='02-NAND-Model'!G43 -> 0.093843631 | F41: =(E41-D41)*100 -> 18.827418
A42: Verdict | C42: =IF(AND(SIGN(F40)=SIGN(F41),ABS(F40)>=ABS(F41)*0.8),"robust ✔","not robust ✘") -> robust ✔ | G42: Test: the paired result must share the sign of the independent weighting and be at least 80% of its magnitude to count as robust. If pairing flips the sign (for example after pulling NAND layers and yield both negative), the divergence conclusion really does depend on the NAND supply assumptions.
A44: [E] The full basis table after v3.0 and v4.0: eight conventions side by side
A45: Basis | D45: 2026 | E45: 2027 | F45: 2028 | G45: The question this number answers
A46: ① v1.0 flow: supply−demand growth gap | D46: ='01-DRAM-Model'!D53 -> -0.096010969 | E46: ='01-DRAM-Model'!E53 -> -0.046477544 | F46: ='01-DRAM-Model'!F53 -> 0.091620263 | G46: Is the gap widening or narrowing this year? (first derivative)
A47: ② v2.0 stock: multiplicative recursion (mixed bases) | D47: ='01-DRAM-Model'!E64 -> -0.13951261 | E47: ='01-DRAM-Model'!F64 -> -0.16813457 | F47: ='01-DRAM-Model'!G64 -> -0.094430551 | G47: ⚠ Denominators inconsistent — see item 1 in block [A]
A48: ③ After the HBM basis correction | D48: ='01-DRAM-Model'!G92 -> -0.13951261 | E48: ='01-DRAM-Model'!H92 -> -0.16813457 | F48: ='01-DRAM-Model'!I92 -> -0.094430551 | G48: Same as ②, but the HBM wafer share is put on a global basis (CXMT dilution removed)
A49: ④ True stock: additive accumulation | D49: ='01-DRAM-Model'!G105 -> -0.12940168 | E49: ='01-DRAM-Model'!H105 -> -0.20882475 | F49: ='01-DRAM-Model'!I105 -> -0.19422988 | G49: If the unbought bits queued up to be repaid, how much is owed in total? (upper bound)
A50: ⑤ v3.0 correction: stock + cleared denominator | D50: =D15 -> -0.049965691 | E50: =E15 -> -0.037525237 | F50: =F15 -> 0.056031095 | G50: How far inventory still is from normal (bases aligned)
A51: ⑥ v3.0 correction: stock + unconstrained denominator, start zeroed | D51: =D16 -> -0.040650072 | E51: =E16 -> -0.087258463 | F51: =F16 -> -0.059506331 | G51: How deep the cumulative physical gap is if prices never moved (bases aligned)
A52: ⑦ v3.0 correction: flow + cleared (★ comparable with institutional data) | D52: =D17 -> 0.024989031 | E52: =E17 -> 0.0151899 | F52: =F17 -> 0.11275656 | G52: Benchmark against TrendForce's DRAM sufficiency of −1~−2%
A53: ⑧ v4.0: flow, shipment basis (inventory release removed from the base) | D53: ='06-Inventory-Burn-v4'!$C$35 -> -0.096010969 | E53: ='06-Inventory-Burn-v4'!$D$35 -> -0.061628025 | F53: ='06-Inventory-Burn-v4'!$E$35 -> 0.091767311 | G53: ▲ NEW. What customers can actually receive, once you stop counting bits that came out of inventory rather than out of a fab. This is the basis on which 2027 is still short.
A55: ★★ All eight numbers are correct and all eight answer different questions. The common root of the mistakes in v1.0 and v2.0 was putting numbers from different bases next to each other. v3.0's contribution was not a more accurate gap but aligning each basis's numerator with its denominator so each could be checked against the matching external dataset. v4.0's contribution is the eighth row: separating what was produced from what was shipped.

Sheet 06-Inventory-Burn-v4
A1: 06 · v4.0 Inventory-Exhaustion Edition — the engine behind the three corrections
A2: New sheet, 2026-09-08 | every v4.0 lever lives in the console below, so sheets 01 and 02 keep their v3.0 results reproducible | set every slider to zero and the whole workbook reverts exactly to v3.0
A4: Two news items were verified for this version, and their importance is very nearly the reverse of how they read. NVIDIA asking for 8-high HBM4 sounds like the bigger story but is worth about one percentage point in the model, because it contains two offsetting effects — base-die dilution (−3.7%) and a compounding stacking-yield gain (+4~13%). The item that actually moves the conclusion is Samsung and SK hynix inventory below 10 days: it means roughly 4.9% of 2026 shipments were released from stock rather than produced, and that source is now exhausted. From 2027, shipments can only come from a fab.
A6: [A] v4.0 PARAMETER CONSOLE · the three corrections, each on its own slider
A7: How to use: drag the grey scroll bar, or click the arrows at either end to nudge one step. The yellow cell is the converted current value; the blue cell on the right is the slider's raw integer and can be typed into directly. Set rows 9, 10, 11, 13 and 14 to zero and every table in this workbook reverts to the v3.0 result — that reversibility is deliberate, because two of the three corrections are judgements rather than measurements.
A8: Parameter | B8: Current value | C8: ◀ drag to adjust ▶ | H8: Slider link cell | I8: Adjustable range | J8: Note
A9: Correction 2 · 2026 inventory release (weeks) | B9: =H9/100 -> 2.57 | H9: 257 | I9: 0.00 – 4.00 wk | J9: The bits released from supplier inventory during 2026 and therefore already sitting in the 2026 shipment base. Default 2.57 weeks = the July 2026 reading of 4.00 minus the 2026 Q3 reading of 1.43 (KB Securities). Each step is 0.01 weeks.
A10: Correction 1 · 8-high HBM4 penalty relief (×) | B10: =-H10/100 -> -0.2 | H10: 20 | I10: 0.00 – −0.50× | J10: How much the HBM wafer penalty falls from 2027 once 8-high displaces 12-high. Full arithmetic on sheet 07: at a per-layer bond yield of 0.975 the implied relief is about −0.18×; −0.20 is the round number used here. 2026 keeps the 3.0× penalty because 8-high ships from 2027.
A11: Correction 3 · second de-spec demand ceiling, 2027 (pp) | B11: =-H11/1000 -> -0.025 | H11: 25 | I11: 0.0 – −6.0pp | J11: The part of the NVIDIA 8-high request that is genuinely technical (thermal limits, power, packaging yield) rather than supply-driven, expressed as a cap on 2027 unconstrained demand. v4.0 puts it at −2 to −3pp. Applied to 2027 only.
A12: Drag convention: 0 = off, 1 = report linear, 2 = exact | B12: =H12 -> 1 | H12: 1 | I12: 0, 1 or 2 | J12: How the release is converted into a shipment-growth drag. 1 reproduces the report (subtract the release share, ≈−5.0pp). 2 is the mathematically exact form (1+g)/(1+r)−1, which is about 0.4pp harsher. 0 switches the correction off.
A13: NAND · 2027 demand uplift, eSSD (pp) | B13: =(H13-50)/1000 -> 0.04 | H13: 90 | I13: −5.0 ~ +5.0pp | J13: Moves the N2 base case toward KB Securities' view that AI server investment pulls enterprise SSD alongside server DDR5. Default +4.0pp lifts 2027 NAND demand from 18% to 22%. ⚠ This is an alignment to someone else's judgement, not a new measurement.
A14: NAND · 2027 supply drag (pp) | B14: =(H14-50)/1000 -> -0.03 | H14: 20 | I14: −5.0 ~ +5.0pp | J14: The NAND equivalent of the inventory correction. NAND inventory at 4–5 weeks is tight but far less so than DRAM's 1.43, so v4.0 uses −3.0pp rather than −5.0pp.
A15: Release as a share of one year of supply | B15: =B9/52 -> 0.049423077 | C15: ="2.57 weeks ÷ 52 = "&TEXT(B15,"0.0%")&" of annual supply. This is the single number behind v4.0: that share of 2026 shipments came out of inventory rather than out of production, so 2027 shipment growth starts from a base it cannot repeat." -> 2.57 weeks ÷ 52 = 4.9% of annual supply. This is the single number behind v4.0: that share of 2026 shipments came out of inventory rather than out of production, so 2027 shipment growth starts from a base it cannot repeat.
A16: [B] The 2027 headline: v3.0 → inventory correction → all three corrections
A17: Scenario | B17: Probability | C17: 2027 supply v3.0 (production) | D17: 2027 gap v3.0 | E17: 2027 gap v4.0 (inventory only) | F17: Change (pp) | G17: 2027 gap v4.0 (all three) | H17: 2027 demand v3.0 | I17: 2027 demand v4.0 | J17: 2027 supply after 8-high relief | K17: 2027 shipments v4.0 | L17: Verdict
A18: S1 Extreme tightness | B18: ='01-DRAM-Model'!B48 -> 0.16 | C18: ='01-DRAM-Model'!J21 -> 0.1353816 | D18: ='01-DRAM-Model'!L21 -> -0.1946184 | E18: =IF($B$12=0,C18,IF($B$12=1,C18-$B$15,(1+C18)/(1+$B$15)-1))-H18 -> -0.24404148 | F18: =(E18-D18)*100 -> -4.9423077 | G18: =K18-I18 -> -0.20846197 | H18: ='01-DRAM-Model'!K21+'01-DRAM-Model'!$B$149 -> 0.33 | I18: =H18+$B$11 -> 0.305 | J18: =(1+'01-DRAM-Model'!C21+'01-DRAM-Model'!$B$146)*(1+'01-DRAM-Model'!D21+'01-DRAM-Model'!$B$147)*(((1-'01-DRAM-Model'!G21)+'01-DRAM-Model'!G21/('01-DRAM-Model'!$B$6+$B$10))/((1-'01-DRAM-Model'!G20)+'01-DRAM-Model'!G20/'01-DRAM-Model'!$B$6))-1 -> 0.1459611 | K18: =IF($B$12=0,J18,IF($B$12=1,J18-$B$15,(1+J18)/(1+$B$15)-1)) -> 0.096538026 | L18: =IF(E18<0,IF(D18<0,"short before and after","★ flips to short"),IF(D18<0,"flips to surplus","surplus before and after")) -> short before and after
A19: S2 Base case | B19: ='01-DRAM-Model'!B49 -> 0.4 | C19: ='01-DRAM-Model'!J26 -> 0.1751899 | D19: ='01-DRAM-Model'!L26 -> -0.0948101 | E19: =IF($B$12=0,C19,IF($B$12=1,C19-$B$15,(1+C19)/(1+$B$15)-1))-H19 -> -0.14423318 | F19: =(E19-D19)*100 -> -4.9423077 | G19: =K19-I19 -> -0.10981268 | H19: ='01-DRAM-Model'!K26+'01-DRAM-Model'!$B$149 -> 0.27 | I19: =H19+$B$11 -> 0.245 | J19: =(1+'01-DRAM-Model'!C26+'01-DRAM-Model'!$B$146)*(1+'01-DRAM-Model'!D26+'01-DRAM-Model'!$B$147)*(((1-'01-DRAM-Model'!G26)+'01-DRAM-Model'!G26/('01-DRAM-Model'!$B$6+$B$10))/((1-'01-DRAM-Model'!G25)+'01-DRAM-Model'!G25/'01-DRAM-Model'!$B$6))-1 -> 0.1846104 | K19: =IF($B$12=0,J19,IF($B$12=1,J19-$B$15,(1+J19)/(1+$B$15)-1)) -> 0.13518732 | L19: =IF(E19<0,IF(D19<0,"short before and after","★ flips to short"),IF(D19<0,"flips to surplus","surplus before and after")) -> short before and after
A20: S3 Relief | B20: ='01-DRAM-Model'!B50 -> 0.27 | C20: ='01-DRAM-Model'!J31 -> 0.23315446 | D20: ='01-DRAM-Model'!L31 -> 0.023154458 | E20: =IF($B$12=0,C20,IF($B$12=1,C20-$B$15,(1+C20)/(1+$B$15)-1))-H20 -> -0.026268619 | F20: =(E20-D20)*100 -> -4.9423077 | G20: =K20-I20 -> 0.0078435731 | H20: ='01-DRAM-Model'!K31+'01-DRAM-Model'!$B$149 -> 0.21 | I20: =H20+$B$11 -> 0.185 | J20: =(1+'01-DRAM-Model'!C31+'01-DRAM-Model'!$B$146)*(1+'01-DRAM-Model'!D31+'01-DRAM-Model'!$B$147)*(((1-'01-DRAM-Model'!G31)+'01-DRAM-Model'!G31/('01-DRAM-Model'!$B$6+$B$10))/((1-'01-DRAM-Model'!G30)+'01-DRAM-Model'!G30/'01-DRAM-Model'!$B$6))-1 -> 0.24226665 | K20: =IF($B$12=0,J20,IF($B$12=1,J20-$B$15,(1+J20)/(1+$B$15)-1)) -> 0.19284357 | L20: =IF(E20<0,IF(D20<0,"short before and after","★ flips to short"),IF(D20<0,"flips to surplus","surplus before and after")) -> ★ flips to short
A21: S4 Surplus | B21: ='01-DRAM-Model'!B51 -> 0.17 | C21: ='01-DRAM-Model'!J36 -> 0.28608081 | D21: ='01-DRAM-Model'!L36 -> 0.096080805 | E21: =IF($B$12=0,C21,IF($B$12=1,C21-$B$15,(1+C21)/(1+$B$15)-1))-H21 -> 0.046657728 | F21: =(E21-D21)*100 -> -4.9423077 | G21: =K21-I21 -> 0.07960704 | H21: ='01-DRAM-Model'!K36+'01-DRAM-Model'!$B$149 -> 0.19 | I21: =H21+$B$11 -> 0.165 | J21: =(1+'01-DRAM-Model'!C36+'01-DRAM-Model'!$B$146)*(1+'01-DRAM-Model'!D36+'01-DRAM-Model'!$B$147)*(((1-'01-DRAM-Model'!G36)+'01-DRAM-Model'!G36/('01-DRAM-Model'!$B$6+$B$10))/((1-'01-DRAM-Model'!G35)+'01-DRAM-Model'!G35/'01-DRAM-Model'!$B$6))-1 -> 0.29403012 | K21: =IF($B$12=0,J21,IF($B$12=1,J21-$B$15,(1+J21)/(1+$B$15)-1)) -> 0.24460704 | L21: =IF(E21<0,IF(D21<0,"short before and after","★ flips to short"),IF(D21<0,"flips to surplus","surplus before and after")) -> surplus before and after
A22: S5 Collapse | B22: ='01-DRAM-Model'!B52 -> 0 | C22: ='01-DRAM-Model'!J41 -> 0.34029297 | D22: ='01-DRAM-Model'!L41 -> 0.21029297 | E22: =IF($B$12=0,C22,IF($B$12=1,C22-$B$15,(1+C22)/(1+$B$15)-1))-H22 -> 0.1608699 | F22: =(E22-D22)*100 -> -4.9423077 | G22: =K22-I22 -> 0.19261106 | H22: ='01-DRAM-Model'!K41+'01-DRAM-Model'!$B$149 -> 0.13 | I22: =H22+$B$11 -> 0.105 | J22: =(1+'01-DRAM-Model'!C41+'01-DRAM-Model'!$B$146)*(1+'01-DRAM-Model'!D41+'01-DRAM-Model'!$B$147)*(((1-'01-DRAM-Model'!G41)+'01-DRAM-Model'!G41/('01-DRAM-Model'!$B$6+$B$10))/((1-'01-DRAM-Model'!G40)+'01-DRAM-Model'!G40/'01-DRAM-Model'!$B$6))-1 -> 0.34703413 | K22: =IF($B$12=0,J22,IF($B$12=1,J22-$B$15,(1+J22)/(1+$B$15)-1)) -> 0.29761106 | L22: =IF(E22<0,IF(D22<0,"short before and after","★ flips to short"),IF(D22<0,"flips to surplus","surplus before and after")) -> surplus before and after
A23: Probability weighted (mean) | B23: =SUM(B18:B22) -> 1 | C23: =SUMPRODUCT($B$18:$B$22,C18:C22) -> 0.20332246 | D23: =SUMPRODUCT($B$18:$B$22,D18:D22) -> -0.046477544 | E23: =SUMPRODUCT($B$18:$B$22,E18:E22) -> -0.095900621 | F23: =(E23-D23)*100 -> -4.9423077 | G23: =SUMPRODUCT($B$18:$B$22,G18:G22) -> -0.061628025 | H23: =SUMPRODUCT($B$18:$B$22,H18:H22) -> 0.2498 | I23: =SUMPRODUCT($B$18:$B$22,I18:I22) -> 0.2248 | J23: =SUMPRODUCT($B$18:$B$22,J18:J22) -> 0.21259505 | K23: =SUMPRODUCT($B$18:$B$22,K18:K22) -> 0.16317198
A24: Probability median | D24: =INDEX(D18:D22,IFERROR(MATCH(0.5,'01-DRAM-Model'!$C$48:$C$52,1)+1,1)) -> -0.0948101 | E24: =INDEX(E18:E22,IFERROR(MATCH(0.5,'01-DRAM-Model'!$C$48:$C$52,1)+1,1)) -> -0.14423318 | G24: =INDEX(G18:G22,IFERROR(MATCH(0.5,'01-DRAM-Model'!$C$48:$C$52,1)+1,1)) -> -0.10981268
A25: Probability that 2027 is still short | D25: =SUMPRODUCT((D18:D22<0)*$B$18:$B$22) -> 0.56 | E25: =SUMPRODUCT((E18:E22<0)*$B$18:$B$22) -> 0.83 | G25: =SUMPRODUCT((G18:G22<0)*$B$18:$B$22) -> 0.56
A26: ★★★ The single most important line in v4.0: on the inventory correction alone the probability that DRAM is still short in 2027 rises from 53% to 78%, because S3 — the relief scenario carrying 25% probability — moves from +1.7% (turns to surplus) to −3.3% (still short). What moved it was not a demand datapoint but a supply-side accounting fact. Column G shows what happens once the other two corrections are applied as well: they push in the opposite direction and S3 returns to the boundary. Both numbers are in the report; only one can be the headline. See block [D].
A27: [C] Full v4.0 model: three years, all three corrections applied
A28: The inventory drag applies to 2027 only: the release sits in the 2026 base, so it depresses the 2026→2027 comparison and then washes out. The 8-high relief applies from 2027 onward. The de-spec demand ceiling is applied to 2027 only, which is conservative — if the 600kW rack power limit is a genuine physical ceiling it should persist into 2028 as well.
A29: Scenario | B29: Probability | C29: ④ Flow 2026 | D29: ④ Flow 2027 | E29: ④ Flow 2028 | F29: ② Stock 2026 | G29: ② Stock 2027 | H29: ② Stock 2028 | I29: 2028 supply (helper) | J29: 2028 demand (helper) | K29: Verdict
A30: S1 Extreme tightness | B30: =B18 -> 0.16 | C30: ='01-DRAM-Model'!L20 -> -0.12501097 | D30: =G18 -> -0.20846197 | E30: =I30-J30 -> -0.10149613 | F30: ='01-DRAM-Model'!M20 -> -0.15874825 | G30: =(1+F30)*(1+K18)/(1+I18)-1 -> -0.29313062 | H30: =(1+G30)*(1+I30)/(1+J30)-1 -> -0.34874652 | I30: =(1+'01-DRAM-Model'!C22+'01-DRAM-Model'!$B$146)*(1+'01-DRAM-Model'!D22+'01-DRAM-Model'!$B$147)*(((1-'01-DRAM-Model'!G22)+'01-DRAM-Model'!G22/('01-DRAM-Model'!$B$6+$B$10))/((1-'01-DRAM-Model'!G21)+'01-DRAM-Model'!G21/('01-DRAM-Model'!$B$6+$B$10)))-1 -> 0.18850387 | J30: ='01-DRAM-Model'!K22+'01-DRAM-Model'!$B$149 -> 0.29 | K30: =IF(D30<0,"still short in 2027",IF(D30<0.05,"close to balance in 2027","surplus in 2027")) -> still short in 2027
A31: S2 Base case | B31: =B19 -> 0.4 | C31: ='01-DRAM-Model'!L25 -> -0.10501097 | D31: =G19 -> -0.10981268 | E31: =I31-J31 -> 0.023503893 | F31: ='01-DRAM-Model'!M25 -> -0.14570558 | G31: =(1+F31)*(1+K19)/(1+I19)-1 -> -0.22105687 | H31: =(1+G31)*(1+I31)/(1+J31)-1 -> -0.20641032 | I31: =(1+'01-DRAM-Model'!C27+'01-DRAM-Model'!$B$146)*(1+'01-DRAM-Model'!D27+'01-DRAM-Model'!$B$147)*(((1-'01-DRAM-Model'!G27)+'01-DRAM-Model'!G27/('01-DRAM-Model'!$B$6+$B$10))/((1-'01-DRAM-Model'!G26)+'01-DRAM-Model'!G26/('01-DRAM-Model'!$B$6+$B$10)))-1 -> 0.27350389 | J31: ='01-DRAM-Model'!K27+'01-DRAM-Model'!$B$149 -> 0.25 | K31: =IF(D31<0,"still short in 2027",IF(D31<0.05,"close to balance in 2027","surplus in 2027")) -> still short in 2027
A32: S3 Relief | B32: =B20 -> 0.27 | C32: ='01-DRAM-Model'!L30 -> -0.085010969 | D32: =G20 -> 0.0078435731 | E32: =I32-J32 -> 0.18292474 | F32: ='01-DRAM-Model'!M30 -> -0.13225213 | G32: =(1+F32)*(1+K20)/(1+I20)-1 -> -0.12650846 | H32: =(1+G32)*(1+I32)/(1+J32)-1 -> 0.0077631453 | I32: =(1+'01-DRAM-Model'!C32+'01-DRAM-Model'!$B$146)*(1+'01-DRAM-Model'!D32+'01-DRAM-Model'!$B$147)*(((1-'01-DRAM-Model'!G32)+'01-DRAM-Model'!G32/('01-DRAM-Model'!$B$6+$B$10))/((1-'01-DRAM-Model'!G31)+'01-DRAM-Model'!G31/('01-DRAM-Model'!$B$6+$B$10)))-1 -> 0.37292474 | J32: ='01-DRAM-Model'!K32+'01-DRAM-Model'!$B$149 -> 0.19 | K32: =IF(D32<0,"still short in 2027",IF(D32<0.05,"close to balance in 2027","surplus in 2027")) -> close to balance in 2027
A33: S4 Surplus | B33: =B21 -> 0.17 | C33: ='01-DRAM-Model'!L35 -> -0.065010969 | D33: =G21 -> 0.07960704 | E33: =I33-J33 -> 0.28950267 | F33: ='01-DRAM-Model'!M35 -> -0.11836816 | G33: =(1+F33)*(1+K21)/(1+I21)-1 -> -0.058124298 | H33: =(1+G33)*(1+I33)/(1+J33)-1 -> 0.17493171 | I33: =(1+'01-DRAM-Model'!C37+'01-DRAM-Model'!$B$146)*(1+'01-DRAM-Model'!D37+'01-DRAM-Model'!$B$147)*(((1-'01-DRAM-Model'!G37)+'01-DRAM-Model'!G37/('01-DRAM-Model'!$B$6+$B$10))/((1-'01-DRAM-Model'!G36)+'01-DRAM-Model'!G36/('01-DRAM-Model'!$B$6+$B$10)))-1 -> 0.45950267 | J33: ='01-DRAM-Model'!K37+'01-DRAM-Model'!$B$149 -> 0.17 | K33: =IF(D33<0,"still short in 2027",IF(D33<0.05,"close to balance in 2027","surplus in 2027")) -> surplus in 2027
A34: S5 Collapse | B34: =B22 -> 0 | C34: ='01-DRAM-Model'!L40 -> -0.0050109692 | D34: =G22 -> 0.19261106 | E34: =I34-J34 -> 0.57316137 | F34: ='01-DRAM-Model'!M40 -> -0.073916136 | G34: =(1+F34)*(1+K22)/(1+I22)-1 -> 0.087508292 | H34: =(1+G34)*(1+I34)/(1+J34)-1 -> 0.75774243 | I34: =(1+'01-DRAM-Model'!C42+'01-DRAM-Model'!$B$146)*(1+'01-DRAM-Model'!D42+'01-DRAM-Model'!$B$147)*(((1-'01-DRAM-Model'!G42)+'01-DRAM-Model'!G42/('01-DRAM-Model'!$B$6+$B$10))/((1-'01-DRAM-Model'!G41)+'01-DRAM-Model'!G41/('01-DRAM-Model'!$B$6+$B$10)))-1 -> 0.50316137 | J34: ='01-DRAM-Model'!K42+'01-DRAM-Model'!$B$149 -> -0.07 | K34: =IF(D34<0,"still short in 2027",IF(D34<0.05,"close to balance in 2027","surplus in 2027")) -> surplus in 2027
A35: Probability weighted (mean) | B35: =SUM(B30:B34) -> 1 | C35: =SUMPRODUCT($B$30:$B$34,C30:C34) -> -0.096010969 | D35: =SUMPRODUCT($B$30:$B$34,D30:D34) -> -0.061628025 | E35: =SUMPRODUCT($B$30:$B$34,E30:E34) -> 0.091767311 | F35: =SUMPRODUCT($B$30:$B$34,F30:F34) -> -0.13951261 | G35: =SUMPRODUCT($B$30:$B$34,G30:G34) -> -0.17936206 | H35: =SUMPRODUCT($B$30:$B$34,H30:H34) -> -0.10652913
A36: Probability median | C36: =INDEX(C30:C34,IFERROR(MATCH(0.5,'01-DRAM-Model'!$C$48:$C$52,1)+1,1)) -> -0.10501097 | D36: =INDEX(D30:D34,IFERROR(MATCH(0.5,'01-DRAM-Model'!$C$48:$C$52,1)+1,1)) -> -0.10981268 | E36: =INDEX(E30:E34,IFERROR(MATCH(0.5,'01-DRAM-Model'!$C$48:$C$52,1)+1,1)) -> 0.023503893 | F36: =INDEX(F30:F34,IFERROR(MATCH(0.5,'01-DRAM-Model'!$C$48:$C$52,1)+1,1)) -> -0.14570558 | G36: =INDEX(G30:G34,IFERROR(MATCH(0.5,'01-DRAM-Model'!$C$48:$C$52,1)+1,1)) -> -0.22105687 | H36: =INDEX(H30:H34,IFERROR(MATCH(0.5,'01-DRAM-Model'!$C$48:$C$52,1)+1,1)) -> -0.20641032
A37: Rows 35 and 36 are what sheets 00, 01 and 05 link to for the 'v4.0 fully corrected' lines. Note that 2026 is unchanged from v3.0 on purpose — see audit finding B6 in block [F], which is the honest objection to doing it this way.
A39: [D] ⚠ Reconciling v4.0's own two headline numbers
A40: Step | C40: 2027 weighted growth gap | D40: Contribution (pp) | E40: Note
A41: v3.0, probability weighted | C41: ='01-DRAM-Model'!E53 -> -0.046477544 | D41: — | E41: The published v3.0 figure, on a production basis with the 3.0× penalty and unconstrained demand.
A42: Correction 1 · 8-high HBM4 lowers the wafer penalty from 2027 | C42: — | D42: =(J23-C23)*100 -> 0.92725959 | E42: Easing. The report quotes +0.8pp from the change in the HBM drag itself (−6.25pp → −5.41pp); propagated through the supply formula it is slightly larger, because the drag acts on an already-enlarged wafer and node base.
A43: Correction 2 · inventory exhaustion removes the 2026 release from the 2027 base | C43: — | D43: =(K23-J23)*100 -> -4.9423077 | E43: Tightening, and the largest of the three. Under convention 1 this is the report's −5.0pp; under convention 2 (exact) it is about −5.4pp.
A44: Correction 3 · the second de-spec caps unconstrained demand | C44: — | D44: =(H23-I23)*100 -> 2.5 | E44: Easing. Only the technical half of the de-spec counts — heat, power and packaging yield. The supply-driven half (cannot get the parts) is not a real fall in demand, it merely defers it.
A45: v4.0 with all three corrections | C45: =G23 -> -0.061628025 | D45: =(G23-'01-DRAM-Model'!E53)*100 -> -1.5150481 | E45: ★ The internally consistent v4.0 answer. The three contributions above are exactly additive to this line.
A46: v4.0 report headline (section 4.2, correction 2 only) | C46: =E23 -> -0.095900621 | D46: =(E23-'01-DRAM-Model'!E53)*100 -> -4.9423077 | E46: The −7.3% quoted at the top of the report, which applies the inventory correction alone.
A47: Unexplained difference between the two | C47: — | D47: =(E23-G23)*100 -> -3.4272596 | E47: ⚠ Audit finding A7. Section 4.1 of the report nets the three corrections to about −1.7pp while section 4.2 quotes a −5.0pp move. Both cannot be the headline. The defensible statement is that the inventory correction alone gives −7.3% and a 78% probability of shortage, and that the fully corrected figure is materially shallower — so the honest range for 2027 is between the two, not a single number.
A48: [E] The 4.9% arithmetic, written out
A49: Step | B49: Value | C49: Where it comes from
A50: July 2026 supplier inventory (weeks) | B50: 4 | C50: Luminix, DRAM Cycle Mid-2026 Update: a 3–5 week range, midpoint taken. Editable.
A51: 2026 Q3 supplier inventory (weeks) | B51: ='01-DRAM-Model'!$B$12 -> 1.43 | C51: KB Securities, 2026-09-07: below 10 days at Samsung and SK hynix = below 1.43 weeks. The two together hold about 64% of global DRAM revenue, so this is close to an industry reading.
A52: Bits released over the period (weeks) | B52: =B50-B51 -> 2.57 | C52: The drawdown. This volume was shipped to customers but not produced in the period.
A53: As a share of one year of supply | B53: =B52/52 -> 0.049423077 | C53: ★ Roughly 4.9%. This is the number the whole of v4.0 turns on.
A54: Value used by the console slider (weeks) | B54: =B9 -> 2.57 | C54: Row 9 above. Defaulted to the derived figure; drag it to test how sensitive the conclusion is to the release estimate.
A55: Drag applied to 2027 shipment growth | B55: =IF($B$12=0,0,IF($B$12=1,-$B$15,(1/(1+$B$15)-1))) -> -0.049423077 | C55: Convention 1 subtracts the release share directly, reproducing the report. Convention 2 uses the exact multiplicative form, which is slightly harsher because the base itself was inflated.
A56: ★ Why this is a supply fact and not a demand fact: for three years the market ran short without running out, because it was drawing down inventory — from 31 weeks in early 2023 to under 1.5 in 2026 Q3, a cumulative drawdown worth more than half of one year's demand. Nothing about demand has to change for 2027 to be tighter than 2026; the buffer that absorbed the shortfall simply no longer exists.
A59: [F] Five audit findings new in v4.0 (running total across all versions: 20)
A60: Grade | B60: Issue | E60: Why it is a problem | I60: How this workbook handles it
A61: A7 | B61: v4.0's own two headline numbers disagree | E61: Section 4.2 quotes 2027 moving from −2.3% to −7.3% (a −5.0pp move) while section 4.1 nets the three corrections to roughly −1.7pp. The first applies correction 2 alone; the second applies all three. Both are presented as the version's answer. | I61: → Block [D] above computes both and shows the exact size of the discrepancy. The honest statement is a range, not a point.
A62: B6 | B62: The inventory correction is applied on one side only | E62: If about 4.9% of 2026 shipments came out of inventory, then 2026 shipment growth was INFLATED by roughly the same amount, not just 2027 depressed. v4.0 (and this workbook's table [C], to stay comparable with it) adjusts 2027 only. | I62: → Recorded, not silently fixed. A symmetric treatment would make 2026 look better and 2027 worse by a similar amount; the two-year average is unaffected, which is itself worth knowing.
A63: B7 | B63: The NAND correction aligns to someone else's judgement rather than to new data | E63: The report itself flags this: 2027 NAND demand was raised from 18% to 22% and supply cut by 3pp in order to move toward KB Securities' view, without any independent read on enterprise SSD bit demand. | I63: → Implemented as two reversible sliders (rows 13 and 14) rather than as edits to the sheet 02 grid. Set them to zero and NAND reverts exactly to v3.0.
A64: C5 | B64: The coordinate origin was wrong: 'today' was off by eleven days | E64: Several prior reports were dated 2026-08-28 when the actual date was 2026-09-08. Correctly dated new material was discarded as future-dated crawler noise, and at least one already-published earnings event was written up as a future event. | I64: → The methodology fix is on sheet 08 block [C]: confirming the current date becomes check zero before any price or data verification. This is more fundamental than any single wrong price — a wrong origin makes correct data look wrong.
A65: C6 | B65: The 8-high relief is computed with a mixed-year penalty | E65: The report holds the 2026 equivalent-capacity index at the 3.0× value while using 2.8× for 2027, which is what produces −5.41pp rather than −5.99pp. That is defensible, since 8-high ships from 2027, but it is an assumption and was not stated. | I65: → Stated explicitly and implemented that way (2026 keeps 3.0×, 2027–28 use the relieved penalty). Sheet 07 shows what the alternative treatment would give.
A66: Cumulative audit findings across the model's life: 10 in v2.0's workbook (A×4, B×3, C×3), 5 new in v3.0 (A×2, B×2, C×1), 5 new in v4.0 (A×1, B×2, C×2) — 20 in total, all retained, none removed. The pattern is itself the point: v1.0's error was found by a reader, v2.0's while building the workbook, v3.0's while cross-calibrating against NVIDIA, and v4.0's while checking two news items. Treat any single quantitative conclusion — including this one — as provisional, and give priority to directly observable physical indicators: inventory weeks, quota ratios, contract prices.
A158: Chart notes | Chart 1: supplier inventory from 31 weeks to under 1.5. The vertical axis is deliberately not logarithmic — the point is how violent the drawdown is. | Chart 2: the 2027 growth gap by scenario, before and after the inventory correction. S3 crossing the zero axis is the whole of v4.0 in one picture. | Chart 3: the three corrections decomposed — two easing, one tightening, the tightening one much the largest.

Sheet 07-HBM-8High-Math-v4
A1: 07 · v4.0: the 8-high HBM4 arithmetic, done properly
A2: Two opposing effects that mostly cancel | base-die dilution against a compounding stacking-yield gain | the result is why a headline that sounds major is worth about one percentage point in the model
A4: There are two intuitive answers here and both are wrong, because each computes only half of it. Answer A: '8 layers is four fewer DRAM die than 12, so it saves wafers and eases supply.' Answer B: '8-high holds only two thirds the capacity of 12-high, so you need more stacks to hold capacity and it consumes more wafers.' The arithmetic below computes both effects and nets them.
A6: [A] Effect A — base-die dilution: 8-high is worse
A7: Stack height | B7: Total die per stack | C7: Share of die that produce bits | D7: Relative to 12-high | E7: Note
A8: 8-high | B8: 1 base + 8 core = 9 | C8: =8/9 -> 0.88888889 | D8: =(8/9)/(12/13)-1 -> -0.037037037 | E8: ★ The height NVIDIA is asking for
A9: 12-high | B9: 1 base + 12 core = 13 | C9: =12/13 -> 0.92307692 | D9: =(12/13)/(12/13)-1 -> 0 | E9: The current mainstream height
A10: 16-high | B10: 1 base + 16 core = 17 | C10: =16/17 -> 0.94117647 | D10: =(16/17)/(12/13)-1 -> 0.019607843 | E10: What NVIDIA was demanding eight months ago
A11: Every HBM stack needs one base die, and the base die produces no bits at all. Spread over 9 die instead of 13, that overhead costs 8-high about 3.70% relative to 12-high. This part is fixed and does not depend on yield.
A13: [B] Effect B — stacking yield compounds: 8-high is better, and the advantage grows as yield falls
A14: Per-layer bond yield | B14: 8-high stack yield | C14: 12-high stack yield | D14: 8-high yield advantage | E14: Base-die dilution | F14: Net wafer efficiency per bit | G14: Implied HBM penalty at 3.0× base
A15: 0.995 | B15: =A15^8 -> 0.96069304 | C15: =A15^12 -> 0.94162281 | D15: =B15/C15-1 -> 0.020252522 | E15: =$D$8 -> -0.037037037 | F15: =(1+D15)*(1+E15)-1 -> -0.017534608 | G15: =3/(1+F15) -> 3.0535427
A16: 0.99 | B16: =A16^8 -> 0.92274469 | C16: =A16^12 -> 0.88638487 | D16: =B16/C16-1 -> 0.041020356 | E16: =$D$8 -> -0.037037037 | F16: =(1+D16)*(1+E16)-1 -> 0.0024640462 | G16: =3/(1+F16) -> 2.992626
A17: 0.98 | B17: =A17^8 -> 0.85076302 | C17: =A17^12 -> 0.78471672 | D17: =B17/C17-1 -> 0.084165785 | E17: =$D$8 -> -0.037037037 | F17: =(1+D17)*(1+E17)-1 -> 0.044011496 | G17: =3/(1+F17) -> 2.8735316
A18: 0.97 | B18: =A18^8 -> 0.78374336 | C18: =A18^12 -> 0.69384236 | D18: =B18/C18-1 -> 0.12956977 | E18: =$D$8 -> -0.037037037 | F18: =(1+D18)*(1+E18)-1 -> 0.087733857 | G18: =3/(1+F18) -> 2.7580276
A19: 0.95 | B19: =A19^8 -> 0.66342043 | C19: =A19^12 -> 0.54036009 | D19: =B19/C19-1 -> 0.22773766 | E19: =$D$8 -> -0.037037037 | F19: =(1+D19)*(1+E19)-1 -> 0.1822659 | G19: =3/(1+F19) -> 2.5375002
A20: ★★ Stacking yield compounds: if the per-layer bond yield is y, an n-layer stack yields roughly y to the power n. And the cost of a failure matters more than the yield itself — a 12-high stack that fails on the last layer destroys twelve good die plus a base die; an 8-high failure destroys nine. ★★★ NVIDIA's stated reasons explicitly include packaging yield, which tells you yield is not where anyone would like it to be. At a per-layer yield of 0.97–0.98 the net gain is about 4%–9%, implying an effective penalty of roughly 2.75×–2.87× against the 3.0× base.
A22: [C] Parameterised: one slider for the per-layer bond yield
A23: Drag the slider to see how the net effect and the implied wafer penalty move. This is where the −0.20× default on the sheet 06 console comes from — at a per-layer yield of 0.975 the implied relief is about −0.18×, and −0.20 is the round number used.
A24: Parameter | B24: Current value | C24: ◀ drag to adjust ▶ | H24: Slider link cell | I24: Adjustable range | J24: Note
A25: Per-layer bond yield | B25: =H25/1000 -> 0.975 | H25: 975 | I25: 0.900 – 0.999 | J25: The yield of a single layer-to-layer bond. Nobody publishes this figure; it is inferred from the fact that NVIDIA cites packaging yield as a reason.
A26: 8-high stack yield | B26: =B25^8 -> 0.8166518 | C26: y raised to the 8th power.
A27: 12-high stack yield | B27: =B25^12 -> 0.73799835 | C27: y raised to the 12th power. The gap widens fast as y falls.
A28: 8-high yield advantage | B28: =B26/B27-1 -> 0.10657674 | C28: Purely the compounding effect.
A29: Base-die dilution | B29: =$D$8 -> -0.037037037 | C29: Fixed at −3.70%, from block [A].
A30: Net wafer efficiency per bit | B30: =(1+B28)*(1+B29)-1 -> 0.065592416 | C30: ★ The number that matters. Positive means 8-high delivers more bits per wafer than 12-high.
A31: Implied HBM wafer penalty | B31: =3/(1+B30) -> 2.8153354 | C31: Against the 3.0× base confirmed by KB Securities.
A32: Implied relief for the sheet 06 slider | B32: =B31-3 -> -0.18466465 | C32: ★ Compare with the −0.20× default in row 10 of sheet 06.
A34: [D] Feeding it into the model formula: E = (1 − h) + h ÷ p
A35: Case | B35: 2026 E-index (h = 22%) | C35: 2027 E-index (h = 30%) | D35: 2027 HBM drag | E35: Change vs the base case | F35: Note
A36: p = 3.0 | B36: =(1-0.22)+0.22/3 -> 0.85333333 | C36: =(1-0.3)+0.3/3 -> 0.8 | D36: =C36/B36-1 -> -0.0625 | E36: =(D36-$D$36)*100 -> 0 | F36: Original model — the v3.0 basis
A37: p = 2.9 | B37: =(1-0.22)+0.22/3 -> 0.85333333 | C37: =(1-0.3)+0.3/2.9 -> 0.80344828 | D37: =C37/B37-1 -> -0.058459052 | E37: =(D37-$D$36)*100 -> 0.40409483 | F37: 8-high brings p down to 2.9
A38: p = 2.8 | B38: =(1-0.22)+0.22/3 -> 0.85333333 | C38: =(1-0.3)+0.3/2.8 -> 0.80714286 | D38: =C38/B38-1 -> -0.054129464 | E38: =(D38-$D$36)*100 -> 0.83705357 | F38: 8-high brings p down to 2.8 — the v4.0 default
A39: p = 2.7 | B39: =(1-0.22)+0.22/3 -> 0.85333333 | C39: =(1-0.3)+0.3/2.7 -> 0.81111111 | D39: =C39/B39-1 -> -0.049479167 | E39: =(D39-$D$36)*100 -> 1.3020833 | F39: 8-high brings p down to 2.7 — already an aggressive assumption
A40: ★★★ Conclusion: even if the penalty falls all the way from 3.0 to 2.7, the 2027 HBM drag only improves from −6.25pp to −4.95pp. Propagated through the supply formula that is worth roughly 1.3 percentage points on the growth gap. 8-high is a second-order effect on the DRAM balance and does not change the conclusion. | Note the convention: the 2026 column keeps p = 3.0 in every row, because 8-high ships from 2027. Apply the lower penalty to both years and the 2027 drag would read −5.99pp rather than −5.41pp; the difference is entirely that convention, and it is recorded as audit finding C6 on sheet 06.
A42: [E] The two-sided verdict: what 8-high does outside the DRAM balance
A43: Dimension | B43: Direction | C43: Explanation
A44: HBM bit demand | B44: ⚠ negative | C44: HBM capacity per GPU grows more slowly. The 'Rubin Ultra delivers 384GB per GPU' assumption inside scenario S1 is weakened.
A45: Confirmation that the gap exists | B45: ✅ strongly positive | C45: ★ Part of NVIDIA's reason for cutting the specification is that it cannot obtain the parts. That is the strongest possible evidence the gap is real — more direct than any supply-demand table. Eight months ago NVIDIA was demanding 16-high and pushing per-pin speeds above 11 Gbps; the reversal took eight months.
A46: Advanced packaging | B46: ⚠ negative for CoWoS | C46: To hold total capacity, 8-high needs about 1.5× the number of stacks: base die +50% and a large increase in interposer area. The bottleneck moves partly from DRAM bits to packaging.
A47: Net judgement | B47: — | C47: ★★ It shifts part of the constraint from 'DRAM bits' to 'advanced packaging' — and packaging is outside this model's boundary. That is why CoWoS capacity is item 5 on the v4.0 tracking list, tagged as something this model cannot compute.
A48: ★ The counter-intuitive but important takeaway: a headline that sounds major is worth 1.3 percentage points in the model, while a single inventory reading is worth five. Size of headline and size of model impact are close to uncorrelated — which is exactly what a quantitative framework is for.
A81: Chart note | The net wafer efficiency of 8-high against 12-high, plotted against the per-layer bond yield. The line crosses zero at about y = 0.99: above that, 8-high is actually worse, because base-die dilution dominates. Below it the compounding yield advantage takes over and grows quickly. NVIDIA citing packaging yield as a reason places us on the right-hand side of that crossing.

Sheet 08-Tracking-List-v4
A1: 08 · v4.0 falsifiable tracking list
A2: What has been added or promoted since v3.0, what has been retained, and the one methodology lesson that sits outside the model altogether
A4: [A] New and upgraded items
A5: Priority | B5: Indicator | C5: Current reading | D5: Status | E5: Threshold / what to watch for
A6: 1 | B6: Supplier inventory weeks | C6: Below 10 days (KB, 2026 Q3) | D6: ▲ promoted | E6: ★ Promoted from item 19 in v3.0 to first place. Back above 3 weeks means the tightness is easing; a further fall means 2027 sees genuine allocation failures rather than merely high prices. This is the only physical anchor of the stock basis and the most fragile single parameter in the model.
A7: 2 | B7: Independent read on eSSD bit demand | C7: Not obtained | D7: ▲ new | E7: ★ The sole source of the disagreement with KB Securities on NAND. Until it exists, the NAND correction on sheet 02 block [F] remains an alignment to someone else's judgement rather than a measurement.
A8: 3 | B8: Actual shipment mix of 8-high HBM4 / HBM4E | C8: Just beginning | D8: ▲ new | E8: Above 50% would mean the de-spec is structural; if it is only a transition step, the demand-ceiling judgement on sheet 06 row 11 has to be withdrawn.
A9: 4 | B9: HBM capacity per GPU (Rubin Ultra actual specification) | C9: Assumed 384GB | D9: ▲ upgraded | E9: Determines directly whether scenario S1 stands. The 8-high request has already weakened the assumption.
A10: 5 | B10: CoWoS / advanced packaging capacity | C10: Not quantified | D10: ▲ new | E10: ★ 8-high moves part of the bottleneck here, and this model cannot compute it. Recorded honestly as outside the boundary rather than approximated.
A11: 6 | B11: HBM wafers as a share of total DRAM wafers | C11: 30% at end-2027 (TrendForce) | D11: retained | E11: Item 1 in v3.0 and still central. If the 2027 outturn is below 26%, the economics reversal is happening and 3–5pp of extra supply is released.
A12: 7 | B12: 2027 HBM contract price negotiations | C12: +70~140% (TrendForce forecast) | D12: retained | E12: Item 2 in v3.0. ⚠ If large increases are agreed, the reversal assumption behind S3 and S4 (40% of probability combined) has to be reweighted.
A13: 8 | B13: Memory as a share of AI infrastructure investment | C13: 14% in 2025 → 57% in 2027 (KB) | D13: ▲ new | E13: ⚠ A different basis from the model's 'DRAM+NAND = 47% → 68% of CSP capex'. Putting the two on one denominator is a task, not just a comparison.
A15: [B] Key items retained from v3.0
A16: # | B16: Indicator | C16: Current reading | D16: Side | E16: Why it still matters
A17: 9 | B17: Micron Idaho ID1 first wafer | C17: Target mid-2027 | D17: supply | E17: The first verifiable milestone of the 2028 capacity wave.
A18: 10 | B18: Samsung P5 tool move-in | C18: Completion 1H27, mass production 2H28 | D18: supply | E18: Already about six months ahead of the original plan; any further acceleration is a warning signal.
A19: 11 | B19: SK hynix and Samsung 1c ramp | C19: SK targets 160–190k wpm by end-2026; Samsung above 200k | D19: supply | E19: Sets the node-migration bit uplift directly.
A20: 12 | B20: Conventional DRAM contract price, quarter on quarter | C20: 1Q26 +93~98% → 2Q26 +58~63% → 3Q26 +13~18% | D20: price | E20: The first hard signal that the model needs re-estimating would be any quarter turning negative early.
A21: 13 | B21: LTA price-ceiling coverage and level | C21: Some LTAs signed from 2Q26 include ceilings; Sandisk NBM covers ~50% of FY27 bits | D21: price | E21: ★ v3.0 called this the most important item on the list. It determines how much of the physical gap still explains price at all.
A22: 14 | B22: DDR4 versus DDR5 price spread | C22: Both 16Gb contract prices at $35–40; the DDR5 premium has vanished | D22: price | E22: A deeply abnormal state; the direction in which it normalises tells you whether the supply constraint is easing.
A23: 15 | B23: Top four cloud vendors' 2027 capex guidance | C23: +63% on NVIDIA's basis, +50% on TrendForce's | D23: demand | E23: To turn 2027 positive, demand growth must fall from 26% to about 15.5%. Still the only realistic path.
A24: 16 | B24: NVIDIA supply and capacity commitments (next 10-Q) | C24: $279.0bn | D24: demand | E24: A sequential fall of more than 15% would be the first hard signal that demand expectations are being cut.
A26: [C] The methodology lesson that is not in the model
A27: The correction that matters most in v4.0 is not a parameter. Several earlier reports were dated 2026-08-28 when the real date was 2026-09-08 — an eleven-day error in the coordinate origin.
A28: The consequence was not a missing datapoint but an inverted filter: pages correctly dated 8/31, 9/1 and 9/7 were repeatedly discarded as future-dated crawler noise. One already-published earnings release was written up as an event four days in the future. Two price errors that had been blamed on bad snapshots turned out to be correct data rejected for being 'in the future'.
A29: ★★★ A wrong origin makes every correct datapoint look wrong. That is a more fundamental failure than any single mispriced quote, because it is systematic and self-reinforcing: the more current the data, the more likely it is to be thrown away.
A30: ★ From v4.0 onward, confirming today's date is check zero of any price or data verification, before the source is even opened.
A32: [D] Effect on the company work in this series
A33: Report | B33: Effect | F33: Direction
A34: Micron, SK hynix, Samsung, Sandisk, Western Digital | B34: The probability that 2027 is still short rises. | F34: ✅ positive
A35: Rambus deep dive | B35: Stronger support for main-memory demand, but antitrust risk remains the first-order variable. | F35: ✅ mildly positive
A36: Applied Materials deep dive | B36: Stronger support for 2027–2028 capex, but the structural risk from Chinese localisation is unchanged. | F36: ✅ mildly positive
A37: Aehr deep dive | B37: ⚠ Fewer HBM die per package weakens the scrap-cost economics argued in section 1.4.2 (an AI processor plus 8 HBM die plus interposer plus substrate). But 8-high may raise the number of stacks by about 1.5×, which pushes the other way. Net effect undetermined — flagged as an information gap. | F37: ⚠ mildly negative
A38: Coherent, Lumentum, Marvell, Astera Labs, Credo | B38: Little effect — their bottleneck is optics and interconnect, not DRAM bits. | F38: neutral
A40: [E] Closing statement
A41: Three judgements are worth stating plainly. First: the second de-spec has happened, and its motive is two-sided. NVIDIA's stated reasons include both the technical (heat, power, packaging yield) and the supply-driven (availability under tight supply). Supply-driven de-spec is not a real fall in demand — it defers demand. So the unconstrained-demand basis is not overturned; it is given a physical ceiling, and 600kW of rack power is that ceiling.
A42: Second: part of the bottleneck is moving to advanced packaging, which is outside this model's boundary. Holding total capacity with 8-high needs about 1.5× the stacks — base die +50% and a large increase in interposer area. Enough DRAM bits may not be enough CoWoS. It is item 5 on the list above, labelled honestly as something this model cannot compute.
A43: Third, and most important: the arithmetic in this workbook is only as good as its origin. v1.0's error was found by a reader, v2.0's while building the workbook, v3.0's while cross-calibrating against NVIDIA, and v4.0's while checking two news items and the date. Every version has found the previous version's mistake, which is a reason to hold any single quantitative conclusion loosely and to give priority to directly observable physical indicators.
A44: This workbook is for research and study only. It is not investment advice and not an offer to buy or sell any security. All forward-looking judgements may be wrong. Make your own decisions in light of your own research and risk tolerance. If you work at a regulated institution, confirm the applicable personal-account reporting and pre-clearance requirements before trading.
